Workbook
Name LEMI_PARRAINAGE_REGISTRE: 'REGISTRE_PARRAINS'!$A$7:$J$106
Name LEMI_PARRAINAGE_FILLEULS: 'FILLEULS'!$A$7:$J$106
Name LEMI_PARRAINAGE_COMMISSIONS: 'COMMISSIONS_PARRAINAGE'!$A$7:$M$106

Sheet ACCUEIL
A2: LEMI SARL — PROGRAMME DE PARRAINAGE CLIENT
A3: Tontine Habitat | Abidjan, Côte d'Ivoire | BRASUS v3.2 | Digital Mastery Agency
B5: KPI FLASH — PARRAINAGE
B6: Commissions versées ce mois (FCFA) | C6: =IFERROR(SUMPRODUCT((COMMISSIONS_PARRAINAGE!H7:H106="Payé")*(MONTH(COMMISSIONS_PARRAINAGE!K7:K106)=MONTH(TODAY()))*(YEAR(COMMISSIONS_PARRAINAGE!K7:K106)=YEAR(TODAY()))*COMMISSIONS_PARRAINAGE!G7:G106),0) | D6: Calculé depuis COMMISSIONS_PARRAINAGE
B7: Filleuls éligibles ce mois | C7: =IFERROR(COUNTIFS(FILLEULS!G7:G106,"*ÉLIGIBLE*",FILLEULS!E7:E106,">="&DATE(YEAR(TODAY()),MONTH(TODAY()),1)),0) | D7: Filleuls avec statut ÉLIGIBLE
B8: Parrain le plus actif | C8: =IFERROR(INDEX(REGISTRE_PARRAINS!B7:B106,MATCH(MAX(REGISTRE_PARRAINS!H7:H106),REGISTRE_PARRAINS!H7:H106,0)),"—") | D8: Par nombre de filleuls cumulés
B9: Commissions en attente de validation | C9: =IFERROR(COUNTIF(COMMISSIONS_PARRAINAGE!H7:H106,"À valider"),0) | D9: Requièrent validation DG
B10: Total parrains inscrits | C10: =IFERROR(COUNTA(REGISTRE_PARRAINS!B7:B106)-COUNTBLANK(REGISTRE_PARRAINS!B7:B106),0) | D10: Depuis REGISTRE_PARRAINS
B12: NAVIGATION
B13: 📊 DASHBOARD_PARRAINAGE | C13: Courbes, barres, top parrains, répartitions | D13: Onglet 2
B14: 📗 REGISTRE_PARRAINS | C14: Inscription et suivi des parrains | D14: Onglet 3
B15: 👥 FILLEULS | C15: Déclaration et éligibilité des filleuls | D15: Onglet 4
B16: 💰 COMMISSIONS_PARRAINAGE | C16: Calcul, validation DG, paiement | D16: Onglet 5
B17: 🚨 ALERTES_FRAUDE | C17: Verrous 1-5 — Signaux et blocages | D17: Onglet 6
B18: 📋 TACHES_PERIODIQUES | C18: Planning quotidien / hebdo / mensuel / trimestriel | D18: Onglet 7
B20: RÈGLES DU PROGRAMME
B21: Taux de commission | C21: 2,5% de l'acompte de signature (30% du contrat)
B22: Déclenchement | C22: Dès réception confirmée de l'acompte du filleul
B23: Mode de paiement | C23: Orange Money ou Wave — versement direct au parrain
B24: Plafond filleuls | C24: Aucun — volume illimité
B25: Qui peut parrainer | C25: Clients actifs, prospects ET partenaires
B26: Déclaration obligatoire | C26: Code parrain au 1er contact — après signature = refusé
B27: Validation | C27: Double contrôle : éligibilité auto + validation DG
A29: Dernière mise à jour : =TEXT(TODAY(),"DD/MM/YYYY") | BRASUS v3.2 | LEMI SARL | DMA Abidjan

Sheet DASHBOARD_PARRAINAGE
A1: LEMI SARL | DASHBOARD PARRAINAGE | BRASUS v3.2
A2: 🔒 Indicateurs consolidés automatiquement — Lecture seule | Mis à jour : 18/06/2026
B4: ÉVOLUTION MENSUELLE — FILLEULS PARRAINÉS | H4: COMMISSIONS VERSÉES PAR MOIS (FCFA)
B5: Jan | C5: Fév | D5: Mar | E5: Avr | F5: Mai | G5: Juin | H5: Jan | I5: Fév | J5: Mar | K5: Avr | L5: Mai | M5: Juin
B6: 0 | C6: 0 | D6: 0 | E6: 0 | F6: 0 | G6: 0 | H6: 0 | I6: 0 | J6: 0 | K6: 0 | L6: 0 | M6: 0
B8: TOP 5 — MEILLEURS PARRAINS | H8: RÉPARTITION PAR TYPE DE PARRAIN
B9: # | C9: NOM PARRAIN | D9: TYPE | E9: NB FILLEULS | F9: COMMISSIONS (FCFA) | G9: STATUT | H9: TYPE | I9: NOMBRE | J9: % DU TOTAL | K9: COMMISSIONS | L9: COMM. MOY. | M9: FILLEULS MOY.
B10: 1 | C10: — | D10: — | E10: 0 | F10: 0 FCFA | G10: — | H10: Client actif | I10: =IFERROR(COUNTIF(REGISTRE_PARRAINS!D7:D106,"Client"),0) | J10: 0% | K10: 0 FCFA | L10: 0 FCFA | M10: 0
B11: 2 | C11: — | D11: — | E11: 0 | F11: 0 FCFA | G11: — | H11: Prospect | I11: =IFERROR(COUNTIF(REGISTRE_PARRAINS!D7:D106,"Prospect"),0) | J11: 0% | K11: 0 FCFA | L11: 0 FCFA | M11: 0
B12: 3 | C12: — | D12: — | E12: 0 | F12: 0 FCFA | G12: — | H12: Partenaire | I12: =IFERROR(COUNTIF(REGISTRE_PARRAINS!D7:D106,"Partenaire"),0) | J12: 0% | K12: 0 FCFA | L12: 0 FCFA | M12: 0
B13: 4 | C13: — | D13: — | E13: 0 | F13: 0 FCFA | G13: —
B14: 5 | C14: — | D14: — | E14: 0 | F14: 0 FCFA | G14: —
B16: JAUGE — COMMISSIONS EN ATTENTE DE VALIDATION DG
B17: Commissions À VALIDER | H17: =IFERROR(COUNTIF(COMMISSIONS_PARRAINAGE!H7:H106,"À valider"),0)
B18: Montant total à valider (FCFA) | H18: =IFERROR(SUMPRODUCT((COMMISSIONS_PARRAINAGE!H7:H106="À valider")*COMMISSIONS_PARRAINAGE!G7:G106),0)
B19: Commissions VALIDÉES DG (non payées) | H19: =IFERROR(COUNTIF(COMMISSIONS_PARRAINAGE!H7:H106,"Validé DG"),0)
B20: Commissions PAYÉES ce mois | H20: =IFERROR(COUNTIF(COMMISSIONS_PARRAINAGE!H7:H106,"Payé"),0)
B21: Clawbacks actifs | H21: =IFERROR(COUNTIF(COMMISSIONS_PARRAINAGE!M7:M106,"*DÉDUIRE*"),0)

Sheet REGISTRE_PARRAINS
A1: 📗 REGISTRE DES PARRAINS — LEMI SARL | BRASUS v3.2
A2: Plage nommée : LEMI_PARRAINAGE_REGISTRE | Colonnes A-F : saisie | Colonnes G-J : calcul auto 🔒
A3: ✏️ ZONE SAISIE — Colonnes déverrouillées | F3: 🔒 ZONE CALCUL — Colonnes verrouillées (auto)
A4: 📋 ORDRE CANONIQUE A→J: | B4: A=CODE | C4: B=NOM PRÉNOM | D4: C=TÉLÉPHONE | E4: D=TYPE | F4: E=DATE INSCRIPTION | G4: F=N° MOBILE MONEY | H4: G=STATUT | I4: H=NB FILLEULS | J4: I=TOTAL COMMISSIONS | K4: J=STATUT COMPTE
A5: INFORMATIONS PARRAIN (saisie manuelle) | F5: DONNÉES CALCULÉES AUTOMATIQUEMENT
A6: CODE PARRAIN | B6: NOM PRÉNOM | C6: TÉLÉPHONE | D6: TYPE | E6: DATE INSCRIPTION | F6: N° ORANGE MONEY / WAVE | G6: STATUT PARRAIN | H6: NB FILLEULS CUMULÉS | I6: TOTAL COMMISSIONS (FCFA) | J6: STATUT COMPTE
A7: LEMI-PARR-001 | B7: Nom et prénom | C7: 07 XX XX XX XX | E7: JJ/MM/AAAA | G7: =IFERROR(IF(B7="","",IF(COUNTIF(FILLEULS!G7:G106,"*ÉLIGIBLE*")>0,"Actif","Inscrit")),"—") | H7: =IFERROR(COUNTIF(FILLEULS!D7:D106,A7),0) | I7: =IFERROR(SUMPRODUCT((COMMISSIONS_PARRAINAGE!C7:C106=A7)*(COMMISSIONS_PARRAINAGE!H7:H106="Payé")*COMMISSIONS_PARRAINAGE!G7:G106),0) | J7: =IFERROR(IF(B7="","","Actif"),"—")
A8: LEMI-PARR-002 | G8: =IFERROR(IF(B8="","",IF(COUNTIF(FILLEULS!G7:G106,"*ÉLIGIBLE*")>0,"Actif","Inscrit")),"—") | H8: =IFERROR(COUNTIF(FILLEULS!D7:D106,A8),0) | I8: =IFERROR(SUMPRODUCT((COMMISSIONS_PARRAINAGE!C7:C106=A8)*(COMMISSIONS_PARRAINAGE!H7:H106="Payé")*COMMISSIONS_PARRAINAGE!G7:G106),0) | J8: =IFERROR(IF(B8="","","Actif"),"—")
A9: LEMI-PARR-003 | G9: =IFERROR(IF(B9="","",IF(COUNTIF(FILLEULS!G7:G106,"*ÉLIGIBLE*")>0,"Actif","Inscrit")),"—") | H9: =IFERROR(COUNTIF(FILLEULS!D7:D106,A9),0) | I9: =IFERROR(SUMPRODUCT((COMMISSIONS_PARRAINAGE!C7:C106=A9)*(COMMISSIONS_PARRAINAGE!H7:H106="Payé")*COMMISSIONS_PARRAINAGE!G7:G106),0) | J9: =IFERROR(IF(B9="","","Actif"),"—")
A10: LEMI-PARR-004 | G10: =IFERROR(IF(B10="","",IF(COUNTIF(FILLEULS!G7:G106,"*ÉLIGIBLE*")>0,"Actif","Inscrit")),"—") | H10: =IFERROR(COUNTIF(FILLEULS!D7:D106,A10),0) | I10: =IFERROR(SUMPRODUCT((COMMISSIONS_PARRAINAGE!C7:C106=A10)*(COMMISSIONS_PARRAINAGE!H7:H106="Payé")*COMMISSIONS_PARRAINAGE!G7:G106),0) | J10: =IFERROR(IF(B10="","","Actif"),"—")
A11: LEMI-PARR-005 | G11: =IFERROR(IF(B11="","",IF(COUNTIF(FILLEULS!G7:G106,"*ÉLIGIBLE*")>0,"Actif","Inscrit")),"—") | H11: =IFERROR(COUNTIF(FILLEULS!D7:D106,A11),0) | I11: =IFERROR(SUMPRODUCT((COMMISSIONS_PARRAINAGE!C7:C106=A11)*(COMMISSIONS_PARRAINAGE!H7:H106="Payé")*COMMISSIONS_PARRAINAGE!G7:G106),0) | J11: =IFERROR(IF(B11="","","Actif"),"—")
A12: LEMI-PARR-006 | G12: =IFERROR(IF(B12="","",IF(COUNTIF(FILLEULS!G7:G106,"*ÉLIGIBLE*")>0,"Actif","Inscrit")),"—") | H12: =IFERROR(COUNTIF(FILLEULS!D7:D106,A12),0) | I12: =IFERROR(SUMPRODUCT((COMMISSIONS_PARRAINAGE!C7:C106=A12)*(COMMISSIONS_PARRAINAGE!H7:H106="Payé")*COMMISSIONS_PARRAINAGE!G7:G106),0) | J12: =IFERROR(IF(B12="","","Actif"),"—")
A13: LEMI-PARR-007 | G13: =IFERROR(IF(B13="","",IF(COUNTIF(FILLEULS!G7:G106,"*ÉLIGIBLE*")>0,"Actif","Inscrit")),"—") | H13: =IFERROR(COUNTIF(FILLEULS!D7:D106,A13),0) | I13: =IFERROR(SUMPRODUCT((COMMISSIONS_PARRAINAGE!C7:C106=A13)*(COMMISSIONS_PARRAINAGE!H7:H106="Payé")*COMMISSIONS_PARRAINAGE!G7:G106),0) | J13: =IFERROR(IF(B13="","","Actif"),"—")
A14: LEMI-PARR-008 | G14: =IFERROR(IF(B14="","",IF(COUNTIF(FILLEULS!G7:G106,"*ÉLIGIBLE*")>0,"Actif","Inscrit")),"—") | H14: =IFERROR(COUNTIF(FILLEULS!D7:D106,A14),0) | I14: =IFERROR(SUMPRODUCT((COMMISSIONS_PARRAINAGE!C7:C106=A14)*(COMMISSIONS_PARRAINAGE!H7:H106="Payé")*COMMISSIONS_PARRAINAGE!G7:G106),0) | J14: =IFERROR(IF(B14="","","Actif"),"—")
A15: LEMI-PARR-009 | G15: =IFERROR(IF(B15="","",IF(COUNTIF(FILLEULS!G7:G106,"*ÉLIGIBLE*")>0,"Actif","Inscrit")),"—") | H15: =IFERROR(COUNTIF(FILLEULS!D7:D106,A15),0) | I15: =IFERROR(SUMPRODUCT((COMMISSIONS_PARRAINAGE!C7:C106=A15)*(COMMISSIONS_PARRAINAGE!H7:H106="Payé")*COMMISSIONS_PARRAINAGE!G7:G106),0) | J15: =IFERROR(IF(B15="","","Actif"),"—")
A16: LEMI-PARR-010 | G16: =IFERROR(IF(B16="","",IF(COUNTIF(FILLEULS!G7:G106,"*ÉLIGIBLE*")>0,"Actif","Inscrit")),"—") | H16: =IFERROR(COUNTIF(FILLEULS!D7:D106,A16),0) | I16: =IFERROR(SUMPRODUCT((COMMISSIONS_PARRAINAGE!C7:C106=A16)*(COMMISSIONS_PARRAINAGE!H7:H106="Payé")*COMMISSIONS_PARRAINAGE!G7:G106),0) | J16: =IFERROR(IF(B16="","","Actif"),"—")
A17: LEMI-PARR-011 | G17: =IFERROR(IF(B17="","",IF(COUNTIF(FILLEULS!G7:G106,"*ÉLIGIBLE*")>0,"Actif","Inscrit")),"—") | H17: =IFERROR(COUNTIF(FILLEULS!D7:D106,A17),0) | I17: =IFERROR(SUMPRODUCT((COMMISSIONS_PARRAINAGE!C7:C106=A17)*(COMMISSIONS_PARRAINAGE!H7:H106="Payé")*COMMISSIONS_PARRAINAGE!G7:G106),0) | J17: =IFERROR(IF(B17="","","Actif"),"—")
A18: LEMI-PARR-012 | G18: =IFERROR(IF(B18="","",IF(COUNTIF(FILLEULS!G7:G106,"*ÉLIGIBLE*")>0,"Actif","Inscrit")),"—") | H18: =IFERROR(COUNTIF(FILLEULS!D7:D106,A18),0) | I18: =IFERROR(SUMPRODUCT((COMMISSIONS_PARRAINAGE!C7:C106=A18)*(COMMISSIONS_PARRAINAGE!H7:H106="Payé")*COMMISSIONS_PARRAINAGE!G7:G106),0) | J18: =IFERROR(IF(B18="","","Actif"),"—")
A19: LEMI-PARR-013 | G19: =IFERROR(IF(B19="","",IF(COUNTIF(FILLEULS!G7:G106,"*ÉLIGIBLE*")>0,"Actif","Inscrit")),"—") | H19: =IFERROR(COUNTIF(FILLEULS!D7:D106,A19),0) | I19: =IFERROR(SUMPRODUCT((COMMISSIONS_PARRAINAGE!C7:C106=A19)*(COMMISSIONS_PARRAINAGE!H7:H106="Payé")*COMMISSIONS_PARRAINAGE!G7:G106),0) | J19: =IFERROR(IF(B19="","","Actif"),"—")
A20: LEMI-PARR-014 | G20: =IFERROR(IF(B20="","",IF(COUNTIF(FILLEULS!G7:G106,"*ÉLIGIBLE*")>0,"Actif","Inscrit")),"—") | H20: =IFERROR(COUNTIF(FILLEULS!D7:D106,A20),0) | I20: =IFERROR(SUMPRODUCT((COMMISSIONS_PARRAINAGE!C7:C106=A20)*(COMMISSIONS_PARRAINAGE!H7:H106="Payé")*COMMISSIONS_PARRAINAGE!G7:G106),0) | J20: =IFERROR(IF(B20="","","Actif"),"—")
A21: LEMI-PARR-015 | G21: =IFERROR(IF(B21="","",IF(COUNTIF(FILLEULS!G7:G106,"*ÉLIGIBLE*")>0,"Actif","Inscrit")),"—") | H21: =IFERROR(COUNTIF(FILLEULS!D7:D106,A21),0) | I21: =IFERROR(SUMPRODUCT((COMMISSIONS_PARRAINAGE!C7:C106=A21)*(COMMISSIONS_PARRAINAGE!H7:H106="Payé")*COMMISSIONS_PARRAINAGE!G7:G106),0) | J21: =IFERROR(IF(B21="","","Actif"),"—")
A22: LEMI-PARR-016 | G22: =IFERROR(IF(B22="","",IF(COUNTIF(FILLEULS!G7:G106,"*ÉLIGIBLE*")>0,"Actif","Inscrit")),"—") | H22: =IFERROR(COUNTIF(FILLEULS!D7:D106,A22),0) | I22: =IFERROR(SUMPRODUCT((COMMISSIONS_PARRAINAGE!C7:C106=A22)*(COMMISSIONS_PARRAINAGE!H7:H106="Payé")*COMMISSIONS_PARRAINAGE!G7:G106),0) | J22: =IFERROR(IF(B22="","","Actif"),"—")
A23: LEMI-PARR-017 | G23: =IFERROR(IF(B23="","",IF(COUNTIF(FILLEULS!G7:G106,"*ÉLIGIBLE*")>0,"Actif","Inscrit")),"—") | H23: =IFERROR(COUNTIF(FILLEULS!D7:D106,A23),0) | I23: =IFERROR(SUMPRODUCT((COMMISSIONS_PARRAINAGE!C7:C106=A23)*(COMMISSIONS_PARRAINAGE!H7:H106="Payé")*COMMISSIONS_PARRAINAGE!G7:G106),0) | J23: =IFERROR(IF(B23="","","Actif"),"—")
A24: LEMI-PARR-018 | G24: =IFERROR(IF(B24="","",IF(COUNTIF(FILLEULS!G7:G106,"*ÉLIGIBLE*")>0,"Actif","Inscrit")),"—") | H24: =IFERROR(COUNTIF(FILLEULS!D7:D106,A24),0) | I24: =IFERROR(SUMPRODUCT((COMMISSIONS_PARRAINAGE!C7:C106=A24)*(COMMISSIONS_PARRAINAGE!H7:H106="Payé")*COMMISSIONS_PARRAINAGE!G7:G106),0) | J24: =IFERROR(IF(B24="","","Actif"),"—")
A25: LEMI-PARR-019 | G25: =IFERROR(IF(B25="","",IF(COUNTIF(FILLEULS!G7:G106,"*ÉLIGIBLE*")>0,"Actif","Inscrit")),"—") | H25: =IFERROR(COUNTIF(FILLEULS!D7:D106,A25),0) | I25: =IFERROR(SUMPRODUCT((COMMISSIONS_PARRAINAGE!C7:C106=A25)*(COMMISSIONS_PARRAINAGE!H7:H106="Payé")*COMMISSIONS_PARRAINAGE!G7:G106),0) | J25: =IFERROR(IF(B25="","","Actif"),"—")
A26: LEMI-PARR-020 | G26: =IFERROR(IF(B26="","",IF(COUNTIF(FILLEULS!G7:G106,"*ÉLIGIBLE*")>0,"Actif","Inscrit")),"—") | H26: =IFERROR(COUNTIF(FILLEULS!D7:D106,A26),0) | I26: =IFERROR(SUMPRODUCT((COMMISSIONS_PARRAINAGE!C7:C106=A26)*(COMMISSIONS_PARRAINAGE!H7:H106="Payé")*COMMISSIONS_PARRAINAGE!G7:G106),0) | J26: =IFERROR(IF(B26="","","Actif"),"—")
A27: LEMI-PARR-021 | G27: =IFERROR(IF(B27="","",IF(COUNTIF(FILLEULS!G7:G106,"*ÉLIGIBLE*")>0,"Actif","Inscrit")),"—") | H27: =IFERROR(COUNTIF(FILLEULS!D7:D106,A27),0) | I27: =IFERROR(SUMPRODUCT((COMMISSIONS_PARRAINAGE!C7:C106=A27)*(COMMISSIONS_PARRAINAGE!H7:H106="Payé")*COMMISSIONS_PARRAINAGE!G7:G106),0) | J27: =IFERROR(IF(B27="","","Actif"),"—")
A28: LEMI-PARR-022 | G28: =IFERROR(IF(B28="","",IF(COUNTIF(FILLEULS!G7:G106,"*ÉLIGIBLE*")>0,"Actif","Inscrit")),"—") | H28: =IFERROR(COUNTIF(FILLEULS!D7:D106,A28),0) | I28: =IFERROR(SUMPRODUCT((COMMISSIONS_PARRAINAGE!C7:C106=A28)*(COMMISSIONS_PARRAINAGE!H7:H106="Payé")*COMMISSIONS_PARRAINAGE!G7:G106),0) | J28: =IFERROR(IF(B28="","","Actif"),"—")
A29: LEMI-PARR-023 | G29: =IFERROR(IF(B29="","",IF(COUNTIF(FILLEULS!G7:G106,"*ÉLIGIBLE*")>0,"Actif","Inscrit")),"—") | H29: =IFERROR(COUNTIF(FILLEULS!D7:D106,A29),0) | I29: =IFERROR(SUMPRODUCT((COMMISSIONS_PARRAINAGE!C7:C106=A29)*(COMMISSIONS_PARRAINAGE!H7:H106="Payé")*COMMISSIONS_PARRAINAGE!G7:G106),0) | J29: =IFERROR(IF(B29="","","Actif"),"—")
A30: LEMI-PARR-024 | G30: =IFERROR(IF(B30="","",IF(COUNTIF(FILLEULS!G7:G106,"*ÉLIGIBLE*")>0,"Actif","Inscrit")),"—") | H30: =IFERROR(COUNTIF(FILLEULS!D7:D106,A30),0) | I30: =IFERROR(SUMPRODUCT((COMMISSIONS_PARRAINAGE!C7:C106=A30)*(COMMISSIONS_PARRAINAGE!H7:H106="Payé")*COMMISSIONS_PARRAINAGE!G7:G106),0) | J30: =IFERROR(IF(B30="","","Actif"),"—")
A31: LEMI-PARR-025 | G31: =IFERROR(IF(B31="","",IF(COUNTIF(FILLEULS!G7:G106,"*ÉLIGIBLE*")>0,"Actif","Inscrit")),"—") | H31: =IFERROR(COUNTIF(FILLEULS!D7:D106,A31),0) | I31: =IFERROR(SUMPRODUCT((COMMISSIONS_PARRAINAGE!C7:C106=A31)*(COMMISSIONS_PARRAINAGE!H7:H106="Payé")*COMMISSIONS_PARRAINAGE!G7:G106),0) | J31: =IFERROR(IF(B31="","","Actif"),"—")
A32: LEMI-PARR-026 | G32: =IFERROR(IF(B32="","",IF(COUNTIF(FILLEULS!G7:G106,"*ÉLIGIBLE*")>0,"Actif","Inscrit")),"—") | H32: =IFERROR(COUNTIF(FILLEULS!D7:D106,A32),0) | I32: =IFERROR(SUMPRODUCT((COMMISSIONS_PARRAINAGE!C7:C106=A32)*(COMMISSIONS_PARRAINAGE!H7:H106="Payé")*COMMISSIONS_PARRAINAGE!G7:G106),0) | J32: =IFERROR(IF(B32="","","Actif"),"—")
A33: LEMI-PARR-027 | G33: =IFERROR(IF(B33="","",IF(COUNTIF(FILLEULS!G7:G106,"*ÉLIGIBLE*")>0,"Actif","Inscrit")),"—") | H33: =IFERROR(COUNTIF(FILLEULS!D7:D106,A33),0) | I33: =IFERROR(SUMPRODUCT((COMMISSIONS_PARRAINAGE!C7:C106=A33)*(COMMISSIONS_PARRAINAGE!H7:H106="Payé")*COMMISSIONS_PARRAINAGE!G7:G106),0) | J33: =IFERROR(IF(B33="","","Actif"),"—")
A34: LEMI-PARR-028 | G34: =IFERROR(IF(B34="","",IF(COUNTIF(FILLEULS!G7:G106,"*ÉLIGIBLE*")>0,"Actif","Inscrit")),"—") | H34: =IFERROR(COUNTIF(FILLEULS!D7:D106,A34),0) | I34: =IFERROR(SUMPRODUCT((COMMISSIONS_PARRAINAGE!C7:C106=A34)*(COMMISSIONS_PARRAINAGE!H7:H106="Payé")*COMMISSIONS_PARRAINAGE!G7:G106),0) | J34: =IFERROR(IF(B34="","","Actif"),"—")
A35: LEMI-PARR-029 | G35: =IFERROR(IF(B35="","",IF(COUNTIF(FILLEULS!G7:G106,"*ÉLIGIBLE*")>0,"Actif","Inscrit")),"—") | H35: =IFERROR(COUNTIF(FILLEULS!D7:D106,A35),0) | I35: =IFERROR(SUMPRODUCT((COMMISSIONS_PARRAINAGE!C7:C106=A35)*(COMMISSIONS_PARRAINAGE!H7:H106="Payé")*COMMISSIONS_PARRAINAGE!G7:G106),0) | J35: =IFERROR(IF(B35="","","Actif"),"—")
A36: LEMI-PARR-030 | G36: =IFERROR(IF(B36="","",IF(COUNTIF(FILLEULS!G7:G106,"*ÉLIGIBLE*")>0,"Actif","Inscrit")),"—") | H36: =IFERROR(COUNTIF(FILLEULS!D7:D106,A36),0) | I36: =IFERROR(SUMPRODUCT((COMMISSIONS_PARRAINAGE!C7:C106=A36)*(COMMISSIONS_PARRAINAGE!H7:H106="Payé")*COMMISSIONS_PARRAINAGE!G7:G106),0) | J36: =IFERROR(IF(B36="","","Actif"),"—")
A37: LEMI-PARR-031 | G37: =IFERROR(IF(B37="","",IF(COUNTIF(FILLEULS!G7:G106,"*ÉLIGIBLE*")>0,"Actif","Inscrit")),"—") | H37: =IFERROR(COUNTIF(FILLEULS!D7:D106,A37),0) | I37: =IFERROR(SUMPRODUCT((COMMISSIONS_PARRAINAGE!C7:C106=A37)*(COMMISSIONS_PARRAINAGE!H7:H106="Payé")*COMMISSIONS_PARRAINAGE!G7:G106),0) | J37: =IFERROR(IF(B37="","","Actif"),"—")
A38: LEMI-PARR-032 | G38: =IFERROR(IF(B38="","",IF(COUNTIF(FILLEULS!G7:G106,"*ÉLIGIBLE*")>0,"Actif","Inscrit")),"—") | H38: =IFERROR(COUNTIF(FILLEULS!D7:D106,A38),0) | I38: =IFERROR(SUMPRODUCT((COMMISSIONS_PARRAINAGE!C7:C106=A38)*(COMMISSIONS_PARRAINAGE!H7:H106="Payé")*COMMISSIONS_PARRAINAGE!G7:G106),0) | J38: =IFERROR(IF(B38="","","Actif"),"—")
A39: LEMI-PARR-033 | G39: =IFERROR(IF(B39="","",IF(COUNTIF(FILLEULS!G7:G106,"*ÉLIGIBLE*")>0,"Actif","Inscrit")),"—") | H39: =IFERROR(COUNTIF(FILLEULS!D7:D106,A39),0) | I39: =IFERROR(SUMPRODUCT((COMMISSIONS_PARRAINAGE!C7:C106=A39)*(COMMISSIONS_PARRAINAGE!H7:H106="Payé")*COMMISSIONS_PARRAINAGE!G7:G106),0) | J39: =IFERROR(IF(B39="","","Actif"),"—")
A40: LEMI-PARR-034 | G40: =IFERROR(IF(B40="","",IF(COUNTIF(FILLEULS!G7:G106,"*ÉLIGIBLE*")>0,"Actif","Inscrit")),"—") | H40: =IFERROR(COUNTIF(FILLEULS!D7:D106,A40),0) | I40: =IFERROR(SUMPRODUCT((COMMISSIONS_PARRAINAGE!C7:C106=A40)*(COMMISSIONS_PARRAINAGE!H7:H106="Payé")*COMMISSIONS_PARRAINAGE!G7:G106),0) | J40: =IFERROR(IF(B40="","","Actif"),"—")
A41: LEMI-PARR-035 | G41: =IFERROR(IF(B41="","",IF(COUNTIF(FILLEULS!G7:G106,"*ÉLIGIBLE*")>0,"Actif","Inscrit")),"—") | H41: =IFERROR(COUNTIF(FILLEULS!D7:D106,A41),0) | I41: =IFERROR(SUMPRODUCT((COMMISSIONS_PARRAINAGE!C7:C106=A41)*(COMMISSIONS_PARRAINAGE!H7:H106="Payé")*COMMISSIONS_PARRAINAGE!G7:G106),0) | J41: =IFERROR(IF(B41="","","Actif"),"—")
A42: LEMI-PARR-036 | G42: =IFERROR(IF(B42="","",IF(COUNTIF(FILLEULS!G7:G106,"*ÉLIGIBLE*")>0,"Actif","Inscrit")),"—") | H42: =IFERROR(COUNTIF(FILLEULS!D7:D106,A42),0) | I42: =IFERROR(SUMPRODUCT((COMMISSIONS_PARRAINAGE!C7:C106=A42)*(COMMISSIONS_PARRAINAGE!H7:H106="Payé")*COMMISSIONS_PARRAINAGE!G7:G106),0) | J42: =IFERROR(IF(B42="","","Actif"),"—")
A43: LEMI-PARR-037 | G43: =IFERROR(IF(B43="","",IF(COUNTIF(FILLEULS!G7:G106,"*ÉLIGIBLE*")>0,"Actif","Inscrit")),"—") | H43: =IFERROR(COUNTIF(FILLEULS!D7:D106,A43),0) | I43: =IFERROR(SUMPRODUCT((COMMISSIONS_PARRAINAGE!C7:C106=A43)*(COMMISSIONS_PARRAINAGE!H7:H106="Payé")*COMMISSIONS_PARRAINAGE!G7:G106),0) | J43: =IFERROR(IF(B43="","","Actif"),"—")
A44: LEMI-PARR-038 | G44: =IFERROR(IF(B44="","",IF(COUNTIF(FILLEULS!G7:G106,"*ÉLIGIBLE*")>0,"Actif","Inscrit")),"—") | H44: =IFERROR(COUNTIF(FILLEULS!D7:D106,A44),0) | I44: =IFERROR(SUMPRODUCT((COMMISSIONS_PARRAINAGE!C7:C106=A44)*(COMMISSIONS_PARRAINAGE!H7:H106="Payé")*COMMISSIONS_PARRAINAGE!G7:G106),0) | J44: =IFERROR(IF(B44="","","Actif"),"—")
A45: LEMI-PARR-039 | G45: =IFERROR(IF(B45="","",IF(COUNTIF(FILLEULS!G7:G106,"*ÉLIGIBLE*")>0,"Actif","Inscrit")),"—") | H45: =IFERROR(COUNTIF(FILLEULS!D7:D106,A45),0) | I45: =IFERROR(SUMPRODUCT((COMMISSIONS_PARRAINAGE!C7:C106=A45)*(COMMISSIONS_PARRAINAGE!H7:H106="Payé")*COMMISSIONS_PARRAINAGE!G7:G106),0) | J45: =IFERROR(IF(B45="","","Actif"),"—")
A46: LEMI-PARR-040 | G46: =IFERROR(IF(B46="","",IF(COUNTIF(FILLEULS!G7:G106,"*ÉLIGIBLE*")>0,"Actif","Inscrit")),"—") | H46: =IFERROR(COUNTIF(FILLEULS!D7:D106,A46),0) | I46: =IFERROR(SUMPRODUCT((COMMISSIONS_PARRAINAGE!C7:C106=A46)*(COMMISSIONS_PARRAINAGE!H7:H106="Payé")*COMMISSIONS_PARRAINAGE!G7:G106),0) | J46: =IFERROR(IF(B46="","","Actif"),"—")
A47: LEMI-PARR-041 | G47: =IFERROR(IF(B47="","",IF(COUNTIF(FILLEULS!G7:G106,"*ÉLIGIBLE*")>0,"Actif","Inscrit")),"—") | H47: =IFERROR(COUNTIF(FILLEULS!D7:D106,A47),0) | I47: =IFERROR(SUMPRODUCT((COMMISSIONS_PARRAINAGE!C7:C106=A47)*(COMMISSIONS_PARRAINAGE!H7:H106="Payé")*COMMISSIONS_PARRAINAGE!G7:G106),0) | J47: =IFERROR(IF(B47="","","Actif"),"—")
A48: LEMI-PARR-042 | G48: =IFERROR(IF(B48="","",IF(COUNTIF(FILLEULS!G7:G106,"*ÉLIGIBLE*")>0,"Actif","Inscrit")),"—") | H48: =IFERROR(COUNTIF(FILLEULS!D7:D106,A48),0) | I48: =IFERROR(SUMPRODUCT((COMMISSIONS_PARRAINAGE!C7:C106=A48)*(COMMISSIONS_PARRAINAGE!H7:H106="Payé")*COMMISSIONS_PARRAINAGE!G7:G106),0) | J48: =IFERROR(IF(B48="","","Actif"),"—")
A49: LEMI-PARR-043 | G49: =IFERROR(IF(B49="","",IF(COUNTIF(FILLEULS!G7:G106,"*ÉLIGIBLE*")>0,"Actif","Inscrit")),"—") | H49: =IFERROR(COUNTIF(FILLEULS!D7:D106,A49),0) | I49: =IFERROR(SUMPRODUCT((COMMISSIONS_PARRAINAGE!C7:C106=A49)*(COMMISSIONS_PARRAINAGE!H7:H106="Payé")*COMMISSIONS_PARRAINAGE!G7:G106),0) | J49: =IFERROR(IF(B49="","","Actif"),"—")
A50: LEMI-PARR-044 | G50: =IFERROR(IF(B50="","",IF(COUNTIF(FILLEULS!G7:G106,"*ÉLIGIBLE*")>0,"Actif","Inscrit")),"—") | H50: =IFERROR(COUNTIF(FILLEULS!D7:D106,A50),0) | I50: =IFERROR(SUMPRODUCT((COMMISSIONS_PARRAINAGE!C7:C106=A50)*(COMMISSIONS_PARRAINAGE!H7:H106="Payé")*COMMISSIONS_PARRAINAGE!G7:G106),0) | J50: =IFERROR(IF(B50="","","Actif"),"—")
A51: LEMI-PARR-045 | G51: =IFERROR(IF(B51="","",IF(COUNTIF(FILLEULS!G7:G106,"*ÉLIGIBLE*")>0,"Actif","Inscrit")),"—") | H51: =IFERROR(COUNTIF(FILLEULS!D7:D106,A51),0) | I51: =IFERROR(SUMPRODUCT((COMMISSIONS_PARRAINAGE!C7:C106=A51)*(COMMISSIONS_PARRAINAGE!H7:H106="Payé")*COMMISSIONS_PARRAINAGE!G7:G106),0) | J51: =IFERROR(IF(B51="","","Actif"),"—")
A52: LEMI-PARR-046 | G52: =IFERROR(IF(B52="","",IF(COUNTIF(FILLEULS!G7:G106,"*ÉLIGIBLE*")>0,"Actif","Inscrit")),"—") | H52: =IFERROR(COUNTIF(FILLEULS!D7:D106,A52),0) | I52: =IFERROR(SUMPRODUCT((COMMISSIONS_PARRAINAGE!C7:C106=A52)*(COMMISSIONS_PARRAINAGE!H7:H106="Payé")*COMMISSIONS_PARRAINAGE!G7:G106),0) | J52: =IFERROR(IF(B52="","","Actif"),"—")
A53: LEMI-PARR-047 | G53: =IFERROR(IF(B53="","",IF(COUNTIF(FILLEULS!G7:G106,"*ÉLIGIBLE*")>0,"Actif","Inscrit")),"—") | H53: =IFERROR(COUNTIF(FILLEULS!D7:D106,A53),0) | I53: =IFERROR(SUMPRODUCT((COMMISSIONS_PARRAINAGE!C7:C106=A53)*(COMMISSIONS_PARRAINAGE!H7:H106="Payé")*COMMISSIONS_PARRAINAGE!G7:G106),0) | J53: =IFERROR(IF(B53="","","Actif"),"—")
A54: LEMI-PARR-048 | G54: =IFERROR(IF(B54="","",IF(COUNTIF(FILLEULS!G7:G106,"*ÉLIGIBLE*")>0,"Actif","Inscrit")),"—") | H54: =IFERROR(COUNTIF(FILLEULS!D7:D106,A54),0) | I54: =IFERROR(SUMPRODUCT((COMMISSIONS_PARRAINAGE!C7:C106=A54)*(COMMISSIONS_PARRAINAGE!H7:H106="Payé")*COMMISSIONS_PARRAINAGE!G7:G106),0) | J54: =IFERROR(IF(B54="","","Actif"),"—")
A55: LEMI-PARR-049 | G55: =IFERROR(IF(B55="","",IF(COUNTIF(FILLEULS!G7:G106,"*ÉLIGIBLE*")>0,"Actif","Inscrit")),"—") | H55: =IFERROR(COUNTIF(FILLEULS!D7:D106,A55),0) | I55: =IFERROR(SUMPRODUCT((COMMISSIONS_PARRAINAGE!C7:C106=A55)*(COMMISSIONS_PARRAINAGE!H7:H106="Payé")*COMMISSIONS_PARRAINAGE!G7:G106),0) | J55: =IFERROR(IF(B55="","","Actif"),"—")
A56: LEMI-PARR-050 | G56: =IFERROR(IF(B56="","",IF(COUNTIF(FILLEULS!G7:G106,"*ÉLIGIBLE*")>0,"Actif","Inscrit")),"—") | H56: =IFERROR(COUNTIF(FILLEULS!D7:D106,A56),0) | I56: =IFERROR(SUMPRODUCT((COMMISSIONS_PARRAINAGE!C7:C106=A56)*(COMMISSIONS_PARRAINAGE!H7:H106="Payé")*COMMISSIONS_PARRAINAGE!G7:G106),0) | J56: =IFERROR(IF(B56="","","Actif"),"—")
A57: LEMI-PARR-051 | G57: =IFERROR(IF(B57="","",IF(COUNTIF(FILLEULS!G7:G106,"*ÉLIGIBLE*")>0,"Actif","Inscrit")),"—") | H57: =IFERROR(COUNTIF(FILLEULS!D7:D106,A57),0) | I57: =IFERROR(SUMPRODUCT((COMMISSIONS_PARRAINAGE!C7:C106=A57)*(COMMISSIONS_PARRAINAGE!H7:H106="Payé")*COMMISSIONS_PARRAINAGE!G7:G106),0) | J57: =IFERROR(IF(B57="","","Actif"),"—")
A58: LEMI-PARR-052 | G58: =IFERROR(IF(B58="","",IF(COUNTIF(FILLEULS!G7:G106,"*ÉLIGIBLE*")>0,"Actif","Inscrit")),"—") | H58: =IFERROR(COUNTIF(FILLEULS!D7:D106,A58),0) | I58: =IFERROR(SUMPRODUCT((COMMISSIONS_PARRAINAGE!C7:C106=A58)*(COMMISSIONS_PARRAINAGE!H7:H106="Payé")*COMMISSIONS_PARRAINAGE!G7:G106),0) | J58: =IFERROR(IF(B58="","","Actif"),"—")
A59: LEMI-PARR-053 | G59: =IFERROR(IF(B59="","",IF(COUNTIF(FILLEULS!G7:G106,"*ÉLIGIBLE*")>0,"Actif","Inscrit")),"—") | H59: =IFERROR(COUNTIF(FILLEULS!D7:D106,A59),0) | I59: =IFERROR(SUMPRODUCT((COMMISSIONS_PARRAINAGE!C7:C106=A59)*(COMMISSIONS_PARRAINAGE!H7:H106="Payé")*COMMISSIONS_PARRAINAGE!G7:G106),0) | J59: =IFERROR(IF(B59="","","Actif"),"—")
A60: LEMI-PARR-054 | G60: =IFERROR(IF(B60="","",IF(COUNTIF(FILLEULS!G7:G106,"*ÉLIGIBLE*")>0,"Actif","Inscrit")),"—") | H60: =IFERROR(COUNTIF(FILLEULS!D7:D106,A60),0) | I60: =IFERROR(SUMPRODUCT((COMMISSIONS_PARRAINAGE!C7:C106=A60)*(COMMISSIONS_PARRAINAGE!H7:H106="Payé")*COMMISSIONS_PARRAINAGE!G7:G106),0) | J60: =IFERROR(IF(B60="","","Actif"),"—")
A61: LEMI-PARR-055 | G61: =IFERROR(IF(B61="","",IF(COUNTIF(FILLEULS!G7:G106,"*ÉLIGIBLE*")>0,"Actif","Inscrit")),"—") | H61: =IFERROR(COUNTIF(FILLEULS!D7:D106,A61),0) | I61: =IFERROR(SUMPRODUCT((COMMISSIONS_PARRAINAGE!C7:C106=A61)*(COMMISSIONS_PARRAINAGE!H7:H106="Payé")*COMMISSIONS_PARRAINAGE!G7:G106),0) | J61: =IFERROR(IF(B61="","","Actif"),"—")
A62: LEMI-PARR-056 | G62: =IFERROR(IF(B62="","",IF(COUNTIF(FILLEULS!G7:G106,"*ÉLIGIBLE*")>0,"Actif","Inscrit")),"—") | H62: =IFERROR(COUNTIF(FILLEULS!D7:D106,A62),0) | I62: =IFERROR(SUMPRODUCT((COMMISSIONS_PARRAINAGE!C7:C106=A62)*(COMMISSIONS_PARRAINAGE!H7:H106="Payé")*COMMISSIONS_PARRAINAGE!G7:G106),0) | J62: =IFERROR(IF(B62="","","Actif"),"—")
A63: LEMI-PARR-057 | G63: =IFERROR(IF(B63="","",IF(COUNTIF(FILLEULS!G7:G106,"*ÉLIGIBLE*")>0,"Actif","Inscrit")),"—") | H63: =IFERROR(COUNTIF(FILLEULS!D7:D106,A63),0) | I63: =IFERROR(SUMPRODUCT((COMMISSIONS_PARRAINAGE!C7:C106=A63)*(COMMISSIONS_PARRAINAGE!H7:H106="Payé")*COMMISSIONS_PARRAINAGE!G7:G106),0) | J63: =IFERROR(IF(B63="","","Actif"),"—")
A64: LEMI-PARR-058 | G64: =IFERROR(IF(B64="","",IF(COUNTIF(FILLEULS!G7:G106,"*ÉLIGIBLE*")>0,"Actif","Inscrit")),"—") | H64: =IFERROR(COUNTIF(FILLEULS!D7:D106,A64),0) | I64: =IFERROR(SUMPRODUCT((COMMISSIONS_PARRAINAGE!C7:C106=A64)*(COMMISSIONS_PARRAINAGE!H7:H106="Payé")*COMMISSIONS_PARRAINAGE!G7:G106),0) | J64: =IFERROR(IF(B64="","","Actif"),"—")
A65: LEMI-PARR-059 | G65: =IFERROR(IF(B65="","",IF(COUNTIF(FILLEULS!G7:G106,"*ÉLIGIBLE*")>0,"Actif","Inscrit")),"—") | H65: =IFERROR(COUNTIF(FILLEULS!D7:D106,A65),0) | I65: =IFERROR(SUMPRODUCT((COMMISSIONS_PARRAINAGE!C7:C106=A65)*(COMMISSIONS_PARRAINAGE!H7:H106="Payé")*COMMISSIONS_PARRAINAGE!G7:G106),0) | J65: =IFERROR(IF(B65="","","Actif"),"—")
A66: LEMI-PARR-060 | G66: =IFERROR(IF(B66="","",IF(COUNTIF(FILLEULS!G7:G106,"*ÉLIGIBLE*")>0,"Actif","Inscrit")),"—") | H66: =IFERROR(COUNTIF(FILLEULS!D7:D106,A66),0) | I66: =IFERROR(SUMPRODUCT((COMMISSIONS_PARRAINAGE!C7:C106=A66)*(COMMISSIONS_PARRAINAGE!H7:H106="Payé")*COMMISSIONS_PARRAINAGE!G7:G106),0) | J66: =IFERROR(IF(B66="","","Actif"),"—")
A67: LEMI-PARR-061 | G67: =IFERROR(IF(B67="","",IF(COUNTIF(FILLEULS!G7:G106,"*ÉLIGIBLE*")>0,"Actif","Inscrit")),"—") | H67: =IFERROR(COUNTIF(FILLEULS!D7:D106,A67),0) | I67: =IFERROR(SUMPRODUCT((COMMISSIONS_PARRAINAGE!C7:C106=A67)*(COMMISSIONS_PARRAINAGE!H7:H106="Payé")*COMMISSIONS_PARRAINAGE!G7:G106),0) | J67: =IFERROR(IF(B67="","","Actif"),"—")
A68: LEMI-PARR-062 | G68: =IFERROR(IF(B68="","",IF(COUNTIF(FILLEULS!G7:G106,"*ÉLIGIBLE*")>0,"Actif","Inscrit")),"—") | H68: =IFERROR(COUNTIF(FILLEULS!D7:D106,A68),0) | I68: =IFERROR(SUMPRODUCT((COMMISSIONS_PARRAINAGE!C7:C106=A68)*(COMMISSIONS_PARRAINAGE!H7:H106="Payé")*COMMISSIONS_PARRAINAGE!G7:G106),0) | J68: =IFERROR(IF(B68="","","Actif"),"—")
A69: LEMI-PARR-063 | G69: =IFERROR(IF(B69="","",IF(COUNTIF(FILLEULS!G7:G106,"*ÉLIGIBLE*")>0,"Actif","Inscrit")),"—") | H69: =IFERROR(COUNTIF(FILLEULS!D7:D106,A69),0) | I69: =IFERROR(SUMPRODUCT((COMMISSIONS_PARRAINAGE!C7:C106=A69)*(COMMISSIONS_PARRAINAGE!H7:H106="Payé")*COMMISSIONS_PARRAINAGE!G7:G106),0) | J69: =IFERROR(IF(B69="","","Actif"),"—")
A70: LEMI-PARR-064 | G70: =IFERROR(IF(B70="","",IF(COUNTIF(FILLEULS!G7:G106,"*ÉLIGIBLE*")>0,"Actif","Inscrit")),"—") | H70: =IFERROR(COUNTIF(FILLEULS!D7:D106,A70),0) | I70: =IFERROR(SUMPRODUCT((COMMISSIONS_PARRAINAGE!C7:C106=A70)*(COMMISSIONS_PARRAINAGE!H7:H106="Payé")*COMMISSIONS_PARRAINAGE!G7:G106),0) | J70: =IFERROR(IF(B70="","","Actif"),"—")
A71: LEMI-PARR-065 | G71: =IFERROR(IF(B71="","",IF(COUNTIF(FILLEULS!G7:G106,"*ÉLIGIBLE*")>0,"Actif","Inscrit")),"—") | H71: =IFERROR(COUNTIF(FILLEULS!D7:D106,A71),0) | I71: =IFERROR(SUMPRODUCT((COMMISSIONS_PARRAINAGE!C7:C106=A71)*(COMMISSIONS_PARRAINAGE!H7:H106="Payé")*COMMISSIONS_PARRAINAGE!G7:G106),0) | J71: =IFERROR(IF(B71="","","Actif"),"—")
A72: LEMI-PARR-066 | G72: =IFERROR(IF(B72="","",IF(COUNTIF(FILLEULS!G7:G106,"*ÉLIGIBLE*")>0,"Actif","Inscrit")),"—") | H72: =IFERROR(COUNTIF(FILLEULS!D7:D106,A72),0) | I72: =IFERROR(SUMPRODUCT((COMMISSIONS_PARRAINAGE!C7:C106=A72)*(COMMISSIONS_PARRAINAGE!H7:H106="Payé")*COMMISSIONS_PARRAINAGE!G7:G106),0) | J72: =IFERROR(IF(B72="","","Actif"),"—")
A73: LEMI-PARR-067 | G73: =IFERROR(IF(B73="","",IF(COUNTIF(FILLEULS!G7:G106,"*ÉLIGIBLE*")>0,"Actif","Inscrit")),"—") | H73: =IFERROR(COUNTIF(FILLEULS!D7:D106,A73),0) | I73: =IFERROR(SUMPRODUCT((COMMISSIONS_PARRAINAGE!C7:C106=A73)*(COMMISSIONS_PARRAINAGE!H7:H106="Payé")*COMMISSIONS_PARRAINAGE!G7:G106),0) | J73: =IFERROR(IF(B73="","","Actif"),"—")
A74: LEMI-PARR-068 | G74: =IFERROR(IF(B74="","",IF(COUNTIF(FILLEULS!G7:G106,"*ÉLIGIBLE*")>0,"Actif","Inscrit")),"—") | H74: =IFERROR(COUNTIF(FILLEULS!D7:D106,A74),0) | I74: =IFERROR(SUMPRODUCT((COMMISSIONS_PARRAINAGE!C7:C106=A74)*(COMMISSIONS_PARRAINAGE!H7:H106="Payé")*COMMISSIONS_PARRAINAGE!G7:G106),0) | J74: =IFERROR(IF(B74="","","Actif"),"—")
A75: LEMI-PARR-069 | G75: =IFERROR(IF(B75="","",IF(COUNTIF(FILLEULS!G7:G106,"*ÉLIGIBLE*")>0,"Actif","Inscrit")),"—") | H75: =IFERROR(COUNTIF(FILLEULS!D7:D106,A75),0) | I75: =IFERROR(SUMPRODUCT((COMMISSIONS_PARRAINAGE!C7:C106=A75)*(COMMISSIONS_PARRAINAGE!H7:H106="Payé")*COMMISSIONS_PARRAINAGE!G7:G106),0) | J75: =IFERROR(IF(B75="","","Actif"),"—")
A76: LEMI-PARR-070 | G76: =IFERROR(IF(B76="","",IF(COUNTIF(FILLEULS!G7:G106,"*ÉLIGIBLE*")>0,"Actif","Inscrit")),"—") | H76: =IFERROR(COUNTIF(FILLEULS!D7:D106,A76),0) | I76: =IFERROR(SUMPRODUCT((COMMISSIONS_PARRAINAGE!C7:C106=A76)*(COMMISSIONS_PARRAINAGE!H7:H106="Payé")*COMMISSIONS_PARRAINAGE!G7:G106),0) | J76: =IFERROR(IF(B76="","","Actif"),"—")
A77: LEMI-PARR-071 | G77: =IFERROR(IF(B77="","",IF(COUNTIF(FILLEULS!G7:G106,"*ÉLIGIBLE*")>0,"Actif","Inscrit")),"—") | H77: =IFERROR(COUNTIF(FILLEULS!D7:D106,A77),0) | I77: =IFERROR(SUMPRODUCT((COMMISSIONS_PARRAINAGE!C7:C106=A77)*(COMMISSIONS_PARRAINAGE!H7:H106="Payé")*COMMISSIONS_PARRAINAGE!G7:G106),0) | J77: =IFERROR(IF(B77="","","Actif"),"—")
A78: LEMI-PARR-072 | G78: =IFERROR(IF(B78="","",IF(COUNTIF(FILLEULS!G7:G106,"*ÉLIGIBLE*")>0,"Actif","Inscrit")),"—") | H78: =IFERROR(COUNTIF(FILLEULS!D7:D106,A78),0) | I78: =IFERROR(SUMPRODUCT((COMMISSIONS_PARRAINAGE!C7:C106=A78)*(COMMISSIONS_PARRAINAGE!H7:H106="Payé")*COMMISSIONS_PARRAINAGE!G7:G106),0) | J78: =IFERROR(IF(B78="","","Actif"),"—")
A79: LEMI-PARR-073 | G79: =IFERROR(IF(B79="","",IF(COUNTIF(FILLEULS!G7:G106,"*ÉLIGIBLE*")>0,"Actif","Inscrit")),"—") | H79: =IFERROR(COUNTIF(FILLEULS!D7:D106,A79),0) | I79: =IFERROR(SUMPRODUCT((COMMISSIONS_PARRAINAGE!C7:C106=A79)*(COMMISSIONS_PARRAINAGE!H7:H106="Payé")*COMMISSIONS_PARRAINAGE!G7:G106),0) | J79: =IFERROR(IF(B79="","","Actif"),"—")
A80: LEMI-PARR-074 | G80: =IFERROR(IF(B80="","",IF(COUNTIF(FILLEULS!G7:G106,"*ÉLIGIBLE*")>0,"Actif","Inscrit")),"—") | H80: =IFERROR(COUNTIF(FILLEULS!D7:D106,A80),0) | I80: =IFERROR(SUMPRODUCT((COMMISSIONS_PARRAINAGE!C7:C106=A80)*(COMMISSIONS_PARRAINAGE!H7:H106="Payé")*COMMISSIONS_PARRAINAGE!G7:G106),0) | J80: =IFERROR(IF(B80="","","Actif"),"—")
A81: LEMI-PARR-075 | G81: =IFERROR(IF(B81="","",IF(COUNTIF(FILLEULS!G7:G106,"*ÉLIGIBLE*")>0,"Actif","Inscrit")),"—") | H81: =IFERROR(COUNTIF(FILLEULS!D7:D106,A81),0) | I81: =IFERROR(SUMPRODUCT((COMMISSIONS_PARRAINAGE!C7:C106=A81)*(COMMISSIONS_PARRAINAGE!H7:H106="Payé")*COMMISSIONS_PARRAINAGE!G7:G106),0) | J81: =IFERROR(IF(B81="","","Actif"),"—")
A82: LEMI-PARR-076 | G82: =IFERROR(IF(B82="","",IF(COUNTIF(FILLEULS!G7:G106,"*ÉLIGIBLE*")>0,"Actif","Inscrit")),"—") | H82: =IFERROR(COUNTIF(FILLEULS!D7:D106,A82),0) | I82: =IFERROR(SUMPRODUCT((COMMISSIONS_PARRAINAGE!C7:C106=A82)*(COMMISSIONS_PARRAINAGE!H7:H106="Payé")*COMMISSIONS_PARRAINAGE!G7:G106),0) | J82: =IFERROR(IF(B82="","","Actif"),"—")
A83: LEMI-PARR-077 | G83: =IFERROR(IF(B83="","",IF(COUNTIF(FILLEULS!G7:G106,"*ÉLIGIBLE*")>0,"Actif","Inscrit")),"—") | H83: =IFERROR(COUNTIF(FILLEULS!D7:D106,A83),0) | I83: =IFERROR(SUMPRODUCT((COMMISSIONS_PARRAINAGE!C7:C106=A83)*(COMMISSIONS_PARRAINAGE!H7:H106="Payé")*COMMISSIONS_PARRAINAGE!G7:G106),0) | J83: =IFERROR(IF(B83="","","Actif"),"—")
A84: LEMI-PARR-078 | G84: =IFERROR(IF(B84="","",IF(COUNTIF(FILLEULS!G7:G106,"*ÉLIGIBLE*")>0,"Actif","Inscrit")),"—") | H84: =IFERROR(COUNTIF(FILLEULS!D7:D106,A84),0) | I84: =IFERROR(SUMPRODUCT((COMMISSIONS_PARRAINAGE!C7:C106=A84)*(COMMISSIONS_PARRAINAGE!H7:H106="Payé")*COMMISSIONS_PARRAINAGE!G7:G106),0) | J84: =IFERROR(IF(B84="","","Actif"),"—")
A85: LEMI-PARR-079 | G85: =IFERROR(IF(B85="","",IF(COUNTIF(FILLEULS!G7:G106,"*ÉLIGIBLE*")>0,"Actif","Inscrit")),"—") | H85: =IFERROR(COUNTIF(FILLEULS!D7:D106,A85),0) | I85: =IFERROR(SUMPRODUCT((COMMISSIONS_PARRAINAGE!C7:C106=A85)*(COMMISSIONS_PARRAINAGE!H7:H106="Payé")*COMMISSIONS_PARRAINAGE!G7:G106),0) | J85: =IFERROR(IF(B85="","","Actif"),"—")
A86: LEMI-PARR-080 | G86: =IFERROR(IF(B86="","",IF(COUNTIF(FILLEULS!G7:G106,"*ÉLIGIBLE*")>0,"Actif","Inscrit")),"—") | H86: =IFERROR(COUNTIF(FILLEULS!D7:D106,A86),0) | I86: =IFERROR(SUMPRODUCT((COMMISSIONS_PARRAINAGE!C7:C106=A86)*(COMMISSIONS_PARRAINAGE!H7:H106="Payé")*COMMISSIONS_PARRAINAGE!G7:G106),0) | J86: =IFERROR(IF(B86="","","Actif"),"—")
A87: LEMI-PARR-081 | G87: =IFERROR(IF(B87="","",IF(COUNTIF(FILLEULS!G7:G106,"*ÉLIGIBLE*")>0,"Actif","Inscrit")),"—") | H87: =IFERROR(COUNTIF(FILLEULS!D7:D106,A87),0) | I87: =IFERROR(SUMPRODUCT((COMMISSIONS_PARRAINAGE!C7:C106=A87)*(COMMISSIONS_PARRAINAGE!H7:H106="Payé")*COMMISSIONS_PARRAINAGE!G7:G106),0) | J87: =IFERROR(IF(B87="","","Actif"),"—")
A88: LEMI-PARR-082 | G88: =IFERROR(IF(B88="","",IF(COUNTIF(FILLEULS!G7:G106,"*ÉLIGIBLE*")>0,"Actif","Inscrit")),"—") | H88: =IFERROR(COUNTIF(FILLEULS!D7:D106,A88),0) | I88: =IFERROR(SUMPRODUCT((COMMISSIONS_PARRAINAGE!C7:C106=A88)*(COMMISSIONS_PARRAINAGE!H7:H106="Payé")*COMMISSIONS_PARRAINAGE!G7:G106),0) | J88: =IFERROR(IF(B88="","","Actif"),"—")
A89: LEMI-PARR-083 | G89: =IFERROR(IF(B89="","",IF(COUNTIF(FILLEULS!G7:G106,"*ÉLIGIBLE*")>0,"Actif","Inscrit")),"—") | H89: =IFERROR(COUNTIF(FILLEULS!D7:D106,A89),0) | I89: =IFERROR(SUMPRODUCT((COMMISSIONS_PARRAINAGE!C7:C106=A89)*(COMMISSIONS_PARRAINAGE!H7:H106="Payé")*COMMISSIONS_PARRAINAGE!G7:G106),0) | J89: =IFERROR(IF(B89="","","Actif"),"—")
A90: LEMI-PARR-084 | G90: =IFERROR(IF(B90="","",IF(COUNTIF(FILLEULS!G7:G106,"*ÉLIGIBLE*")>0,"Actif","Inscrit")),"—") | H90: =IFERROR(COUNTIF(FILLEULS!D7:D106,A90),0) | I90: =IFERROR(SUMPRODUCT((COMMISSIONS_PARRAINAGE!C7:C106=A90)*(COMMISSIONS_PARRAINAGE!H7:H106="Payé")*COMMISSIONS_PARRAINAGE!G7:G106),0) | J90: =IFERROR(IF(B90="","","Actif"),"—")
A91: LEMI-PARR-085 | G91: =IFERROR(IF(B91="","",IF(COUNTIF(FILLEULS!G7:G106,"*ÉLIGIBLE*")>0,"Actif","Inscrit")),"—") | H91: =IFERROR(COUNTIF(FILLEULS!D7:D106,A91),0) | I91: =IFERROR(SUMPRODUCT((COMMISSIONS_PARRAINAGE!C7:C106=A91)*(COMMISSIONS_PARRAINAGE!H7:H106="Payé")*COMMISSIONS_PARRAINAGE!G7:G106),0) | J91: =IFERROR(IF(B91="","","Actif"),"—")
A92: LEMI-PARR-086 | G92: =IFERROR(IF(B92="","",IF(COUNTIF(FILLEULS!G7:G106,"*ÉLIGIBLE*")>0,"Actif","Inscrit")),"—") | H92: =IFERROR(COUNTIF(FILLEULS!D7:D106,A92),0) | I92: =IFERROR(SUMPRODUCT((COMMISSIONS_PARRAINAGE!C7:C106=A92)*(COMMISSIONS_PARRAINAGE!H7:H106="Payé")*COMMISSIONS_PARRAINAGE!G7:G106),0) | J92: =IFERROR(IF(B92="","","Actif"),"—")
A93: LEMI-PARR-087 | G93: =IFERROR(IF(B93="","",IF(COUNTIF(FILLEULS!G7:G106,"*ÉLIGIBLE*")>0,"Actif","Inscrit")),"—") | H93: =IFERROR(COUNTIF(FILLEULS!D7:D106,A93),0) | I93: =IFERROR(SUMPRODUCT((COMMISSIONS_PARRAINAGE!C7:C106=A93)*(COMMISSIONS_PARRAINAGE!H7:H106="Payé")*COMMISSIONS_PARRAINAGE!G7:G106),0) | J93: =IFERROR(IF(B93="","","Actif"),"—")
A94: LEMI-PARR-088 | G94: =IFERROR(IF(B94="","",IF(COUNTIF(FILLEULS!G7:G106,"*ÉLIGIBLE*")>0,"Actif","Inscrit")),"—") | H94: =IFERROR(COUNTIF(FILLEULS!D7:D106,A94),0) | I94: =IFERROR(SUMPRODUCT((COMMISSIONS_PARRAINAGE!C7:C106=A94)*(COMMISSIONS_PARRAINAGE!H7:H106="Payé")*COMMISSIONS_PARRAINAGE!G7:G106),0) | J94: =IFERROR(IF(B94="","","Actif"),"—")
A95: LEMI-PARR-089 | G95: =IFERROR(IF(B95="","",IF(COUNTIF(FILLEULS!G7:G106,"*ÉLIGIBLE*")>0,"Actif","Inscrit")),"—") | H95: =IFERROR(COUNTIF(FILLEULS!D7:D106,A95),0) | I95: =IFERROR(SUMPRODUCT((COMMISSIONS_PARRAINAGE!C7:C106=A95)*(COMMISSIONS_PARRAINAGE!H7:H106="Payé")*COMMISSIONS_PARRAINAGE!G7:G106),0) | J95: =IFERROR(IF(B95="","","Actif"),"—")
A96: LEMI-PARR-090 | G96: =IFERROR(IF(B96="","",IF(COUNTIF(FILLEULS!G7:G106,"*ÉLIGIBLE*")>0,"Actif","Inscrit")),"—") | H96: =IFERROR(COUNTIF(FILLEULS!D7:D106,A96),0) | I96: =IFERROR(SUMPRODUCT((COMMISSIONS_PARRAINAGE!C7:C106=A96)*(COMMISSIONS_PARRAINAGE!H7:H106="Payé")*COMMISSIONS_PARRAINAGE!G7:G106),0) | J96: =IFERROR(IF(B96="","","Actif"),"—")
A97: LEMI-PARR-091 | G97: =IFERROR(IF(B97="","",IF(COUNTIF(FILLEULS!G7:G106,"*ÉLIGIBLE*")>0,"Actif","Inscrit")),"—") | H97: =IFERROR(COUNTIF(FILLEULS!D7:D106,A97),0) | I97: =IFERROR(SUMPRODUCT((COMMISSIONS_PARRAINAGE!C7:C106=A97)*(COMMISSIONS_PARRAINAGE!H7:H106="Payé")*COMMISSIONS_PARRAINAGE!G7:G106),0) | J97: =IFERROR(IF(B97="","","Actif"),"—")
A98: LEMI-PARR-092 | G98: =IFERROR(IF(B98="","",IF(COUNTIF(FILLEULS!G7:G106,"*ÉLIGIBLE*")>0,"Actif","Inscrit")),"—") | H98: =IFERROR(COUNTIF(FILLEULS!D7:D106,A98),0) | I98: =IFERROR(SUMPRODUCT((COMMISSIONS_PARRAINAGE!C7:C106=A98)*(COMMISSIONS_PARRAINAGE!H7:H106="Payé")*COMMISSIONS_PARRAINAGE!G7:G106),0) | J98: =IFERROR(IF(B98="","","Actif"),"—")
A99: LEMI-PARR-093 | G99: =IFERROR(IF(B99="","",IF(COUNTIF(FILLEULS!G7:G106,"*ÉLIGIBLE*")>0,"Actif","Inscrit")),"—") | H99: =IFERROR(COUNTIF(FILLEULS!D7:D106,A99),0) | I99: =IFERROR(SUMPRODUCT((COMMISSIONS_PARRAINAGE!C7:C106=A99)*(COMMISSIONS_PARRAINAGE!H7:H106="Payé")*COMMISSIONS_PARRAINAGE!G7:G106),0) | J99: =IFERROR(IF(B99="","","Actif"),"—")
A100: LEMI-PARR-094 | G100: =IFERROR(IF(B100="","",IF(COUNTIF(FILLEULS!G7:G106,"*ÉLIGIBLE*")>0,"Actif","Inscrit")),"—") | H100: =IFERROR(COUNTIF(FILLEULS!D7:D106,A100),0) | I100: =IFERROR(SUMPRODUCT((COMMISSIONS_PARRAINAGE!C7:C106=A100)*(COMMISSIONS_PARRAINAGE!H7:H106="Payé")*COMMISSIONS_PARRAINAGE!G7:G106),0) | J100: =IFERROR(IF(B100="","","Actif"),"—")
...

Sheet FILLEULS
A1: 👥 FILLEULS DÉCLARÉS — CONTRÔLE D'ÉLIGIBILITÉ | LEMI SARL | BRASUS v3.2
A2: Plage nommée : LEMI_PARRAINAGE_FILLEULS | Colonnes A-F : saisie | Colonnes G-J : contrôle auto 🔒
A3: 🚨 VERROUS ANTI-FRAUDE ACTIFS : V1 (unicité téléphone) | V2 (déclaration au 1er contact) | V5 (signaux faibles)
A5: ✏️ ZONE SAISIE | G5: 🔒 CONTRÔLE AUTOMATIQUE (Verrous 1-2-5)
A6: ID FILLEUL | B6: NOM PRÉNOM FILLEUL | C6: TÉLÉPHONE FILLEUL | D6: CODE PARRAIN DÉCLARÉ | E6: DATE DÉCLARATION | F6: DATE 1ER CONTACT (CRM) | G6: ÉLIGIBILITÉ (AUTO) | H6: STATUT CONTRAT (CRM) | I6: MONTANT ACOMPTE (CRM) | J6: SIGNAL ALERTE (V5)
A7: FIL-001 | B7: Nom et prénom | C7: 07 XX XX XX XX | D7: LEMI-PARR-XXX | E7: JJ/MM/AAAA | F7: JJ/MM/AAAA (depuis CRM) | G7: =IFERROR(IF(B7=""," ",IF(COUNTIF(C$7:C$6,C7)+COUNTIF(REGISTRE_PARRAINS!C7:C106,C7)>0,"🚫 REFUSÉ — NUMÉRO DÉJÀ ENREGISTRÉ",IF(AND(E7<>"",F7<>"",E7<>F7),"🚫 REFUSÉ — CODE DÉCLARÉ HORS DÉLAI","✅ ÉLIGIBLE")))," ") | H7: =IFERROR(IF(B7="","","À vérifier CRM")," ") | I7: =IFERROR(IF(B7="","","Réf. CRM")," ") | J7: =IFERROR(IF(B7=""," ",IF(COUNTIF(REGISTRE_PARRAINS!C7:C106,C7)>0,"⚠️ MÊME ADRESSE/TEL QUE PARRAIN"," "))," ")
A8: FIL-002 | G8: =IFERROR(IF(B8=""," ",IF(COUNTIF(C$7:C$7,C8)+COUNTIF(REGISTRE_PARRAINS!C7:C106,C8)>0,"🚫 REFUSÉ — NUMÉRO DÉJÀ ENREGISTRÉ",IF(AND(E8<>"",F8<>"",E8<>F8),"🚫 REFUSÉ — CODE DÉCLARÉ HORS DÉLAI","✅ ÉLIGIBLE")))," ") | H8: =IFERROR(IF(B8="","","À vérifier CRM")," ") | I8: =IFERROR(IF(B8="","","Réf. CRM")," ") | J8: =IFERROR(IF(B8=""," ",IF(COUNTIF(REGISTRE_PARRAINS!C7:C106,C8)>0,"⚠️ MÊME ADRESSE/TEL QUE PARRAIN"," "))," ")
A9: FIL-003 | G9: =IFERROR(IF(B9=""," ",IF(COUNTIF(C$7:C$8,C9)+COUNTIF(REGISTRE_PARRAINS!C7:C106,C9)>0,"🚫 REFUSÉ — NUMÉRO DÉJÀ ENREGISTRÉ",IF(AND(E9<>"",F9<>"",E9<>F9),"🚫 REFUSÉ — CODE DÉCLARÉ HORS DÉLAI","✅ ÉLIGIBLE")))," ") | H9: =IFERROR(IF(B9="","","À vérifier CRM")," ") | I9: =IFERROR(IF(B9="","","Réf. CRM")," ") | J9: =IFERROR(IF(B9=""," ",IF(COUNTIF(REGISTRE_PARRAINS!C7:C106,C9)>0,"⚠️ MÊME ADRESSE/TEL QUE PARRAIN"," "))," ")
A10: FIL-004 | G10: =IFERROR(IF(B10=""," ",IF(COUNTIF(C$7:C$9,C10)+COUNTIF(REGISTRE_PARRAINS!C7:C106,C10)>0,"🚫 REFUSÉ — NUMÉRO DÉJÀ ENREGISTRÉ",IF(AND(E10<>"",F10<>"",E10<>F10),"🚫 REFUSÉ — CODE DÉCLARÉ HORS DÉLAI","✅ ÉLIGIBLE")))," ") | H10: =IFERROR(IF(B10="","","À vérifier CRM")," ") | I10: =IFERROR(IF(B10="","","Réf. CRM")," ") | J10: =IFERROR(IF(B10=""," ",IF(COUNTIF(REGISTRE_PARRAINS!C7:C106,C10)>0,"⚠️ MÊME ADRESSE/TEL QUE PARRAIN"," "))," ")
A11: FIL-005 | G11: =IFERROR(IF(B11=""," ",IF(COUNTIF(C$7:C$10,C11)+COUNTIF(REGISTRE_PARRAINS!C7:C106,C11)>0,"🚫 REFUSÉ — NUMÉRO DÉJÀ ENREGISTRÉ",IF(AND(E11<>"",F11<>"",E11<>F11),"🚫 REFUSÉ — CODE DÉCLARÉ HORS DÉLAI","✅ ÉLIGIBLE")))," ") | H11: =IFERROR(IF(B11="","","À vérifier CRM")," ") | I11: =IFERROR(IF(B11="","","Réf. CRM")," ") | J11: =IFERROR(IF(B11=""," ",IF(COUNTIF(REGISTRE_PARRAINS!C7:C106,C11)>0,"⚠️ MÊME ADRESSE/TEL QUE PARRAIN"," "))," ")
A12: FIL-006 | G12: =IFERROR(IF(B12=""," ",IF(COUNTIF(C$7:C$11,C12)+COUNTIF(REGISTRE_PARRAINS!C7:C106,C12)>0,"🚫 REFUSÉ — NUMÉRO DÉJÀ ENREGISTRÉ",IF(AND(E12<>"",F12<>"",E12<>F12),"🚫 REFUSÉ — CODE DÉCLARÉ HORS DÉLAI","✅ ÉLIGIBLE")))," ") | H12: =IFERROR(IF(B12="","","À vérifier CRM")," ") | I12: =IFERROR(IF(B12="","","Réf. CRM")," ") | J12: =IFERROR(IF(B12=""," ",IF(COUNTIF(REGISTRE_PARRAINS!C7:C106,C12)>0,"⚠️ MÊME ADRESSE/TEL QUE PARRAIN"," "))," ")
A13: FIL-007 | G13: =IFERROR(IF(B13=""," ",IF(COUNTIF(C$7:C$12,C13)+COUNTIF(REGISTRE_PARRAINS!C7:C106,C13)>0,"🚫 REFUSÉ — NUMÉRO DÉJÀ ENREGISTRÉ",IF(AND(E13<>"",F13<>"",E13<>F13),"🚫 REFUSÉ — CODE DÉCLARÉ HORS DÉLAI","✅ ÉLIGIBLE")))," ") | H13: =IFERROR(IF(B13="","","À vérifier CRM")," ") | I13: =IFERROR(IF(B13="","","Réf. CRM")," ") | J13: =IFERROR(IF(B13=""," ",IF(COUNTIF(REGISTRE_PARRAINS!C7:C106,C13)>0,"⚠️ MÊME ADRESSE/TEL QUE PARRAIN"," "))," ")
A14: FIL-008 | G14: =IFERROR(IF(B14=""," ",IF(COUNTIF(C$7:C$13,C14)+COUNTIF(REGISTRE_PARRAINS!C7:C106,C14)>0,"🚫 REFUSÉ — NUMÉRO DÉJÀ ENREGISTRÉ",IF(AND(E14<>"",F14<>"",E14<>F14),"🚫 REFUSÉ — CODE DÉCLARÉ HORS DÉLAI","✅ ÉLIGIBLE")))," ") | H14: =IFERROR(IF(B14="","","À vérifier CRM")," ") | I14: =IFERROR(IF(B14="","","Réf. CRM")," ") | J14: =IFERROR(IF(B14=""," ",IF(COUNTIF(REGISTRE_PARRAINS!C7:C106,C14)>0,"⚠️ MÊME ADRESSE/TEL QUE PARRAIN"," "))," ")
A15: FIL-009 | G15: =IFERROR(IF(B15=""," ",IF(COUNTIF(C$7:C$14,C15)+COUNTIF(REGISTRE_PARRAINS!C7:C106,C15)>0,"🚫 REFUSÉ — NUMÉRO DÉJÀ ENREGISTRÉ",IF(AND(E15<>"",F15<>"",E15<>F15),"🚫 REFUSÉ — CODE DÉCLARÉ HORS DÉLAI","✅ ÉLIGIBLE")))," ") | H15: =IFERROR(IF(B15="","","À vérifier CRM")," ") | I15: =IFERROR(IF(B15="","","Réf. CRM")," ") | J15: =IFERROR(IF(B15=""," ",IF(COUNTIF(REGISTRE_PARRAINS!C7:C106,C15)>0,"⚠️ MÊME ADRESSE/TEL QUE PARRAIN"," "))," ")
A16: FIL-010 | G16: =IFERROR(IF(B16=""," ",IF(COUNTIF(C$7:C$15,C16)+COUNTIF(REGISTRE_PARRAINS!C7:C106,C16)>0,"🚫 REFUSÉ — NUMÉRO DÉJÀ ENREGISTRÉ",IF(AND(E16<>"",F16<>"",E16<>F16),"🚫 REFUSÉ — CODE DÉCLARÉ HORS DÉLAI","✅ ÉLIGIBLE")))," ") | H16: =IFERROR(IF(B16="","","À vérifier CRM")," ") | I16: =IFERROR(IF(B16="","","Réf. CRM")," ") | J16: =IFERROR(IF(B16=""," ",IF(COUNTIF(REGISTRE_PARRAINS!C7:C106,C16)>0,"⚠️ MÊME ADRESSE/TEL QUE PARRAIN"," "))," ")
A17: FIL-011 | G17: =IFERROR(IF(B17=""," ",IF(COUNTIF(C$7:C$16,C17)+COUNTIF(REGISTRE_PARRAINS!C7:C106,C17)>0,"🚫 REFUSÉ — NUMÉRO DÉJÀ ENREGISTRÉ",IF(AND(E17<>"",F17<>"",E17<>F17),"🚫 REFUSÉ — CODE DÉCLARÉ HORS DÉLAI","✅ ÉLIGIBLE")))," ") | H17: =IFERROR(IF(B17="","","À vérifier CRM")," ") | I17: =IFERROR(IF(B17="","","Réf. CRM")," ") | J17: =IFERROR(IF(B17=""," ",IF(COUNTIF(REGISTRE_PARRAINS!C7:C106,C17)>0,"⚠️ MÊME ADRESSE/TEL QUE PARRAIN"," "))," ")
A18: FIL-012 | G18: =IFERROR(IF(B18=""," ",IF(COUNTIF(C$7:C$17,C18)+COUNTIF(REGISTRE_PARRAINS!C7:C106,C18)>0,"🚫 REFUSÉ — NUMÉRO DÉJÀ ENREGISTRÉ",IF(AND(E18<>"",F18<>"",E18<>F18),"🚫 REFUSÉ — CODE DÉCLARÉ HORS DÉLAI","✅ ÉLIGIBLE")))," ") | H18: =IFERROR(IF(B18="","","À vérifier CRM")," ") | I18: =IFERROR(IF(B18="","","Réf. CRM")," ") | J18: =IFERROR(IF(B18=""," ",IF(COUNTIF(REGISTRE_PARRAINS!C7:C106,C18)>0,"⚠️ MÊME ADRESSE/TEL QUE PARRAIN"," "))," ")
A19: FIL-013 | G19: =IFERROR(IF(B19=""," ",IF(COUNTIF(C$7:C$18,C19)+COUNTIF(REGISTRE_PARRAINS!C7:C106,C19)>0,"🚫 REFUSÉ — NUMÉRO DÉJÀ ENREGISTRÉ",IF(AND(E19<>"",F19<>"",E19<>F19),"🚫 REFUSÉ — CODE DÉCLARÉ HORS DÉLAI","✅ ÉLIGIBLE")))," ") | H19: =IFERROR(IF(B19="","","À vérifier CRM")," ") | I19: =IFERROR(IF(B19="","","Réf. CRM")," ") | J19: =IFERROR(IF(B19=""," ",IF(COUNTIF(REGISTRE_PARRAINS!C7:C106,C19)>0,"⚠️ MÊME ADRESSE/TEL QUE PARRAIN"," "))," ")
A20: FIL-014 | G20: =IFERROR(IF(B20=""," ",IF(COUNTIF(C$7:C$19,C20)+COUNTIF(REGISTRE_PARRAINS!C7:C106,C20)>0,"🚫 REFUSÉ — NUMÉRO DÉJÀ ENREGISTRÉ",IF(AND(E20<>"",F20<>"",E20<>F20),"🚫 REFUSÉ — CODE DÉCLARÉ HORS DÉLAI","✅ ÉLIGIBLE")))," ") | H20: =IFERROR(IF(B20="","","À vérifier CRM")," ") | I20: =IFERROR(IF(B20="","","Réf. CRM")," ") | J20: =IFERROR(IF(B20=""," ",IF(COUNTIF(REGISTRE_PARRAINS!C7:C106,C20)>0,"⚠️ MÊME ADRESSE/TEL QUE PARRAIN"," "))," ")
A21: FIL-015 | G21: =IFERROR(IF(B21=""," ",IF(COUNTIF(C$7:C$20,C21)+COUNTIF(REGISTRE_PARRAINS!C7:C106,C21)>0,"🚫 REFUSÉ — NUMÉRO DÉJÀ ENREGISTRÉ",IF(AND(E21<>"",F21<>"",E21<>F21),"🚫 REFUSÉ — CODE DÉCLARÉ HORS DÉLAI","✅ ÉLIGIBLE")))," ") | H21: =IFERROR(IF(B21="","","À vérifier CRM")," ") | I21: =IFERROR(IF(B21="","","Réf. CRM")," ") | J21: =IFERROR(IF(B21=""," ",IF(COUNTIF(REGISTRE_PARRAINS!C7:C106,C21)>0,"⚠️ MÊME ADRESSE/TEL QUE PARRAIN"," "))," ")
A22: FIL-016 | G22: =IFERROR(IF(B22=""," ",IF(COUNTIF(C$7:C$21,C22)+COUNTIF(REGISTRE_PARRAINS!C7:C106,C22)>0,"🚫 REFUSÉ — NUMÉRO DÉJÀ ENREGISTRÉ",IF(AND(E22<>"",F22<>"",E22<>F22),"🚫 REFUSÉ — CODE DÉCLARÉ HORS DÉLAI","✅ ÉLIGIBLE")))," ") | H22: =IFERROR(IF(B22="","","À vérifier CRM")," ") | I22: =IFERROR(IF(B22="","","Réf. CRM")," ") | J22: =IFERROR(IF(B22=""," ",IF(COUNTIF(REGISTRE_PARRAINS!C7:C106,C22)>0,"⚠️ MÊME ADRESSE/TEL QUE PARRAIN"," "))," ")
A23: FIL-017 | G23: =IFERROR(IF(B23=""," ",IF(COUNTIF(C$7:C$22,C23)+COUNTIF(REGISTRE_PARRAINS!C7:C106,C23)>0,"🚫 REFUSÉ — NUMÉRO DÉJÀ ENREGISTRÉ",IF(AND(E23<>"",F23<>"",E23<>F23),"🚫 REFUSÉ — CODE DÉCLARÉ HORS DÉLAI","✅ ÉLIGIBLE")))," ") | H23: =IFERROR(IF(B23="","","À vérifier CRM")," ") | I23: =IFERROR(IF(B23="","","Réf. CRM")," ") | J23: =IFERROR(IF(B23=""," ",IF(COUNTIF(REGISTRE_PARRAINS!C7:C106,C23)>0,"⚠️ MÊME ADRESSE/TEL QUE PARRAIN"," "))," ")
A24: FIL-018 | G24: =IFERROR(IF(B24=""," ",IF(COUNTIF(C$7:C$23,C24)+COUNTIF(REGISTRE_PARRAINS!C7:C106,C24)>0,"🚫 REFUSÉ — NUMÉRO DÉJÀ ENREGISTRÉ",IF(AND(E24<>"",F24<>"",E24<>F24),"🚫 REFUSÉ — CODE DÉCLARÉ HORS DÉLAI","✅ ÉLIGIBLE")))," ") | H24: =IFERROR(IF(B24="","","À vérifier CRM")," ") | I24: =IFERROR(IF(B24="","","Réf. CRM")," ") | J24: =IFERROR(IF(B24=""," ",IF(COUNTIF(REGISTRE_PARRAINS!C7:C106,C24)>0,"⚠️ MÊME ADRESSE/TEL QUE PARRAIN"," "))," ")
A25: FIL-019 | G25: =IFERROR(IF(B25=""," ",IF(COUNTIF(C$7:C$24,C25)+COUNTIF(REGISTRE_PARRAINS!C7:C106,C25)>0,"🚫 REFUSÉ — NUMÉRO DÉJÀ ENREGISTRÉ",IF(AND(E25<>"",F25<>"",E25<>F25),"🚫 REFUSÉ — CODE DÉCLARÉ HORS DÉLAI","✅ ÉLIGIBLE")))," ") | H25: =IFERROR(IF(B25="","","À vérifier CRM")," ") | I25: =IFERROR(IF(B25="","","Réf. CRM")," ") | J25: =IFERROR(IF(B25=""," ",IF(COUNTIF(REGISTRE_PARRAINS!C7:C106,C25)>0,"⚠️ MÊME ADRESSE/TEL QUE PARRAIN"," "))," ")
A26: FIL-020 | G26: =IFERROR(IF(B26=""," ",IF(COUNTIF(C$7:C$25,C26)+COUNTIF(REGISTRE_PARRAINS!C7:C106,C26)>0,"🚫 REFUSÉ — NUMÉRO DÉJÀ ENREGISTRÉ",IF(AND(E26<>"",F26<>"",E26<>F26),"🚫 REFUSÉ — CODE DÉCLARÉ HORS DÉLAI","✅ ÉLIGIBLE")))," ") | H26: =IFERROR(IF(B26="","","À vérifier CRM")," ") | I26: =IFERROR(IF(B26="","","Réf. CRM")," ") | J26: =IFERROR(IF(B26=""," ",IF(COUNTIF(REGISTRE_PARRAINS!C7:C106,C26)>0,"⚠️ MÊME ADRESSE/TEL QUE PARRAIN"," "))," ")
A27: FIL-021 | G27: =IFERROR(IF(B27=""," ",IF(COUNTIF(C$7:C$26,C27)+COUNTIF(REGISTRE_PARRAINS!C7:C106,C27)>0,"🚫 REFUSÉ — NUMÉRO DÉJÀ ENREGISTRÉ",IF(AND(E27<>"",F27<>"",E27<>F27),"🚫 REFUSÉ — CODE DÉCLARÉ HORS DÉLAI","✅ ÉLIGIBLE")))," ") | H27: =IFERROR(IF(B27="","","À vérifier CRM")," ") | I27: =IFERROR(IF(B27="","","Réf. CRM")," ") | J27: =IFERROR(IF(B27=""," ",IF(COUNTIF(REGISTRE_PARRAINS!C7:C106,C27)>0,"⚠️ MÊME ADRESSE/TEL QUE PARRAIN"," "))," ")
A28: FIL-022 | G28: =IFERROR(IF(B28=""," ",IF(COUNTIF(C$7:C$27,C28)+COUNTIF(REGISTRE_PARRAINS!C7:C106,C28)>0,"🚫 REFUSÉ — NUMÉRO DÉJÀ ENREGISTRÉ",IF(AND(E28<>"",F28<>"",E28<>F28),"🚫 REFUSÉ — CODE DÉCLARÉ HORS DÉLAI","✅ ÉLIGIBLE")))," ") | H28: =IFERROR(IF(B28="","","À vérifier CRM")," ") | I28: =IFERROR(IF(B28="","","Réf. CRM")," ") | J28: =IFERROR(IF(B28=""," ",IF(COUNTIF(REGISTRE_PARRAINS!C7:C106,C28)>0,"⚠️ MÊME ADRESSE/TEL QUE PARRAIN"," "))," ")
A29: FIL-023 | G29: =IFERROR(IF(B29=""," ",IF(COUNTIF(C$7:C$28,C29)+COUNTIF(REGISTRE_PARRAINS!C7:C106,C29)>0,"🚫 REFUSÉ — NUMÉRO DÉJÀ ENREGISTRÉ",IF(AND(E29<>"",F29<>"",E29<>F29),"🚫 REFUSÉ — CODE DÉCLARÉ HORS DÉLAI","✅ ÉLIGIBLE")))," ") | H29: =IFERROR(IF(B29="","","À vérifier CRM")," ") | I29: =IFERROR(IF(B29="","","Réf. CRM")," ") | J29: =IFERROR(IF(B29=""," ",IF(COUNTIF(REGISTRE_PARRAINS!C7:C106,C29)>0,"⚠️ MÊME ADRESSE/TEL QUE PARRAIN"," "))," ")
A30: FIL-024 | G30: =IFERROR(IF(B30=""," ",IF(COUNTIF(C$7:C$29,C30)+COUNTIF(REGISTRE_PARRAINS!C7:C106,C30)>0,"🚫 REFUSÉ — NUMÉRO DÉJÀ ENREGISTRÉ",IF(AND(E30<>"",F30<>"",E30<>F30),"🚫 REFUSÉ — CODE DÉCLARÉ HORS DÉLAI","✅ ÉLIGIBLE")))," ") | H30: =IFERROR(IF(B30="","","À vérifier CRM")," ") | I30: =IFERROR(IF(B30="","","Réf. CRM")," ") | J30: =IFERROR(IF(B30=""," ",IF(COUNTIF(REGISTRE_PARRAINS!C7:C106,C30)>0,"⚠️ MÊME ADRESSE/TEL QUE PARRAIN"," "))," ")
A31: FIL-025 | G31: =IFERROR(IF(B31=""," ",IF(COUNTIF(C$7:C$30,C31)+COUNTIF(REGISTRE_PARRAINS!C7:C106,C31)>0,"🚫 REFUSÉ — NUMÉRO DÉJÀ ENREGISTRÉ",IF(AND(E31<>"",F31<>"",E31<>F31),"🚫 REFUSÉ — CODE DÉCLARÉ HORS DÉLAI","✅ ÉLIGIBLE")))," ") | H31: =IFERROR(IF(B31="","","À vérifier CRM")," ") | I31: =IFERROR(IF(B31="","","Réf. CRM")," ") | J31: =IFERROR(IF(B31=""," ",IF(COUNTIF(REGISTRE_PARRAINS!C7:C106,C31)>0,"⚠️ MÊME ADRESSE/TEL QUE PARRAIN"," "))," ")
A32: FIL-026 | G32: =IFERROR(IF(B32=""," ",IF(COUNTIF(C$7:C$31,C32)+COUNTIF(REGISTRE_PARRAINS!C7:C106,C32)>0,"🚫 REFUSÉ — NUMÉRO DÉJÀ ENREGISTRÉ",IF(AND(E32<>"",F32<>"",E32<>F32),"🚫 REFUSÉ — CODE DÉCLARÉ HORS DÉLAI","✅ ÉLIGIBLE")))," ") | H32: =IFERROR(IF(B32="","","À vérifier CRM")," ") | I32: =IFERROR(IF(B32="","","Réf. CRM")," ") | J32: =IFERROR(IF(B32=""," ",IF(COUNTIF(REGISTRE_PARRAINS!C7:C106,C32)>0,"⚠️ MÊME ADRESSE/TEL QUE PARRAIN"," "))," ")
A33: FIL-027 | G33: =IFERROR(IF(B33=""," ",IF(COUNTIF(C$7:C$32,C33)+COUNTIF(REGISTRE_PARRAINS!C7:C106,C33)>0,"🚫 REFUSÉ — NUMÉRO DÉJÀ ENREGISTRÉ",IF(AND(E33<>"",F33<>"",E33<>F33),"🚫 REFUSÉ — CODE DÉCLARÉ HORS DÉLAI","✅ ÉLIGIBLE")))," ") | H33: =IFERROR(IF(B33="","","À vérifier CRM")," ") | I33: =IFERROR(IF(B33="","","Réf. CRM")," ") | J33: =IFERROR(IF(B33=""," ",IF(COUNTIF(REGISTRE_PARRAINS!C7:C106,C33)>0,"⚠️ MÊME ADRESSE/TEL QUE PARRAIN"," "))," ")
A34: FIL-028 | G34: =IFERROR(IF(B34=""," ",IF(COUNTIF(C$7:C$33,C34)+COUNTIF(REGISTRE_PARRAINS!C7:C106,C34)>0,"🚫 REFUSÉ — NUMÉRO DÉJÀ ENREGISTRÉ",IF(AND(E34<>"",F34<>"",E34<>F34),"🚫 REFUSÉ — CODE DÉCLARÉ HORS DÉLAI","✅ ÉLIGIBLE")))," ") | H34: =IFERROR(IF(B34="","","À vérifier CRM")," ") | I34: =IFERROR(IF(B34="","","Réf. CRM")," ") | J34: =IFERROR(IF(B34=""," ",IF(COUNTIF(REGISTRE_PARRAINS!C7:C106,C34)>0,"⚠️ MÊME ADRESSE/TEL QUE PARRAIN"," "))," ")
A35: FIL-029 | G35: =IFERROR(IF(B35=""," ",IF(COUNTIF(C$7:C$34,C35)+COUNTIF(REGISTRE_PARRAINS!C7:C106,C35)>0,"🚫 REFUSÉ — NUMÉRO DÉJÀ ENREGISTRÉ",IF(AND(E35<>"",F35<>"",E35<>F35),"🚫 REFUSÉ — CODE DÉCLARÉ HORS DÉLAI","✅ ÉLIGIBLE")))," ") | H35: =IFERROR(IF(B35="","","À vérifier CRM")," ") | I35: =IFERROR(IF(B35="","","Réf. CRM")," ") | J35: =IFERROR(IF(B35=""," ",IF(COUNTIF(REGISTRE_PARRAINS!C7:C106,C35)>0,"⚠️ MÊME ADRESSE/TEL QUE PARRAIN"," "))," ")
A36: FIL-030 | G36: =IFERROR(IF(B36=""," ",IF(COUNTIF(C$7:C$35,C36)+COUNTIF(REGISTRE_PARRAINS!C7:C106,C36)>0,"🚫 REFUSÉ — NUMÉRO DÉJÀ ENREGISTRÉ",IF(AND(E36<>"",F36<>"",E36<>F36),"🚫 REFUSÉ — CODE DÉCLARÉ HORS DÉLAI","✅ ÉLIGIBLE")))," ") | H36: =IFERROR(IF(B36="","","À vérifier CRM")," ") | I36: =IFERROR(IF(B36="","","Réf. CRM")," ") | J36: =IFERROR(IF(B36=""," ",IF(COUNTIF(REGISTRE_PARRAINS!C7:C106,C36)>0,"⚠️ MÊME ADRESSE/TEL QUE PARRAIN"," "))," ")
A37: FIL-031 | G37: =IFERROR(IF(B37=""," ",IF(COUNTIF(C$7:C$36,C37)+COUNTIF(REGISTRE_PARRAINS!C7:C106,C37)>0,"🚫 REFUSÉ — NUMÉRO DÉJÀ ENREGISTRÉ",IF(AND(E37<>"",F37<>"",E37<>F37),"🚫 REFUSÉ — CODE DÉCLARÉ HORS DÉLAI","✅ ÉLIGIBLE")))," ") | H37: =IFERROR(IF(B37="","","À vérifier CRM")," ") | I37: =IFERROR(IF(B37="","","Réf. CRM")," ") | J37: =IFERROR(IF(B37=""," ",IF(COUNTIF(REGISTRE_PARRAINS!C7:C106,C37)>0,"⚠️ MÊME ADRESSE/TEL QUE PARRAIN"," "))," ")
A38: FIL-032 | G38: =IFERROR(IF(B38=""," ",IF(COUNTIF(C$7:C$37,C38)+COUNTIF(REGISTRE_PARRAINS!C7:C106,C38)>0,"🚫 REFUSÉ — NUMÉRO DÉJÀ ENREGISTRÉ",IF(AND(E38<>"",F38<>"",E38<>F38),"🚫 REFUSÉ — CODE DÉCLARÉ HORS DÉLAI","✅ ÉLIGIBLE")))," ") | H38: =IFERROR(IF(B38="","","À vérifier CRM")," ") | I38: =IFERROR(IF(B38="","","Réf. CRM")," ") | J38: =IFERROR(IF(B38=""," ",IF(COUNTIF(REGISTRE_PARRAINS!C7:C106,C38)>0,"⚠️ MÊME ADRESSE/TEL QUE PARRAIN"," "))," ")
A39: FIL-033 | G39: =IFERROR(IF(B39=""," ",IF(COUNTIF(C$7:C$38,C39)+COUNTIF(REGISTRE_PARRAINS!C7:C106,C39)>0,"🚫 REFUSÉ — NUMÉRO DÉJÀ ENREGISTRÉ",IF(AND(E39<>"",F39<>"",E39<>F39),"🚫 REFUSÉ — CODE DÉCLARÉ HORS DÉLAI","✅ ÉLIGIBLE")))," ") | H39: =IFERROR(IF(B39="","","À vérifier CRM")," ") | I39: =IFERROR(IF(B39="","","Réf. CRM")," ") | J39: =IFERROR(IF(B39=""," ",IF(COUNTIF(REGISTRE_PARRAINS!C7:C106,C39)>0,"⚠️ MÊME ADRESSE/TEL QUE PARRAIN"," "))," ")
A40: FIL-034 | G40: =IFERROR(IF(B40=""," ",IF(COUNTIF(C$7:C$39,C40)+COUNTIF(REGISTRE_PARRAINS!C7:C106,C40)>0,"🚫 REFUSÉ — NUMÉRO DÉJÀ ENREGISTRÉ",IF(AND(E40<>"",F40<>"",E40<>F40),"🚫 REFUSÉ — CODE DÉCLARÉ HORS DÉLAI","✅ ÉLIGIBLE")))," ") | H40: =IFERROR(IF(B40="","","À vérifier CRM")," ") | I40: =IFERROR(IF(B40="","","Réf. CRM")," ") | J40: =IFERROR(IF(B40=""," ",IF(COUNTIF(REGISTRE_PARRAINS!C7:C106,C40)>0,"⚠️ MÊME ADRESSE/TEL QUE PARRAIN"," "))," ")
A41: FIL-035 | G41: =IFERROR(IF(B41=""," ",IF(COUNTIF(C$7:C$40,C41)+COUNTIF(REGISTRE_PARRAINS!C7:C106,C41)>0,"🚫 REFUSÉ — NUMÉRO DÉJÀ ENREGISTRÉ",IF(AND(E41<>"",F41<>"",E41<>F41),"🚫 REFUSÉ — CODE DÉCLARÉ HORS DÉLAI","✅ ÉLIGIBLE")))," ") | H41: =IFERROR(IF(B41="","","À vérifier CRM")," ") | I41: =IFERROR(IF(B41="","","Réf. CRM")," ") | J41: =IFERROR(IF(B41=""," ",IF(COUNTIF(REGISTRE_PARRAINS!C7:C106,C41)>0,"⚠️ MÊME ADRESSE/TEL QUE PARRAIN"," "))," ")
A42: FIL-036 | G42: =IFERROR(IF(B42=""," ",IF(COUNTIF(C$7:C$41,C42)+COUNTIF(REGISTRE_PARRAINS!C7:C106,C42)>0,"🚫 REFUSÉ — NUMÉRO DÉJÀ ENREGISTRÉ",IF(AND(E42<>"",F42<>"",E42<>F42),"🚫 REFUSÉ — CODE DÉCLARÉ HORS DÉLAI","✅ ÉLIGIBLE")))," ") | H42: =IFERROR(IF(B42="","","À vérifier CRM")," ") | I42: =IFERROR(IF(B42="","","Réf. CRM")," ") | J42: =IFERROR(IF(B42=""," ",IF(COUNTIF(REGISTRE_PARRAINS!C7:C106,C42)>0,"⚠️ MÊME ADRESSE/TEL QUE PARRAIN"," "))," ")
A43: FIL-037 | G43: =IFERROR(IF(B43=""," ",IF(COUNTIF(C$7:C$42,C43)+COUNTIF(REGISTRE_PARRAINS!C7:C106,C43)>0,"🚫 REFUSÉ — NUMÉRO DÉJÀ ENREGISTRÉ",IF(AND(E43<>"",F43<>"",E43<>F43),"🚫 REFUSÉ — CODE DÉCLARÉ HORS DÉLAI","✅ ÉLIGIBLE")))," ") | H43: =IFERROR(IF(B43="","","À vérifier CRM")," ") | I43: =IFERROR(IF(B43="","","Réf. CRM")," ") | J43: =IFERROR(IF(B43=""," ",IF(COUNTIF(REGISTRE_PARRAINS!C7:C106,C43)>0,"⚠️ MÊME ADRESSE/TEL QUE PARRAIN"," "))," ")
A44: FIL-038 | G44: =IFERROR(IF(B44=""," ",IF(COUNTIF(C$7:C$43,C44)+COUNTIF(REGISTRE_PARRAINS!C7:C106,C44)>0,"🚫 REFUSÉ — NUMÉRO DÉJÀ ENREGISTRÉ",IF(AND(E44<>"",F44<>"",E44<>F44),"🚫 REFUSÉ — CODE DÉCLARÉ HORS DÉLAI","✅ ÉLIGIBLE")))," ") | H44: =IFERROR(IF(B44="","","À vérifier CRM")," ") | I44: =IFERROR(IF(B44="","","Réf. CRM")," ") | J44: =IFERROR(IF(B44=""," ",IF(COUNTIF(REGISTRE_PARRAINS!C7:C106,C44)>0,"⚠️ MÊME ADRESSE/TEL QUE PARRAIN"," "))," ")
A45: FIL-039 | G45: =IFERROR(IF(B45=""," ",IF(COUNTIF(C$7:C$44,C45)+COUNTIF(REGISTRE_PARRAINS!C7:C106,C45)>0,"🚫 REFUSÉ — NUMÉRO DÉJÀ ENREGISTRÉ",IF(AND(E45<>"",F45<>"",E45<>F45),"🚫 REFUSÉ — CODE DÉCLARÉ HORS DÉLAI","✅ ÉLIGIBLE")))," ") | H45: =IFERROR(IF(B45="","","À vérifier CRM")," ") | I45: =IFERROR(IF(B45="","","Réf. CRM")," ") | J45: =IFERROR(IF(B45=""," ",IF(COUNTIF(REGISTRE_PARRAINS!C7:C106,C45)>0,"⚠️ MÊME ADRESSE/TEL QUE PARRAIN"," "))," ")
A46: FIL-040 | G46: =IFERROR(IF(B46=""," ",IF(COUNTIF(C$7:C$45,C46)+COUNTIF(REGISTRE_PARRAINS!C7:C106,C46)>0,"🚫 REFUSÉ — NUMÉRO DÉJÀ ENREGISTRÉ",IF(AND(E46<>"",F46<>"",E46<>F46),"🚫 REFUSÉ — CODE DÉCLARÉ HORS DÉLAI","✅ ÉLIGIBLE")))," ") | H46: =IFERROR(IF(B46="","","À vérifier CRM")," ") | I46: =IFERROR(IF(B46="","","Réf. CRM")," ") | J46: =IFERROR(IF(B46=""," ",IF(COUNTIF(REGISTRE_PARRAINS!C7:C106,C46)>0,"⚠️ MÊME ADRESSE/TEL QUE PARRAIN"," "))," ")
A47: FIL-041 | G47: =IFERROR(IF(B47=""," ",IF(COUNTIF(C$7:C$46,C47)+COUNTIF(REGISTRE_PARRAINS!C7:C106,C47)>0,"🚫 REFUSÉ — NUMÉRO DÉJÀ ENREGISTRÉ",IF(AND(E47<>"",F47<>"",E47<>F47),"🚫 REFUSÉ — CODE DÉCLARÉ HORS DÉLAI","✅ ÉLIGIBLE")))," ") | H47: =IFERROR(IF(B47="","","À vérifier CRM")," ") | I47: =IFERROR(IF(B47="","","Réf. CRM")," ") | J47: =IFERROR(IF(B47=""," ",IF(COUNTIF(REGISTRE_PARRAINS!C7:C106,C47)>0,"⚠️ MÊME ADRESSE/TEL QUE PARRAIN"," "))," ")
A48: FIL-042 | G48: =IFERROR(IF(B48=""," ",IF(COUNTIF(C$7:C$47,C48)+COUNTIF(REGISTRE_PARRAINS!C7:C106,C48)>0,"🚫 REFUSÉ — NUMÉRO DÉJÀ ENREGISTRÉ",IF(AND(E48<>"",F48<>"",E48<>F48),"🚫 REFUSÉ — CODE DÉCLARÉ HORS DÉLAI","✅ ÉLIGIBLE")))," ") | H48: =IFERROR(IF(B48="","","À vérifier CRM")," ") | I48: =IFERROR(IF(B48="","","Réf. CRM")," ") | J48: =IFERROR(IF(B48=""," ",IF(COUNTIF(REGISTRE_PARRAINS!C7:C106,C48)>0,"⚠️ MÊME ADRESSE/TEL QUE PARRAIN"," "))," ")
A49: FIL-043 | G49: =IFERROR(IF(B49=""," ",IF(COUNTIF(C$7:C$48,C49)+COUNTIF(REGISTRE_PARRAINS!C7:C106,C49)>0,"🚫 REFUSÉ — NUMÉRO DÉJÀ ENREGISTRÉ",IF(AND(E49<>"",F49<>"",E49<>F49),"🚫 REFUSÉ — CODE DÉCLARÉ HORS DÉLAI","✅ ÉLIGIBLE")))," ") | H49: =IFERROR(IF(B49="","","À vérifier CRM")," ") | I49: =IFERROR(IF(B49="","","Réf. CRM")," ") | J49: =IFERROR(IF(B49=""," ",IF(COUNTIF(REGISTRE_PARRAINS!C7:C106,C49)>0,"⚠️ MÊME ADRESSE/TEL QUE PARRAIN"," "))," ")
A50: FIL-044 | G50: =IFERROR(IF(B50=""," ",IF(COUNTIF(C$7:C$49,C50)+COUNTIF(REGISTRE_PARRAINS!C7:C106,C50)>0,"🚫 REFUSÉ — NUMÉRO DÉJÀ ENREGISTRÉ",IF(AND(E50<>"",F50<>"",E50<>F50),"🚫 REFUSÉ — CODE DÉCLARÉ HORS DÉLAI","✅ ÉLIGIBLE")))," ") | H50: =IFERROR(IF(B50="","","À vérifier CRM")," ") | I50: =IFERROR(IF(B50="","","Réf. CRM")," ") | J50: =IFERROR(IF(B50=""," ",IF(COUNTIF(REGISTRE_PARRAINS!C7:C106,C50)>0,"⚠️ MÊME ADRESSE/TEL QUE PARRAIN"," "))," ")
A51: FIL-045 | G51: =IFERROR(IF(B51=""," ",IF(COUNTIF(C$7:C$50,C51)+COUNTIF(REGISTRE_PARRAINS!C7:C106,C51)>0,"🚫 REFUSÉ — NUMÉRO DÉJÀ ENREGISTRÉ",IF(AND(E51<>"",F51<>"",E51<>F51),"🚫 REFUSÉ — CODE DÉCLARÉ HORS DÉLAI","✅ ÉLIGIBLE")))," ") | H51: =IFERROR(IF(B51="","","À vérifier CRM")," ") | I51: =IFERROR(IF(B51="","","Réf. CRM")," ") | J51: =IFERROR(IF(B51=""," ",IF(COUNTIF(REGISTRE_PARRAINS!C7:C106,C51)>0,"⚠️ MÊME ADRESSE/TEL QUE PARRAIN"," "))," ")
A52: FIL-046 | G52: =IFERROR(IF(B52=""," ",IF(COUNTIF(C$7:C$51,C52)+COUNTIF(REGISTRE_PARRAINS!C7:C106,C52)>0,"🚫 REFUSÉ — NUMÉRO DÉJÀ ENREGISTRÉ",IF(AND(E52<>"",F52<>"",E52<>F52),"🚫 REFUSÉ — CODE DÉCLARÉ HORS DÉLAI","✅ ÉLIGIBLE")))," ") | H52: =IFERROR(IF(B52="","","À vérifier CRM")," ") | I52: =IFERROR(IF(B52="","","Réf. CRM")," ") | J52: =IFERROR(IF(B52=""," ",IF(COUNTIF(REGISTRE_PARRAINS!C7:C106,C52)>0,"⚠️ MÊME ADRESSE/TEL QUE PARRAIN"," "))," ")
A53: FIL-047 | G53: =IFERROR(IF(B53=""," ",IF(COUNTIF(C$7:C$52,C53)+COUNTIF(REGISTRE_PARRAINS!C7:C106,C53)>0,"🚫 REFUSÉ — NUMÉRO DÉJÀ ENREGISTRÉ",IF(AND(E53<>"",F53<>"",E53<>F53),"🚫 REFUSÉ — CODE DÉCLARÉ HORS DÉLAI","✅ ÉLIGIBLE")))," ") | H53: =IFERROR(IF(B53="","","À vérifier CRM")," ") | I53: =IFERROR(IF(B53="","","Réf. CRM")," ") | J53: =IFERROR(IF(B53=""," ",IF(COUNTIF(REGISTRE_PARRAINS!C7:C106,C53)>0,"⚠️ MÊME ADRESSE/TEL QUE PARRAIN"," "))," ")
A54: FIL-048 | G54: =IFERROR(IF(B54=""," ",IF(COUNTIF(C$7:C$53,C54)+COUNTIF(REGISTRE_PARRAINS!C7:C106,C54)>0,"🚫 REFUSÉ — NUMÉRO DÉJÀ ENREGISTRÉ",IF(AND(E54<>"",F54<>"",E54<>F54),"🚫 REFUSÉ — CODE DÉCLARÉ HORS DÉLAI","✅ ÉLIGIBLE")))," ") | H54: =IFERROR(IF(B54="","","À vérifier CRM")," ") | I54: =IFERROR(IF(B54="","","Réf. CRM")," ") | J54: =IFERROR(IF(B54=""," ",IF(COUNTIF(REGISTRE_PARRAINS!C7:C106,C54)>0,"⚠️ MÊME ADRESSE/TEL QUE PARRAIN"," "))," ")
A55: FIL-049 | G55: =IFERROR(IF(B55=""," ",IF(COUNTIF(C$7:C$54,C55)+COUNTIF(REGISTRE_PARRAINS!C7:C106,C55)>0,"🚫 REFUSÉ — NUMÉRO DÉJÀ ENREGISTRÉ",IF(AND(E55<>"",F55<>"",E55<>F55),"🚫 REFUSÉ — CODE DÉCLARÉ HORS DÉLAI","✅ ÉLIGIBLE")))," ") | H55: =IFERROR(IF(B55="","","À vérifier CRM")," ") | I55: =IFERROR(IF(B55="","","Réf. CRM")," ") | J55: =IFERROR(IF(B55=""," ",IF(COUNTIF(REGISTRE_PARRAINS!C7:C106,C55)>0,"⚠️ MÊME ADRESSE/TEL QUE PARRAIN"," "))," ")
A56: FIL-050 | G56: =IFERROR(IF(B56=""," ",IF(COUNTIF(C$7:C$55,C56)+COUNTIF(REGISTRE_PARRAINS!C7:C106,C56)>0,"🚫 REFUSÉ — NUMÉRO DÉJÀ ENREGISTRÉ",IF(AND(E56<>"",F56<>"",E56<>F56),"🚫 REFUSÉ — CODE DÉCLARÉ HORS DÉLAI","✅ ÉLIGIBLE")))," ") | H56: =IFERROR(IF(B56="","","À vérifier CRM")," ") | I56: =IFERROR(IF(B56="","","Réf. CRM")," ") | J56: =IFERROR(IF(B56=""," ",IF(COUNTIF(REGISTRE_PARRAINS!C7:C106,C56)>0,"⚠️ MÊME ADRESSE/TEL QUE PARRAIN"," "))," ")
A57: FIL-051 | G57: =IFERROR(IF(B57=""," ",IF(COUNTIF(C$7:C$56,C57)+COUNTIF(REGISTRE_PARRAINS!C7:C106,C57)>0,"🚫 REFUSÉ — NUMÉRO DÉJÀ ENREGISTRÉ",IF(AND(E57<>"",F57<>"",E57<>F57),"🚫 REFUSÉ — CODE DÉCLARÉ HORS DÉLAI","✅ ÉLIGIBLE")))," ") | H57: =IFERROR(IF(B57="","","À vérifier CRM")," ") | I57: =IFERROR(IF(B57="","","Réf. CRM")," ") | J57: =IFERROR(IF(B57=""," ",IF(COUNTIF(REGISTRE_PARRAINS!C7:C106,C57)>0,"⚠️ MÊME ADRESSE/TEL QUE PARRAIN"," "))," ")
A58: FIL-052 | G58: =IFERROR(IF(B58=""," ",IF(COUNTIF(C$7:C$57,C58)+COUNTIF(REGISTRE_PARRAINS!C7:C106,C58)>0,"🚫 REFUSÉ — NUMÉRO DÉJÀ ENREGISTRÉ",IF(AND(E58<>"",F58<>"",E58<>F58),"🚫 REFUSÉ — CODE DÉCLARÉ HORS DÉLAI","✅ ÉLIGIBLE")))," ") | H58: =IFERROR(IF(B58="","","À vérifier CRM")," ") | I58: =IFERROR(IF(B58="","","Réf. CRM")," ") | J58: =IFERROR(IF(B58=""," ",IF(COUNTIF(REGISTRE_PARRAINS!C7:C106,C58)>0,"⚠️ MÊME ADRESSE/TEL QUE PARRAIN"," "))," ")
A59: FIL-053 | G59: =IFERROR(IF(B59=""," ",IF(COUNTIF(C$7:C$58,C59)+COUNTIF(REGISTRE_PARRAINS!C7:C106,C59)>0,"🚫 REFUSÉ — NUMÉRO DÉJÀ ENREGISTRÉ",IF(AND(E59<>"",F59<>"",E59<>F59),"🚫 REFUSÉ — CODE DÉCLARÉ HORS DÉLAI","✅ ÉLIGIBLE")))," ") | H59: =IFERROR(IF(B59="","","À vérifier CRM")," ") | I59: =IFERROR(IF(B59="","","Réf. CRM")," ") | J59: =IFERROR(IF(B59=""," ",IF(COUNTIF(REGISTRE_PARRAINS!C7:C106,C59)>0,"⚠️ MÊME ADRESSE/TEL QUE PARRAIN"," "))," ")
A60: FIL-054 | G60: =IFERROR(IF(B60=""," ",IF(COUNTIF(C$7:C$59,C60)+COUNTIF(REGISTRE_PARRAINS!C7:C106,C60)>0,"🚫 REFUSÉ — NUMÉRO DÉJÀ ENREGISTRÉ",IF(AND(E60<>"",F60<>"",E60<>F60),"🚫 REFUSÉ — CODE DÉCLARÉ HORS DÉLAI","✅ ÉLIGIBLE")))," ") | H60: =IFERROR(IF(B60="","","À vérifier CRM")," ") | I60: =IFERROR(IF(B60="","","Réf. CRM")," ") | J60: =IFERROR(IF(B60=""," ",IF(COUNTIF(REGISTRE_PARRAINS!C7:C106,C60)>0,"⚠️ MÊME ADRESSE/TEL QUE PARRAIN"," "))," ")
A61: FIL-055 | G61: =IFERROR(IF(B61=""," ",IF(COUNTIF(C$7:C$60,C61)+COUNTIF(REGISTRE_PARRAINS!C7:C106,C61)>0,"🚫 REFUSÉ — NUMÉRO DÉJÀ ENREGISTRÉ",IF(AND(E61<>"",F61<>"",E61<>F61),"🚫 REFUSÉ — CODE DÉCLARÉ HORS DÉLAI","✅ ÉLIGIBLE")))," ") | H61: =IFERROR(IF(B61="","","À vérifier CRM")," ") | I61: =IFERROR(IF(B61="","","Réf. CRM")," ") | J61: =IFERROR(IF(B61=""," ",IF(COUNTIF(REGISTRE_PARRAINS!C7:C106,C61)>0,"⚠️ MÊME ADRESSE/TEL QUE PARRAIN"," "))," ")
A62: FIL-056 | G62: =IFERROR(IF(B62=""," ",IF(COUNTIF(C$7:C$61,C62)+COUNTIF(REGISTRE_PARRAINS!C7:C106,C62)>0,"🚫 REFUSÉ — NUMÉRO DÉJÀ ENREGISTRÉ",IF(AND(E62<>"",F62<>"",E62<>F62),"🚫 REFUSÉ — CODE DÉCLARÉ HORS DÉLAI","✅ ÉLIGIBLE")))," ") | H62: =IFERROR(IF(B62="","","À vérifier CRM")," ") | I62: =IFERROR(IF(B62="","","Réf. CRM")," ") | J62: =IFERROR(IF(B62=""," ",IF(COUNTIF(REGISTRE_PARRAINS!C7:C106,C62)>0,"⚠️ MÊME ADRESSE/TEL QUE PARRAIN"," "))," ")
A63: FIL-057 | G63: =IFERROR(IF(B63=""," ",IF(COUNTIF(C$7:C$62,C63)+COUNTIF(REGISTRE_PARRAINS!C7:C106,C63)>0,"🚫 REFUSÉ — NUMÉRO DÉJÀ ENREGISTRÉ",IF(AND(E63<>"",F63<>"",E63<>F63),"🚫 REFUSÉ — CODE DÉCLARÉ HORS DÉLAI","✅ ÉLIGIBLE")))," ") | H63: =IFERROR(IF(B63="","","À vérifier CRM")," ") | I63: =IFERROR(IF(B63="","","Réf. CRM")," ") | J63: =IFERROR(IF(B63=""," ",IF(COUNTIF(REGISTRE_PARRAINS!C7:C106,C63)>0,"⚠️ MÊME ADRESSE/TEL QUE PARRAIN"," "))," ")
A64: FIL-058 | G64: =IFERROR(IF(B64=""," ",IF(COUNTIF(C$7:C$63,C64)+COUNTIF(REGISTRE_PARRAINS!C7:C106,C64)>0,"🚫 REFUSÉ — NUMÉRO DÉJÀ ENREGISTRÉ",IF(AND(E64<>"",F64<>"",E64<>F64),"🚫 REFUSÉ — CODE DÉCLARÉ HORS DÉLAI","✅ ÉLIGIBLE")))," ") | H64: =IFERROR(IF(B64="","","À vérifier CRM")," ") | I64: =IFERROR(IF(B64="","","Réf. CRM")," ") | J64: =IFERROR(IF(B64=""," ",IF(COUNTIF(REGISTRE_PARRAINS!C7:C106,C64)>0,"⚠️ MÊME ADRESSE/TEL QUE PARRAIN"," "))," ")
A65: FIL-059 | G65: =IFERROR(IF(B65=""," ",IF(COUNTIF(C$7:C$64,C65)+COUNTIF(REGISTRE_PARRAINS!C7:C106,C65)>0,"🚫 REFUSÉ — NUMÉRO DÉJÀ ENREGISTRÉ",IF(AND(E65<>"",F65<>"",E65<>F65),"🚫 REFUSÉ — CODE DÉCLARÉ HORS DÉLAI","✅ ÉLIGIBLE")))," ") | H65: =IFERROR(IF(B65="","","À vérifier CRM")," ") | I65: =IFERROR(IF(B65="","","Réf. CRM")," ") | J65: =IFERROR(IF(B65=""," ",IF(COUNTIF(REGISTRE_PARRAINS!C7:C106,C65)>0,"⚠️ MÊME ADRESSE/TEL QUE PARRAIN"," "))," ")
A66: FIL-060 | G66: =IFERROR(IF(B66=""," ",IF(COUNTIF(C$7:C$65,C66)+COUNTIF(REGISTRE_PARRAINS!C7:C106,C66)>0,"🚫 REFUSÉ — NUMÉRO DÉJÀ ENREGISTRÉ",IF(AND(E66<>"",F66<>"",E66<>F66),"🚫 REFUSÉ — CODE DÉCLARÉ HORS DÉLAI","✅ ÉLIGIBLE")))," ") | H66: =IFERROR(IF(B66="","","À vérifier CRM")," ") | I66: =IFERROR(IF(B66="","","Réf. CRM")," ") | J66: =IFERROR(IF(B66=""," ",IF(COUNTIF(REGISTRE_PARRAINS!C7:C106,C66)>0,"⚠️ MÊME ADRESSE/TEL QUE PARRAIN"," "))," ")
A67: FIL-061 | G67: =IFERROR(IF(B67=""," ",IF(COUNTIF(C$7:C$66,C67)+COUNTIF(REGISTRE_PARRAINS!C7:C106,C67)>0,"🚫 REFUSÉ — NUMÉRO DÉJÀ ENREGISTRÉ",IF(AND(E67<>"",F67<>"",E67<>F67),"🚫 REFUSÉ — CODE DÉCLARÉ HORS DÉLAI","✅ ÉLIGIBLE")))," ") | H67: =IFERROR(IF(B67="","","À vérifier CRM")," ") | I67: =IFERROR(IF(B67="","","Réf. CRM")," ") | J67: =IFERROR(IF(B67=""," ",IF(COUNTIF(REGISTRE_PARRAINS!C7:C106,C67)>0,"⚠️ MÊME ADRESSE/TEL QUE PARRAIN"," "))," ")
A68: FIL-062 | G68: =IFERROR(IF(B68=""," ",IF(COUNTIF(C$7:C$67,C68)+COUNTIF(REGISTRE_PARRAINS!C7:C106,C68)>0,"🚫 REFUSÉ — NUMÉRO DÉJÀ ENREGISTRÉ",IF(AND(E68<>"",F68<>"",E68<>F68),"🚫 REFUSÉ — CODE DÉCLARÉ HORS DÉLAI","✅ ÉLIGIBLE")))," ") | H68: =IFERROR(IF(B68="","","À vérifier CRM")," ") | I68: =IFERROR(IF(B68="","","Réf. CRM")," ") | J68: =IFERROR(IF(B68=""," ",IF(COUNTIF(REGISTRE_PARRAINS!C7:C106,C68)>0,"⚠️ MÊME ADRESSE/TEL QUE PARRAIN"," "))," ")
A69: FIL-063 | G69: =IFERROR(IF(B69=""," ",IF(COUNTIF(C$7:C$68,C69)+COUNTIF(REGISTRE_PARRAINS!C7:C106,C69)>0,"🚫 REFUSÉ — NUMÉRO DÉJÀ ENREGISTRÉ",IF(AND(E69<>"",F69<>"",E69<>F69),"🚫 REFUSÉ — CODE DÉCLARÉ HORS DÉLAI","✅ ÉLIGIBLE")))," ") | H69: =IFERROR(IF(B69="","","À vérifier CRM")," ") | I69: =IFERROR(IF(B69="","","Réf. CRM")," ") | J69: =IFERROR(IF(B69=""," ",IF(COUNTIF(REGISTRE_PARRAINS!C7:C106,C69)>0,"⚠️ MÊME ADRESSE/TEL QUE PARRAIN"," "))," ")
A70: FIL-064 | G70: =IFERROR(IF(B70=""," ",IF(COUNTIF(C$7:C$69,C70)+COUNTIF(REGISTRE_PARRAINS!C7:C106,C70)>0,"🚫 REFUSÉ — NUMÉRO DÉJÀ ENREGISTRÉ",IF(AND(E70<>"",F70<>"",E70<>F70),"🚫 REFUSÉ — CODE DÉCLARÉ HORS DÉLAI","✅ ÉLIGIBLE")))," ") | H70: =IFERROR(IF(B70="","","À vérifier CRM")," ") | I70: =IFERROR(IF(B70="","","Réf. CRM")," ") | J70: =IFERROR(IF(B70=""," ",IF(COUNTIF(REGISTRE_PARRAINS!C7:C106,C70)>0,"⚠️ MÊME ADRESSE/TEL QUE PARRAIN"," "))," ")
A71: FIL-065 | G71: =IFERROR(IF(B71=""," ",IF(COUNTIF(C$7:C$70,C71)+COUNTIF(REGISTRE_PARRAINS!C7:C106,C71)>0,"🚫 REFUSÉ — NUMÉRO DÉJÀ ENREGISTRÉ",IF(AND(E71<>"",F71<>"",E71<>F71),"🚫 REFUSÉ — CODE DÉCLARÉ HORS DÉLAI","✅ ÉLIGIBLE")))," ") | H71: =IFERROR(IF(B71="","","À vérifier CRM")," ") | I71: =IFERROR(IF(B71="","","Réf. CRM")," ") | J71: =IFERROR(IF(B71=""," ",IF(COUNTIF(REGISTRE_PARRAINS!C7:C106,C71)>0,"⚠️ MÊME ADRESSE/TEL QUE PARRAIN"," "))," ")
A72: FIL-066 | G72: =IFERROR(IF(B72=""," ",IF(COUNTIF(C$7:C$71,C72)+COUNTIF(REGISTRE_PARRAINS!C7:C106,C72)>0,"🚫 REFUSÉ — NUMÉRO DÉJÀ ENREGISTRÉ",IF(AND(E72<>"",F72<>"",E72<>F72),"🚫 REFUSÉ — CODE DÉCLARÉ HORS DÉLAI","✅ ÉLIGIBLE")))," ") | H72: =IFERROR(IF(B72="","","À vérifier CRM")," ") | I72: =IFERROR(IF(B72="","","Réf. CRM")," ") | J72: =IFERROR(IF(B72=""," ",IF(COUNTIF(REGISTRE_PARRAINS!C7:C106,C72)>0,"⚠️ MÊME ADRESSE/TEL QUE PARRAIN"," "))," ")
A73: FIL-067 | G73: =IFERROR(IF(B73=""," ",IF(COUNTIF(C$7:C$72,C73)+COUNTIF(REGISTRE_PARRAINS!C7:C106,C73)>0,"🚫 REFUSÉ — NUMÉRO DÉJÀ ENREGISTRÉ",IF(AND(E73<>"",F73<>"",E73<>F73),"🚫 REFUSÉ — CODE DÉCLARÉ HORS DÉLAI","✅ ÉLIGIBLE")))," ") | H73: =IFERROR(IF(B73="","","À vérifier CRM")," ") | I73: =IFERROR(IF(B73="","","Réf. CRM")," ") | J73: =IFERROR(IF(B73=""," ",IF(COUNTIF(REGISTRE_PARRAINS!C7:C106,C73)>0,"⚠️ MÊME ADRESSE/TEL QUE PARRAIN"," "))," ")
A74: FIL-068 | G74: =IFERROR(IF(B74=""," ",IF(COUNTIF(C$7:C$73,C74)+COUNTIF(REGISTRE_PARRAINS!C7:C106,C74)>0,"🚫 REFUSÉ — NUMÉRO DÉJÀ ENREGISTRÉ",IF(AND(E74<>"",F74<>"",E74<>F74),"🚫 REFUSÉ — CODE DÉCLARÉ HORS DÉLAI","✅ ÉLIGIBLE")))," ") | H74: =IFERROR(IF(B74="","","À vérifier CRM")," ") | I74: =IFERROR(IF(B74="","","Réf. CRM")," ") | J74: =IFERROR(IF(B74=""," ",IF(COUNTIF(REGISTRE_PARRAINS!C7:C106,C74)>0,"⚠️ MÊME ADRESSE/TEL QUE PARRAIN"," "))," ")
A75: FIL-069 | G75: =IFERROR(IF(B75=""," ",IF(COUNTIF(C$7:C$74,C75)+COUNTIF(REGISTRE_PARRAINS!C7:C106,C75)>0,"🚫 REFUSÉ — NUMÉRO DÉJÀ ENREGISTRÉ",IF(AND(E75<>"",F75<>"",E75<>F75),"🚫 REFUSÉ — CODE DÉCLARÉ HORS DÉLAI","✅ ÉLIGIBLE")))," ") | H75: =IFERROR(IF(B75="","","À vérifier CRM")," ") | I75: =IFERROR(IF(B75="","","Réf. CRM")," ") | J75: =IFERROR(IF(B75=""," ",IF(COUNTIF(REGISTRE_PARRAINS!C7:C106,C75)>0,"⚠️ MÊME ADRESSE/TEL QUE PARRAIN"," "))," ")
A76: FIL-070 | G76: =IFERROR(IF(B76=""," ",IF(COUNTIF(C$7:C$75,C76)+COUNTIF(REGISTRE_PARRAINS!C7:C106,C76)>0,"🚫 REFUSÉ — NUMÉRO DÉJÀ ENREGISTRÉ",IF(AND(E76<>"",F76<>"",E76<>F76),"🚫 REFUSÉ — CODE DÉCLARÉ HORS DÉLAI","✅ ÉLIGIBLE")))," ") | H76: =IFERROR(IF(B76="","","À vérifier CRM")," ") | I76: =IFERROR(IF(B76="","","Réf. CRM")," ") | J76: =IFERROR(IF(B76=""," ",IF(COUNTIF(REGISTRE_PARRAINS!C7:C106,C76)>0,"⚠️ MÊME ADRESSE/TEL QUE PARRAIN"," "))," ")
A77: FIL-071 | G77: =IFERROR(IF(B77=""," ",IF(COUNTIF(C$7:C$76,C77)+COUNTIF(REGISTRE_PARRAINS!C7:C106,C77)>0,"🚫 REFUSÉ — NUMÉRO DÉJÀ ENREGISTRÉ",IF(AND(E77<>"",F77<>"",E77<>F77),"🚫 REFUSÉ — CODE DÉCLARÉ HORS DÉLAI","✅ ÉLIGIBLE")))," ") | H77: =IFERROR(IF(B77="","","À vérifier CRM")," ") | I77: =IFERROR(IF(B77="","","Réf. CRM")," ") | J77: =IFERROR(IF(B77=""," ",IF(COUNTIF(REGISTRE_PARRAINS!C7:C106,C77)>0,"⚠️ MÊME ADRESSE/TEL QUE PARRAIN"," "))," ")
A78: FIL-072 | G78: =IFERROR(IF(B78=""," ",IF(COUNTIF(C$7:C$77,C78)+COUNTIF(REGISTRE_PARRAINS!C7:C106,C78)>0,"🚫 REFUSÉ — NUMÉRO DÉJÀ ENREGISTRÉ",IF(AND(E78<>"",F78<>"",E78<>F78),"🚫 REFUSÉ — CODE DÉCLARÉ HORS DÉLAI","✅ ÉLIGIBLE")))," ") | H78: =IFERROR(IF(B78="","","À vérifier CRM")," ") | I78: =IFERROR(IF(B78="","","Réf. CRM")," ") | J78: =IFERROR(IF(B78=""," ",IF(COUNTIF(REGISTRE_PARRAINS!C7:C106,C78)>0,"⚠️ MÊME ADRESSE/TEL QUE PARRAIN"," "))," ")
A79: FIL-073 | G79: =IFERROR(IF(B79=""," ",IF(COUNTIF(C$7:C$78,C79)+COUNTIF(REGISTRE_PARRAINS!C7:C106,C79)>0,"🚫 REFUSÉ — NUMÉRO DÉJÀ ENREGISTRÉ",IF(AND(E79<>"",F79<>"",E79<>F79),"🚫 REFUSÉ — CODE DÉCLARÉ HORS DÉLAI","✅ ÉLIGIBLE")))," ") | H79: =IFERROR(IF(B79="","","À vérifier CRM")," ") | I79: =IFERROR(IF(B79="","","Réf. CRM")," ") | J79: =IFERROR(IF(B79=""," ",IF(COUNTIF(REGISTRE_PARRAINS!C7:C106,C79)>0,"⚠️ MÊME ADRESSE/TEL QUE PARRAIN"," "))," ")
A80: FIL-074 | G80: =IFERROR(IF(B80=""," ",IF(COUNTIF(C$7:C$79,C80)+COUNTIF(REGISTRE_PARRAINS!C7:C106,C80)>0,"🚫 REFUSÉ — NUMÉRO DÉJÀ ENREGISTRÉ",IF(AND(E80<>"",F80<>"",E80<>F80),"🚫 REFUSÉ — CODE DÉCLARÉ HORS DÉLAI","✅ ÉLIGIBLE")))," ") | H80: =IFERROR(IF(B80="","","À vérifier CRM")," ") | I80: =IFERROR(IF(B80="","","Réf. CRM")," ") | J80: =IFERROR(IF(B80=""," ",IF(COUNTIF(REGISTRE_PARRAINS!C7:C106,C80)>0,"⚠️ MÊME ADRESSE/TEL QUE PARRAIN"," "))," ")
A81: FIL-075 | G81: =IFERROR(IF(B81=""," ",IF(COUNTIF(C$7:C$80,C81)+COUNTIF(REGISTRE_PARRAINS!C7:C106,C81)>0,"🚫 REFUSÉ — NUMÉRO DÉJÀ ENREGISTRÉ",IF(AND(E81<>"",F81<>"",E81<>F81),"🚫 REFUSÉ — CODE DÉCLARÉ HORS DÉLAI","✅ ÉLIGIBLE")))," ") | H81: =IFERROR(IF(B81="","","À vérifier CRM")," ") | I81: =IFERROR(IF(B81="","","Réf. CRM")," ") | J81: =IFERROR(IF(B81=""," ",IF(COUNTIF(REGISTRE_PARRAINS!C7:C106,C81)>0,"⚠️ MÊME ADRESSE/TEL QUE PARRAIN"," "))," ")
A82: FIL-076 | G82: =IFERROR(IF(B82=""," ",IF(COUNTIF(C$7:C$81,C82)+COUNTIF(REGISTRE_PARRAINS!C7:C106,C82)>0,"🚫 REFUSÉ — NUMÉRO DÉJÀ ENREGISTRÉ",IF(AND(E82<>"",F82<>"",E82<>F82),"🚫 REFUSÉ — CODE DÉCLARÉ HORS DÉLAI","✅ ÉLIGIBLE")))," ") | H82: =IFERROR(IF(B82="","","À vérifier CRM")," ") | I82: =IFERROR(IF(B82="","","Réf. CRM")," ") | J82: =IFERROR(IF(B82=""," ",IF(COUNTIF(REGISTRE_PARRAINS!C7:C106,C82)>0,"⚠️ MÊME ADRESSE/TEL QUE PARRAIN"," "))," ")
A83: FIL-077 | G83: =IFERROR(IF(B83=""," ",IF(COUNTIF(C$7:C$82,C83)+COUNTIF(REGISTRE_PARRAINS!C7:C106,C83)>0,"🚫 REFUSÉ — NUMÉRO DÉJÀ ENREGISTRÉ",IF(AND(E83<>"",F83<>"",E83<>F83),"🚫 REFUSÉ — CODE DÉCLARÉ HORS DÉLAI","✅ ÉLIGIBLE")))," ") | H83: =IFERROR(IF(B83="","","À vérifier CRM")," ") | I83: =IFERROR(IF(B83="","","Réf. CRM")," ") | J83: =IFERROR(IF(B83=""," ",IF(COUNTIF(REGISTRE_PARRAINS!C7:C106,C83)>0,"⚠️ MÊME ADRESSE/TEL QUE PARRAIN"," "))," ")
A84: FIL-078 | G84: =IFERROR(IF(B84=""," ",IF(COUNTIF(C$7:C$83,C84)+COUNTIF(REGISTRE_PARRAINS!C7:C106,C84)>0,"🚫 REFUSÉ — NUMÉRO DÉJÀ ENREGISTRÉ",IF(AND(E84<>"",F84<>"",E84<>F84),"🚫 REFUSÉ — CODE DÉCLARÉ HORS DÉLAI","✅ ÉLIGIBLE")))," ") | H84: =IFERROR(IF(B84="","","À vérifier CRM")," ") | I84: =IFERROR(IF(B84="","","Réf. CRM")," ") | J84: =IFERROR(IF(B84=""," ",IF(COUNTIF(REGISTRE_PARRAINS!C7:C106,C84)>0,"⚠️ MÊME ADRESSE/TEL QUE PARRAIN"," "))," ")
A85: FIL-079 | G85: =IFERROR(IF(B85=""," ",IF(COUNTIF(C$7:C$84,C85)+COUNTIF(REGISTRE_PARRAINS!C7:C106,C85)>0,"🚫 REFUSÉ — NUMÉRO DÉJÀ ENREGISTRÉ",IF(AND(E85<>"",F85<>"",E85<>F85),"🚫 REFUSÉ — CODE DÉCLARÉ HORS DÉLAI","✅ ÉLIGIBLE")))," ") | H85: =IFERROR(IF(B85="","","À vérifier CRM")," ") | I85: =IFERROR(IF(B85="","","Réf. CRM")," ") | J85: =IFERROR(IF(B85=""," ",IF(COUNTIF(REGISTRE_PARRAINS!C7:C106,C85)>0,"⚠️ MÊME ADRESSE/TEL QUE PARRAIN"," "))," ")
A86: FIL-080 | G86: =IFERROR(IF(B86=""," ",IF(COUNTIF(C$7:C$85,C86)+COUNTIF(REGISTRE_PARRAINS!C7:C106,C86)>0,"🚫 REFUSÉ — NUMÉRO DÉJÀ ENREGISTRÉ",IF(AND(E86<>"",F86<>"",E86<>F86),"🚫 REFUSÉ — CODE DÉCLARÉ HORS DÉLAI","✅ ÉLIGIBLE")))," ") | H86: =IFERROR(IF(B86="","","À vérifier CRM")," ") | I86: =IFERROR(IF(B86="","","Réf. CRM")," ") | J86: =IFERROR(IF(B86=""," ",IF(COUNTIF(REGISTRE_PARRAINS!C7:C106,C86)>0,"⚠️ MÊME ADRESSE/TEL QUE PARRAIN"," "))," ")
A87: FIL-081 | G87: =IFERROR(IF(B87=""," ",IF(COUNTIF(C$7:C$86,C87)+COUNTIF(REGISTRE_PARRAINS!C7:C106,C87)>0,"🚫 REFUSÉ — NUMÉRO DÉJÀ ENREGISTRÉ",IF(AND(E87<>"",F87<>"",E87<>F87),"🚫 REFUSÉ — CODE DÉCLARÉ HORS DÉLAI","✅ ÉLIGIBLE")))," ") | H87: =IFERROR(IF(B87="","","À vérifier CRM")," ") | I87: =IFERROR(IF(B87="","","Réf. CRM")," ") | J87: =IFERROR(IF(B87=""," ",IF(COUNTIF(REGISTRE_PARRAINS!C7:C106,C87)>0,"⚠️ MÊME ADRESSE/TEL QUE PARRAIN"," "))," ")
A88: FIL-082 | G88: =IFERROR(IF(B88=""," ",IF(COUNTIF(C$7:C$87,C88)+COUNTIF(REGISTRE_PARRAINS!C7:C106,C88)>0,"🚫 REFUSÉ — NUMÉRO DÉJÀ ENREGISTRÉ",IF(AND(E88<>"",F88<>"",E88<>F88),"🚫 REFUSÉ — CODE DÉCLARÉ HORS DÉLAI","✅ ÉLIGIBLE")))," ") | H88: =IFERROR(IF(B88="","","À vérifier CRM")," ") | I88: =IFERROR(IF(B88="","","Réf. CRM")," ") | J88: =IFERROR(IF(B88=""," ",IF(COUNTIF(REGISTRE_PARRAINS!C7:C106,C88)>0,"⚠️ MÊME ADRESSE/TEL QUE PARRAIN"," "))," ")
A89: FIL-083 | G89: =IFERROR(IF(B89=""," ",IF(COUNTIF(C$7:C$88,C89)+COUNTIF(REGISTRE_PARRAINS!C7:C106,C89)>0,"🚫 REFUSÉ — NUMÉRO DÉJÀ ENREGISTRÉ",IF(AND(E89<>"",F89<>"",E89<>F89),"🚫 REFUSÉ — CODE DÉCLARÉ HORS DÉLAI","✅ ÉLIGIBLE")))," ") | H89: =IFERROR(IF(B89="","","À vérifier CRM")," ") | I89: =IFERROR(IF(B89="","","Réf. CRM")," ") | J89: =IFERROR(IF(B89=""," ",IF(COUNTIF(REGISTRE_PARRAINS!C7:C106,C89)>0,"⚠️ MÊME ADRESSE/TEL QUE PARRAIN"," "))," ")
A90: FIL-084 | G90: =IFERROR(IF(B90=""," ",IF(COUNTIF(C$7:C$89,C90)+COUNTIF(REGISTRE_PARRAINS!C7:C106,C90)>0,"🚫 REFUSÉ — NUMÉRO DÉJÀ ENREGISTRÉ",IF(AND(E90<>"",F90<>"",E90<>F90),"🚫 REFUSÉ — CODE DÉCLARÉ HORS DÉLAI","✅ ÉLIGIBLE")))," ") | H90: =IFERROR(IF(B90="","","À vérifier CRM")," ") | I90: =IFERROR(IF(B90="","","Réf. CRM")," ") | J90: =IFERROR(IF(B90=""," ",IF(COUNTIF(REGISTRE_PARRAINS!C7:C106,C90)>0,"⚠️ MÊME ADRESSE/TEL QUE PARRAIN"," "))," ")
A91: FIL-085 | G91: =IFERROR(IF(B91=""," ",IF(COUNTIF(C$7:C$90,C91)+COUNTIF(REGISTRE_PARRAINS!C7:C106,C91)>0,"🚫 REFUSÉ — NUMÉRO DÉJÀ ENREGISTRÉ",IF(AND(E91<>"",F91<>"",E91<>F91),"🚫 REFUSÉ — CODE DÉCLARÉ HORS DÉLAI","✅ ÉLIGIBLE")))," ") | H91: =IFERROR(IF(B91="","","À vérifier CRM")," ") | I91: =IFERROR(IF(B91="","","Réf. CRM")," ") | J91: =IFERROR(IF(B91=""," ",IF(COUNTIF(REGISTRE_PARRAINS!C7:C106,C91)>0,"⚠️ MÊME ADRESSE/TEL QUE PARRAIN"," "))," ")
A92: FIL-086 | G92: =IFERROR(IF(B92=""," ",IF(COUNTIF(C$7:C$91,C92)+COUNTIF(REGISTRE_PARRAINS!C7:C106,C92)>0,"🚫 REFUSÉ — NUMÉRO DÉJÀ ENREGISTRÉ",IF(AND(E92<>"",F92<>"",E92<>F92),"🚫 REFUSÉ — CODE DÉCLARÉ HORS DÉLAI","✅ ÉLIGIBLE")))," ") | H92: =IFERROR(IF(B92="","","À vérifier CRM")," ") | I92: =IFERROR(IF(B92="","","Réf. CRM")," ") | J92: =IFERROR(IF(B92=""," ",IF(COUNTIF(REGISTRE_PARRAINS!C7:C106,C92)>0,"⚠️ MÊME ADRESSE/TEL QUE PARRAIN"," "))," ")
A93: FIL-087 | G93: =IFERROR(IF(B93=""," ",IF(COUNTIF(C$7:C$92,C93)+COUNTIF(REGISTRE_PARRAINS!C7:C106,C93)>0,"🚫 REFUSÉ — NUMÉRO DÉJÀ ENREGISTRÉ",IF(AND(E93<>"",F93<>"",E93<>F93),"🚫 REFUSÉ — CODE DÉCLARÉ HORS DÉLAI","✅ ÉLIGIBLE")))," ") | H93: =IFERROR(IF(B93="","","À vérifier CRM")," ") | I93: =IFERROR(IF(B93="","","Réf. CRM")," ") | J93: =IFERROR(IF(B93=""," ",IF(COUNTIF(REGISTRE_PARRAINS!C7:C106,C93)>0,"⚠️ MÊME ADRESSE/TEL QUE PARRAIN"," "))," ")
A94: FIL-088 | G94: =IFERROR(IF(B94=""," ",IF(COUNTIF(C$7:C$93,C94)+COUNTIF(REGISTRE_PARRAINS!C7:C106,C94)>0,"🚫 REFUSÉ — NUMÉRO DÉJÀ ENREGISTRÉ",IF(AND(E94<>"",F94<>"",E94<>F94),"🚫 REFUSÉ — CODE DÉCLARÉ HORS DÉLAI","✅ ÉLIGIBLE")))," ") | H94: =IFERROR(IF(B94="","","À vérifier CRM")," ") | I94: =IFERROR(IF(B94="","","Réf. CRM")," ") | J94: =IFERROR(IF(B94=""," ",IF(COUNTIF(REGISTRE_PARRAINS!C7:C106,C94)>0,"⚠️ MÊME ADRESSE/TEL QUE PARRAIN"," "))," ")
A95: FIL-089 | G95: =IFERROR(IF(B95=""," ",IF(COUNTIF(C$7:C$94,C95)+COUNTIF(REGISTRE_PARRAINS!C7:C106,C95)>0,"🚫 REFUSÉ — NUMÉRO DÉJÀ ENREGISTRÉ",IF(AND(E95<>"",F95<>"",E95<>F95),"🚫 REFUSÉ — CODE DÉCLARÉ HORS DÉLAI","✅ ÉLIGIBLE")))," ") | H95: =IFERROR(IF(B95="","","À vérifier CRM")," ") | I95: =IFERROR(IF(B95="","","Réf. CRM")," ") | J95: =IFERROR(IF(B95=""," ",IF(COUNTIF(REGISTRE_PARRAINS!C7:C106,C95)>0,"⚠️ MÊME ADRESSE/TEL QUE PARRAIN"," "))," ")
A96: FIL-090 | G96: =IFERROR(IF(B96=""," ",IF(COUNTIF(C$7:C$95,C96)+COUNTIF(REGISTRE_PARRAINS!C7:C106,C96)>0,"🚫 REFUSÉ — NUMÉRO DÉJÀ ENREGISTRÉ",IF(AND(E96<>"",F96<>"",E96<>F96),"🚫 REFUSÉ — CODE DÉCLARÉ HORS DÉLAI","✅ ÉLIGIBLE")))," ") | H96: =IFERROR(IF(B96="","","À vérifier CRM")," ") | I96: =IFERROR(IF(B96="","","Réf. CRM")," ") | J96: =IFERROR(IF(B96=""," ",IF(COUNTIF(REGISTRE_PARRAINS!C7:C106,C96)>0,"⚠️ MÊME ADRESSE/TEL QUE PARRAIN"," "))," ")
A97: FIL-091 | G97: =IFERROR(IF(B97=""," ",IF(COUNTIF(C$7:C$96,C97)+COUNTIF(REGISTRE_PARRAINS!C7:C106,C97)>0,"🚫 REFUSÉ — NUMÉRO DÉJÀ ENREGISTRÉ",IF(AND(E97<>"",F97<>"",E97<>F97),"🚫 REFUSÉ — CODE DÉCLARÉ HORS DÉLAI","✅ ÉLIGIBLE")))," ") | H97: =IFERROR(IF(B97="","","À vérifier CRM")," ") | I97: =IFERROR(IF(B97="","","Réf. CRM")," ") | J97: =IFERROR(IF(B97=""," ",IF(COUNTIF(REGISTRE_PARRAINS!C7:C106,C97)>0,"⚠️ MÊME ADRESSE/TEL QUE PARRAIN"," "))," ")
A98: FIL-092 | G98: =IFERROR(IF(B98=""," ",IF(COUNTIF(C$7:C$97,C98)+COUNTIF(REGISTRE_PARRAINS!C7:C106,C98)>0,"🚫 REFUSÉ — NUMÉRO DÉJÀ ENREGISTRÉ",IF(AND(E98<>"",F98<>"",E98<>F98),"🚫 REFUSÉ — CODE DÉCLARÉ HORS DÉLAI","✅ ÉLIGIBLE")))," ") | H98: =IFERROR(IF(B98="","","À vérifier CRM")," ") | I98: =IFERROR(IF(B98="","","Réf. CRM")," ") | J98: =IFERROR(IF(B98=""," ",IF(COUNTIF(REGISTRE_PARRAINS!C7:C106,C98)>0,"⚠️ MÊME ADRESSE/TEL QUE PARRAIN"," "))," ")
A99: FIL-093 | G99: =IFERROR(IF(B99=""," ",IF(COUNTIF(C$7:C$98,C99)+COUNTIF(REGISTRE_PARRAINS!C7:C106,C99)>0,"🚫 REFUSÉ — NUMÉRO DÉJÀ ENREGISTRÉ",IF(AND(E99<>"",F99<>"",E99<>F99),"🚫 REFUSÉ — CODE DÉCLARÉ HORS DÉLAI","✅ ÉLIGIBLE")))," ") | H99: =IFERROR(IF(B99="","","À vérifier CRM")," ") | I99: =IFERROR(IF(B99="","","Réf. CRM")," ") | J99: =IFERROR(IF(B99=""," ",IF(COUNTIF(REGISTRE_PARRAINS!C7:C106,C99)>0,"⚠️ MÊME ADRESSE/TEL QUE PARRAIN"," "))," ")
A100: FIL-094 | G100: =IFERROR(IF(B100=""," ",IF(COUNTIF(C$7:C$99,C100)+COUNTIF(REGISTRE_PARRAINS!C7:C106,C100)>0,"🚫 REFUSÉ — NUMÉRO DÉJÀ ENREGISTRÉ",IF(AND(E100<>"",F100<>"",E100<>F100),"🚫 REFUSÉ — CODE DÉCLARÉ HORS DÉLAI","✅ ÉLIGIBLE")))," ") | H100: =IFERROR(IF(B100="","","À vérifier CRM")," ") | I100: =IFERROR(IF(B100="","","Réf. CRM")," ") | J100: =IFERROR(IF(B100=""," ",IF(COUNTIF(REGISTRE_PARRAINS!C7:C106,C100)>0,"⚠️ MÊME ADRESSE/TEL QUE PARRAIN"," "))," ")
A101: FIL-095 | G101: =IFERROR(IF(B101=""," ",IF(COUNTIF(C$7:C$100,C101)+COUNTIF(REGISTRE_PARRAINS!C7:C106,C101)>0,"🚫 REFUSÉ — NUMÉRO DÉJÀ ENREGISTRÉ",IF(AND(E101<>"",F101<>"",E101<>F101),"🚫 REFUSÉ — CODE DÉCLARÉ HORS DÉLAI","✅ ÉLIGIBLE")))," ") | H101: =IFERROR(IF(B101="","","À vérifier CRM")," ") | I101: =IFERROR(IF(B101="","","Réf. CRM")," ") | J101: =IFERROR(IF(B101=""," ",IF(COUNTIF(REGISTRE_PARRAINS!C7:C106,C101)>0,"⚠️ MÊME ADRESSE/TEL QUE PARRAIN"," "))," ")
...

Sheet COMMISSIONS_PARRAINAGE
A1: 💰 COMMISSIONS DE PARRAINAGE — LEMI SARL | BRASUS v3.2
A2: Plage nommée : LEMI_PARRAINAGE_COMMISSIONS | Commission = Acompte filleul × 2,5% | Validation DG obligatoire avant paiement
A3: 🔒 CALCUL AUTOMATIQUE — Ne pas modifier | H3: ✏️ WORKFLOW DE VALIDATION — DG uniquement | M3: 🔒 CLAWBACK
A5: DONNÉES COMMISSION (auto) | H5: VALIDATION & PAIEMENT (DG) | M5: CLAWBACK
A6: ID COMMISSION | B6: CODE PARRAIN | C6: NOM PARRAIN | D6: FILLEUL | E6: ACOMPTE FILLEUL (FCFA) | F6: DATE RÉCEPTION ACOMPTE | G6: COMMISSION DUE (FCFA) | H6: STATUT | I6: VALIDÉ DG | J6: DATE VALIDATION | K6: RÉF. TRANSACTION OM/WAVE | L6: NOTES | M6: ALERTE CLAWBACK
A7: COM-001 | B7: =IFERROR(IF(FILLEULS!D7="","",FILLEULS!D7)," ") | C7: =IFERROR(IF(B7=" ","",VLOOKUP(B7,REGISTRE_PARRAINS!A7:B106,2,FALSE))," ") | D7: =IFERROR(IF(FILLEULS!B7="","",FILLEULS!B7)," ") | E7: =IFERROR(IF(FILLEULS!I7="","",FILLEULS!I7)," ") | F7: =IFERROR(IF(FILLEULS!E7="","",FILLEULS!E7)," ") | G7: =IFERROR(IF(AND(FILLEULS!G7="✅ ÉLIGIBLE",E7<>""),ROUND(E7*0.025,0),0),0) | H7: À valider | M7: =IFERROR(IF(AND(FILLEULS!H7="Remboursé",FILLEULS!G7<>""),"🔻 À DÉDUIRE — Commission à reprendre"," ")," ")
A8: COM-002 | B8: =IFERROR(IF(FILLEULS!D8="","",FILLEULS!D8)," ") | C8: =IFERROR(IF(B8=" ","",VLOOKUP(B8,REGISTRE_PARRAINS!A7:B106,2,FALSE))," ") | D8: =IFERROR(IF(FILLEULS!B8="","",FILLEULS!B8)," ") | E8: =IFERROR(IF(FILLEULS!I8="","",FILLEULS!I8)," ") | F8: =IFERROR(IF(FILLEULS!E8="","",FILLEULS!E8)," ") | G8: =IFERROR(IF(AND(FILLEULS!G8="✅ ÉLIGIBLE",E8<>""),ROUND(E8*0.025,0),0),0) | M8: =IFERROR(IF(AND(FILLEULS!H8="Remboursé",FILLEULS!G8<>""),"🔻 À DÉDUIRE — Commission à reprendre"," ")," ")
A9: COM-003 | B9: =IFERROR(IF(FILLEULS!D9="","",FILLEULS!D9)," ") | C9: =IFERROR(IF(B9=" ","",VLOOKUP(B9,REGISTRE_PARRAINS!A7:B106,2,FALSE))," ") | D9: =IFERROR(IF(FILLEULS!B9="","",FILLEULS!B9)," ") | E9: =IFERROR(IF(FILLEULS!I9="","",FILLEULS!I9)," ") | F9: =IFERROR(IF(FILLEULS!E9="","",FILLEULS!E9)," ") | G9: =IFERROR(IF(AND(FILLEULS!G9="✅ ÉLIGIBLE",E9<>""),ROUND(E9*0.025,0),0),0) | M9: =IFERROR(IF(AND(FILLEULS!H9="Remboursé",FILLEULS!G9<>""),"🔻 À DÉDUIRE — Commission à reprendre"," ")," ")
A10: COM-004 | B10: =IFERROR(IF(FILLEULS!D10="","",FILLEULS!D10)," ") | C10: =IFERROR(IF(B10=" ","",VLOOKUP(B10,REGISTRE_PARRAINS!A7:B106,2,FALSE))," ") | D10: =IFERROR(IF(FILLEULS!B10="","",FILLEULS!B10)," ") | E10: =IFERROR(IF(FILLEULS!I10="","",FILLEULS!I10)," ") | F10: =IFERROR(IF(FILLEULS!E10="","",FILLEULS!E10)," ") | G10: =IFERROR(IF(AND(FILLEULS!G10="✅ ÉLIGIBLE",E10<>""),ROUND(E10*0.025,0),0),0) | M10: =IFERROR(IF(AND(FILLEULS!H10="Remboursé",FILLEULS!G10<>""),"🔻 À DÉDUIRE — Commission à reprendre"," ")," ")
A11: COM-005 | B11: =IFERROR(IF(FILLEULS!D11="","",FILLEULS!D11)," ") | C11: =IFERROR(IF(B11=" ","",VLOOKUP(B11,REGISTRE_PARRAINS!A7:B106,2,FALSE))," ") | D11: =IFERROR(IF(FILLEULS!B11="","",FILLEULS!B11)," ") | E11: =IFERROR(IF(FILLEULS!I11="","",FILLEULS!I11)," ") | F11: =IFERROR(IF(FILLEULS!E11="","",FILLEULS!E11)," ") | G11: =IFERROR(IF(AND(FILLEULS!G11="✅ ÉLIGIBLE",E11<>""),ROUND(E11*0.025,0),0),0) | M11: =IFERROR(IF(AND(FILLEULS!H11="Remboursé",FILLEULS!G11<>""),"🔻 À DÉDUIRE — Commission à reprendre"," ")," ")
A12: COM-006 | B12: =IFERROR(IF(FILLEULS!D12="","",FILLEULS!D12)," ") | C12: =IFERROR(IF(B12=" ","",VLOOKUP(B12,REGISTRE_PARRAINS!A7:B106,2,FALSE))," ") | D12: =IFERROR(IF(FILLEULS!B12="","",FILLEULS!B12)," ") | E12: =IFERROR(IF(FILLEULS!I12="","",FILLEULS!I12)," ") | F12: =IFERROR(IF(FILLEULS!E12="","",FILLEULS!E12)," ") | G12: =IFERROR(IF(AND(FILLEULS!G12="✅ ÉLIGIBLE",E12<>""),ROUND(E12*0.025,0),0),0) | M12: =IFERROR(IF(AND(FILLEULS!H12="Remboursé",FILLEULS!G12<>""),"🔻 À DÉDUIRE — Commission à reprendre"," ")," ")
A13: COM-007 | B13: =IFERROR(IF(FILLEULS!D13="","",FILLEULS!D13)," ") | C13: =IFERROR(IF(B13=" ","",VLOOKUP(B13,REGISTRE_PARRAINS!A7:B106,2,FALSE))," ") | D13: =IFERROR(IF(FILLEULS!B13="","",FILLEULS!B13)," ") | E13: =IFERROR(IF(FILLEULS!I13="","",FILLEULS!I13)," ") | F13: =IFERROR(IF(FILLEULS!E13="","",FILLEULS!E13)," ") | G13: =IFERROR(IF(AND(FILLEULS!G13="✅ ÉLIGIBLE",E13<>""),ROUND(E13*0.025,0),0),0) | M13: =IFERROR(IF(AND(FILLEULS!H13="Remboursé",FILLEULS!G13<>""),"🔻 À DÉDUIRE — Commission à reprendre"," ")," ")
A14: COM-008 | B14: =IFERROR(IF(FILLEULS!D14="","",FILLEULS!D14)," ") | C14: =IFERROR(IF(B14=" ","",VLOOKUP(B14,REGISTRE_PARRAINS!A7:B106,2,FALSE))," ") | D14: =IFERROR(IF(FILLEULS!B14="","",FILLEULS!B14)," ") | E14: =IFERROR(IF(FILLEULS!I14="","",FILLEULS!I14)," ") | F14: =IFERROR(IF(FILLEULS!E14="","",FILLEULS!E14)," ") | G14: =IFERROR(IF(AND(FILLEULS!G14="✅ ÉLIGIBLE",E14<>""),ROUND(E14*0.025,0),0),0) | M14: =IFERROR(IF(AND(FILLEULS!H14="Remboursé",FILLEULS!G14<>""),"🔻 À DÉDUIRE — Commission à reprendre"," ")," ")
A15: COM-009 | B15: =IFERROR(IF(FILLEULS!D15="","",FILLEULS!D15)," ") | C15: =IFERROR(IF(B15=" ","",VLOOKUP(B15,REGISTRE_PARRAINS!A7:B106,2,FALSE))," ") | D15: =IFERROR(IF(FILLEULS!B15="","",FILLEULS!B15)," ") | E15: =IFERROR(IF(FILLEULS!I15="","",FILLEULS!I15)," ") | F15: =IFERROR(IF(FILLEULS!E15="","",FILLEULS!E15)," ") | G15: =IFERROR(IF(AND(FILLEULS!G15="✅ ÉLIGIBLE",E15<>""),ROUND(E15*0.025,0),0),0) | M15: =IFERROR(IF(AND(FILLEULS!H15="Remboursé",FILLEULS!G15<>""),"🔻 À DÉDUIRE — Commission à reprendre"," ")," ")
A16: COM-010 | B16: =IFERROR(IF(FILLEULS!D16="","",FILLEULS!D16)," ") | C16: =IFERROR(IF(B16=" ","",VLOOKUP(B16,REGISTRE_PARRAINS!A7:B106,2,FALSE))," ") | D16: =IFERROR(IF(FILLEULS!B16="","",FILLEULS!B16)," ") | E16: =IFERROR(IF(FILLEULS!I16="","",FILLEULS!I16)," ") | F16: =IFERROR(IF(FILLEULS!E16="","",FILLEULS!E16)," ") | G16: =IFERROR(IF(AND(FILLEULS!G16="✅ ÉLIGIBLE",E16<>""),ROUND(E16*0.025,0),0),0) | M16: =IFERROR(IF(AND(FILLEULS!H16="Remboursé",FILLEULS!G16<>""),"🔻 À DÉDUIRE — Commission à reprendre"," ")," ")
A17: COM-011 | B17: =IFERROR(IF(FILLEULS!D17="","",FILLEULS!D17)," ") | C17: =IFERROR(IF(B17=" ","",VLOOKUP(B17,REGISTRE_PARRAINS!A7:B106,2,FALSE))," ") | D17: =IFERROR(IF(FILLEULS!B17="","",FILLEULS!B17)," ") | E17: =IFERROR(IF(FILLEULS!I17="","",FILLEULS!I17)," ") | F17: =IFERROR(IF(FILLEULS!E17="","",FILLEULS!E17)," ") | G17: =IFERROR(IF(AND(FILLEULS!G17="✅ ÉLIGIBLE",E17<>""),ROUND(E17*0.025,0),0),0) | M17: =IFERROR(IF(AND(FILLEULS!H17="Remboursé",FILLEULS!G17<>""),"🔻 À DÉDUIRE — Commission à reprendre"," ")," ")
A18: COM-012 | B18: =IFERROR(IF(FILLEULS!D18="","",FILLEULS!D18)," ") | C18: =IFERROR(IF(B18=" ","",VLOOKUP(B18,REGISTRE_PARRAINS!A7:B106,2,FALSE))," ") | D18: =IFERROR(IF(FILLEULS!B18="","",FILLEULS!B18)," ") | E18: =IFERROR(IF(FILLEULS!I18="","",FILLEULS!I18)," ") | F18: =IFERROR(IF(FILLEULS!E18="","",FILLEULS!E18)," ") | G18: =IFERROR(IF(AND(FILLEULS!G18="✅ ÉLIGIBLE",E18<>""),ROUND(E18*0.025,0),0),0) | M18: =IFERROR(IF(AND(FILLEULS!H18="Remboursé",FILLEULS!G18<>""),"🔻 À DÉDUIRE — Commission à reprendre"," ")," ")
A19: COM-013 | B19: =IFERROR(IF(FILLEULS!D19="","",FILLEULS!D19)," ") | C19: =IFERROR(IF(B19=" ","",VLOOKUP(B19,REGISTRE_PARRAINS!A7:B106,2,FALSE))," ") | D19: =IFERROR(IF(FILLEULS!B19="","",FILLEULS!B19)," ") | E19: =IFERROR(IF(FILLEULS!I19="","",FILLEULS!I19)," ") | F19: =IFERROR(IF(FILLEULS!E19="","",FILLEULS!E19)," ") | G19: =IFERROR(IF(AND(FILLEULS!G19="✅ ÉLIGIBLE",E19<>""),ROUND(E19*0.025,0),0),0) | M19: =IFERROR(IF(AND(FILLEULS!H19="Remboursé",FILLEULS!G19<>""),"🔻 À DÉDUIRE — Commission à reprendre"," ")," ")
A20: COM-014 | B20: =IFERROR(IF(FILLEULS!D20="","",FILLEULS!D20)," ") | C20: =IFERROR(IF(B20=" ","",VLOOKUP(B20,REGISTRE_PARRAINS!A7:B106,2,FALSE))," ") | D20: =IFERROR(IF(FILLEULS!B20="","",FILLEULS!B20)," ") | E20: =IFERROR(IF(FILLEULS!I20="","",FILLEULS!I20)," ") | F20: =IFERROR(IF(FILLEULS!E20="","",FILLEULS!E20)," ") | G20: =IFERROR(IF(AND(FILLEULS!G20="✅ ÉLIGIBLE",E20<>""),ROUND(E20*0.025,0),0),0) | M20: =IFERROR(IF(AND(FILLEULS!H20="Remboursé",FILLEULS!G20<>""),"🔻 À DÉDUIRE — Commission à reprendre"," ")," ")
A21: COM-015 | B21: =IFERROR(IF(FILLEULS!D21="","",FILLEULS!D21)," ") | C21: =IFERROR(IF(B21=" ","",VLOOKUP(B21,REGISTRE_PARRAINS!A7:B106,2,FALSE))," ") | D21: =IFERROR(IF(FILLEULS!B21="","",FILLEULS!B21)," ") | E21: =IFERROR(IF(FILLEULS!I21="","",FILLEULS!I21)," ") | F21: =IFERROR(IF(FILLEULS!E21="","",FILLEULS!E21)," ") | G21: =IFERROR(IF(AND(FILLEULS!G21="✅ ÉLIGIBLE",E21<>""),ROUND(E21*0.025,0),0),0) | M21: =IFERROR(IF(AND(FILLEULS!H21="Remboursé",FILLEULS!G21<>""),"🔻 À DÉDUIRE — Commission à reprendre"," ")," ")
A22: COM-016 | B22: =IFERROR(IF(FILLEULS!D22="","",FILLEULS!D22)," ") | C22: =IFERROR(IF(B22=" ","",VLOOKUP(B22,REGISTRE_PARRAINS!A7:B106,2,FALSE))," ") | D22: =IFERROR(IF(FILLEULS!B22="","",FILLEULS!B22)," ") | E22: =IFERROR(IF(FILLEULS!I22="","",FILLEULS!I22)," ") | F22: =IFERROR(IF(FILLEULS!E22="","",FILLEULS!E22)," ") | G22: =IFERROR(IF(AND(FILLEULS!G22="✅ ÉLIGIBLE",E22<>""),ROUND(E22*0.025,0),0),0) | M22: =IFERROR(IF(AND(FILLEULS!H22="Remboursé",FILLEULS!G22<>""),"🔻 À DÉDUIRE — Commission à reprendre"," ")," ")
A23: COM-017 | B23: =IFERROR(IF(FILLEULS!D23="","",FILLEULS!D23)," ") | C23: =IFERROR(IF(B23=" ","",VLOOKUP(B23,REGISTRE_PARRAINS!A7:B106,2,FALSE))," ") | D23: =IFERROR(IF(FILLEULS!B23="","",FILLEULS!B23)," ") | E23: =IFERROR(IF(FILLEULS!I23="","",FILLEULS!I23)," ") | F23: =IFERROR(IF(FILLEULS!E23="","",FILLEULS!E23)," ") | G23: =IFERROR(IF(AND(FILLEULS!G23="✅ ÉLIGIBLE",E23<>""),ROUND(E23*0.025,0),0),0) | M23: =IFERROR(IF(AND(FILLEULS!H23="Remboursé",FILLEULS!G23<>""),"🔻 À DÉDUIRE — Commission à reprendre"," ")," ")
A24: COM-018 | B24: =IFERROR(IF(FILLEULS!D24="","",FILLEULS!D24)," ") | C24: =IFERROR(IF(B24=" ","",VLOOKUP(B24,REGISTRE_PARRAINS!A7:B106,2,FALSE))," ") | D24: =IFERROR(IF(FILLEULS!B24="","",FILLEULS!B24)," ") | E24: =IFERROR(IF(FILLEULS!I24="","",FILLEULS!I24)," ") | F24: =IFERROR(IF(FILLEULS!E24="","",FILLEULS!E24)," ") | G24: =IFERROR(IF(AND(FILLEULS!G24="✅ ÉLIGIBLE",E24<>""),ROUND(E24*0.025,0),0),0) | M24: =IFERROR(IF(AND(FILLEULS!H24="Remboursé",FILLEULS!G24<>""),"🔻 À DÉDUIRE — Commission à reprendre"," ")," ")
A25: COM-019 | B25: =IFERROR(IF(FILLEULS!D25="","",FILLEULS!D25)," ") | C25: =IFERROR(IF(B25=" ","",VLOOKUP(B25,REGISTRE_PARRAINS!A7:B106,2,FALSE))," ") | D25: =IFERROR(IF(FILLEULS!B25="","",FILLEULS!B25)," ") | E25: =IFERROR(IF(FILLEULS!I25="","",FILLEULS!I25)," ") | F25: =IFERROR(IF(FILLEULS!E25="","",FILLEULS!E25)," ") | G25: =IFERROR(IF(AND(FILLEULS!G25="✅ ÉLIGIBLE",E25<>""),ROUND(E25*0.025,0),0),0) | M25: =IFERROR(IF(AND(FILLEULS!H25="Remboursé",FILLEULS!G25<>""),"🔻 À DÉDUIRE — Commission à reprendre"," ")," ")
A26: COM-020 | B26: =IFERROR(IF(FILLEULS!D26="","",FILLEULS!D26)," ") | C26: =IFERROR(IF(B26=" ","",VLOOKUP(B26,REGISTRE_PARRAINS!A7:B106,2,FALSE))," ") | D26: =IFERROR(IF(FILLEULS!B26="","",FILLEULS!B26)," ") | E26: =IFERROR(IF(FILLEULS!I26="","",FILLEULS!I26)," ") | F26: =IFERROR(IF(FILLEULS!E26="","",FILLEULS!E26)," ") | G26: =IFERROR(IF(AND(FILLEULS!G26="✅ ÉLIGIBLE",E26<>""),ROUND(E26*0.025,0),0),0) | M26: =IFERROR(IF(AND(FILLEULS!H26="Remboursé",FILLEULS!G26<>""),"🔻 À DÉDUIRE — Commission à reprendre"," ")," ")
A27: COM-021 | B27: =IFERROR(IF(FILLEULS!D27="","",FILLEULS!D27)," ") | C27: =IFERROR(IF(B27=" ","",VLOOKUP(B27,REGISTRE_PARRAINS!A7:B106,2,FALSE))," ") | D27: =IFERROR(IF(FILLEULS!B27="","",FILLEULS!B27)," ") | E27: =IFERROR(IF(FILLEULS!I27="","",FILLEULS!I27)," ") | F27: =IFERROR(IF(FILLEULS!E27="","",FILLEULS!E27)," ") | G27: =IFERROR(IF(AND(FILLEULS!G27="✅ ÉLIGIBLE",E27<>""),ROUND(E27*0.025,0),0),0) | M27: =IFERROR(IF(AND(FILLEULS!H27="Remboursé",FILLEULS!G27<>""),"🔻 À DÉDUIRE — Commission à reprendre"," ")," ")
A28: COM-022 | B28: =IFERROR(IF(FILLEULS!D28="","",FILLEULS!D28)," ") | C28: =IFERROR(IF(B28=" ","",VLOOKUP(B28,REGISTRE_PARRAINS!A7:B106,2,FALSE))," ") | D28: =IFERROR(IF(FILLEULS!B28="","",FILLEULS!B28)," ") | E28: =IFERROR(IF(FILLEULS!I28="","",FILLEULS!I28)," ") | F28: =IFERROR(IF(FILLEULS!E28="","",FILLEULS!E28)," ") | G28: =IFERROR(IF(AND(FILLEULS!G28="✅ ÉLIGIBLE",E28<>""),ROUND(E28*0.025,0),0),0) | M28: =IFERROR(IF(AND(FILLEULS!H28="Remboursé",FILLEULS!G28<>""),"🔻 À DÉDUIRE — Commission à reprendre"," ")," ")
A29: COM-023 | B29: =IFERROR(IF(FILLEULS!D29="","",FILLEULS!D29)," ") | C29: =IFERROR(IF(B29=" ","",VLOOKUP(B29,REGISTRE_PARRAINS!A7:B106,2,FALSE))," ") | D29: =IFERROR(IF(FILLEULS!B29="","",FILLEULS!B29)," ") | E29: =IFERROR(IF(FILLEULS!I29="","",FILLEULS!I29)," ") | F29: =IFERROR(IF(FILLEULS!E29="","",FILLEULS!E29)," ") | G29: =IFERROR(IF(AND(FILLEULS!G29="✅ ÉLIGIBLE",E29<>""),ROUND(E29*0.025,0),0),0) | M29: =IFERROR(IF(AND(FILLEULS!H29="Remboursé",FILLEULS!G29<>""),"🔻 À DÉDUIRE — Commission à reprendre"," ")," ")
A30: COM-024 | B30: =IFERROR(IF(FILLEULS!D30="","",FILLEULS!D30)," ") | C30: =IFERROR(IF(B30=" ","",VLOOKUP(B30,REGISTRE_PARRAINS!A7:B106,2,FALSE))," ") | D30: =IFERROR(IF(FILLEULS!B30="","",FILLEULS!B30)," ") | E30: =IFERROR(IF(FILLEULS!I30="","",FILLEULS!I30)," ") | F30: =IFERROR(IF(FILLEULS!E30="","",FILLEULS!E30)," ") | G30: =IFERROR(IF(AND(FILLEULS!G30="✅ ÉLIGIBLE",E30<>""),ROUND(E30*0.025,0),0),0) | M30: =IFERROR(IF(AND(FILLEULS!H30="Remboursé",FILLEULS!G30<>""),"🔻 À DÉDUIRE — Commission à reprendre"," ")," ")
A31: COM-025 | B31: =IFERROR(IF(FILLEULS!D31="","",FILLEULS!D31)," ") | C31: =IFERROR(IF(B31=" ","",VLOOKUP(B31,REGISTRE_PARRAINS!A7:B106,2,FALSE))," ") | D31: =IFERROR(IF(FILLEULS!B31="","",FILLEULS!B31)," ") | E31: =IFERROR(IF(FILLEULS!I31="","",FILLEULS!I31)," ") | F31: =IFERROR(IF(FILLEULS!E31="","",FILLEULS!E31)," ") | G31: =IFERROR(IF(AND(FILLEULS!G31="✅ ÉLIGIBLE",E31<>""),ROUND(E31*0.025,0),0),0) | M31: =IFERROR(IF(AND(FILLEULS!H31="Remboursé",FILLEULS!G31<>""),"🔻 À DÉDUIRE — Commission à reprendre"," ")," ")
A32: COM-026 | B32: =IFERROR(IF(FILLEULS!D32="","",FILLEULS!D32)," ") | C32: =IFERROR(IF(B32=" ","",VLOOKUP(B32,REGISTRE_PARRAINS!A7:B106,2,FALSE))," ") | D32: =IFERROR(IF(FILLEULS!B32="","",FILLEULS!B32)," ") | E32: =IFERROR(IF(FILLEULS!I32="","",FILLEULS!I32)," ") | F32: =IFERROR(IF(FILLEULS!E32="","",FILLEULS!E32)," ") | G32: =IFERROR(IF(AND(FILLEULS!G32="✅ ÉLIGIBLE",E32<>""),ROUND(E32*0.025,0),0),0) | M32: =IFERROR(IF(AND(FILLEULS!H32="Remboursé",FILLEULS!G32<>""),"🔻 À DÉDUIRE — Commission à reprendre"," ")," ")
A33: COM-027 | B33: =IFERROR(IF(FILLEULS!D33="","",FILLEULS!D33)," ") | C33: =IFERROR(IF(B33=" ","",VLOOKUP(B33,REGISTRE_PARRAINS!A7:B106,2,FALSE))," ") | D33: =IFERROR(IF(FILLEULS!B33="","",FILLEULS!B33)," ") | E33: =IFERROR(IF(FILLEULS!I33="","",FILLEULS!I33)," ") | F33: =IFERROR(IF(FILLEULS!E33="","",FILLEULS!E33)," ") | G33: =IFERROR(IF(AND(FILLEULS!G33="✅ ÉLIGIBLE",E33<>""),ROUND(E33*0.025,0),0),0) | M33: =IFERROR(IF(AND(FILLEULS!H33="Remboursé",FILLEULS!G33<>""),"🔻 À DÉDUIRE — Commission à reprendre"," ")," ")
A34: COM-028 | B34: =IFERROR(IF(FILLEULS!D34="","",FILLEULS!D34)," ") | C34: =IFERROR(IF(B34=" ","",VLOOKUP(B34,REGISTRE_PARRAINS!A7:B106,2,FALSE))," ") | D34: =IFERROR(IF(FILLEULS!B34="","",FILLEULS!B34)," ") | E34: =IFERROR(IF(FILLEULS!I34="","",FILLEULS!I34)," ") | F34: =IFERROR(IF(FILLEULS!E34="","",FILLEULS!E34)," ") | G34: =IFERROR(IF(AND(FILLEULS!G34="✅ ÉLIGIBLE",E34<>""),ROUND(E34*0.025,0),0),0) | M34: =IFERROR(IF(AND(FILLEULS!H34="Remboursé",FILLEULS!G34<>""),"🔻 À DÉDUIRE — Commission à reprendre"," ")," ")
A35: COM-029 | B35: =IFERROR(IF(FILLEULS!D35="","",FILLEULS!D35)," ") | C35: =IFERROR(IF(B35=" ","",VLOOKUP(B35,REGISTRE_PARRAINS!A7:B106,2,FALSE))," ") | D35: =IFERROR(IF(FILLEULS!B35="","",FILLEULS!B35)," ") | E35: =IFERROR(IF(FILLEULS!I35="","",FILLEULS!I35)," ") | F35: =IFERROR(IF(FILLEULS!E35="","",FILLEULS!E35)," ") | G35: =IFERROR(IF(AND(FILLEULS!G35="✅ ÉLIGIBLE",E35<>""),ROUND(E35*0.025,0),0),0) | M35: =IFERROR(IF(AND(FILLEULS!H35="Remboursé",FILLEULS!G35<>""),"🔻 À DÉDUIRE — Commission à reprendre"," ")," ")
A36: COM-030 | B36: =IFERROR(IF(FILLEULS!D36="","",FILLEULS!D36)," ") | C36: =IFERROR(IF(B36=" ","",VLOOKUP(B36,REGISTRE_PARRAINS!A7:B106,2,FALSE))," ") | D36: =IFERROR(IF(FILLEULS!B36="","",FILLEULS!B36)," ") | E36: =IFERROR(IF(FILLEULS!I36="","",FILLEULS!I36)," ") | F36: =IFERROR(IF(FILLEULS!E36="","",FILLEULS!E36)," ") | G36: =IFERROR(IF(AND(FILLEULS!G36="✅ ÉLIGIBLE",E36<>""),ROUND(E36*0.025,0),0),0) | M36: =IFERROR(IF(AND(FILLEULS!H36="Remboursé",FILLEULS!G36<>""),"🔻 À DÉDUIRE — Commission à reprendre"," ")," ")
A37: COM-031 | B37: =IFERROR(IF(FILLEULS!D37="","",FILLEULS!D37)," ") | C37: =IFERROR(IF(B37=" ","",VLOOKUP(B37,REGISTRE_PARRAINS!A7:B106,2,FALSE))," ") | D37: =IFERROR(IF(FILLEULS!B37="","",FILLEULS!B37)," ") | E37: =IFERROR(IF(FILLEULS!I37="","",FILLEULS!I37)," ") | F37: =IFERROR(IF(FILLEULS!E37="","",FILLEULS!E37)," ") | G37: =IFERROR(IF(AND(FILLEULS!G37="✅ ÉLIGIBLE",E37<>""),ROUND(E37*0.025,0),0),0) | M37: =IFERROR(IF(AND(FILLEULS!H37="Remboursé",FILLEULS!G37<>""),"🔻 À DÉDUIRE — Commission à reprendre"," ")," ")
A38: COM-032 | B38: =IFERROR(IF(FILLEULS!D38="","",FILLEULS!D38)," ") | C38: =IFERROR(IF(B38=" ","",VLOOKUP(B38,REGISTRE_PARRAINS!A7:B106,2,FALSE))," ") | D38: =IFERROR(IF(FILLEULS!B38="","",FILLEULS!B38)," ") | E38: =IFERROR(IF(FILLEULS!I38="","",FILLEULS!I38)," ") | F38: =IFERROR(IF(FILLEULS!E38="","",FILLEULS!E38)," ") | G38: =IFERROR(IF(AND(FILLEULS!G38="✅ ÉLIGIBLE",E38<>""),ROUND(E38*0.025,0),0),0) | M38: =IFERROR(IF(AND(FILLEULS!H38="Remboursé",FILLEULS!G38<>""),"🔻 À DÉDUIRE — Commission à reprendre"," ")," ")
A39: COM-033 | B39: =IFERROR(IF(FILLEULS!D39="","",FILLEULS!D39)," ") | C39: =IFERROR(IF(B39=" ","",VLOOKUP(B39,REGISTRE_PARRAINS!A7:B106,2,FALSE))," ") | D39: =IFERROR(IF(FILLEULS!B39="","",FILLEULS!B39)," ") | E39: =IFERROR(IF(FILLEULS!I39="","",FILLEULS!I39)," ") | F39: =IFERROR(IF(FILLEULS!E39="","",FILLEULS!E39)," ") | G39: =IFERROR(IF(AND(FILLEULS!G39="✅ ÉLIGIBLE",E39<>""),ROUND(E39*0.025,0),0),0) | M39: =IFERROR(IF(AND(FILLEULS!H39="Remboursé",FILLEULS!G39<>""),"🔻 À DÉDUIRE — Commission à reprendre"," ")," ")
A40: COM-034 | B40: =IFERROR(IF(FILLEULS!D40="","",FILLEULS!D40)," ") | C40: =IFERROR(IF(B40=" ","",VLOOKUP(B40,REGISTRE_PARRAINS!A7:B106,2,FALSE))," ") | D40: =IFERROR(IF(FILLEULS!B40="","",FILLEULS!B40)," ") | E40: =IFERROR(IF(FILLEULS!I40="","",FILLEULS!I40)," ") | F40: =IFERROR(IF(FILLEULS!E40="","",FILLEULS!E40)," ") | G40: =IFERROR(IF(AND(FILLEULS!G40="✅ ÉLIGIBLE",E40<>""),ROUND(E40*0.025,0),0),0) | M40: =IFERROR(IF(AND(FILLEULS!H40="Remboursé",FILLEULS!G40<>""),"🔻 À DÉDUIRE — Commission à reprendre"," ")," ")
A41: COM-035 | B41: =IFERROR(IF(FILLEULS!D41="","",FILLEULS!D41)," ") | C41: =IFERROR(IF(B41=" ","",VLOOKUP(B41,REGISTRE_PARRAINS!A7:B106,2,FALSE))," ") | D41: =IFERROR(IF(FILLEULS!B41="","",FILLEULS!B41)," ") | E41: =IFERROR(IF(FILLEULS!I41="","",FILLEULS!I41)," ") | F41: =IFERROR(IF(FILLEULS!E41="","",FILLEULS!E41)," ") | G41: =IFERROR(IF(AND(FILLEULS!G41="✅ ÉLIGIBLE",E41<>""),ROUND(E41*0.025,0),0),0) | M41: =IFERROR(IF(AND(FILLEULS!H41="Remboursé",FILLEULS!G41<>""),"🔻 À DÉDUIRE — Commission à reprendre"," ")," ")
A42: COM-036 | B42: =IFERROR(IF(FILLEULS!D42="","",FILLEULS!D42)," ") | C42: =IFERROR(IF(B42=" ","",VLOOKUP(B42,REGISTRE_PARRAINS!A7:B106,2,FALSE))," ") | D42: =IFERROR(IF(FILLEULS!B42="","",FILLEULS!B42)," ") | E42: =IFERROR(IF(FILLEULS!I42="","",FILLEULS!I42)," ") | F42: =IFERROR(IF(FILLEULS!E42="","",FILLEULS!E42)," ") | G42: =IFERROR(IF(AND(FILLEULS!G42="✅ ÉLIGIBLE",E42<>""),ROUND(E42*0.025,0),0),0) | M42: =IFERROR(IF(AND(FILLEULS!H42="Remboursé",FILLEULS!G42<>""),"🔻 À DÉDUIRE — Commission à reprendre"," ")," ")
A43: COM-037 | B43: =IFERROR(IF(FILLEULS!D43="","",FILLEULS!D43)," ") | C43: =IFERROR(IF(B43=" ","",VLOOKUP(B43,REGISTRE_PARRAINS!A7:B106,2,FALSE))," ") | D43: =IFERROR(IF(FILLEULS!B43="","",FILLEULS!B43)," ") | E43: =IFERROR(IF(FILLEULS!I43="","",FILLEULS!I43)," ") | F43: =IFERROR(IF(FILLEULS!E43="","",FILLEULS!E43)," ") | G43: =IFERROR(IF(AND(FILLEULS!G43="✅ ÉLIGIBLE",E43<>""),ROUND(E43*0.025,0),0),0) | M43: =IFERROR(IF(AND(FILLEULS!H43="Remboursé",FILLEULS!G43<>""),"🔻 À DÉDUIRE — Commission à reprendre"," ")," ")
A44: COM-038 | B44: =IFERROR(IF(FILLEULS!D44="","",FILLEULS!D44)," ") | C44: =IFERROR(IF(B44=" ","",VLOOKUP(B44,REGISTRE_PARRAINS!A7:B106,2,FALSE))," ") | D44: =IFERROR(IF(FILLEULS!B44="","",FILLEULS!B44)," ") | E44: =IFERROR(IF(FILLEULS!I44="","",FILLEULS!I44)," ") | F44: =IFERROR(IF(FILLEULS!E44="","",FILLEULS!E44)," ") | G44: =IFERROR(IF(AND(FILLEULS!G44="✅ ÉLIGIBLE",E44<>""),ROUND(E44*0.025,0),0),0) | M44: =IFERROR(IF(AND(FILLEULS!H44="Remboursé",FILLEULS!G44<>""),"🔻 À DÉDUIRE — Commission à reprendre"," ")," ")
A45: COM-039 | B45: =IFERROR(IF(FILLEULS!D45="","",FILLEULS!D45)," ") | C45: =IFERROR(IF(B45=" ","",VLOOKUP(B45,REGISTRE_PARRAINS!A7:B106,2,FALSE))," ") | D45: =IFERROR(IF(FILLEULS!B45="","",FILLEULS!B45)," ") | E45: =IFERROR(IF(FILLEULS!I45="","",FILLEULS!I45)," ") | F45: =IFERROR(IF(FILLEULS!E45="","",FILLEULS!E45)," ") | G45: =IFERROR(IF(AND(FILLEULS!G45="✅ ÉLIGIBLE",E45<>""),ROUND(E45*0.025,0),0),0) | M45: =IFERROR(IF(AND(FILLEULS!H45="Remboursé",FILLEULS!G45<>""),"🔻 À DÉDUIRE — Commission à reprendre"," ")," ")
A46: COM-040 | B46: =IFERROR(IF(FILLEULS!D46="","",FILLEULS!D46)," ") | C46: =IFERROR(IF(B46=" ","",VLOOKUP(B46,REGISTRE_PARRAINS!A7:B106,2,FALSE))," ") | D46: =IFERROR(IF(FILLEULS!B46="","",FILLEULS!B46)," ") | E46: =IFERROR(IF(FILLEULS!I46="","",FILLEULS!I46)," ") | F46: =IFERROR(IF(FILLEULS!E46="","",FILLEULS!E46)," ") | G46: =IFERROR(IF(AND(FILLEULS!G46="✅ ÉLIGIBLE",E46<>""),ROUND(E46*0.025,0),0),0) | M46: =IFERROR(IF(AND(FILLEULS!H46="Remboursé",FILLEULS!G46<>""),"🔻 À DÉDUIRE — Commission à reprendre"," ")," ")
A47: COM-041 | B47: =IFERROR(IF(FILLEULS!D47="","",FILLEULS!D47)," ") | C47: =IFERROR(IF(B47=" ","",VLOOKUP(B47,REGISTRE_PARRAINS!A7:B106,2,FALSE))," ") | D47: =IFERROR(IF(FILLEULS!B47="","",FILLEULS!B47)," ") | E47: =IFERROR(IF(FILLEULS!I47="","",FILLEULS!I47)," ") | F47: =IFERROR(IF(FILLEULS!E47="","",FILLEULS!E47)," ") | G47: =IFERROR(IF(AND(FILLEULS!G47="✅ ÉLIGIBLE",E47<>""),ROUND(E47*0.025,0),0),0) | M47: =IFERROR(IF(AND(FILLEULS!H47="Remboursé",FILLEULS!G47<>""),"🔻 À DÉDUIRE — Commission à reprendre"," ")," ")
A48: COM-042 | B48: =IFERROR(IF(FILLEULS!D48="","",FILLEULS!D48)," ") | C48: =IFERROR(IF(B48=" ","",VLOOKUP(B48,REGISTRE_PARRAINS!A7:B106,2,FALSE))," ") | D48: =IFERROR(IF(FILLEULS!B48="","",FILLEULS!B48)," ") | E48: =IFERROR(IF(FILLEULS!I48="","",FILLEULS!I48)," ") | F48: =IFERROR(IF(FILLEULS!E48="","",FILLEULS!E48)," ") | G48: =IFERROR(IF(AND(FILLEULS!G48="✅ ÉLIGIBLE",E48<>""),ROUND(E48*0.025,0),0),0) | M48: =IFERROR(IF(AND(FILLEULS!H48="Remboursé",FILLEULS!G48<>""),"🔻 À DÉDUIRE — Commission à reprendre"," ")," ")
A49: COM-043 | B49: =IFERROR(IF(FILLEULS!D49="","",FILLEULS!D49)," ") | C49: =IFERROR(IF(B49=" ","",VLOOKUP(B49,REGISTRE_PARRAINS!A7:B106,2,FALSE))," ") | D49: =IFERROR(IF(FILLEULS!B49="","",FILLEULS!B49)," ") | E49: =IFERROR(IF(FILLEULS!I49="","",FILLEULS!I49)," ") | F49: =IFERROR(IF(FILLEULS!E49="","",FILLEULS!E49)," ") | G49: =IFERROR(IF(AND(FILLEULS!G49="✅ ÉLIGIBLE",E49<>""),ROUND(E49*0.025,0),0),0) | M49: =IFERROR(IF(AND(FILLEULS!H49="Remboursé",FILLEULS!G49<>""),"🔻 À DÉDUIRE — Commission à reprendre"," ")," ")
A50: COM-044 | B50: =IFERROR(IF(FILLEULS!D50="","",FILLEULS!D50)," ") | C50: =IFERROR(IF(B50=" ","",VLOOKUP(B50,REGISTRE_PARRAINS!A7:B106,2,FALSE))," ") | D50: =IFERROR(IF(FILLEULS!B50="","",FILLEULS!B50)," ") | E50: =IFERROR(IF(FILLEULS!I50="","",FILLEULS!I50)," ") | F50: =IFERROR(IF(FILLEULS!E50="","",FILLEULS!E50)," ") | G50: =IFERROR(IF(AND(FILLEULS!G50="✅ ÉLIGIBLE",E50<>""),ROUND(E50*0.025,0),0),0) | M50: =IFERROR(IF(AND(FILLEULS!H50="Remboursé",FILLEULS!G50<>""),"🔻 À DÉDUIRE — Commission à reprendre"," ")," ")
A51: COM-045 | B51: =IFERROR(IF(FILLEULS!D51="","",FILLEULS!D51)," ") | C51: =IFERROR(IF(B51=" ","",VLOOKUP(B51,REGISTRE_PARRAINS!A7:B106,2,FALSE))," ") | D51: =IFERROR(IF(FILLEULS!B51="","",FILLEULS!B51)," ") | E51: =IFERROR(IF(FILLEULS!I51="","",FILLEULS!I51)," ") | F51: =IFERROR(IF(FILLEULS!E51="","",FILLEULS!E51)," ") | G51: =IFERROR(IF(AND(FILLEULS!G51="✅ ÉLIGIBLE",E51<>""),ROUND(E51*0.025,0),0),0) | M51: =IFERROR(IF(AND(FILLEULS!H51="Remboursé",FILLEULS!G51<>""),"🔻 À DÉDUIRE — Commission à reprendre"," ")," ")
A52: COM-046 | B52: =IFERROR(IF(FILLEULS!D52="","",FILLEULS!D52)," ") | C52: =IFERROR(IF(B52=" ","",VLOOKUP(B52,REGISTRE_PARRAINS!A7:B106,2,FALSE))," ") | D52: =IFERROR(IF(FILLEULS!B52="","",FILLEULS!B52)," ") | E52: =IFERROR(IF(FILLEULS!I52="","",FILLEULS!I52)," ") | F52: =IFERROR(IF(FILLEULS!E52="","",FILLEULS!E52)," ") | G52: =IFERROR(IF(AND(FILLEULS!G52="✅ ÉLIGIBLE",E52<>""),ROUND(E52*0.025,0),0),0) | M52: =IFERROR(IF(AND(FILLEULS!H52="Remboursé",FILLEULS!G52<>""),"🔻 À DÉDUIRE — Commission à reprendre"," ")," ")
A53: COM-047 | B53: =IFERROR(IF(FILLEULS!D53="","",FILLEULS!D53)," ") | C53: =IFERROR(IF(B53=" ","",VLOOKUP(B53,REGISTRE_PARRAINS!A7:B106,2,FALSE))," ") | D53: =IFERROR(IF(FILLEULS!B53="","",FILLEULS!B53)," ") | E53: =IFERROR(IF(FILLEULS!I53="","",FILLEULS!I53)," ") | F53: =IFERROR(IF(FILLEULS!E53="","",FILLEULS!E53)," ") | G53: =IFERROR(IF(AND(FILLEULS!G53="✅ ÉLIGIBLE",E53<>""),ROUND(E53*0.025,0),0),0) | M53: =IFERROR(IF(AND(FILLEULS!H53="Remboursé",FILLEULS!G53<>""),"🔻 À DÉDUIRE — Commission à reprendre"," ")," ")
A54: COM-048 | B54: =IFERROR(IF(FILLEULS!D54="","",FILLEULS!D54)," ") | C54: =IFERROR(IF(B54=" ","",VLOOKUP(B54,REGISTRE_PARRAINS!A7:B106,2,FALSE))," ") | D54: =IFERROR(IF(FILLEULS!B54="","",FILLEULS!B54)," ") | E54: =IFERROR(IF(FILLEULS!I54="","",FILLEULS!I54)," ") | F54: =IFERROR(IF(FILLEULS!E54="","",FILLEULS!E54)," ") | G54: =IFERROR(IF(AND(FILLEULS!G54="✅ ÉLIGIBLE",E54<>""),ROUND(E54*0.025,0),0),0) | M54: =IFERROR(IF(AND(FILLEULS!H54="Remboursé",FILLEULS!G54<>""),"🔻 À DÉDUIRE — Commission à reprendre"," ")," ")
A55: COM-049 | B55: =IFERROR(IF(FILLEULS!D55="","",FILLEULS!D55)," ") | C55: =IFERROR(IF(B55=" ","",VLOOKUP(B55,REGISTRE_PARRAINS!A7:B106,2,FALSE))," ") | D55: =IFERROR(IF(FILLEULS!B55="","",FILLEULS!B55)," ") | E55: =IFERROR(IF(FILLEULS!I55="","",FILLEULS!I55)," ") | F55: =IFERROR(IF(FILLEULS!E55="","",FILLEULS!E55)," ") | G55: =IFERROR(IF(AND(FILLEULS!G55="✅ ÉLIGIBLE",E55<>""),ROUND(E55*0.025,0),0),0) | M55: =IFERROR(IF(AND(FILLEULS!H55="Remboursé",FILLEULS!G55<>""),"🔻 À DÉDUIRE — Commission à reprendre"," ")," ")
A56: COM-050 | B56: =IFERROR(IF(FILLEULS!D56="","",FILLEULS!D56)," ") | C56: =IFERROR(IF(B56=" ","",VLOOKUP(B56,REGISTRE_PARRAINS!A7:B106,2,FALSE))," ") | D56: =IFERROR(IF(FILLEULS!B56="","",FILLEULS!B56)," ") | E56: =IFERROR(IF(FILLEULS!I56="","",FILLEULS!I56)," ") | F56: =IFERROR(IF(FILLEULS!E56="","",FILLEULS!E56)," ") | G56: =IFERROR(IF(AND(FILLEULS!G56="✅ ÉLIGIBLE",E56<>""),ROUND(E56*0.025,0),0),0) | M56: =IFERROR(IF(AND(FILLEULS!H56="Remboursé",FILLEULS!G56<>""),"🔻 À DÉDUIRE — Commission à reprendre"," ")," ")
A57: COM-051 | B57: =IFERROR(IF(FILLEULS!D57="","",FILLEULS!D57)," ") | C57: =IFERROR(IF(B57=" ","",VLOOKUP(B57,REGISTRE_PARRAINS!A7:B106,2,FALSE))," ") | D57: =IFERROR(IF(FILLEULS!B57="","",FILLEULS!B57)," ") | E57: =IFERROR(IF(FILLEULS!I57="","",FILLEULS!I57)," ") | F57: =IFERROR(IF(FILLEULS!E57="","",FILLEULS!E57)," ") | G57: =IFERROR(IF(AND(FILLEULS!G57="✅ ÉLIGIBLE",E57<>""),ROUND(E57*0.025,0),0),0) | M57: =IFERROR(IF(AND(FILLEULS!H57="Remboursé",FILLEULS!G57<>""),"🔻 À DÉDUIRE — Commission à reprendre"," ")," ")
A58: COM-052 | B58: =IFERROR(IF(FILLEULS!D58="","",FILLEULS!D58)," ") | C58: =IFERROR(IF(B58=" ","",VLOOKUP(B58,REGISTRE_PARRAINS!A7:B106,2,FALSE))," ") | D58: =IFERROR(IF(FILLEULS!B58="","",FILLEULS!B58)," ") | E58: =IFERROR(IF(FILLEULS!I58="","",FILLEULS!I58)," ") | F58: =IFERROR(IF(FILLEULS!E58="","",FILLEULS!E58)," ") | G58: =IFERROR(IF(AND(FILLEULS!G58="✅ ÉLIGIBLE",E58<>""),ROUND(E58*0.025,0),0),0) | M58: =IFERROR(IF(AND(FILLEULS!H58="Remboursé",FILLEULS!G58<>""),"🔻 À DÉDUIRE — Commission à reprendre"," ")," ")
A59: COM-053 | B59: =IFERROR(IF(FILLEULS!D59="","",FILLEULS!D59)," ") | C59: =IFERROR(IF(B59=" ","",VLOOKUP(B59,REGISTRE_PARRAINS!A7:B106,2,FALSE))," ") | D59: =IFERROR(IF(FILLEULS!B59="","",FILLEULS!B59)," ") | E59: =IFERROR(IF(FILLEULS!I59="","",FILLEULS!I59)," ") | F59: =IFERROR(IF(FILLEULS!E59="","",FILLEULS!E59)," ") | G59: =IFERROR(IF(AND(FILLEULS!G59="✅ ÉLIGIBLE",E59<>""),ROUND(E59*0.025,0),0),0) | M59: =IFERROR(IF(AND(FILLEULS!H59="Remboursé",FILLEULS!G59<>""),"🔻 À DÉDUIRE — Commission à reprendre"," ")," ")
A60: COM-054 | B60: =IFERROR(IF(FILLEULS!D60="","",FILLEULS!D60)," ") | C60: =IFERROR(IF(B60=" ","",VLOOKUP(B60,REGISTRE_PARRAINS!A7:B106,2,FALSE))," ") | D60: =IFERROR(IF(FILLEULS!B60="","",FILLEULS!B60)," ") | E60: =IFERROR(IF(FILLEULS!I60="","",FILLEULS!I60)," ") | F60: =IFERROR(IF(FILLEULS!E60="","",FILLEULS!E60)," ") | G60: =IFERROR(IF(AND(FILLEULS!G60="✅ ÉLIGIBLE",E60<>""),ROUND(E60*0.025,0),0),0) | M60: =IFERROR(IF(AND(FILLEULS!H60="Remboursé",FILLEULS!G60<>""),"🔻 À DÉDUIRE — Commission à reprendre"," ")," ")
A61: COM-055 | B61: =IFERROR(IF(FILLEULS!D61="","",FILLEULS!D61)," ") | C61: =IFERROR(IF(B61=" ","",VLOOKUP(B61,REGISTRE_PARRAINS!A7:B106,2,FALSE))," ") | D61: =IFERROR(IF(FILLEULS!B61="","",FILLEULS!B61)," ") | E61: =IFERROR(IF(FILLEULS!I61="","",FILLEULS!I61)," ") | F61: =IFERROR(IF(FILLEULS!E61="","",FILLEULS!E61)," ") | G61: =IFERROR(IF(AND(FILLEULS!G61="✅ ÉLIGIBLE",E61<>""),ROUND(E61*0.025,0),0),0) | M61: =IFERROR(IF(AND(FILLEULS!H61="Remboursé",FILLEULS!G61<>""),"🔻 À DÉDUIRE — Commission à reprendre"," ")," ")
A62: COM-056 | B62: =IFERROR(IF(FILLEULS!D62="","",FILLEULS!D62)," ") | C62: =IFERROR(IF(B62=" ","",VLOOKUP(B62,REGISTRE_PARRAINS!A7:B106,2,FALSE))," ") | D62: =IFERROR(IF(FILLEULS!B62="","",FILLEULS!B62)," ") | E62: =IFERROR(IF(FILLEULS!I62="","",FILLEULS!I62)," ") | F62: =IFERROR(IF(FILLEULS!E62="","",FILLEULS!E62)," ") | G62: =IFERROR(IF(AND(FILLEULS!G62="✅ ÉLIGIBLE",E62<>""),ROUND(E62*0.025,0),0),0) | M62: =IFERROR(IF(AND(FILLEULS!H62="Remboursé",FILLEULS!G62<>""),"🔻 À DÉDUIRE — Commission à reprendre"," ")," ")
A63: COM-057 | B63: =IFERROR(IF(FILLEULS!D63="","",FILLEULS!D63)," ") | C63: =IFERROR(IF(B63=" ","",VLOOKUP(B63,REGISTRE_PARRAINS!A7:B106,2,FALSE))," ") | D63: =IFERROR(IF(FILLEULS!B63="","",FILLEULS!B63)," ") | E63: =IFERROR(IF(FILLEULS!I63="","",FILLEULS!I63)," ") | F63: =IFERROR(IF(FILLEULS!E63="","",FILLEULS!E63)," ") | G63: =IFERROR(IF(AND(FILLEULS!G63="✅ ÉLIGIBLE",E63<>""),ROUND(E63*0.025,0),0),0) | M63: =IFERROR(IF(AND(FILLEULS!H63="Remboursé",FILLEULS!G63<>""),"🔻 À DÉDUIRE — Commission à reprendre"," ")," ")
A64: COM-058 | B64: =IFERROR(IF(FILLEULS!D64="","",FILLEULS!D64)," ") | C64: =IFERROR(IF(B64=" ","",VLOOKUP(B64,REGISTRE_PARRAINS!A7:B106,2,FALSE))," ") | D64: =IFERROR(IF(FILLEULS!B64="","",FILLEULS!B64)," ") | E64: =IFERROR(IF(FILLEULS!I64="","",FILLEULS!I64)," ") | F64: =IFERROR(IF(FILLEULS!E64="","",FILLEULS!E64)," ") | G64: =IFERROR(IF(AND(FILLEULS!G64="✅ ÉLIGIBLE",E64<>""),ROUND(E64*0.025,0),0),0) | M64: =IFERROR(IF(AND(FILLEULS!H64="Remboursé",FILLEULS!G64<>""),"🔻 À DÉDUIRE — Commission à reprendre"," ")," ")
A65: COM-059 | B65: =IFERROR(IF(FILLEULS!D65="","",FILLEULS!D65)," ") | C65: =IFERROR(IF(B65=" ","",VLOOKUP(B65,REGISTRE_PARRAINS!A7:B106,2,FALSE))," ") | D65: =IFERROR(IF(FILLEULS!B65="","",FILLEULS!B65)," ") | E65: =IFERROR(IF(FILLEULS!I65="","",FILLEULS!I65)," ") | F65: =IFERROR(IF(FILLEULS!E65="","",FILLEULS!E65)," ") | G65: =IFERROR(IF(AND(FILLEULS!G65="✅ ÉLIGIBLE",E65<>""),ROUND(E65*0.025,0),0),0) | M65: =IFERROR(IF(AND(FILLEULS!H65="Remboursé",FILLEULS!G65<>""),"🔻 À DÉDUIRE — Commission à reprendre"," ")," ")
A66: COM-060 | B66: =IFERROR(IF(FILLEULS!D66="","",FILLEULS!D66)," ") | C66: =IFERROR(IF(B66=" ","",VLOOKUP(B66,REGISTRE_PARRAINS!A7:B106,2,FALSE))," ") | D66: =IFERROR(IF(FILLEULS!B66="","",FILLEULS!B66)," ") | E66: =IFERROR(IF(FILLEULS!I66="","",FILLEULS!I66)," ") | F66: =IFERROR(IF(FILLEULS!E66="","",FILLEULS!E66)," ") | G66: =IFERROR(IF(AND(FILLEULS!G66="✅ ÉLIGIBLE",E66<>""),ROUND(E66*0.025,0),0),0) | M66: =IFERROR(IF(AND(FILLEULS!H66="Remboursé",FILLEULS!G66<>""),"🔻 À DÉDUIRE — Commission à reprendre"," ")," ")
A67: COM-061 | B67: =IFERROR(IF(FILLEULS!D67="","",FILLEULS!D67)," ") | C67: =IFERROR(IF(B67=" ","",VLOOKUP(B67,REGISTRE_PARRAINS!A7:B106,2,FALSE))," ") | D67: =IFERROR(IF(FILLEULS!B67="","",FILLEULS!B67)," ") | E67: =IFERROR(IF(FILLEULS!I67="","",FILLEULS!I67)," ") | F67: =IFERROR(IF(FILLEULS!E67="","",FILLEULS!E67)," ") | G67: =IFERROR(IF(AND(FILLEULS!G67="✅ ÉLIGIBLE",E67<>""),ROUND(E67*0.025,0),0),0) | M67: =IFERROR(IF(AND(FILLEULS!H67="Remboursé",FILLEULS!G67<>""),"🔻 À DÉDUIRE — Commission à reprendre"," ")," ")
A68: COM-062 | B68: =IFERROR(IF(FILLEULS!D68="","",FILLEULS!D68)," ") | C68: =IFERROR(IF(B68=" ","",VLOOKUP(B68,REGISTRE_PARRAINS!A7:B106,2,FALSE))," ") | D68: =IFERROR(IF(FILLEULS!B68="","",FILLEULS!B68)," ") | E68: =IFERROR(IF(FILLEULS!I68="","",FILLEULS!I68)," ") | F68: =IFERROR(IF(FILLEULS!E68="","",FILLEULS!E68)," ") | G68: =IFERROR(IF(AND(FILLEULS!G68="✅ ÉLIGIBLE",E68<>""),ROUND(E68*0.025,0),0),0) | M68: =IFERROR(IF(AND(FILLEULS!H68="Remboursé",FILLEULS!G68<>""),"🔻 À DÉDUIRE — Commission à reprendre"," ")," ")
A69: COM-063 | B69: =IFERROR(IF(FILLEULS!D69="","",FILLEULS!D69)," ") | C69: =IFERROR(IF(B69=" ","",VLOOKUP(B69,REGISTRE_PARRAINS!A7:B106,2,FALSE))," ") | D69: =IFERROR(IF(FILLEULS!B69="","",FILLEULS!B69)," ") | E69: =IFERROR(IF(FILLEULS!I69="","",FILLEULS!I69)," ") | F69: =IFERROR(IF(FILLEULS!E69="","",FILLEULS!E69)," ") | G69: =IFERROR(IF(AND(FILLEULS!G69="✅ ÉLIGIBLE",E69<>""),ROUND(E69*0.025,0),0),0) | M69: =IFERROR(IF(AND(FILLEULS!H69="Remboursé",FILLEULS!G69<>""),"🔻 À DÉDUIRE — Commission à reprendre"," ")," ")
A70: COM-064 | B70: =IFERROR(IF(FILLEULS!D70="","",FILLEULS!D70)," ") | C70: =IFERROR(IF(B70=" ","",VLOOKUP(B70,REGISTRE_PARRAINS!A7:B106,2,FALSE))," ") | D70: =IFERROR(IF(FILLEULS!B70="","",FILLEULS!B70)," ") | E70: =IFERROR(IF(FILLEULS!I70="","",FILLEULS!I70)," ") | F70: =IFERROR(IF(FILLEULS!E70="","",FILLEULS!E70)," ") | G70: =IFERROR(IF(AND(FILLEULS!G70="✅ ÉLIGIBLE",E70<>""),ROUND(E70*0.025,0),0),0) | M70: =IFERROR(IF(AND(FILLEULS!H70="Remboursé",FILLEULS!G70<>""),"🔻 À DÉDUIRE — Commission à reprendre"," ")," ")
A71: COM-065 | B71: =IFERROR(IF(FILLEULS!D71="","",FILLEULS!D71)," ") | C71: =IFERROR(IF(B71=" ","",VLOOKUP(B71,REGISTRE_PARRAINS!A7:B106,2,FALSE))," ") | D71: =IFERROR(IF(FILLEULS!B71="","",FILLEULS!B71)," ") | E71: =IFERROR(IF(FILLEULS!I71="","",FILLEULS!I71)," ") | F71: =IFERROR(IF(FILLEULS!E71="","",FILLEULS!E71)," ") | G71: =IFERROR(IF(AND(FILLEULS!G71="✅ ÉLIGIBLE",E71<>""),ROUND(E71*0.025,0),0),0) | M71: =IFERROR(IF(AND(FILLEULS!H71="Remboursé",FILLEULS!G71<>""),"🔻 À DÉDUIRE — Commission à reprendre"," ")," ")
A72: COM-066 | B72: =IFERROR(IF(FILLEULS!D72="","",FILLEULS!D72)," ") | C72: =IFERROR(IF(B72=" ","",VLOOKUP(B72,REGISTRE_PARRAINS!A7:B106,2,FALSE))," ") | D72: =IFERROR(IF(FILLEULS!B72="","",FILLEULS!B72)," ") | E72: =IFERROR(IF(FILLEULS!I72="","",FILLEULS!I72)," ") | F72: =IFERROR(IF(FILLEULS!E72="","",FILLEULS!E72)," ") | G72: =IFERROR(IF(AND(FILLEULS!G72="✅ ÉLIGIBLE",E72<>""),ROUND(E72*0.025,0),0),0) | M72: =IFERROR(IF(AND(FILLEULS!H72="Remboursé",FILLEULS!G72<>""),"🔻 À DÉDUIRE — Commission à reprendre"," ")," ")
A73: COM-067 | B73: =IFERROR(IF(FILLEULS!D73="","",FILLEULS!D73)," ") | C73: =IFERROR(IF(B73=" ","",VLOOKUP(B73,REGISTRE_PARRAINS!A7:B106,2,FALSE))," ") | D73: =IFERROR(IF(FILLEULS!B73="","",FILLEULS!B73)," ") | E73: =IFERROR(IF(FILLEULS!I73="","",FILLEULS!I73)," ") | F73: =IFERROR(IF(FILLEULS!E73="","",FILLEULS!E73)," ") | G73: =IFERROR(IF(AND(FILLEULS!G73="✅ ÉLIGIBLE",E73<>""),ROUND(E73*0.025,0),0),0) | M73: =IFERROR(IF(AND(FILLEULS!H73="Remboursé",FILLEULS!G73<>""),"🔻 À DÉDUIRE — Commission à reprendre"," ")," ")
A74: COM-068 | B74: =IFERROR(IF(FILLEULS!D74="","",FILLEULS!D74)," ") | C74: =IFERROR(IF(B74=" ","",VLOOKUP(B74,REGISTRE_PARRAINS!A7:B106,2,FALSE))," ") | D74: =IFERROR(IF(FILLEULS!B74="","",FILLEULS!B74)," ") | E74: =IFERROR(IF(FILLEULS!I74="","",FILLEULS!I74)," ") | F74: =IFERROR(IF(FILLEULS!E74="","",FILLEULS!E74)," ") | G74: =IFERROR(IF(AND(FILLEULS!G74="✅ ÉLIGIBLE",E74<>""),ROUND(E74*0.025,0),0),0) | M74: =IFERROR(IF(AND(FILLEULS!H74="Remboursé",FILLEULS!G74<>""),"🔻 À DÉDUIRE — Commission à reprendre"," ")," ")
A75: COM-069 | B75: =IFERROR(IF(FILLEULS!D75="","",FILLEULS!D75)," ") | C75: =IFERROR(IF(B75=" ","",VLOOKUP(B75,REGISTRE_PARRAINS!A7:B106,2,FALSE))," ") | D75: =IFERROR(IF(FILLEULS!B75="","",FILLEULS!B75)," ") | E75: =IFERROR(IF(FILLEULS!I75="","",FILLEULS!I75)," ") | F75: =IFERROR(IF(FILLEULS!E75="","",FILLEULS!E75)," ") | G75: =IFERROR(IF(AND(FILLEULS!G75="✅ ÉLIGIBLE",E75<>""),ROUND(E75*0.025,0),0),0) | M75: =IFERROR(IF(AND(FILLEULS!H75="Remboursé",FILLEULS!G75<>""),"🔻 À DÉDUIRE — Commission à reprendre"," ")," ")
A76: COM-070 | B76: =IFERROR(IF(FILLEULS!D76="","",FILLEULS!D76)," ") | C76: =IFERROR(IF(B76=" ","",VLOOKUP(B76,REGISTRE_PARRAINS!A7:B106,2,FALSE))," ") | D76: =IFERROR(IF(FILLEULS!B76="","",FILLEULS!B76)," ") | E76: =IFERROR(IF(FILLEULS!I76="","",FILLEULS!I76)," ") | F76: =IFERROR(IF(FILLEULS!E76="","",FILLEULS!E76)," ") | G76: =IFERROR(IF(AND(FILLEULS!G76="✅ ÉLIGIBLE",E76<>""),ROUND(E76*0.025,0),0),0) | M76: =IFERROR(IF(AND(FILLEULS!H76="Remboursé",FILLEULS!G76<>""),"🔻 À DÉDUIRE — Commission à reprendre"," ")," ")
A77: COM-071 | B77: =IFERROR(IF(FILLEULS!D77="","",FILLEULS!D77)," ") | C77: =IFERROR(IF(B77=" ","",VLOOKUP(B77,REGISTRE_PARRAINS!A7:B106,2,FALSE))," ") | D77: =IFERROR(IF(FILLEULS!B77="","",FILLEULS!B77)," ") | E77: =IFERROR(IF(FILLEULS!I77="","",FILLEULS!I77)," ") | F77: =IFERROR(IF(FILLEULS!E77="","",FILLEULS!E77)," ") | G77: =IFERROR(IF(AND(FILLEULS!G77="✅ ÉLIGIBLE",E77<>""),ROUND(E77*0.025,0),0),0) | M77: =IFERROR(IF(AND(FILLEULS!H77="Remboursé",FILLEULS!G77<>""),"🔻 À DÉDUIRE — Commission à reprendre"," ")," ")
A78: COM-072 | B78: =IFERROR(IF(FILLEULS!D78="","",FILLEULS!D78)," ") | C78: =IFERROR(IF(B78=" ","",VLOOKUP(B78,REGISTRE_PARRAINS!A7:B106,2,FALSE))," ") | D78: =IFERROR(IF(FILLEULS!B78="","",FILLEULS!B78)," ") | E78: =IFERROR(IF(FILLEULS!I78="","",FILLEULS!I78)," ") | F78: =IFERROR(IF(FILLEULS!E78="","",FILLEULS!E78)," ") | G78: =IFERROR(IF(AND(FILLEULS!G78="✅ ÉLIGIBLE",E78<>""),ROUND(E78*0.025,0),0),0) | M78: =IFERROR(IF(AND(FILLEULS!H78="Remboursé",FILLEULS!G78<>""),"🔻 À DÉDUIRE — Commission à reprendre"," ")," ")
A79: COM-073 | B79: =IFERROR(IF(FILLEULS!D79="","",FILLEULS!D79)," ") | C79: =IFERROR(IF(B79=" ","",VLOOKUP(B79,REGISTRE_PARRAINS!A7:B106,2,FALSE))," ") | D79: =IFERROR(IF(FILLEULS!B79="","",FILLEULS!B79)," ") | E79: =IFERROR(IF(FILLEULS!I79="","",FILLEULS!I79)," ") | F79: =IFERROR(IF(FILLEULS!E79="","",FILLEULS!E79)," ") | G79: =IFERROR(IF(AND(FILLEULS!G79="✅ ÉLIGIBLE",E79<>""),ROUND(E79*0.025,0),0),0) | M79: =IFERROR(IF(AND(FILLEULS!H79="Remboursé",FILLEULS!G79<>""),"🔻 À DÉDUIRE — Commission à reprendre"," ")," ")
A80: COM-074 | B80: =IFERROR(IF(FILLEULS!D80="","",FILLEULS!D80)," ") | C80: =IFERROR(IF(B80=" ","",VLOOKUP(B80,REGISTRE_PARRAINS!A7:B106,2,FALSE))," ") | D80: =IFERROR(IF(FILLEULS!B80="","",FILLEULS!B80)," ") | E80: =IFERROR(IF(FILLEULS!I80="","",FILLEULS!I80)," ") | F80: =IFERROR(IF(FILLEULS!E80="","",FILLEULS!E80)," ") | G80: =IFERROR(IF(AND(FILLEULS!G80="✅ ÉLIGIBLE",E80<>""),ROUND(E80*0.025,0),0),0) | M80: =IFERROR(IF(AND(FILLEULS!H80="Remboursé",FILLEULS!G80<>""),"🔻 À DÉDUIRE — Commission à reprendre"," ")," ")
A81: COM-075 | B81: =IFERROR(IF(FILLEULS!D81="","",FILLEULS!D81)," ") | C81: =IFERROR(IF(B81=" ","",VLOOKUP(B81,REGISTRE_PARRAINS!A7:B106,2,FALSE))," ") | D81: =IFERROR(IF(FILLEULS!B81="","",FILLEULS!B81)," ") | E81: =IFERROR(IF(FILLEULS!I81="","",FILLEULS!I81)," ") | F81: =IFERROR(IF(FILLEULS!E81="","",FILLEULS!E81)," ") | G81: =IFERROR(IF(AND(FILLEULS!G81="✅ ÉLIGIBLE",E81<>""),ROUND(E81*0.025,0),0),0) | M81: =IFERROR(IF(AND(FILLEULS!H81="Remboursé",FILLEULS!G81<>""),"🔻 À DÉDUIRE — Commission à reprendre"," ")," ")
A82: COM-076 | B82: =IFERROR(IF(FILLEULS!D82="","",FILLEULS!D82)," ") | C82: =IFERROR(IF(B82=" ","",VLOOKUP(B82,REGISTRE_PARRAINS!A7:B106,2,FALSE))," ") | D82: =IFERROR(IF(FILLEULS!B82="","",FILLEULS!B82)," ") | E82: =IFERROR(IF(FILLEULS!I82="","",FILLEULS!I82)," ") | F82: =IFERROR(IF(FILLEULS!E82="","",FILLEULS!E82)," ") | G82: =IFERROR(IF(AND(FILLEULS!G82="✅ ÉLIGIBLE",E82<>""),ROUND(E82*0.025,0),0),0) | M82: =IFERROR(IF(AND(FILLEULS!H82="Remboursé",FILLEULS!G82<>""),"🔻 À DÉDUIRE — Commission à reprendre"," ")," ")
A83: COM-077 | B83: =IFERROR(IF(FILLEULS!D83="","",FILLEULS!D83)," ") | C83: =IFERROR(IF(B83=" ","",VLOOKUP(B83,REGISTRE_PARRAINS!A7:B106,2,FALSE))," ") | D83: =IFERROR(IF(FILLEULS!B83="","",FILLEULS!B83)," ") | E83: =IFERROR(IF(FILLEULS!I83="","",FILLEULS!I83)," ") | F83: =IFERROR(IF(FILLEULS!E83="","",FILLEULS!E83)," ") | G83: =IFERROR(IF(AND(FILLEULS!G83="✅ ÉLIGIBLE",E83<>""),ROUND(E83*0.025,0),0),0) | M83: =IFERROR(IF(AND(FILLEULS!H83="Remboursé",FILLEULS!G83<>""),"🔻 À DÉDUIRE — Commission à reprendre"," ")," ")
A84: COM-078 | B84: =IFERROR(IF(FILLEULS!D84="","",FILLEULS!D84)," ") | C84: =IFERROR(IF(B84=" ","",VLOOKUP(B84,REGISTRE_PARRAINS!A7:B106,2,FALSE))," ") | D84: =IFERROR(IF(FILLEULS!B84="","",FILLEULS!B84)," ") | E84: =IFERROR(IF(FILLEULS!I84="","",FILLEULS!I84)," ") | F84: =IFERROR(IF(FILLEULS!E84="","",FILLEULS!E84)," ") | G84: =IFERROR(IF(AND(FILLEULS!G84="✅ ÉLIGIBLE",E84<>""),ROUND(E84*0.025,0),0),0) | M84: =IFERROR(IF(AND(FILLEULS!H84="Remboursé",FILLEULS!G84<>""),"🔻 À DÉDUIRE — Commission à reprendre"," ")," ")
A85: COM-079 | B85: =IFERROR(IF(FILLEULS!D85="","",FILLEULS!D85)," ") | C85: =IFERROR(IF(B85=" ","",VLOOKUP(B85,REGISTRE_PARRAINS!A7:B106,2,FALSE))," ") | D85: =IFERROR(IF(FILLEULS!B85="","",FILLEULS!B85)," ") | E85: =IFERROR(IF(FILLEULS!I85="","",FILLEULS!I85)," ") | F85: =IFERROR(IF(FILLEULS!E85="","",FILLEULS!E85)," ") | G85: =IFERROR(IF(AND(FILLEULS!G85="✅ ÉLIGIBLE",E85<>""),ROUND(E85*0.025,0),0),0) | M85: =IFERROR(IF(AND(FILLEULS!H85="Remboursé",FILLEULS!G85<>""),"🔻 À DÉDUIRE — Commission à reprendre"," ")," ")
A86: COM-080 | B86: =IFERROR(IF(FILLEULS!D86="","",FILLEULS!D86)," ") | C86: =IFERROR(IF(B86=" ","",VLOOKUP(B86,REGISTRE_PARRAINS!A7:B106,2,FALSE))," ") | D86: =IFERROR(IF(FILLEULS!B86="","",FILLEULS!B86)," ") | E86: =IFERROR(IF(FILLEULS!I86="","",FILLEULS!I86)," ") | F86: =IFERROR(IF(FILLEULS!E86="","",FILLEULS!E86)," ") | G86: =IFERROR(IF(AND(FILLEULS!G86="✅ ÉLIGIBLE",E86<>""),ROUND(E86*0.025,0),0),0) | M86: =IFERROR(IF(AND(FILLEULS!H86="Remboursé",FILLEULS!G86<>""),"🔻 À DÉDUIRE — Commission à reprendre"," ")," ")
A87: COM-081 | B87: =IFERROR(IF(FILLEULS!D87="","",FILLEULS!D87)," ") | C87: =IFERROR(IF(B87=" ","",VLOOKUP(B87,REGISTRE_PARRAINS!A7:B106,2,FALSE))," ") | D87: =IFERROR(IF(FILLEULS!B87="","",FILLEULS!B87)," ") | E87: =IFERROR(IF(FILLEULS!I87="","",FILLEULS!I87)," ") | F87: =IFERROR(IF(FILLEULS!E87="","",FILLEULS!E87)," ") | G87: =IFERROR(IF(AND(FILLEULS!G87="✅ ÉLIGIBLE",E87<>""),ROUND(E87*0.025,0),0),0) | M87: =IFERROR(IF(AND(FILLEULS!H87="Remboursé",FILLEULS!G87<>""),"🔻 À DÉDUIRE — Commission à reprendre"," ")," ")
A88: COM-082 | B88: =IFERROR(IF(FILLEULS!D88="","",FILLEULS!D88)," ") | C88: =IFERROR(IF(B88=" ","",VLOOKUP(B88,REGISTRE_PARRAINS!A7:B106,2,FALSE))," ") | D88: =IFERROR(IF(FILLEULS!B88="","",FILLEULS!B88)," ") | E88: =IFERROR(IF(FILLEULS!I88="","",FILLEULS!I88)," ") | F88: =IFERROR(IF(FILLEULS!E88="","",FILLEULS!E88)," ") | G88: =IFERROR(IF(AND(FILLEULS!G88="✅ ÉLIGIBLE",E88<>""),ROUND(E88*0.025,0),0),0) | M88: =IFERROR(IF(AND(FILLEULS!H88="Remboursé",FILLEULS!G88<>""),"🔻 À DÉDUIRE — Commission à reprendre"," ")," ")
A89: COM-083 | B89: =IFERROR(IF(FILLEULS!D89="","",FILLEULS!D89)," ") | C89: =IFERROR(IF(B89=" ","",VLOOKUP(B89,REGISTRE_PARRAINS!A7:B106,2,FALSE))," ") | D89: =IFERROR(IF(FILLEULS!B89="","",FILLEULS!B89)," ") | E89: =IFERROR(IF(FILLEULS!I89="","",FILLEULS!I89)," ") | F89: =IFERROR(IF(FILLEULS!E89="","",FILLEULS!E89)," ") | G89: =IFERROR(IF(AND(FILLEULS!G89="✅ ÉLIGIBLE",E89<>""),ROUND(E89*0.025,0),0),0) | M89: =IFERROR(IF(AND(FILLEULS!H89="Remboursé",FILLEULS!G89<>""),"🔻 À DÉDUIRE — Commission à reprendre"," ")," ")
A90: COM-084 | B90: =IFERROR(IF(FILLEULS!D90="","",FILLEULS!D90)," ") | C90: =IFERROR(IF(B90=" ","",VLOOKUP(B90,REGISTRE_PARRAINS!A7:B106,2,FALSE))," ") | D90: =IFERROR(IF(FILLEULS!B90="","",FILLEULS!B90)," ") | E90: =IFERROR(IF(FILLEULS!I90="","",FILLEULS!I90)," ") | F90: =IFERROR(IF(FILLEULS!E90="","",FILLEULS!E90)," ") | G90: =IFERROR(IF(AND(FILLEULS!G90="✅ ÉLIGIBLE",E90<>""),ROUND(E90*0.025,0),0),0) | M90: =IFERROR(IF(AND(FILLEULS!H90="Remboursé",FILLEULS!G90<>""),"🔻 À DÉDUIRE — Commission à reprendre"," ")," ")
A91: COM-085 | B91: =IFERROR(IF(FILLEULS!D91="","",FILLEULS!D91)," ") | C91: =IFERROR(IF(B91=" ","",VLOOKUP(B91,REGISTRE_PARRAINS!A7:B106,2,FALSE))," ") | D91: =IFERROR(IF(FILLEULS!B91="","",FILLEULS!B91)," ") | E91: =IFERROR(IF(FILLEULS!I91="","",FILLEULS!I91)," ") | F91: =IFERROR(IF(FILLEULS!E91="","",FILLEULS!E91)," ") | G91: =IFERROR(IF(AND(FILLEULS!G91="✅ ÉLIGIBLE",E91<>""),ROUND(E91*0.025,0),0),0) | M91: =IFERROR(IF(AND(FILLEULS!H91="Remboursé",FILLEULS!G91<>""),"🔻 À DÉDUIRE — Commission à reprendre"," ")," ")
A92: COM-086 | B92: =IFERROR(IF(FILLEULS!D92="","",FILLEULS!D92)," ") | C92: =IFERROR(IF(B92=" ","",VLOOKUP(B92,REGISTRE_PARRAINS!A7:B106,2,FALSE))," ") | D92: =IFERROR(IF(FILLEULS!B92="","",FILLEULS!B92)," ") | E92: =IFERROR(IF(FILLEULS!I92="","",FILLEULS!I92)," ") | F92: =IFERROR(IF(FILLEULS!E92="","",FILLEULS!E92)," ") | G92: =IFERROR(IF(AND(FILLEULS!G92="✅ ÉLIGIBLE",E92<>""),ROUND(E92*0.025,0),0),0) | M92: =IFERROR(IF(AND(FILLEULS!H92="Remboursé",FILLEULS!G92<>""),"🔻 À DÉDUIRE — Commission à reprendre"," ")," ")
A93: COM-087 | B93: =IFERROR(IF(FILLEULS!D93="","",FILLEULS!D93)," ") | C93: =IFERROR(IF(B93=" ","",VLOOKUP(B93,REGISTRE_PARRAINS!A7:B106,2,FALSE))," ") | D93: =IFERROR(IF(FILLEULS!B93="","",FILLEULS!B93)," ") | E93: =IFERROR(IF(FILLEULS!I93="","",FILLEULS!I93)," ") | F93: =IFERROR(IF(FILLEULS!E93="","",FILLEULS!E93)," ") | G93: =IFERROR(IF(AND(FILLEULS!G93="✅ ÉLIGIBLE",E93<>""),ROUND(E93*0.025,0),0),0) | M93: =IFERROR(IF(AND(FILLEULS!H93="Remboursé",FILLEULS!G93<>""),"🔻 À DÉDUIRE — Commission à reprendre"," ")," ")
A94: COM-088 | B94: =IFERROR(IF(FILLEULS!D94="","",FILLEULS!D94)," ") | C94: =IFERROR(IF(B94=" ","",VLOOKUP(B94,REGISTRE_PARRAINS!A7:B106,2,FALSE))," ") | D94: =IFERROR(IF(FILLEULS!B94="","",FILLEULS!B94)," ") | E94: =IFERROR(IF(FILLEULS!I94="","",FILLEULS!I94)," ") | F94: =IFERROR(IF(FILLEULS!E94="","",FILLEULS!E94)," ") | G94: =IFERROR(IF(AND(FILLEULS!G94="✅ ÉLIGIBLE",E94<>""),ROUND(E94*0.025,0),0),0) | M94: =IFERROR(IF(AND(FILLEULS!H94="Remboursé",FILLEULS!G94<>""),"🔻 À DÉDUIRE — Commission à reprendre"," ")," ")
A95: COM-089 | B95: =IFERROR(IF(FILLEULS!D95="","",FILLEULS!D95)," ") | C95: =IFERROR(IF(B95=" ","",VLOOKUP(B95,REGISTRE_PARRAINS!A7:B106,2,FALSE))," ") | D95: =IFERROR(IF(FILLEULS!B95="","",FILLEULS!B95)," ") | E95: =IFERROR(IF(FILLEULS!I95="","",FILLEULS!I95)," ") | F95: =IFERROR(IF(FILLEULS!E95="","",FILLEULS!E95)," ") | G95: =IFERROR(IF(AND(FILLEULS!G95="✅ ÉLIGIBLE",E95<>""),ROUND(E95*0.025,0),0),0) | M95: =IFERROR(IF(AND(FILLEULS!H95="Remboursé",FILLEULS!G95<>""),"🔻 À DÉDUIRE — Commission à reprendre"," ")," ")
A96: COM-090 | B96: =IFERROR(IF(FILLEULS!D96="","",FILLEULS!D96)," ") | C96: =IFERROR(IF(B96=" ","",VLOOKUP(B96,REGISTRE_PARRAINS!A7:B106,2,FALSE))," ") | D96: =IFERROR(IF(FILLEULS!B96="","",FILLEULS!B96)," ") | E96: =IFERROR(IF(FILLEULS!I96="","",FILLEULS!I96)," ") | F96: =IFERROR(IF(FILLEULS!E96="","",FILLEULS!E96)," ") | G96: =IFERROR(IF(AND(FILLEULS!G96="✅ ÉLIGIBLE",E96<>""),ROUND(E96*0.025,0),0),0) | M96: =IFERROR(IF(AND(FILLEULS!H96="Remboursé",FILLEULS!G96<>""),"🔻 À DÉDUIRE — Commission à reprendre"," ")," ")
A97: COM-091 | B97: =IFERROR(IF(FILLEULS!D97="","",FILLEULS!D97)," ") | C97: =IFERROR(IF(B97=" ","",VLOOKUP(B97,REGISTRE_PARRAINS!A7:B106,2,FALSE))," ") | D97: =IFERROR(IF(FILLEULS!B97="","",FILLEULS!B97)," ") | E97: =IFERROR(IF(FILLEULS!I97="","",FILLEULS!I97)," ") | F97: =IFERROR(IF(FILLEULS!E97="","",FILLEULS!E97)," ") | G97: =IFERROR(IF(AND(FILLEULS!G97="✅ ÉLIGIBLE",E97<>""),ROUND(E97*0.025,0),0),0) | M97: =IFERROR(IF(AND(FILLEULS!H97="Remboursé",FILLEULS!G97<>""),"🔻 À DÉDUIRE — Commission à reprendre"," ")," ")
A98: COM-092 | B98: =IFERROR(IF(FILLEULS!D98="","",FILLEULS!D98)," ") | C98: =IFERROR(IF(B98=" ","",VLOOKUP(B98,REGISTRE_PARRAINS!A7:B106,2,FALSE))," ") | D98: =IFERROR(IF(FILLEULS!B98="","",FILLEULS!B98)," ") | E98: =IFERROR(IF(FILLEULS!I98="","",FILLEULS!I98)," ") | F98: =IFERROR(IF(FILLEULS!E98="","",FILLEULS!E98)," ") | G98: =IFERROR(IF(AND(FILLEULS!G98="✅ ÉLIGIBLE",E98<>""),ROUND(E98*0.025,0),0),0) | M98: =IFERROR(IF(AND(FILLEULS!H98="Remboursé",FILLEULS!G98<>""),"🔻 À DÉDUIRE — Commission à reprendre"," ")," ")
A99: COM-093 | B99: =IFERROR(IF(FILLEULS!D99="","",FILLEULS!D99)," ") | C99: =IFERROR(IF(B99=" ","",VLOOKUP(B99,REGISTRE_PARRAINS!A7:B106,2,FALSE))," ") | D99: =IFERROR(IF(FILLEULS!B99="","",FILLEULS!B99)," ") | E99: =IFERROR(IF(FILLEULS!I99="","",FILLEULS!I99)," ") | F99: =IFERROR(IF(FILLEULS!E99="","",FILLEULS!E99)," ") | G99: =IFERROR(IF(AND(FILLEULS!G99="✅ ÉLIGIBLE",E99<>""),ROUND(E99*0.025,0),0),0) | M99: =IFERROR(IF(AND(FILLEULS!H99="Remboursé",FILLEULS!G99<>""),"🔻 À DÉDUIRE — Commission à reprendre"," ")," ")
A100: COM-094 | B100: =IFERROR(IF(FILLEULS!D100="","",FILLEULS!D100)," ") | C100: =IFERROR(IF(B100=" ","",VLOOKUP(B100,REGISTRE_PARRAINS!A7:B106,2,FALSE))," ") | D100: =IFERROR(IF(FILLEULS!B100="","",FILLEULS!B100)," ") | E100: =IFERROR(IF(FILLEULS!I100="","",FILLEULS!I100)," ") | F100: =IFERROR(IF(FILLEULS!E100="","",FILLEULS!E100)," ") | G100: =IFERROR(IF(AND(FILLEULS!G100="✅ ÉLIGIBLE",E100<>""),ROUND(E100*0.025,0),0),0) | M100: =IFERROR(IF(AND(FILLEULS!H100="Remboursé",FILLEULS!G100<>""),"🔻 À DÉDUIRE — Commission à reprendre"," ")," ")
A101: COM-095 | B101: =IFERROR(IF(FILLEULS!D101="","",FILLEULS!D101)," ") | C101: =IFERROR(IF(B101=" ","",VLOOKUP(B101,REGISTRE_PARRAINS!A7:B106,2,FALSE))," ") | D101: =IFERROR(IF(FILLEULS!B101="","",FILLEULS!B101)," ") | E101: =IFERROR(IF(FILLEULS!I101="","",FILLEULS!I101)," ") | F101: =IFERROR(IF(FILLEULS!E101="","",FILLEULS!E101)," ") | G101: =IFERROR(IF(AND(FILLEULS!G101="✅ ÉLIGIBLE",E101<>""),ROUND(E101*0.025,0),0),0) | M101: =IFERROR(IF(AND(FILLEULS!H101="Remboursé",FILLEULS!G101<>""),"🔻 À DÉDUIRE — Commission à reprendre"," ")," ")
...

Sheet ALERTES_FRAUDE
A1: 🚨 ALERTES FRAUDE — VERROUS 1 à 5 | LEMI SARL | BRASUS v3.2
A2: 🔒 Toutes les colonnes sont verrouillées sauf STATUT TRAITEMENT (réservé DG) | Calcul auto depuis verrous
A3: BLOQUANT = Opération refusée automatiquement | REVUE MANUELLE = Signal orange, flux non interrompu
A5: DATE DÉTECTION | B5: TYPE SIGNAL | C5: PARRAIN CONCERNÉ | D5: FILLEUL CONCERNÉ | E5: NIVEAU | F5: DÉTAIL | G5: STATUT TRAITEMENT

Sheet TACHES_PERIODIQUES
A1: 📋 TÂCHES PÉRIODIQUES — MODULE PARRAINAGE | LEMI SARL | BRASUS v3.2
A2: 🔒 Zone A — Planning opérationnel du programme de parrainage — Lecture seule
A4: FRÉQUENCE | B4: TÂCHE | C4: RESPONSABLE | D4: DÉLAI | E4: STATUT
A5: QUOTIDIEN | B5: Vérifier les nouveaux filleuls déclarés — contrôler éligibilité (Verrous 1-2) | C5: Resp. Commercial | D5: 10h00 | E5: 🟢
B6: Traiter les commissions au statut "À valider" — valider ou refuser | C6: DG | D6: 17h00 | E6: 🟢
B7: Vérifier les alertes fraude du jour — traiter les signaux bloquants | C7: DG | D7: 17h30 | E7: 🟢
A8: HEBDOMADAIRE | B8: Vérifier ALERTES_FRAUDE — traiter chaque signal orange (Verrou 5) | C8: DG | D8: Vendredi 16h | E8: 🟢
B9: Effectuer les virements Orange Money/Wave des commissions validées DG | C9: Resp. Financier | D9: Vendredi | E9: 🟢
B10: Mettre à jour le classement Top 5 parrains — communiquer au DG | C10: Resp. Commercial | D10: Vendredi | E10: 🟢
A11: MENSUEL | B11: Rapport parrainage mensuel — nb filleuls, montant versé, top parrains, ROI | C11: Resp. Commercial | D11: J+2 du mois | E11: 🟢
B12: Vérifier les clawbacks du mois — déductions correctement appliquées | C12: Resp. Financier | D12: J+3 du mois | E12: 🟢
B13: Intégrer les commissions versées dans 02_FINANCE charges mensuelles | C13: Resp. Financier | D13: J+5 du mois | E13: 🟢
A14: TRIMESTRIEL | B14: Bilan du programme — ROI parrainage vs coût acquisition Meta Ads | C14: DG + DMA | D14: Fin trimestre | E14: 🟢
B15: Évaluer le taux de commission (2,5%) — ajuster si nécessaire | C15: DG + DMA | D15: Fin trimestre | E15: 🟢
A16: ANNUEL | B16: Décision de reconduction / ajustement du taux de commission | C16: DG | D16: Avril 2027 | E16: 🟢
A18: CHECKLIST DE VALIDATION DU MODULE
A19: ✅ | B19: Code parrain généré automatiquement et unique (LEMI-PARR-XXX)
A20: ✅ | B20: Verrou 1 (unicité téléphone) : actif — NB.SI bloque les doublons
A21: ✅ | B21: Verrou 2 (déclaration 1er contact) : actif — comparaison dates
A22: ✅ | B22: Verrou 3 (clawback) : ligne de dette auto si remboursement < 30j
A23: ✅ | B23: Verrou 4 : aucune commission → Payé sans case DG cochée + ref. transaction
A24: ✅ | B24: Verrou 5 (signaux faibles) : alertes orange non bloquantes activées
A25: ✅ | B25: Commission = Acompte filleul × 2,5% — formule vérifiée
A26: ✅ | B26: Référence externe vers CRM fonctionnelle (pas de ressaisie)
A27: ✅ | B27: Commissions intégrées dans FINANCE charges mensuelles
A28: ✅ | B28: KPI parrainage visibles dans DASHBOARD
A29: ✅ | B29: Couleurs et verrouillage conformes au système BRASUS existant
