Workbook

Sheet 1 — MISSIONS DU JOUR
A1: LEMI SARL | RESPONSABLE FINANCE | MISSIONS DU JOUR — [DATE DU JOUR] | BRASUS v3.2
A2: ZONE A — GÉNÉRÉ PAR BRASUS 🔒 (Ne pas modifier) | F2: ZONE B — VOTRE SAISIE ✏️ (Remplissez ici)
A3: N° | B3: MISSION | C3: OBJECTIF LIÉ | D3: RÉSULTAT ATTENDU | E3: PRIORITÉ | F3: STATUT | G3: ACTIONS RÉALISÉES | H3: RÉSULTAT OBTENU | I3: DIFFICULTÉ | J3: ESCALADE
A4: 1 | B4: Enregistrer tous les encaissements et décaissements du jour (Wave, Orange Money, virement bancaire) | C4: Trésorerie à jour en temps réel | Solde journalier calculé et validé avant 18h | D4: Journal de caisse complet — Trésorerie disponible communiquée au DG via WhatsApp | E4: HAUTE
A5: 2 | B5: Vérifier les échéances Tontine Habitat du mois — identifier les retards de paiement clients | C5: 0 impayé > J+3 non détecté | Liste retards transmise au Commercial pour relance immédiate | D5: Liste impayés par client (montant, jours de retard, pénalités J+7 calculées) envoyée Commercial + DG | E5: HAUTE
A6: 3 | B6: Appliquer le protocole recouvrement LEMI SARL pour tous les clients en retard > J+7 | C6: 100% des retards > J+7 avec pénalité 1%/semaine calculée et relevé envoyé au client | D6: Pénalités calculées et communiquées aux clients — J+30 signalés pour suspension formelle des travaux | E6: HAUTE
A7: 4 | B7: Préparer les devis, factures et contrats Tontine demandés par le département Commercial | C7: Délai de traitement < 24h | Tous documents > 100 000 FCFA validés par DG avant envoi | D7: Documents traités, archivés dans Google Drive /Facturation/ — Numérotation séquentielle respectée | E7: MOYENNE
A8: 5 | B8: Calculer la marge brute des chantiers livrés cette semaine (matériaux + MO vs CA encaissé) | C8: Marge brute ≥ 22% minimum | Alerte si marge < 22% — analyse dérive coûts nécessaire | D8: Rapport de marge soumis au DG — Recommandations si marge < cible identifiées et documentées | E8: MOYENNE
A9: ⏰ Clôture automatique à 18h00 — Zone B verrouillée après clôture | F9: Horodatage clôture :

Sheet 2 — EXÉCUTION JOURNALIÈRE
A1: ZONE B — EXÉCUTION JOURNALIÈRE ✏️ | LEMI SARL | Toutes les colonnes sont à remplir
A2: HEURE | B2: ACTION RÉALISÉE | C2: RÉSULTAT OBTENU | D2: BILAN / COMMENTAIRE | E2: BESOIN / ESCALADE
A13: BRASUS analyse ces données chaque soir à 18h00 pour calculer votre taux de performance

Sheet 3 — MES PERFORMANCES
A1: ZONE A — MES PERFORMANCES — RESPONSABLE FINANCE | LEMI SARL | BRASUS v3.2
A2: 🔒 Calculé automatiquement par BRASUS à 18h00 chaque jour — Ne pas modifier
A3: INDICATEUR | B3: VALEUR | C3: BASE DE CALCUL | D3: COMMENTAIRE BRASUS
A4: TAUX D'EXÉCUTION JOURNALIER | B4: [ Calculé à 18h00 ] | C4: Statuts FAIT dans Onglet 1 Zone B
A5: TAUX D'EXÉCUTION HEBDOMADAIRE | B5: [ Moy. 5 jours ] | C5: Moyenne des taux journaliers
A6: TAUX D'EXÉCUTION MENSUEL | B6: [ Moy. mensuelle ] | C6: Moyenne des taux du mois en cours
A7: TAUX D'EXÉCUTION ANNUEL | B7: [ Moy. annuelle ] | C7: Moyenne depuis le 1er janvier
A9: NIVEAU DE PERFORMANCE | B9: [ Calculé ] | C9: Basé sur le taux journalier du jour
A10: MISSIONS RÉALISÉES / TOTAL | B10: [ Calculé ] | C10: Nombre de FAIT sur 5 missions
A11: DATE DE DERNIÈRE MISE À JOUR | B11: [ Horodatage ] | C11: Clôture automatique 18h00
A12: NIVEAUX DE PERFORMANCE BRASUS
A13: 90 – 100% | B13: 🟢 EXCELLENT | C13: Message de reconnaissance BRASUS
A14: 75 – 89% | B14: 🔵 BON | C14: Encouragement + 1 conseil
A15: 60 – 74% | B15: 🟡 MOYEN | C15: Plan d'amélioration — Onglet 5
A16: 40 – 59% | B16: 🟠 INSUFFISANT | C16: Alerte RH + plan de soutien
A17: < 40% | B17: 🔴 CRITIQUE | C17: Alerte Direction immédiate

Sheet 4 — MON HISTORIQUE
A1: ZONE A — MON HISTORIQUE — RESPONSABLE FINANCE | LEMI SARL | Archivage automatique BRASUS
A2: 🔒 Archives horodatées automatiquement à 18h00 par BRASUS — Ne pas modifier
A3: DATE | B3: MISSIONS RÉALISÉES | C3: TAUX (%) | D3: NIVEAU | E3: COMMENTAIRE BRASUS

Sheet 5 — MON PLAN D'AMÉLIORATION
A1: ZONE A — PLAN D'AMÉLIORATION HEBDOMADAIRE — RESPONSABLE FINANCE | LEMI SARL
A2: 🔒 Généré chaque vendredi soir par BRASUS selon vos performances de la semaine | Ne pas modifier
A3: Semaine du : [DATE DÉBUT] au [DATE FIN] | Taux hebdomadaire : [X]% | Niveau : [NIVEAU]
A4: # | B4: RECOMMANDATION BRASUS | C4: COMMENT FAIRE | D4: DÉLAI | E4: IMPACT
A5: 1 | B5: [ Recommandation BRASUS — Générée chaque vendredi selon vos performances ] | C5: Coller ici le résultat de Claude / BRASUS | D5: Semaine suivante | E5: Moyen
A6: 2 | B6: [ Recommandation BRASUS — Générée chaque vendredi selon vos performances ] | C6: Coller ici le résultat de Claude / BRASUS | D6: Semaine suivante | E6: Moyen
A7: 3 | B7: [ Recommandation BRASUS — Point fort à renforcer ] | C7: Basé sur votre meilleure journée de la semaine | D7: Continu | E7: Élevé
A8: 4 | B8: [ Point de vigilance BRASUS ] | C8: Basé sur votre journée la plus faible | D8: Immédiat | E8: Élevé
A9: 5 | B9: [ Alerte BRASUS si taux < 60% ] | C9: Plan de redressement personnalisé | D9: Immédiat | E9: Critique

Sheet TACHES_PERIODIQUES
A1: 📋 TÂCHES PÉRIODIQUES — FINANCE | LEMI SARL | BRASUS v3.2
A2: 🔒 Planning operationnel Finance — Inclut la gestion des commissions parrainage
A3: 🔒 ZONE A — Taches et delais (verrouille) | E3: ✏️ ZONE B — Suivi execution (deverrouille)
A4: FRÉQUENCE | B4: TÂCHE | C4: RESPONSABLE | D4: DÉLAI | E4: STATUT | F4: DATE EXÉCUTION | G4: COMMENTAIRES
A5: QUOTIDIEN | B5: Enregistrer tous les encaissements et decaissements du jour dans le journal de caisse | C5: Resp. Finance | D5: 17h30
B6: Communiquer la tresorerie disponible au DG via WhatsApp | C6: Resp. Finance | D6: 18h00
B7: Verifier les echeances Tontine Habitat — identifier retards > J+3 | C7: Resp. Finance | D7: 16h00
A8: HEBDOMADAIRE | B8: Executer les virements Orange Money/Wave des commissions parrainage 'Valide DG' | C8: Resp. Finance | D8: Vendredi
B9: Saisir chaque commission versee dans le journal (categorie 'Commission parrainage') | C9: Resp. Finance | D9: Vendredi
B10: Calculer la marge brute des chantiers livres de la semaine | C10: Resp. Finance | D10: Vendredi 16h
A11: MENSUEL | B11: Rapport tresorerie mensuel : encaissements, decaissements, solde | C11: Resp. Finance | D11: J+2 du mois
B12: Verifier le total mensuel des commissions versees vs charges mensuelles | C12: Resp. Finance | D12: J+3 du mois
B13: Appliquer les deductions clawback identifiees dans 08_PARRAINAGE.xlsx | C13: Resp. Finance | D13: J+3 du mois
B14: Bilan recouvrement : clients en retard, penalites, suspensions | C14: Resp. Finance | D14: J+5 du mois
A15: TRIMESTRIEL | B15: Analyse des marges par type de projet (Studio, T2, T3, PDL) | C15: Resp. Finance + DG | D15: Fin de trimestre
A16: ANNUEL | B16: Cloture comptable annuelle — preparation bilan | C16: Resp. Finance + DG | D16: Janvier 2027
A17: Nouvelles taches issues du module 08_PARRAINAGE.xlsx — Integrées par BRASUS v3.2

Sheet DASHBOARD TRESORERIE
A1: 📊 DASHBOARD TRÉSORERIE — LEMI SARL | BRASUS v3.2
A2: 🔒 Consolidation automatique depuis les onglets mensuels — Lecture seule
B4: KPI FLASH — TRÉSORERIE
B5: Total encaissé cumul 13 mois (FCFA) | C5: =IFERROR(SUM(C14:C26),0) -> 0
B6: Total décaissé cumul (FCFA) | C6: =IFERROR(SUM(D14:D26),0) -> 0
B7: Solde net trésorerie (FCFA) | C7: =IFERROR(C5-C6,0) -> 0
B8: Nb opérations décaissement | C8: =IFERROR(COUNTA(D14:D26)-COUNTBLANK(D14:D26),0) -> 0
B9: Postes en dépassement budget | C9: =0 -> 0
B12: RÉCAPITULATIF MENSUEL — ENCAISSEMENTS
B13: MOIS | C13: ENCAISSÉ (FCFA) | D13: DÉCAISSÉ (FCFA) | E13: SOLDE NET
B14: Juin 2026 | C14: 0 | D14: 0 | E14: =IFERROR(C14-D14,0) -> 0
B15: Juil 2026 | C15: 0 | D15: 0 | E15: =IFERROR(C15-D15,0) -> 0
B16: Août 2026 | C16: 0 | D16: 0 | E16: =IFERROR(C16-D16,0) -> 0
B17: Sep 2026 | C17: 0 | D17: 0 | E17: =IFERROR(C17-D17,0) -> 0
B18: Oct 2026 | C18: 0 | D18: 0 | E18: =IFERROR(C18-D18,0) -> 0
B19: Nov 2026 | C19: 0 | D19: 0 | E19: =IFERROR(C19-D19,0) -> 0
B20: Déc 2026 | C20: 0 | D20: 0 | E20: =IFERROR(C20-D20,0) -> 0
B21: Jan 2027 | C21: 0 | D21: 0 | E21: =IFERROR(C21-D21,0) -> 0
B22: Fév 2027 | C22: 0 | D22: 0 | E22: =IFERROR(C22-D22,0) -> 0
B23: Mar 2027 | C23: 0 | D23: 0 | E23: =IFERROR(C23-D23,0) -> 0
B24: Avr 2027 | C24: 0 | D24: 0 | E24: =IFERROR(C24-D24,0) -> 0
B25: Mai 2027 | C25: 0 | D25: 0 | E25: =IFERROR(C25-D25,0) -> 0
B26: Juin 2027 | C26: 0 | D26: 0 | E26: =IFERROR(C26-D26,0) -> 0
B27: TOTAL 13 MOIS | C27: =IFERROR(SUM(C14:C26),0) -> 0 | D27: =IFERROR(SUM(D14:D26),0) -> 0 | E27: =IFERROR(C27-D27,0) -> 0

Sheet SYNC_FINANCE
A3: ✏️ ZONE A — Identité Prospect (saisie CM) | J3: ✏️ ZONE B — Dates & Montants (saisie Resp. Financier) | M3: ⚙️ AUTO — Total | N3: ✏️ ZONE B — Date Levée Conditions | O3: ⚙️ AUTO — ALERTE JOURS
A4: N° | B4: N° IDENTIFIANT | C4: NOM & PRÉNOMS DU PROSPECT | D4: SOURCE DU PROSPECT | E4: DATE PREMIER CONTACT | F4: JOUR | G4: CONTACT TÉLÉPHONIQUE & WHATSAPP | H4: PROFESSION | I4: NUMÉRO DU CONTRAT | J4: DATE DE SIGNATURE DES CONTRATS | K4: APPORT INITIAL (30%) À LA SIGNATURE | L4: MONTANT PAIEMENT À LA SIGNATURE | M4: TOTAL PAIEMENT À LA SIGNATURE | N4: DATE D'ACHÈVEMENT PRÉVUE LEVÉE DE CONDITIONS | O4: NOMBRE DE JOURS RESTANTS LEVÉE DE CONDITIONS
A5: 1 | C5: TANOH KONAN GERVAIS ARMAND | D5: Prospection directe | E5: 15/03/2026 | F5: =IFERROR(IF(E5="","",TEXT(E5,"DDDD")),"" ) -> 15/03/2026 | K5: 0 | L5: 0 | M5: =IFERROR(IF(K5+L5=0,"—",K5+L5),"—") -> — | O5: =IFERROR(IF(N5="","—",MAX(0,INT(N5)-INT(TODAY()))),"—") -> —
A6: 2 | C6: N'DRI ép. NGBESSO AKISSI ELIANE | D6: Réseaux sociaux | E6: 24/09/2024 | F6: =IFERROR(IF(E6="","",TEXT(E6,"DDDD")),"" ) -> 24/09/2024 | G6: 0033 651 75 83 12 | K6: 0 | L6: 0 | M6: =IFERROR(IF(K6+L6=0,"—",K6+L6),"—") -> — | O6: =IFERROR(IF(N6="","—",MAX(0,INT(N6)-INT(TODAY()))),"—") -> —
A7: 3 | C7: N'GORAN KOFFI | D7: Parrainage | E7: 15/03/2026 | F7: =IFERROR(IF(E7="","",TEXT(E7,"DDDD")),"" ) -> 15/03/2026 | G7: 788738933 | K7: 0 | L7: 0 | M7: =IFERROR(IF(K7+L7=0,"—",K7+L7),"—") -> — | O7: =IFERROR(IF(N7="","—",MAX(0,INT(N7)-INT(TODAY()))),"—") -> —
A8: 4 | C8: KOUASSI VINCENT DE PAUL ASSOUMOU | D8: Prospection directe | E8: 04/11/2024 | F8: =IFERROR(IF(E8="","",TEXT(E8,"DDDD")),"" ) -> Thursday | G8: 708010188 | K8: 0 | L8: 0 | M8: =IFERROR(IF(K8+L8=0,"—",K8+L8),"—") -> — | O8: =IFERROR(IF(N8="","—",MAX(0,INT(N8)-INT(TODAY()))),"—") -> —
A9: 5 | C9: KOUASSI HONORE | D9: Prospection directe | E9: 07/08/2025 | F9: =IFERROR(IF(E9="","",TEXT(E9,"DDDD")),"" ) -> Tuesday | G9: 103319771 | K9: 0 | L9: 0 | M9: =IFERROR(IF(K9+L9=0,"—",K9+L9),"—") -> — | O9: =IFERROR(IF(N9="","—",MAX(0,INT(N9)-INT(TODAY()))),"—") -> —
A10: 6 | C10: AKISSI ELIANE KONAN | D10: Prospection directe | E10: 25/08/2025 | F10: =IFERROR(IF(E10="","",TEXT(E10,"DDDD")),"" ) -> 25/08/2025 | G10: 0102197828 | K10: 0 | L10: 0 | M10: =IFERROR(IF(K10+L10=0,"—",K10+L10),"—") -> — | O10: =IFERROR(IF(N10="","—",MAX(0,INT(N10)-INT(TODAY()))),"—") -> —
A11: 7 | C11: BROU LAMBERT KOUASSI | D11: Prospection directe | E11: 30/08/2025 | F11: =IFERROR(IF(E11="","",TEXT(E11,"DDDD")),"" ) -> 30/08/2025 | G11: 0708937533 | K11: 0 | L11: 0 | M11: =IFERROR(IF(K11+L11=0,"—",K11+L11),"—") -> — | O11: =IFERROR(IF(N11="","—",MAX(0,INT(N11)-INT(TODAY()))),"—") -> —
A12: 8 | C12: DJEDRI KOUAKOU JEAN PIERRE | D12: Prospection directe | E12: 10/10/2025 | F12: =IFERROR(IF(E12="","",TEXT(E12,"DDDD")),"" ) -> Friday | G12: 078866828 | K12: 0 | L12: 0 | M12: =IFERROR(IF(K12+L12=0,"—",K12+L12),"—") -> — | O12: =IFERROR(IF(N12="","—",MAX(0,INT(N12)-INT(TODAY()))),"—") -> —
A13: 9 | C13: DJAMAN KOUAKOU MATHIEU | D13: Prospection directe | E13: 17/11/2025 | F13: =IFERROR(IF(E13="","",TEXT(E13,"DDDD")),"" ) -> 17/11/2025 | G13: 0707382557 | K13: 0 | L13: 0 | M13: =IFERROR(IF(K13+L13=0,"—",K13+L13),"—") -> — | O13: =IFERROR(IF(N13="","—",MAX(0,INT(N13)-INT(TODAY()))),"—") -> —
A14: 10 | C14: N'GUESSAN KOUASSI | D14: Prospection directe | E14: 20/12/2025 | F14: =IFERROR(IF(E14="","",TEXT(E14,"DDDD")),"" ) -> 20/12/2025 | G14: 0789937292 | K14: 0 | L14: 0 | M14: =IFERROR(IF(K14+L14=0,"—",K14+L14),"—") -> — | O14: =IFERROR(IF(N14="","—",MAX(0,INT(N14)-INT(TODAY()))),"—") -> —
A15: 11 | C15: N'ZUE N'GUESSAN | D15: Prospection directe | E15: 14/01/2026 | F15: =IFERROR(IF(E15="","",TEXT(E15,"DDDD")),"" ) -> 14/01/2026 | G15: 0747571448 | K15: 0 | L15: 0 | M15: =IFERROR(IF(K15+L15=0,"—",K15+L15),"—") -> — | O15: =IFERROR(IF(N15="","—",MAX(0,INT(N15)-INT(TODAY()))),"—") -> —
A16: 12 | C16: CASIMIR | D16: Prospection directe | E16: 08/04/2026 | F16: =IFERROR(IF(E16="","",TEXT(E16,"DDDD")),"" ) -> Tuesday | G16: 0709411969 | K16: 0 | L16: 0 | M16: =IFERROR(IF(K16+L16=0,"—",K16+L16),"—") -> — | O16: =IFERROR(IF(N16="","—",MAX(0,INT(N16)-INT(TODAY()))),"—") -> —
A17: 13 | F17: =IFERROR(IF(E17="","",TEXT(E17,"DDDD")),"" ) | K17: 0 | L17: 0 | M17: =IFERROR(IF(K17+L17=0,"—",K17+L17),"—") -> — | O17: =IFERROR(IF(N17="","—",MAX(0,INT(N17)-INT(TODAY()))),"—") -> —
A18: 14 | F18: =IFERROR(IF(E18="","",TEXT(E18,"DDDD")),"" ) | K18: 0 | L18: 0 | M18: =IFERROR(IF(K18+L18=0,"—",K18+L18),"—") -> — | O18: =IFERROR(IF(N18="","—",MAX(0,INT(N18)-INT(TODAY()))),"—") -> —
A19: 15 | F19: =IFERROR(IF(E19="","",TEXT(E19,"DDDD")),"" ) | K19: 0 | L19: 0 | M19: =IFERROR(IF(K19+L19=0,"—",K19+L19),"—") -> — | O19: =IFERROR(IF(N19="","—",MAX(0,INT(N19)-INT(TODAY()))),"—") -> —
A20: 16 | F20: =IFERROR(IF(E20="","",TEXT(E20,"DDDD")),"" ) | K20: 0 | L20: 0 | M20: =IFERROR(IF(K20+L20=0,"—",K20+L20),"—") -> — | O20: =IFERROR(IF(N20="","—",MAX(0,INT(N20)-INT(TODAY()))),"—") -> —
A21: 17 | F21: =IFERROR(IF(E21="","",TEXT(E21,"DDDD")),"" ) | K21: 0 | L21: 0 | M21: =IFERROR(IF(K21+L21=0,"—",K21+L21),"—") -> — | O21: =IFERROR(IF(N21="","—",MAX(0,INT(N21)-INT(TODAY()))),"—") -> —
A22: 18 | F22: =IFERROR(IF(E22="","",TEXT(E22,"DDDD")),"" ) | K22: 0 | L22: 0 | M22: =IFERROR(IF(K22+L22=0,"—",K22+L22),"—") -> — | O22: =IFERROR(IF(N22="","—",MAX(0,INT(N22)-INT(TODAY()))),"—") -> —
A23: 19 | F23: =IFERROR(IF(E23="","",TEXT(E23,"DDDD")),"" ) | K23: 0 | L23: 0 | M23: =IFERROR(IF(K23+L23=0,"—",K23+L23),"—") -> — | O23: =IFERROR(IF(N23="","—",MAX(0,INT(N23)-INT(TODAY()))),"—") -> —
A24: 20 | F24: =IFERROR(IF(E24="","",TEXT(E24,"DDDD")),"" ) | K24: 0 | L24: 0 | M24: =IFERROR(IF(K24+L24=0,"—",K24+L24),"—") -> — | O24: =IFERROR(IF(N24="","—",MAX(0,INT(N24)-INT(TODAY()))),"—") -> —
A25: 21 | F25: =IFERROR(IF(E25="","",TEXT(E25,"DDDD")),"" ) | K25: 0 | L25: 0 | M25: =IFERROR(IF(K25+L25=0,"—",K25+L25),"—") -> — | O25: =IFERROR(IF(N25="","—",MAX(0,INT(N25)-INT(TODAY()))),"—") -> —
A26: 22 | F26: =IFERROR(IF(E26="","",TEXT(E26,"DDDD")),"" ) | K26: 0 | L26: 0 | M26: =IFERROR(IF(K26+L26=0,"—",K26+L26),"—") -> — | O26: =IFERROR(IF(N26="","—",MAX(0,INT(N26)-INT(TODAY()))),"—") -> —
A27: 23 | F27: =IFERROR(IF(E27="","",TEXT(E27,"DDDD")),"" ) | K27: 0 | L27: 0 | M27: =IFERROR(IF(K27+L27=0,"—",K27+L27),"—") -> — | O27: =IFERROR(IF(N27="","—",MAX(0,INT(N27)-INT(TODAY()))),"—") -> —
A28: 24 | F28: =IFERROR(IF(E28="","",TEXT(E28,"DDDD")),"" ) | K28: 0 | L28: 0 | M28: =IFERROR(IF(K28+L28=0,"—",K28+L28),"—") -> — | O28: =IFERROR(IF(N28="","—",MAX(0,INT(N28)-INT(TODAY()))),"—") -> —
... A1004: 1000 | F1004: =IFERROR(IF(E1004="","",TEXT(E1004,"DDDD")),"" ) | K1004: 0 | L1004: 0 | M1004: =IFERROR(IF(K1004+L1004=0,"—",K1004+L1004),"—") -> — | O1004: =IFERROR(IF(N1004="","—",MAX(0,INT(N1004)-INT(TODAY()))),"—") -> —
I1005: 🏁 TOTAUX GÉNÉRAUX — 1 000 CONTRATS | K1005: =IFERROR(SUM(K5:K1004),0) -> 0 | L1005: =IFERROR(SUM(L5:L1004),0) -> 0 | M1005: =IFERROR(SUM(K5:K1004)+SUM(L5:L1004),0) -> 0 | O1005: —
I1007: 🔗 FLUX 1 — FORMULES À COPIER DANS TABLEAU BRD DU SUIVI MAÎTRE (ligne 6 = Contrat 1 | ligne 7 = Contrat 2 | ligne N+5 = Contrat N) : X6 = ='[FINANCE_COMPLET_UPDATED.xlsx]SYNC_FINANCE'!$A$5 (N° CONTRAT) Y6 = ='[FINANCE_COMPLET_UPDATED.xlsx]SYNC_FINANCE'!$B$5 (DATE SIGNATURE) Z6 = ='[FINANCE_COMPLET_UPDATED.xlsx]SYNC_FINANCE'!$C$5 (APPORT 30%) AA6= ='[FINANCE_COMPLET_UPDATED.xlsx]SYNC_FINANCE'!$D$5 (MONTANT PAIEMENT) AB6= ='[FINANCE_COMPLET_UPDATED.xlsx]SYNC_FINANCE'!$E$5 (TOTAL PAIEMENT) AC6= ='[FINANCE_COMPLET_UPDATED.xlsx]SYNC_FINANCE'!$F$5 (DATE LEVÉE COND.) AD6= ='[FINANCE_COMPLET_UPDATED.xlsx]SYNC_FINANCE'!$G$5 (JOURS RESTANTS) → Contrat 2 : $5→$6 | Contrat N : $(N+4)
I1009: 🔗 FLUX 2 — PAIEMENTS [MOIS] → SUIVI [MOIS] (exemple Client 1 = ligne 6) : SUIVI JUIN B6 = ='[FINANCE_COMPLET_UPDATED.xlsx]PAIEMENTS JUIN 2026'!$B$6 SUIVI JUIN R6 = ='[FINANCE_COMPLET_UPDATED.xlsx]PAIEMENTS JUIN 2026'!$C$6 SUIVI JUIN K6 = ='[FINANCE_COMPLET_UPDATED.xlsx]PAIEMENTS JUIN 2026'!$D$6 SUIVI JUIN O6 = ='[FINANCE_COMPLET_UPDATED.xlsx]PAIEMENTS JUIN 2026'!$E$6 SUIVI JUIN T6 = ='[FINANCE_COMPLET_UPDATED.xlsx]PAIEMENTS JUIN 2026'!$F$6 SUIVI JUIN U6 = ='[FINANCE_COMPLET_UPDATED.xlsx]PAIEMENTS JUIN 2026'!$G$6 SUIVI JUIN V6 = ='[FINANCE_COMPLET_UPDATED.xlsx]PAIEMENTS JUIN 2026'!$H$6 SUIVI JUIN W6 = ='[FINANCE_COMPLET_UPDATED.xlsx]PAIEMENTS JUIN 2026'!$I$6 SUIVI JUIN X6 = ='[FINANCE_COMPLET_UPDATED.xlsx]PAIEMENTS JUIN 2026'!$J$6 SUIVI JUIN Y6 = ='[FINANCE_COMPLET_UPDATED.xlsx]PAIEMENTS JUIN 2026'!$K$6 SUIVI JUIN Z6 = ='[FINANCE_COMPLET_UPDATED.xlsx]PAIEMENTS JUIN 2026'!$L$6 SUIVI JUIN AA6= ='[FINANCE_COMPLET_UPDATED.xlsx]PAIEMENTS JUIN 2026'!$M$6 SUIVI JUIN AB6= ='[FINANCE_COMPLET_UPDATED.xlsx]PAIEMENTS JUIN 2026'!$N$6 SUIVI JUIN AC6= ='[FINANCE_COMPLET_UPDATED.xlsx]PAIEMENTS JUIN 2026'!$O$6 SUIVI JUIN AD6= ='[FINANCE_COMPLET_UPDATED.xlsx]PAIEMENTS JUIN 2026'!$P$6 → Même logique pour JUILLET 2026 … JUIN 2027 (remplacer nom onglet)

Sheet PAIEMENTS JUIN 2026
A1: 💰 PAIEMENTS JUIN 2026 — LEMI SARL | BRASUS v3.2
A2: ⚠️ Saisie des paiements reçus par semaine. Alimente automatiquement le SUIVI 13 MOIS.
A3: 🔒 Identité client (auto) | K3: 📋 Contrat | N3: ✏️ PAIEMENTS JUIN — 4 semaines × (Paiement + Droit + Apport) | Z3: ⚙️ CALCULS AUTO
N4: 01/06-07/06 | Q4: 08/06-15/06 | T4: 16/06-24/06 | W4: 25/06-30/06
A5: N° | B5: N° IDENTIFIANT | C5: NOM & PRÉNOMS DU CLIENT | D5: SOURCE DU PROSPECT | E5: DATE PREMIER CONTACT | F5: TÉLÉPHONE / WHATSAPP | G5: PROFESSION | H5: RÉGION D'HABITATION | I5: RÉGION DU PROJET | J5: LIEU DU PROJET | K5: N° CONTRAT | L5: MONTANT TTC (FCFA) | M5: MENSUALITÉ (FCFA) | N5: PAIEMENT | O5: DROIT ADHÉSION | P5: APPORT INITIAL | Q5: PAIEMENT | R5: DROIT ADHÉSION | S5: APPORT INITIAL | T5: PAIEMENT | U5: DROIT ADHÉSION | V5: APPORT INITIAL | W5: PAIEMENT | X5: DROIT ADHÉSION | Y5: APPORT INITIAL | Z5: TOTAL MOIS | AA5: MENSUALITÉ DUE | AB5: CUMUL PAIEMENTS | AC5: RESTANT DÛ
A6: 1 | B6: =IFERROR([1]SYNC_PROSPECTION_MKT!$B$5,"") -> 0 | C6: =IFERROR([1]SYNC_PROSPECTION_MKT!$C$5,"") -> TANOH KONAN GERVAIS ARMAND | D6: =IFERROR([1]SYNC_PROSPECTION_MKT!$D$5,"") -> 0 | E6: =IFERROR([1]SYNC_PROSPECTION_MKT!$E$5,"") -> 0 | F6: =IFERROR([1]SYNC_PROSPECTION_MKT!$G$5,"") -> 0 | G6: =IFERROR([1]SYNC_PROSPECTION_MKT!$H$5,"") -> 0 | H6: =IFERROR([1]SYNC_PROSPECTION_MKT!$J$5,"") -> 0 | I6: =IFERROR([1]SYNC_PROSPECTION_MKT!$I$5,"") -> 0 | J6: =IFERROR([1]SYNC_PROSPECTION_MKT!$K$5,"") -> 0 | K6: =IFERROR(SYNC_FINANCE!$I$5,"") -> 0 | L6: =IFERROR([2]SYNC_COMMERCIAL_VENTE!$S$5,"") -> 0 | M6: 0 | N6: 0 | O6: 0 | P6: 0 | Q6: 0 | R6: 0 | S6: 0 | T6: 0 | U6: 0 | V6: 0 | W6: 0 | X6: 0 | Y6: 0 | Z6: =IFERROR(SUM(N6:Y6),0) -> 0 | AA6: =IFERROR((N6+Q6+T6+W6)-M6,0) -> 0 | AB6: =IFERROR(Z6,0) -> 0 | AC6: =IFERROR(L6-AB6,0) -> 0
A7: 2 | B7: =IFERROR([1]SYNC_PROSPECTION_MKT!$B$6,"") -> 0 | C7: =IFERROR([1]SYNC_PROSPECTION_MKT!$C$6,"") -> N'DRI ép. NGBESSO AKISSI ELIANE | D7: =IFERROR([1]SYNC_PROSPECTION_MKT!$D$6,"") -> 0 | E7: =IFERROR([1]SYNC_PROSPECTION_MKT!$E$6,"") -> 0 | F7: =IFERROR([1]SYNC_PROSPECTION_MKT!$G$6,"") -> 0 | G7: =IFERROR([1]SYNC_PROSPECTION_MKT!$H$6,"") -> 0 | H7: =IFERROR([1]SYNC_PROSPECTION_MKT!$J$6,"") -> 0 | I7: =IFERROR([1]SYNC_PROSPECTION_MKT!$I$6,"") -> 0 | J7: =IFERROR([1]SYNC_PROSPECTION_MKT!$K$6,"") -> 0 | K7: =IFERROR(SYNC_FINANCE!$I$6,"") -> 0 | L7: =IFERROR([2]SYNC_COMMERCIAL_VENTE!$S$6,"") -> 0 | M7: 0 | N7: 0 | O7: 0 | P7: 0 | Q7: 0 | R7: 0 | S7: 0 | T7: 0 | U7: 0 | V7: 0 | W7: 0 | X7: 0 | Y7: 0 | Z7: =IFERROR(SUM(N7:Y7),0) -> 0 | AA7: =IFERROR((N7+Q7+T7+W7)-M7,0) -> 0 | AB7: =IFERROR(Z7,0) -> 0 | AC7: =IFERROR(L7-AB7,0) -> 0
A8: 3 | B8: =IFERROR([1]SYNC_PROSPECTION_MKT!$B$7,"") -> 0 | C8: =IFERROR([1]SYNC_PROSPECTION_MKT!$C$7,"") -> N'GORAN KOFFI | D8: =IFERROR([1]SYNC_PROSPECTION_MKT!$D$7,"") -> 0 | E8: =IFERROR([1]SYNC_PROSPECTION_MKT!$E$7,"") -> 0 | F8: =IFERROR([1]SYNC_PROSPECTION_MKT!$G$7,"") -> 0 | G8: =IFERROR([1]SYNC_PROSPECTION_MKT!$H$7,"") -> 0 | H8: =IFERROR([1]SYNC_PROSPECTION_MKT!$J$7,"") -> 0 | I8: =IFERROR([1]SYNC_PROSPECTION_MKT!$I$7,"") -> 0 | J8: =IFERROR([1]SYNC_PROSPECTION_MKT!$K$7,"") -> 0 | K8: =IFERROR(SYNC_FINANCE!$I$7,"") -> 0 | L8: =IFERROR([2]SYNC_COMMERCIAL_VENTE!$S$7,"") -> 0 | M8: 0 | N8: 0 | O8: 0 | P8: 0 | Q8: 0 | R8: 0 | S8: 0 | T8: 0 | U8: 0 | V8: 0 | W8: 0 | X8: 0 | Y8: 0 | Z8: =IFERROR(SUM(N8:Y8),0) -> 0 | AA8: =IFERROR((N8+Q8+T8+W8)-M8,0) -> 0 | AB8: =IFERROR(Z8,0) -> 0 | AC8: =IFERROR(L8-AB8,0) -> 0
A9: 4 | B9: =IFERROR([1]SYNC_PROSPECTION_MKT!$B$8,"") -> 0 | C9: =IFERROR([1]SYNC_PROSPECTION_MKT!$C$8,"") -> KOUASSI VINCENT DE PAUL ASSOUMOU | D9: =IFERROR([1]SYNC_PROSPECTION_MKT!$D$8,"") -> 0 | E9: =IFERROR([1]SYNC_PROSPECTION_MKT!$E$8,"") -> 0 | F9: =IFERROR([1]SYNC_PROSPECTION_MKT!$G$8,"") -> 0 | G9: =IFERROR([1]SYNC_PROSPECTION_MKT!$H$8,"") -> 0 | H9: =IFERROR([1]SYNC_PROSPECTION_MKT!$J$8,"") -> 0 | I9: =IFERROR([1]SYNC_PROSPECTION_MKT!$I$8,"") -> 0 | J9: =IFERROR([1]SYNC_PROSPECTION_MKT!$K$8,"") -> 0 | K9: =IFERROR(SYNC_FINANCE!$I$8,"") -> 0 | L9: =IFERROR([2]SYNC_COMMERCIAL_VENTE!$S$8,"") -> 0 | M9: 0 | N9: 0 | O9: 0 | P9: 0 | Q9: 0 | R9: 0 | S9: 0 | T9: 0 | U9: 0 | V9: 0 | W9: 0 | X9: 0 | Y9: 0 | Z9: =IFERROR(SUM(N9:Y9),0) -> 0 | AA9: =IFERROR((N9+Q9+T9+W9)-M9,0) -> 0 | AB9: =IFERROR(Z9,0) -> 0 | AC9: =IFERROR(L9-AB9,0) -> 0
A10: 5 | B10: =IFERROR([1]SYNC_PROSPECTION_MKT!$B$9,"") -> 0 | C10: =IFERROR([1]SYNC_PROSPECTION_MKT!$C$9,"") -> KOUASSI HONORE | D10: =IFERROR([1]SYNC_PROSPECTION_MKT!$D$9,"") -> 0 | E10: =IFERROR([1]SYNC_PROSPECTION_MKT!$E$9,"") -> 0 | F10: =IFERROR([1]SYNC_PROSPECTION_MKT!$G$9,"") -> 0 | G10: =IFERROR([1]SYNC_PROSPECTION_MKT!$H$9,"") -> 0 | H10: =IFERROR([1]SYNC_PROSPECTION_MKT!$J$9,"") -> 0 | I10: =IFERROR([1]SYNC_PROSPECTION_MKT!$I$9,"") -> 0 | J10: =IFERROR([1]SYNC_PROSPECTION_MKT!$K$9,"") -> 0 | K10: =IFERROR(SYNC_FINANCE!$I$9,"") -> 0 | L10: =IFERROR([2]SYNC_COMMERCIAL_VENTE!$S$9,"") -> 0 | M10: 0 | N10: 0 | O10: 0 | P10: 0 | Q10: 0 | R10: 0 | S10: 0 | T10: 0 | U10: 0 | V10: 0 | W10: 0 | X10: 0 | Y10: 0 | Z10: =IFERROR(SUM(N10:Y10),0) -> 0 | AA10: =IFERROR((N10+Q10+T10+W10)-M10,0) -> 0 | AB10: =IFERROR(Z10,0) -> 0 | AC10: =IFERROR(L10-AB10,0) -> 0
A11: 6 | B11: =IFERROR([1]SYNC_PROSPECTION_MKT!$B$10,"") -> 0 | C11: =IFERROR([1]SYNC_PROSPECTION_MKT!$C$10,"") -> AKISSI ELIANE KONAN | D11: =IFERROR([1]SYNC_PROSPECTION_MKT!$D$10,"") -> 0 | E11: =IFERROR([1]SYNC_PROSPECTION_MKT!$E$10,"") -> 0 | F11: =IFERROR([1]SYNC_PROSPECTION_MKT!$G$10,"") -> 0 | G11: =IFERROR([1]SYNC_PROSPECTION_MKT!$H$10,"") -> 0 | H11: =IFERROR([1]SYNC_PROSPECTION_MKT!$J$10,"") -> 0 | I11: =IFERROR([1]SYNC_PROSPECTION_MKT!$I$10,"") -> 0 | J11: =IFERROR([1]SYNC_PROSPECTION_MKT!$K$10,"") -> 0 | K11: =IFERROR(SYNC_FINANCE!$I$10,"") -> 0 | L11: =IFERROR([2]SYNC_COMMERCIAL_VENTE!$S$10,"") -> 0 | M11: 0 | N11: 0 | O11: 0 | P11: 0 | Q11: 0 | R11: 0 | S11: 0 | T11: 0 | U11: 0 | V11: 0 | W11: 0 | X11: 0 | Y11: 0 | Z11: =IFERROR(SUM(N11:Y11),0) -> 0 | AA11: =IFERROR((N11+Q11+T11+W11)-M11,0) -> 0 | AB11: =IFERROR(Z11,0) -> 0 | AC11: =IFERROR(L11-AB11,0) -> 0
A12: 7 | B12: =IFERROR([1]SYNC_PROSPECTION_MKT!$B$11,"") -> 0 | C12: =IFERROR([1]SYNC_PROSPECTION_MKT!$C$11,"") -> BROU LAMBERT KOUASSI | D12: =IFERROR([1]SYNC_PROSPECTION_MKT!$D$11,"") -> 0 | E12: =IFERROR([1]SYNC_PROSPECTION_MKT!$E$11,"") -> 0 | F12: =IFERROR([1]SYNC_PROSPECTION_MKT!$G$11,"") -> 0 | G12: =IFERROR([1]SYNC_PROSPECTION_MKT!$H$11,"") -> 0 | H12: =IFERROR([1]SYNC_PROSPECTION_MKT!$J$11,"") -> 0 | I12: =IFERROR([1]SYNC_PROSPECTION_MKT!$I$11,"") -> 0 | J12: =IFERROR([1]SYNC_PROSPECTION_MKT!$K$11,"") -> 0 | K12: =IFERROR(SYNC_FINANCE!$I$11,"") -> 0 | L12: =IFERROR([2]SYNC_COMMERCIAL_VENTE!$S$11,"") -> 0 | M12: 0 | N12: 0 | O12: 0 | P12: 0 | Q12: 0 | R12: 0 | S12: 0 | T12: 0 | U12: 0 | V12: 0 | W12: 0 | X12: 0 | Y12: 0 | Z12: =IFERROR(SUM(N12:Y12),0) -> 0 | AA12: =IFERROR((N12+Q12+T12+W12)-M12,0) -> 0 | AB12: =IFERROR(Z12,0) -> 0 | AC12: =IFERROR(L12-AB12,0) -> 0
A13: 8 | B13: =IFERROR([1]SYNC_PROSPECTION_MKT!$B$12,"") -> 0 | C13: =IFERROR([1]SYNC_PROSPECTION_MKT!$C$12,"") -> DJEDRI KOUAKOU JEAN PIERRE | D13: =IFERROR([1]SYNC_PROSPECTION_MKT!$D$12,"") -> 0 | E13: =IFERROR([1]SYNC_PROSPECTION_MKT!$E$12,"") -> 0 | F13: =IFERROR([1]SYNC_PROSPECTION_MKT!$G$12,"") -> 0 | G13: =IFERROR([1]SYNC_PROSPECTION_MKT!$H$12,"") -> 0 | H13: =IFERROR([1]SYNC_PROSPECTION_MKT!$J$12,"") -> 0 | I13: =IFERROR([1]SYNC_PROSPECTION_MKT!$I$12,"") -> 0 | J13: =IFERROR([1]SYNC_PROSPECTION_MKT!$K$12,"") -> 0 | K13: =IFERROR(SYNC_FINANCE!$I$12,"") -> 0 | L13: =IFERROR([2]SYNC_COMMERCIAL_VENTE!$S$12,"") -> 0 | M13: 0 | N13: 0 | O13: 0 | P13: 0 | Q13: 0 | R13: 0 | S13: 0 | T13: 0 | U13: 0 | V13: 0 | W13: 0 | X13: 0 | Y13: 0 | Z13: =IFERROR(SUM(N13:Y13),0) -> 0 | AA13: =IFERROR((N13+Q13+T13+W13)-M13,0) -> 0 | AB13: =IFERROR(Z13,0) -> 0 | AC13: =IFERROR(L13-AB13,0) -> 0
A14: 9 | B14: =IFERROR([1]SYNC_PROSPECTION_MKT!$B$13,"") -> 0 | C14: =IFERROR([1]SYNC_PROSPECTION_MKT!$C$13,"") -> DJAMAN KOUAKOU MATHIEU | D14: =IFERROR([1]SYNC_PROSPECTION_MKT!$D$13,"") -> 0 | E14: =IFERROR([1]SYNC_PROSPECTION_MKT!$E$13,"") -> 0 | F14: =IFERROR([1]SYNC_PROSPECTION_MKT!$G$13,"") -> 0 | G14: =IFERROR([1]SYNC_PROSPECTION_MKT!$H$13,"") -> 0 | H14: =IFERROR([1]SYNC_PROSPECTION_MKT!$J$13,"") -> 0 | I14: =IFERROR([1]SYNC_PROSPECTION_MKT!$I$13,"") -> 0 | J14: =IFERROR([1]SYNC_PROSPECTION_MKT!$K$13,"") -> 0 | K14: =IFERROR(SYNC_FINANCE!$I$13,"") -> 0 | L14: =IFERROR([2]SYNC_COMMERCIAL_VENTE!$S$13,"") -> 0 | M14: 0 | N14: 0 | O14: 0 | P14: 0 | Q14: 0 | R14: 0 | S14: 0 | T14: 0 | U14: 0 | V14: 0 | W14: 0 | X14: 0 | Y14: 0 | Z14: =IFERROR(SUM(N14:Y14),0) -> 0 | AA14: =IFERROR((N14+Q14+T14+W14)-M14,0) -> 0 | AB14: =IFERROR(Z14,0) -> 0 | AC14: =IFERROR(L14-AB14,0) -> 0
A15: 10 | B15: =IFERROR([1]SYNC_PROSPECTION_MKT!$B$14,"") -> 0 | C15: =IFERROR([1]SYNC_PROSPECTION_MKT!$C$14,"") -> N'GUESSAN KOUASSI | D15: =IFERROR([1]SYNC_PROSPECTION_MKT!$D$14,"") -> 0 | E15: =IFERROR([1]SYNC_PROSPECTION_MKT!$E$14,"") -> 0 | F15: =IFERROR([1]SYNC_PROSPECTION_MKT!$G$14,"") -> 0 | G15: =IFERROR([1]SYNC_PROSPECTION_MKT!$H$14,"") -> 0 | H15: =IFERROR([1]SYNC_PROSPECTION_MKT!$J$14,"") -> 0 | I15: =IFERROR([1]SYNC_PROSPECTION_MKT!$I$14,"") -> 0 | J15: =IFERROR([1]SYNC_PROSPECTION_MKT!$K$14,"") -> 0 | K15: =IFERROR(SYNC_FINANCE!$I$14,"") -> 0 | L15: =IFERROR([2]SYNC_COMMERCIAL_VENTE!$S$14,"") -> 0 | M15: 0 | N15: 0 | O15: 0 | P15: 0 | Q15: 0 | R15: 0 | S15: 0 | T15: 0 | U15: 0 | V15: 0 | W15: 0 | X15: 0 | Y15: 0 | Z15: =IFERROR(SUM(N15:Y15),0) -> 0 | AA15: =IFERROR((N15+Q15+T15+W15)-M15,0) -> 0 | AB15: =IFERROR(Z15,0) -> 0 | AC15: =IFERROR(L15-AB15,0) -> 0
A16: 11 | B16: =IFERROR([1]SYNC_PROSPECTION_MKT!$B$15,"") -> 0 | C16: =IFERROR([1]SYNC_PROSPECTION_MKT!$C$15,"") -> N'ZUE N'GUESSAN | D16: =IFERROR([1]SYNC_PROSPECTION_MKT!$D$15,"") -> 0 | E16: =IFERROR([1]SYNC_PROSPECTION_MKT!$E$15,"") -> 0 | F16: =IFERROR([1]SYNC_PROSPECTION_MKT!$G$15,"") -> 0 | G16: =IFERROR([1]SYNC_PROSPECTION_MKT!$H$15,"") -> 0 | H16: =IFERROR([1]SYNC_PROSPECTION_MKT!$J$15,"") -> 0 | I16: =IFERROR([1]SYNC_PROSPECTION_MKT!$I$15,"") -> 0 | J16: =IFERROR([1]SYNC_PROSPECTION_MKT!$K$15,"") -> 0 | K16: =IFERROR(SYNC_FINANCE!$I$15,"") -> 0 | L16: =IFERROR([2]SYNC_COMMERCIAL_VENTE!$S$15,"") -> 0 | M16: 0 | N16: 0 | O16: 0 | P16: 0 | Q16: 0 | R16: 0 | S16: 0 | T16: 0 | U16: 0 | V16: 0 | W16: 0 | X16: 0 | Y16: 0 | Z16: =IFERROR(SUM(N16:Y16),0) -> 0 | AA16: =IFERROR((N16+Q16+T16+W16)-M16,0) -> 0 | AB16: =IFERROR(Z16,0) -> 0 | AC16: =IFERROR(L16-AB16,0) -> 0
A17: 12 | B17: =IFERROR([1]SYNC_PROSPECTION_MKT!$B$16,"") -> 0 | C17: =IFERROR([1]SYNC_PROSPECTION_MKT!$C$16,"") -> CASIMIR | D17: =IFERROR([1]SYNC_PROSPECTION_MKT!$D$16,"") -> 0 | E17: =IFERROR([1]SYNC_PROSPECTION_MKT!$E$16,"") -> 0 | F17: =IFERROR([1]SYNC_PROSPECTION_MKT!$G$16,"") -> 0 | G17: =IFERROR([1]SYNC_PROSPECTION_MKT!$H$16,"") -> 0 | H17: =IFERROR([1]SYNC_PROSPECTION_MKT!$J$16,"") -> 0 | I17: =IFERROR([1]SYNC_PROSPECTION_MKT!$I$16,"") -> 0 | J17: =IFERROR([1]SYNC_PROSPECTION_MKT!$K$16,"") -> 0 | K17: =IFERROR(SYNC_FINANCE!$I$16,"") -> 0 | L17: =IFERROR([2]SYNC_COMMERCIAL_VENTE!$S$16,"") -> 0 | M17: 0 | N17: 0 | O17: 0 | P17: 0 | Q17: 0 | R17: 0 | S17: 0 | T17: 0 | U17: 0 | V17: 0 | W17: 0 | X17: 0 | Y17: 0 | Z17: =IFERROR(SUM(N17:Y17),0) -> 0 | AA17: =IFERROR((N17+Q17+T17+W17)-M17,0) -> 0 | AB17: =IFERROR(Z17,0) -> 0 | AC17: =IFERROR(L17-AB17,0) -> 0
A18: 13 | B18: =IFERROR([1]SYNC_PROSPECTION_MKT!$B$17,"") -> 0 | C18: =IFERROR([1]SYNC_PROSPECTION_MKT!$C$17,"") -> 0 | D18: =IFERROR([1]SYNC_PROSPECTION_MKT!$D$17,"") -> 0 | E18: =IFERROR([1]SYNC_PROSPECTION_MKT!$E$17,"") -> 0 | F18: =IFERROR([1]SYNC_PROSPECTION_MKT!$G$17,"") -> 0 | G18: =IFERROR([1]SYNC_PROSPECTION_MKT!$H$17,"") -> 0 | H18: =IFERROR([1]SYNC_PROSPECTION_MKT!$J$17,"") -> 0 | I18: =IFERROR([1]SYNC_PROSPECTION_MKT!$I$17,"") -> 0 | J18: =IFERROR([1]SYNC_PROSPECTION_MKT!$K$17,"") -> 0 | K18: =IFERROR(SYNC_FINANCE!$I$17,"") -> 0 | L18: =IFERROR([2]SYNC_COMMERCIAL_VENTE!$S$17,"") -> 0 | M18: 0 | N18: 0 | O18: 0 | P18: 0 | Q18: 0 | R18: 0 | S18: 0 | T18: 0 | U18: 0 | V18: 0 | W18: 0 | X18: 0 | Y18: 0 | Z18: =IFERROR(SUM(N18:Y18),0) -> 0 | AA18: =IFERROR((N18+Q18+T18+W18)-M18,0) -> 0 | AB18: =IFERROR(Z18,0) -> 0 | AC18: =IFERROR(L18-AB18,0) -> 0
A19: 14 | B19: =IFERROR([1]SYNC_PROSPECTION_MKT!$B$18,"") -> 0 | C19: =IFERROR([1]SYNC_PROSPECTION_MKT!$C$18,"") -> 0 | D19: =IFERROR([1]SYNC_PROSPECTION_MKT!$D$18,"") -> 0 | E19: =IFERROR([1]SYNC_PROSPECTION_MKT!$E$18,"") -> 0 | F19: =IFERROR([1]SYNC_PROSPECTION_MKT!$G$18,"") -> 0 | G19: =IFERROR([1]SYNC_PROSPECTION_MKT!$H$18,"") -> 0 | H19: =IFERROR([1]SYNC_PROSPECTION_MKT!$J$18,"") -> 0 | I19: =IFERROR([1]SYNC_PROSPECTION_MKT!$I$18,"") -> 0 | J19: =IFERROR([1]SYNC_PROSPECTION_MKT!$K$18,"") -> 0 | K19: =IFERROR(SYNC_FINANCE!$I$18,"") -> 0 | L19: =IFERROR([2]SYNC_COMMERCIAL_VENTE!$S$18,"") -> 0 | M19: 0 | N19: 0 | O19: 0 | P19: 0 | Q19: 0 | R19: 0 | S19: 0 | T19: 0 | U19: 0 | V19: 0 | W19: 0 | X19: 0 | Y19: 0 | Z19: =IFERROR(SUM(N19:Y19),0) -> 0 | AA19: =IFERROR((N19+Q19+T19+W19)-M19,0) -> 0 | AB19: =IFERROR(Z19,0) -> 0 | AC19: =IFERROR(L19-AB19,0) -> 0
A20: 15 | B20: =IFERROR([1]SYNC_PROSPECTION_MKT!$B$19,"") -> 0 | C20: =IFERROR([1]SYNC_PROSPECTION_MKT!$C$19,"") -> 0 | D20: =IFERROR([1]SYNC_PROSPECTION_MKT!$D$19,"") -> 0 | E20: =IFERROR([1]SYNC_PROSPECTION_MKT!$E$19,"") -> 0 | F20: =IFERROR([1]SYNC_PROSPECTION_MKT!$G$19,"") -> 0 | G20: =IFERROR([1]SYNC_PROSPECTION_MKT!$H$19,"") -> 0 | H20: =IFERROR([1]SYNC_PROSPECTION_MKT!$J$19,"") -> 0 | I20: =IFERROR([1]SYNC_PROSPECTION_MKT!$I$19,"") -> 0 | J20: =IFERROR([1]SYNC_PROSPECTION_MKT!$K$19,"") -> 0 | K20: =IFERROR(SYNC_FINANCE!$I$19,"") -> 0 | L20: =IFERROR([2]SYNC_COMMERCIAL_VENTE!$S$19,"") -> 0 | M20: 0 | N20: 0 | O20: 0 | P20: 0 | Q20: 0 | R20: 0 | S20: 0 | T20: 0 | U20: 0 | V20: 0 | W20: 0 | X20: 0 | Y20: 0 | Z20: =IFERROR(SUM(N20:Y20),0) -> 0 | AA20: =IFERROR((N20+Q20+T20+W20)-M20,0) -> 0 | AB20: =IFERROR(Z20,0) -> 0 | AC20: =IFERROR(L20-AB20,0) -> 0
A21: 16 | B21: =IFERROR([1]SYNC_PROSPECTION_MKT!$B$20,"") -> 0 | C21: =IFERROR([1]SYNC_PROSPECTION_MKT!$C$20,"") -> 0 | D21: =IFERROR([1]SYNC_PROSPECTION_MKT!$D$20,"") -> 0 | E21: =IFERROR([1]SYNC_PROSPECTION_MKT!$E$20,"") -> 0 | F21: =IFERROR([1]SYNC_PROSPECTION_MKT!$G$20,"") -> 0 | G21: =IFERROR([1]SYNC_PROSPECTION_MKT!$H$20,"") -> 0 | H21: =IFERROR([1]SYNC_PROSPECTION_MKT!$J$20,"") -> 0 | I21: =IFERROR([1]SYNC_PROSPECTION_MKT!$I$20,"") -> 0 | J21: =IFERROR([1]SYNC_PROSPECTION_MKT!$K$20,"") -> 0 | K21: =IFERROR(SYNC_FINANCE!$I$20,"") -> 0 | L21: =IFERROR([2]SYNC_COMMERCIAL_VENTE!$S$20,"") -> 0 | M21: 0 | N21: 0 | O21: 0 | P21: 0 | Q21: 0 | R21: 0 | S21: 0 | T21: 0 | U21: 0 | V21: 0 | W21: 0 | X21: 0 | Y21: 0 | Z21: =IFERROR(SUM(N21:Y21),0) -> 0 | AA21: =IFERROR((N21+Q21+T21+W21)-M21,0) -> 0 | AB21: =IFERROR(Z21,0) -> 0 | AC21: =IFERROR(L21-AB21,0) -> 0
A22: 17 | B22: =IFERROR([1]SYNC_PROSPECTION_MKT!$B$21,"") -> 0 | C22: =IFERROR([1]SYNC_PROSPECTION_MKT!$C$21,"") -> 0 | D22: =IFERROR([1]SYNC_PROSPECTION_MKT!$D$21,"") -> 0 | E22: =IFERROR([1]SYNC_PROSPECTION_MKT!$E$21,"") -> 0 | F22: =IFERROR([1]SYNC_PROSPECTION_MKT!$G$21,"") -> 0 | G22: =IFERROR([1]SYNC_PROSPECTION_MKT!$H$21,"") -> 0 | H22: =IFERROR([1]SYNC_PROSPECTION_MKT!$J$21,"") -> 0 | I22: =IFERROR([1]SYNC_PROSPECTION_MKT!$I$21,"") -> 0 | J22: =IFERROR([1]SYNC_PROSPECTION_MKT!$K$21,"") -> 0 | K22: =IFERROR(SYNC_FINANCE!$I$21,"") -> 0 | L22: =IFERROR([2]SYNC_COMMERCIAL_VENTE!$S$21,"") -> 0 | M22: 0 | N22: 0 | O22: 0 | P22: 0 | Q22: 0 | R22: 0 | S22: 0 | T22: 0 | U22: 0 | V22: 0 | W22: 0 | X22: 0 | Y22: 0 | Z22: =IFERROR(SUM(N22:Y22),0) -> 0 | AA22: =IFERROR((N22+Q22+T22+W22)-M22,0) -> 0 | AB22: =IFERROR(Z22,0) -> 0 | AC22: =IFERROR(L22-AB22,0) -> 0
A23: 18 | B23: =IFERROR([1]SYNC_PROSPECTION_MKT!$B$22,"") -> 0 | C23: =IFERROR([1]SYNC_PROSPECTION_MKT!$C$22,"") -> 0 | D23: =IFERROR([1]SYNC_PROSPECTION_MKT!$D$22,"") -> 0 | E23: =IFERROR([1]SYNC_PROSPECTION_MKT!$E$22,"") -> 0 | F23: =IFERROR([1]SYNC_PROSPECTION_MKT!$G$22,"") -> 0 | G23: =IFERROR([1]SYNC_PROSPECTION_MKT!$H$22,"") -> 0 | H23: =IFERROR([1]SYNC_PROSPECTION_MKT!$J$22,"") -> 0 | I23: =IFERROR([1]SYNC_PROSPECTION_MKT!$I$22,"") -> 0 | J23: =IFERROR([1]SYNC_PROSPECTION_MKT!$K$22,"") -> 0 | K23: =IFERROR(SYNC_FINANCE!$I$22,"") -> 0 | L23: =IFERROR([2]SYNC_COMMERCIAL_VENTE!$S$22,"") -> 0 | M23: 0 | N23: 0 | O23: 0 | P23: 0 | Q23: 0 | R23: 0 | S23: 0 | T23: 0 | U23: 0 | V23: 0 | W23: 0 | X23: 0 | Y23: 0 | Z23: =IFERROR(SUM(N23:Y23),0) -> 0 | AA23: =IFERROR((N23+Q23+T23+W23)-M23,0) -> 0 | AB23: =IFERROR(Z23,0) -> 0 | AC23: =IFERROR(L23-AB23,0) -> 0
A24: 19 | B24: =IFERROR([1]SYNC_PROSPECTION_MKT!$B$23,"") -> 0 | C24: =IFERROR([1]SYNC_PROSPECTION_MKT!$C$23,"") -> 0 | D24: =IFERROR([1]SYNC_PROSPECTION_MKT!$D$23,"") -> 0 | E24: =IFERROR([1]SYNC_PROSPECTION_MKT!$E$23,"") -> 0 | F24: =IFERROR([1]SYNC_PROSPECTION_MKT!$G$23,"") -> 0 | G24: =IFERROR([1]SYNC_PROSPECTION_MKT!$H$23,"") -> 0 | H24: =IFERROR([1]SYNC_PROSPECTION_MKT!$J$23,"") -> 0 | I24: =IFERROR([1]SYNC_PROSPECTION_MKT!$I$23,"") -> 0 | J24: =IFERROR([1]SYNC_PROSPECTION_MKT!$K$23,"") -> 0 | K24: =IFERROR(SYNC_FINANCE!$I$23,"") -> 0 | L24: =IFERROR([2]SYNC_COMMERCIAL_VENTE!$S$23,"") -> 0 | M24: 0 | N24: 0 | O24: 0 | P24: 0 | Q24: 0 | R24: 0 | S24: 0 | T24: 0 | U24: 0 | V24: 0 | W24: 0 | X24: 0 | Y24: 0 | Z24: =IFERROR(SUM(N24:Y24),0) -> 0 | AA24: =IFERROR((N24+Q24+T24+W24)-M24,0) -> 0 | AB24: =IFERROR(Z24,0) -> 0 | AC24: =IFERROR(L24-AB24,0) -> 0
A25: 20 | B25: =IFERROR([1]SYNC_PROSPECTION_MKT!$B$24,"") -> 0 | C25: =IFERROR([1]SYNC_PROSPECTION_MKT!$C$24,"") -> 0 | D25: =IFERROR([1]SYNC_PROSPECTION_MKT!$D$24,"") -> 0 | E25: =IFERROR([1]SYNC_PROSPECTION_MKT!$E$24,"") -> 0 | F25: =IFERROR([1]SYNC_PROSPECTION_MKT!$G$24,"") -> 0 | G25: =IFERROR([1]SYNC_PROSPECTION_MKT!$H$24,"") -> 0 | H25: =IFERROR([1]SYNC_PROSPECTION_MKT!$J$24,"") -> 0 | I25: =IFERROR([1]SYNC_PROSPECTION_MKT!$I$24,"") -> 0 | J25: =IFERROR([1]SYNC_PROSPECTION_MKT!$K$24,"") -> 0 | K25: =IFERROR(SYNC_FINANCE!$I$24,"") -> 0 | L25: =IFERROR([2]SYNC_COMMERCIAL_VENTE!$S$24,"") -> 0 | M25: 0 | N25: 0 | O25: 0 | P25: 0 | Q25: 0 | R25: 0 | S25: 0 | T25: 0 | U25: 0 | V25: 0 | W25: 0 | X25: 0 | Y25: 0 | Z25: =IFERROR(SUM(N25:Y25),0) -> 0 | AA25: =IFERROR((N25+Q25+T25+W25)-M25,0) -> 0 | AB25: =IFERROR(Z25,0) -> 0 | AC25: =IFERROR(L25-AB25,0) -> 0
A26: 21 | B26: =IFERROR([1]SYNC_PROSPECTION_MKT!$B$25,"") -> 0 | C26: =IFERROR([1]SYNC_PROSPECTION_MKT!$C$25,"") -> 0 | D26: =IFERROR([1]SYNC_PROSPECTION_MKT!$D$25,"") -> 0 | E26: =IFERROR([1]SYNC_PROSPECTION_MKT!$E$25,"") -> 0 | F26: =IFERROR([1]SYNC_PROSPECTION_MKT!$G$25,"") -> 0 | G26: =IFERROR([1]SYNC_PROSPECTION_MKT!$H$25,"") -> 0 | H26: =IFERROR([1]SYNC_PROSPECTION_MKT!$J$25,"") -> 0 | I26: =IFERROR([1]SYNC_PROSPECTION_MKT!$I$25,"") -> 0 | J26: =IFERROR([1]SYNC_PROSPECTION_MKT!$K$25,"") -> 0 | K26: =IFERROR(SYNC_FINANCE!$I$25,"") -> 0 | L26: =IFERROR([2]SYNC_COMMERCIAL_VENTE!$S$25,"") -> 0 | M26: 0 | N26: 0 | O26: 0 | P26: 0 | Q26: 0 | R26: 0 | S26: 0 | T26: 0 | U26: 0 | V26: 0 | W26: 0 | X26: 0 | Y26: 0 | Z26: =IFERROR(SUM(N26:Y26),0) -> 0 | AA26: =IFERROR((N26+Q26+T26+W26)-M26,0) -> 0 | AB26: =IFERROR(Z26,0) -> 0 | AC26: =IFERROR(L26-AB26,0) -> 0
A27: 22 | B27: =IFERROR([1]SYNC_PROSPECTION_MKT!$B$26,"") -> 0 | C27: =IFERROR([1]SYNC_PROSPECTION_MKT!$C$26,"") -> 0 | D27: =IFERROR([1]SYNC_PROSPECTION_MKT!$D$26,"") -> 0 | E27: =IFERROR([1]SYNC_PROSPECTION_MKT!$E$26,"") -> 0 | F27: =IFERROR([1]SYNC_PROSPECTION_MKT!$G$26,"") -> 0 | G27: =IFERROR([1]SYNC_PROSPECTION_MKT!$H$26,"") -> 0 | H27: =IFERROR([1]SYNC_PROSPECTION_MKT!$J$26,"") -> 0 | I27: =IFERROR([1]SYNC_PROSPECTION_MKT!$I$26,"") -> 0 | J27: =IFERROR([1]SYNC_PROSPECTION_MKT!$K$26,"") -> 0 | K27: =IFERROR(SYNC_FINANCE!$I$26,"") -> 0 | L27: =IFERROR([2]SYNC_COMMERCIAL_VENTE!$S$26,"") -> 0 | M27: 0 | N27: 0 | O27: 0 | P27: 0 | Q27: 0 | R27: 0 | S27: 0 | T27: 0 | U27: 0 | V27: 0 | W27: 0 | X27: 0 | Y27: 0 | Z27: =IFERROR(SUM(N27:Y27),0) -> 0 | AA27: =IFERROR((N27+Q27+T27+W27)-M27,0) -> 0 | AB27: =IFERROR(Z27,0) -> 0 | AC27: =IFERROR(L27-AB27,0) -> 0
A28: 23 | B28: =IFERROR([1]SYNC_PROSPECTION_MKT!$B$27,"") -> 0 | C28: =IFERROR([1]SYNC_PROSPECTION_MKT!$C$27,"") -> 0 | D28: =IFERROR([1]SYNC_PROSPECTION_MKT!$D$27,"") -> 0 | E28: =IFERROR([1]SYNC_PROSPECTION_MKT!$E$27,"") -> 0 | F28: =IFERROR([1]SYNC_PROSPECTION_MKT!$G$27,"") -> 0 | G28: =IFERROR([1]SYNC_PROSPECTION_MKT!$H$27,"") -> 0 | H28: =IFERROR([1]SYNC_PROSPECTION_MKT!$J$27,"") -> 0 | I28: =IFERROR([1]SYNC_PROSPECTION_MKT!$I$27,"") -> 0 | J28: =IFERROR([1]SYNC_PROSPECTION_MKT!$K$27,"") -> 0 | K28: =IFERROR(SYNC_FINANCE!$I$27,"") -> 0 | L28: =IFERROR([2]SYNC_COMMERCIAL_VENTE!$S$27,"") -> 0 | M28: 0 | N28: 0 | O28: 0 | P28: 0 | Q28: 0 | R28: 0 | S28: 0 | T28: 0 | U28: 0 | V28: 0 | W28: 0 | X28: 0 | Y28: 0 | Z28: =IFERROR(SUM(N28:Y28),0) -> 0 | AA28: =IFERROR((N28+Q28+T28+W28)-M28,0) -> 0 | AB28: =IFERROR(Z28,0) -> 0 | AC28: =IFERROR(L28-AB28,0) -> 0
A29: 24 | B29: =IFERROR([1]SYNC_PROSPECTION_MKT!$B$28,"") -> 0 | C29: =IFERROR([1]SYNC_PROSPECTION_MKT!$C$28,"") -> 0 | D29: =IFERROR([1]SYNC_PROSPECTION_MKT!$D$28,"") -> 0 | E29: =IFERROR([1]SYNC_PROSPECTION_MKT!$E$28,"") -> 0 | F29: =IFERROR([1]SYNC_PROSPECTION_MKT!$G$28,"") -> 0 | G29: =IFERROR([1]SYNC_PROSPECTION_MKT!$H$28,"") -> 0 | H29: =IFERROR([1]SYNC_PROSPECTION_MKT!$J$28,"") -> 0 | I29: =IFERROR([1]SYNC_PROSPECTION_MKT!$I$28,"") -> 0 | J29: =IFERROR([1]SYNC_PROSPECTION_MKT!$K$28,"") -> 0 | K29: =IFERROR(SYNC_FINANCE!$I$28,"") -> 0 | L29: =IFERROR([2]SYNC_COMMERCIAL_VENTE!$S$28,"") -> 0 | M29: 0 | N29: 0 | O29: 0 | P29: 0 | Q29: 0 | R29: 0 | S29: 0 | T29: 0 | U29: 0 | V29: 0 | W29: 0 | X29: 0 | Y29: 0 | Z29: =IFERROR(SUM(N29:Y29),0) -> 0 | AA29: =IFERROR((N29+Q29+T29+W29)-M29,0) -> 0 | AB29: =IFERROR(Z29,0) -> 0 | AC29: =IFERROR(L29-AB29,0) -> 0
A30: 25 | B30: =IFERROR([1]SYNC_PROSPECTION_MKT!$B$29,"") -> 0 | C30: =IFERROR([1]SYNC_PROSPECTION_MKT!$C$29,"") -> 0 | D30: =IFERROR([1]SYNC_PROSPECTION_MKT!$D$29,"") -> 0 | E30: =IFERROR([1]SYNC_PROSPECTION_MKT!$E$29,"") -> 0 | F30: =IFERROR([1]SYNC_PROSPECTION_MKT!$G$29,"") -> 0 | G30: =IFERROR([1]SYNC_PROSPECTION_MKT!$H$29,"") -> 0 | H30: =IFERROR([1]SYNC_PROSPECTION_MKT!$J$29,"") -> 0 | I30: =IFERROR([1]SYNC_PROSPECTION_MKT!$I$29,"") -> 0 | J30: =IFERROR([1]SYNC_PROSPECTION_MKT!$K$29,"") -> 0 | K30: =IFERROR(SYNC_FINANCE!$I$29,"") -> 0 | L30: =IFERROR([2]SYNC_COMMERCIAL_VENTE!$S$29,"") -> 0 | M30: 0 | N30: 0 | O30: 0 | P30: 0 | Q30: 0 | R30: 0 | S30: 0 | T30: 0 | U30: 0 | V30: 0 | W30: 0 | X30: 0 | Y30: 0 | Z30: =IFERROR(SUM(N30:Y30),0) -> 0 | AA30: =IFERROR((N30+Q30+T30+W30)-M30,0) -> 0 | AB30: =IFERROR(Z30,0) -> 0 | AC30: =IFERROR(L30-AB30,0) -> 0
A31: 26 | B31: =IFERROR([1]SYNC_PROSPECTION_MKT!$B$30,"") -> 0 | C31: =IFERROR([1]SYNC_PROSPECTION_MKT!$C$30,"") -> 0 | D31: =IFERROR([1]SYNC_PROSPECTION_MKT!$D$30,"") -> 0 | E31: =IFERROR([1]SYNC_PROSPECTION_MKT!$E$30,"") -> 0 | F31: =IFERROR([1]SYNC_PROSPECTION_MKT!$G$30,"") -> 0 | G31: =IFERROR([1]SYNC_PROSPECTION_MKT!$H$30,"") -> 0 | H31: =IFERROR([1]SYNC_PROSPECTION_MKT!$J$30,"") -> 0 | I31: =IFERROR([1]SYNC_PROSPECTION_MKT!$I$30,"") -> 0 | J31: =IFERROR([1]SYNC_PROSPECTION_MKT!$K$30,"") -> 0 | K31: =IFERROR(SYNC_FINANCE!$I$30,"") -> 0 | L31: =IFERROR([2]SYNC_COMMERCIAL_VENTE!$S$30,"") -> 0 | M31: 0 | N31: 0 | O31: 0 | P31: 0 | Q31: 0 | R31: 0 | S31: 0 | T31: 0 | U31: 0 | V31: 0 | W31: 0 | X31: 0 | Y31: 0 | Z31: =IFERROR(SUM(N31:Y31),0) -> 0 | AA31: =IFERROR((N31+Q31+T31+W31)-M31,0) -> 0 | AB31: =IFERROR(Z31,0) -> 0 | AC31: =IFERROR(L31-AB31,0) -> 0
A32: 27 | B32: =IFERROR([1]SYNC_PROSPECTION_MKT!$B$31,"") -> 0 | C32: =IFERROR([1]SYNC_PROSPECTION_MKT!$C$31,"") -> 0 | D32: =IFERROR([1]SYNC_PROSPECTION_MKT!$D$31,"") -> 0 | E32: =IFERROR([1]SYNC_PROSPECTION_MKT!$E$31,"") -> 0 | F32: =IFERROR([1]SYNC_PROSPECTION_MKT!$G$31,"") -> 0 | G32: =IFERROR([1]SYNC_PROSPECTION_MKT!$H$31,"") -> 0 | H32: =IFERROR([1]SYNC_PROSPECTION_MKT!$J$31,"") -> 0 | I32: =IFERROR([1]SYNC_PROSPECTION_MKT!$I$31,"") -> 0 | J32: =IFERROR([1]SYNC_PROSPECTION_MKT!$K$31,"") -> 0 | K32: =IFERROR(SYNC_FINANCE!$I$31,"") -> 0 | L32: =IFERROR([2]SYNC_COMMERCIAL_VENTE!$S$31,"") -> 0 | M32: 0 | N32: 0 | O32: 0 | P32: 0 | Q32: 0 | R32: 0 | S32: 0 | T32: 0 | U32: 0 | V32: 0 | W32: 0 | X32: 0 | Y32: 0 | Z32: =IFERROR(SUM(N32:Y32),0) -> 0 | AA32: =IFERROR((N32+Q32+T32+W32)-M32,0) -> 0 | AB32: =IFERROR(Z32,0) -> 0 | AC32: =IFERROR(L32-AB32,0) -> 0
A33: 28 | B33: =IFERROR([1]SYNC_PROSPECTION_MKT!$B$32,"") -> 0 | C33: =IFERROR([1]SYNC_PROSPECTION_MKT!$C$32,"") -> 0 | D33: =IFERROR([1]SYNC_PROSPECTION_MKT!$D$32,"") -> 0 | E33: =IFERROR([1]SYNC_PROSPECTION_MKT!$E$32,"") -> 0 | F33: =IFERROR([1]SYNC_PROSPECTION_MKT!$G$32,"") -> 0 | G33: =IFERROR([1]SYNC_PROSPECTION_MKT!$H$32,"") -> 0 | H33: =IFERROR([1]SYNC_PROSPECTION_MKT!$J$32,"") -> 0 | I33: =IFERROR([1]SYNC_PROSPECTION_MKT!$I$32,"") -> 0 | J33: =IFERROR([1]SYNC_PROSPECTION_MKT!$K$32,"") -> 0 | K33: =IFERROR(SYNC_FINANCE!$I$32,"") -> 0 | L33: =IFERROR([2]SYNC_COMMERCIAL_VENTE!$S$32,"") -> 0 | M33: 0 | N33: 0 | O33: 0 | P33: 0 | Q33: 0 | R33: 0 | S33: 0 | T33: 0 | U33: 0 | V33: 0 | W33: 0 | X33: 0 | Y33: 0 | Z33: =IFERROR(SUM(N33:Y33),0) -> 0 | AA33: =IFERROR((N33+Q33+T33+W33)-M33,0) -> 0 | AB33: =IFERROR(Z33,0) -> 0 | AC33: =IFERROR(L33-AB33,0) -> 0
A34: 29 | B34: =IFERROR([1]SYNC_PROSPECTION_MKT!$B$33,"") -> 0 | C34: =IFERROR([1]SYNC_PROSPECTION_MKT!$C$33,"") -> 0 | D34: =IFERROR([1]SYNC_PROSPECTION_MKT!$D$33,"") -> 0 | E34: =IFERROR([1]SYNC_PROSPECTION_MKT!$E$33,"") -> 0 | F34: =IFERROR([1]SYNC_PROSPECTION_MKT!$G$33,"") -> 0 | G34: =IFERROR([1]SYNC_PROSPECTION_MKT!$H$33,"") -> 0 | H34: =IFERROR([1]SYNC_PROSPECTION_MKT!$J$33,"") -> 0 | I34: =IFERROR([1]SYNC_PROSPECTION_MKT!$I$33,"") -> 0 | J34: =IFERROR([1]SYNC_PROSPECTION_MKT!$K$33,"") -> 0 | K34: =IFERROR(SYNC_FINANCE!$I$33,"") -> 0 | L34: =IFERROR([2]SYNC_COMMERCIAL_VENTE!$S$33,"") -> 0 | M34: 0 | N34: 0 | O34: 0 | P34: 0 | Q34: 0 | R34: 0 | S34: 0 | T34: 0 | U34: 0 | V34: 0 | W34: 0 | X34: 0 | Y34: 0 | Z34: =IFERROR(SUM(N34:Y34),0) -> 0 | AA34: =IFERROR((N34+Q34+T34+W34)-M34,0) -> 0 | AB34: =IFERROR(Z34,0) -> 0 | AC34: =IFERROR(L34-AB34,0) -> 0
A35: 30 | B35: =IFERROR([1]SYNC_PROSPECTION_MKT!$B$34,"") -> 0 | C35: =IFERROR([1]SYNC_PROSPECTION_MKT!$C$34,"") -> 0 | D35: =IFERROR([1]SYNC_PROSPECTION_MKT!$D$34,"") -> 0 | E35: =IFERROR([1]SYNC_PROSPECTION_MKT!$E$34,"") -> 0 | F35: =IFERROR([1]SYNC_PROSPECTION_MKT!$G$34,"") -> 0 | G35: =IFERROR([1]SYNC_PROSPECTION_MKT!$H$34,"") -> 0 | H35: =IFERROR([1]SYNC_PROSPECTION_MKT!$J$34,"") -> 0 | I35: =IFERROR([1]SYNC_PROSPECTION_MKT!$I$34,"") -> 0 | J35: =IFERROR([1]SYNC_PROSPECTION_MKT!$K$34,"") -> 0 | K35: =IFERROR(SYNC_FINANCE!$I$34,"") -> 0 | L35: =IFERROR([2]SYNC_COMMERCIAL_VENTE!$S$34,"") -> 0 | M35: 0 | N35: 0 | O35: 0 | P35: 0 | Q35: 0 | R35: 0 | S35: 0 | T35: 0 | U35: 0 | V35: 0 | W35: 0 | X35: 0 | Y35: 0 | Z35: =IFERROR(SUM(N35:Y35),0) -> 0 | AA35: =IFERROR((N35+Q35+T35+W35)-M35,0) -> 0 | AB35: =IFERROR(Z35,0) -> 0 | AC35: =IFERROR(L35-AB35,0) -> 0
A36: 31 | B36: =IFERROR([1]SYNC_PROSPECTION_MKT!$B$35,"") -> 0 | C36: =IFERROR([1]SYNC_PROSPECTION_MKT!$C$35,"") -> 0 | D36: =IFERROR([1]SYNC_PROSPECTION_MKT!$D$35,"") -> 0 | E36: =IFERROR([1]SYNC_PROSPECTION_MKT!$E$35,"") -> 0 | F36: =IFERROR([1]SYNC_PROSPECTION_MKT!$G$35,"") -> 0 | G36: =IFERROR([1]SYNC_PROSPECTION_MKT!$H$35,"") -> 0 | H36: =IFERROR([1]SYNC_PROSPECTION_MKT!$J$35,"") -> 0 | I36: =IFERROR([1]SYNC_PROSPECTION_MKT!$I$35,"") -> 0 | J36: =IFERROR([1]SYNC_PROSPECTION_MKT!$K$35,"") -> 0 | K36: =IFERROR(SYNC_FINANCE!$I$35,"") -> 0 | L36: =IFERROR([2]SYNC_COMMERCIAL_VENTE!$S$35,"") -> 0 | M36: 0 | N36: 0 | O36: 0 | P36: 0 | Q36: 0 | R36: 0 | S36: 0 | T36: 0 | U36: 0 | V36: 0 | W36: 0 | X36: 0 | Y36: 0 | Z36: =IFERROR(SUM(N36:Y36),0) -> 0 | AA36: =IFERROR((N36+Q36+T36+W36)-M36,0) -> 0 | AB36: =IFERROR(Z36,0) -> 0 | AC36: =IFERROR(L36-AB36,0) -> 0
A37: 32 | B37: =IFERROR([1]SYNC_PROSPECTION_MKT!$B$36,"") -> 0 | C37: =IFERROR([1]SYNC_PROSPECTION_MKT!$C$36,"") -> 0 | D37: =IFERROR([1]SYNC_PROSPECTION_MKT!$D$36,"") -> 0 | E37: =IFERROR([1]SYNC_PROSPECTION_MKT!$E$36,"") -> 0 | F37: =IFERROR([1]SYNC_PROSPECTION_MKT!$G$36,"") -> 0 | G37: =IFERROR([1]SYNC_PROSPECTION_MKT!$H$36,"") -> 0 | H37: =IFERROR([1]SYNC_PROSPECTION_MKT!$J$36,"") -> 0 | I37: =IFERROR([1]SYNC_PROSPECTION_MKT!$I$36,"") -> 0 | J37: =IFERROR([1]SYNC_PROSPECTION_MKT!$K$36,"") -> 0 | K37: =IFERROR(SYNC_FINANCE!$I$36,"") -> 0 | L37: =IFERROR([2]SYNC_COMMERCIAL_VENTE!$S$36,"") -> 0 | M37: 0 | N37: 0 | O37: 0 | P37: 0 | Q37: 0 | R37: 0 | S37: 0 | T37: 0 | U37: 0 | V37: 0 | W37: 0 | X37: 0 | Y37: 0 | Z37: =IFERROR(SUM(N37:Y37),0) -> 0 | AA37: =IFERROR((N37+Q37+T37+W37)-M37,0) -> 0 | AB37: =IFERROR(Z37,0) -> 0 | AC37: =IFERROR(L37-AB37,0) -> 0
A38: 33 | B38: =IFERROR([1]SYNC_PROSPECTION_MKT!$B$37,"") -> 0 | C38: =IFERROR([1]SYNC_PROSPECTION_MKT!$C$37,"") -> 0 | D38: =IFERROR([1]SYNC_PROSPECTION_MKT!$D$37,"") -> 0 | E38: =IFERROR([1]SYNC_PROSPECTION_MKT!$E$37,"") -> 0 | F38: =IFERROR([1]SYNC_PROSPECTION_MKT!$G$37,"") -> 0 | G38: =IFERROR([1]SYNC_PROSPECTION_MKT!$H$37,"") -> 0 | H38: =IFERROR([1]SYNC_PROSPECTION_MKT!$J$37,"") -> 0 | I38: =IFERROR([1]SYNC_PROSPECTION_MKT!$I$37,"") -> 0 | J38: =IFERROR([1]SYNC_PROSPECTION_MKT!$K$37,"") -> 0 | K38: =IFERROR(SYNC_FINANCE!$I$37,"") -> 0 | L38: =IFERROR([2]SYNC_COMMERCIAL_VENTE!$S$37,"") -> 0 | M38: 0 | N38: 0 | O38: 0 | P38: 0 | Q38: 0 | R38: 0 | S38: 0 | T38: 0 | U38: 0 | V38: 0 | W38: 0 | X38: 0 | Y38: 0 | Z38: =IFERROR(SUM(N38:Y38),0) -> 0 | AA38: =IFERROR((N38+Q38+T38+W38)-M38,0) -> 0 | AB38: =IFERROR(Z38,0) -> 0 | AC38: =IFERROR(L38-AB38,0) -> 0
A39: 34 | B39: =IFERROR([1]SYNC_PROSPECTION_MKT!$B$38,"") -> 0 | C39: =IFERROR([1]SYNC_PROSPECTION_MKT!$C$38,"") -> 0 | D39: =IFERROR([1]SYNC_PROSPECTION_MKT!$D$38,"") -> 0 | E39: =IFERROR([1]SYNC_PROSPECTION_MKT!$E$38,"") -> 0 | F39: =IFERROR([1]SYNC_PROSPECTION_MKT!$G$38,"") -> 0 | G39: =IFERROR([1]SYNC_PROSPECTION_MKT!$H$38,"") -> 0 | H39: =IFERROR([1]SYNC_PROSPECTION_MKT!$J$38,"") -> 0 | I39: =IFERROR([1]SYNC_PROSPECTION_MKT!$I$38,"") -> 0 | J39: =IFERROR([1]SYNC_PROSPECTION_MKT!$K$38,"") -> 0 | K39: =IFERROR(SYNC_FINANCE!$I$38,"") -> 0 | L39: =IFERROR([2]SYNC_COMMERCIAL_VENTE!$S$38,"") -> 0 | M39: 0 | N39: 0 | O39: 0 | P39: 0 | Q39: 0 | R39: 0 | S39: 0 | T39: 0 | U39: 0 | V39: 0 | W39: 0 | X39: 0 | Y39: 0 | Z39: =IFERROR(SUM(N39:Y39),0) -> 0 | AA39: =IFERROR((N39+Q39+T39+W39)-M39,0) -> 0 | AB39: =IFERROR(Z39,0) -> 0 | AC39: =IFERROR(L39-AB39,0) -> 0
A40: 35 | B40: =IFERROR([1]SYNC_PROSPECTION_MKT!$B$39,"") -> 0 | C40: =IFERROR([1]SYNC_PROSPECTION_MKT!$C$39,"") -> 0 | D40: =IFERROR([1]SYNC_PROSPECTION_MKT!$D$39,"") -> 0 | E40: =IFERROR([1]SYNC_PROSPECTION_MKT!$E$39,"") -> 0 | F40: =IFERROR([1]SYNC_PROSPECTION_MKT!$G$39,"") -> 0 | G40: =IFERROR([1]SYNC_PROSPECTION_MKT!$H$39,"") -> 0 | H40: =IFERROR([1]SYNC_PROSPECTION_MKT!$J$39,"") -> 0 | I40: =IFERROR([1]SYNC_PROSPECTION_MKT!$I$39,"") -> 0 | J40: =IFERROR([1]SYNC_PROSPECTION_MKT!$K$39,"") -> 0 | K40: =IFERROR(SYNC_FINANCE!$I$39,"") -> 0 | L40: =IFERROR([2]SYNC_COMMERCIAL_VENTE!$S$39,"") -> 0 | M40: 0 | N40: 0 | O40: 0 | P40: 0 | Q40: 0 | R40: 0 | S40: 0 | T40: 0 | U40: 0 | V40: 0 | W40: 0 | X40: 0 | Y40: 0 | Z40: =IFERROR(SUM(N40:Y40),0) -> 0 | AA40: =IFERROR((N40+Q40+T40+W40)-M40,0) -> 0 | AB40: =IFERROR(Z40,0) -> 0 | AC40: =IFERROR(L40-AB40,0) -> 0
A41: 36 | B41: =IFERROR([1]SYNC_PROSPECTION_MKT!$B$40,"") -> 0 | C41: =IFERROR([1]SYNC_PROSPECTION_MKT!$C$40,"") -> 0 | D41: =IFERROR([1]SYNC_PROSPECTION_MKT!$D$40,"") -> 0 | E41: =IFERROR([1]SYNC_PROSPECTION_MKT!$E$40,"") -> 0 | F41: =IFERROR([1]SYNC_PROSPECTION_MKT!$G$40,"") -> 0 | G41: =IFERROR([1]SYNC_PROSPECTION_MKT!$H$40,"") -> 0 | H41: =IFERROR([1]SYNC_PROSPECTION_MKT!$J$40,"") -> 0 | I41: =IFERROR([1]SYNC_PROSPECTION_MKT!$I$40,"") -> 0 | J41: =IFERROR([1]SYNC_PROSPECTION_MKT!$K$40,"") -> 0 | K41: =IFERROR(SYNC_FINANCE!$I$40,"") -> 0 | L41: =IFERROR([2]SYNC_COMMERCIAL_VENTE!$S$40,"") -> 0 | M41: 0 | N41: 0 | O41: 0 | P41: 0 | Q41: 0 | R41: 0 | S41: 0 | T41: 0 | U41: 0 | V41: 0 | W41: 0 | X41: 0 | Y41: 0 | Z41: =IFERROR(SUM(N41:Y41),0) -> 0 | AA41: =IFERROR((N41+Q41+T41+W41)-M41,0) -> 0 | AB41: =IFERROR(Z41,0) -> 0 | AC41: =IFERROR(L41-AB41,0) -> 0
A42: 37 | B42: =IFERROR([1]SYNC_PROSPECTION_MKT!$B$41,"") -> 0 | C42: =IFERROR([1]SYNC_PROSPECTION_MKT!$C$41,"") -> 0 | D42: =IFERROR([1]SYNC_PROSPECTION_MKT!$D$41,"") -> 0 | E42: =IFERROR([1]SYNC_PROSPECTION_MKT!$E$41,"") -> 0 | F42: =IFERROR([1]SYNC_PROSPECTION_MKT!$G$41,"") -> 0 | G42: =IFERROR([1]SYNC_PROSPECTION_MKT!$H$41,"") -> 0 | H42: =IFERROR([1]SYNC_PROSPECTION_MKT!$J$41,"") -> 0 | I42: =IFERROR([1]SYNC_PROSPECTION_MKT!$I$41,"") -> 0 | J42: =IFERROR([1]SYNC_PROSPECTION_MKT!$K$41,"") -> 0 | K42: =IFERROR(SYNC_FINANCE!$I$41,"") -> 0 | L42: =IFERROR([2]SYNC_COMMERCIAL_VENTE!$S$41,"") -> 0 | M42: 0 | N42: 0 | O42: 0 | P42: 0 | Q42: 0 | R42: 0 | S42: 0 | T42: 0 | U42: 0 | V42: 0 | W42: 0 | X42: 0 | Y42: 0 | Z42: =IFERROR(SUM(N42:Y42),0) -> 0 | AA42: =IFERROR((N42+Q42+T42+W42)-M42,0) -> 0 | AB42: =IFERROR(Z42,0) -> 0 | AC42: =IFERROR(L42-AB42,0) -> 0
A43: 38 | B43: =IFERROR([1]SYNC_PROSPECTION_MKT!$B$42,"") -> 0 | C43: =IFERROR([1]SYNC_PROSPECTION_MKT!$C$42,"") -> 0 | D43: =IFERROR([1]SYNC_PROSPECTION_MKT!$D$42,"") -> 0 | E43: =IFERROR([1]SYNC_PROSPECTION_MKT!$E$42,"") -> 0 | F43: =IFERROR([1]SYNC_PROSPECTION_MKT!$G$42,"") -> 0 | G43: =IFERROR([1]SYNC_PROSPECTION_MKT!$H$42,"") -> 0 | H43: =IFERROR([1]SYNC_PROSPECTION_MKT!$J$42,"") -> 0 | I43: =IFERROR([1]SYNC_PROSPECTION_MKT!$I$42,"") -> 0 | J43: =IFERROR([1]SYNC_PROSPECTION_MKT!$K$42,"") -> 0 | K43: =IFERROR(SYNC_FINANCE!$I$42,"") -> 0 | L43: =IFERROR([2]SYNC_COMMERCIAL_VENTE!$S$42,"") -> 0 | M43: 0 | N43: 0 | O43: 0 | P43: 0 | Q43: 0 | R43: 0 | S43: 0 | T43: 0 | U43: 0 | V43: 0 | W43: 0 | X43: 0 | Y43: 0 | Z43: =IFERROR(SUM(N43:Y43),0) -> 0 | AA43: =IFERROR((N43+Q43+T43+W43)-M43,0) -> 0 | AB43: =IFERROR(Z43,0) -> 0 | AC43: =IFERROR(L43-AB43,0) -> 0
A44: 39 | B44: =IFERROR([1]SYNC_PROSPECTION_MKT!$B$43,"") -> 0 | C44: =IFERROR([1]SYNC_PROSPECTION_MKT!$C$43,"") -> 0 | D44: =IFERROR([1]SYNC_PROSPECTION_MKT!$D$43,"") -> 0 | E44: =IFERROR([1]SYNC_PROSPECTION_MKT!$E$43,"") -> 0 | F44: =IFERROR([1]SYNC_PROSPECTION_MKT!$G$43,"") -> 0 | G44: =IFERROR([1]SYNC_PROSPECTION_MKT!$H$43,"") -> 0 | H44: =IFERROR([1]SYNC_PROSPECTION_MKT!$J$43,"") -> 0 | I44: =IFERROR([1]SYNC_PROSPECTION_MKT!$I$43,"") -> 0 | J44: =IFERROR([1]SYNC_PROSPECTION_MKT!$K$43,"") -> 0 | K44: =IFERROR(SYNC_FINANCE!$I$43,"") -> 0 | L44: =IFERROR([2]SYNC_COMMERCIAL_VENTE!$S$43,"") -> 0 | M44: 0 | N44: 0 | O44: 0 | P44: 0 | Q44: 0 | R44: 0 | S44: 0 | T44: 0 | U44: 0 | V44: 0 | W44: 0 | X44: 0 | Y44: 0 | Z44: =IFERROR(SUM(N44:Y44),0) -> 0 | AA44: =IFERROR((N44+Q44+T44+W44)-M44,0) -> 0 | AB44: =IFERROR(Z44,0) -> 0 | AC44: =IFERROR(L44-AB44,0) -> 0
A45: 40 | B45: =IFERROR([1]SYNC_PROSPECTION_MKT!$B$44,"") -> 0 | C45: =IFERROR([1]SYNC_PROSPECTION_MKT!$C$44,"") -> 0 | D45: =IFERROR([1]SYNC_PROSPECTION_MKT!$D$44,"") -> 0 | E45: =IFERROR([1]SYNC_PROSPECTION_MKT!$E$44,"") -> 0 | F45: =IFERROR([1]SYNC_PROSPECTION_MKT!$G$44,"") -> 0 | G45: =IFERROR([1]SYNC_PROSPECTION_MKT!$H$44,"") -> 0 | H45: =IFERROR([1]SYNC_PROSPECTION_MKT!$J$44,"") -> 0 | I45: =IFERROR([1]SYNC_PROSPECTION_MKT!$I$44,"") -> 0 | J45: =IFERROR([1]SYNC_PROSPECTION_MKT!$K$44,"") -> 0 | K45: =IFERROR(SYNC_FINANCE!$I$44,"") -> 0 | L45: =IFERROR([2]SYNC_COMMERCIAL_VENTE!$S$44,"") -> 0 | M45: 0 | N45: 0 | O45: 0 | P45: 0 | Q45: 0 | R45: 0 | S45: 0 | T45: 0 | U45: 0 | V45: 0 | W45: 0 | X45: 0 | Y45: 0 | Z45: =IFERROR(SUM(N45:Y45),0) -> 0 | AA45: =IFERROR((N45+Q45+T45+W45)-M45,0) -> 0 | AB45: =IFERROR(Z45,0) -> 0 | AC45: =IFERROR(L45-AB45,0) -> 0
A46: 41 | B46: =IFERROR([1]SYNC_PROSPECTION_MKT!$B$45,"") -> 0 | C46: =IFERROR([1]SYNC_PROSPECTION_MKT!$C$45,"") -> 0 | D46: =IFERROR([1]SYNC_PROSPECTION_MKT!$D$45,"") -> 0 | E46: =IFERROR([1]SYNC_PROSPECTION_MKT!$E$45,"") -> 0 | F46: =IFERROR([1]SYNC_PROSPECTION_MKT!$G$45,"") -> 0 | G46: =IFERROR([1]SYNC_PROSPECTION_MKT!$H$45,"") -> 0 | H46: =IFERROR([1]SYNC_PROSPECTION_MKT!$J$45,"") -> 0 | I46: =IFERROR([1]SYNC_PROSPECTION_MKT!$I$45,"") -> 0 | J46: =IFERROR([1]SYNC_PROSPECTION_MKT!$K$45,"") -> 0 | K46: =IFERROR(SYNC_FINANCE!$I$45,"") -> 0 | L46: =IFERROR([2]SYNC_COMMERCIAL_VENTE!$S$45,"") -> 0 | M46: 0 | N46: 0 | O46: 0 | P46: 0 | Q46: 0 | R46: 0 | S46: 0 | T46: 0 | U46: 0 | V46: 0 | W46: 0 | X46: 0 | Y46: 0 | Z46: =IFERROR(SUM(N46:Y46),0) -> 0 | AA46: =IFERROR((N46+Q46+T46+W46)-M46,0) -> 0 | AB46: =IFERROR(Z46,0) -> 0 | AC46: =IFERROR(L46-AB46,0) -> 0
A47: 42 | B47: =IFERROR([1]SYNC_PROSPECTION_MKT!$B$46,"") -> 0 | C47: =IFERROR([1]SYNC_PROSPECTION_MKT!$C$46,"") -> 0 | D47: =IFERROR([1]SYNC_PROSPECTION_MKT!$D$46,"") -> 0 | E47: =IFERROR([1]SYNC_PROSPECTION_MKT!$E$46,"") -> 0 | F47: =IFERROR([1]SYNC_PROSPECTION_MKT!$G$46,"") -> 0 | G47: =IFERROR([1]SYNC_PROSPECTION_MKT!$H$46,"") -> 0 | H47: =IFERROR([1]SYNC_PROSPECTION_MKT!$J$46,"") -> 0 | I47: =IFERROR([1]SYNC_PROSPECTION_MKT!$I$46,"") -> 0 | J47: =IFERROR([1]SYNC_PROSPECTION_MKT!$K$46,"") -> 0 | K47: =IFERROR(SYNC_FINANCE!$I$46,"") -> 0 | L47: =IFERROR([2]SYNC_COMMERCIAL_VENTE!$S$46,"") -> 0 | M47: 0 | N47: 0 | O47: 0 | P47: 0 | Q47: 0 | R47: 0 | S47: 0 | T47: 0 | U47: 0 | V47: 0 | W47: 0 | X47: 0 | Y47: 0 | Z47: =IFERROR(SUM(N47:Y47),0) -> 0 | AA47: =IFERROR((N47+Q47+T47+W47)-M47,0) -> 0 | AB47: =IFERROR(Z47,0) -> 0 | AC47: =IFERROR(L47-AB47,0) -> 0
A48: 43 | B48: =IFERROR([1]SYNC_PROSPECTION_MKT!$B$47,"") -> 0 | C48: =IFERROR([1]SYNC_PROSPECTION_MKT!$C$47,"") -> 0 | D48: =IFERROR([1]SYNC_PROSPECTION_MKT!$D$47,"") -> 0 | E48: =IFERROR([1]SYNC_PROSPECTION_MKT!$E$47,"") -> 0 | F48: =IFERROR([1]SYNC_PROSPECTION_MKT!$G$47,"") -> 0 | G48: =IFERROR([1]SYNC_PROSPECTION_MKT!$H$47,"") -> 0 | H48: =IFERROR([1]SYNC_PROSPECTION_MKT!$J$47,"") -> 0 | I48: =IFERROR([1]SYNC_PROSPECTION_MKT!$I$47,"") -> 0 | J48: =IFERROR([1]SYNC_PROSPECTION_MKT!$K$47,"") -> 0 | K48: =IFERROR(SYNC_FINANCE!$I$47,"") -> 0 | L48: =IFERROR([2]SYNC_COMMERCIAL_VENTE!$S$47,"") -> 0 | M48: 0 | N48: 0 | O48: 0 | P48: 0 | Q48: 0 | R48: 0 | S48: 0 | T48: 0 | U48: 0 | V48: 0 | W48: 0 | X48: 0 | Y48: 0 | Z48: =IFERROR(SUM(N48:Y48),0) -> 0 | AA48: =IFERROR((N48+Q48+T48+W48)-M48,0) -> 0 | AB48: =IFERROR(Z48,0) -> 0 | AC48: =IFERROR(L48-AB48,0) -> 0
A49: 44 | B49: =IFERROR([1]SYNC_PROSPECTION_MKT!$B$48,"") -> 0 | C49: =IFERROR([1]SYNC_PROSPECTION_MKT!$C$48,"") -> 0 | D49: =IFERROR([1]SYNC_PROSPECTION_MKT!$D$48,"") -> 0 | E49: =IFERROR([1]SYNC_PROSPECTION_MKT!$E$48,"") -> 0 | F49: =IFERROR([1]SYNC_PROSPECTION_MKT!$G$48,"") -> 0 | G49: =IFERROR([1]SYNC_PROSPECTION_MKT!$H$48,"") -> 0 | H49: =IFERROR([1]SYNC_PROSPECTION_MKT!$J$48,"") -> 0 | I49: =IFERROR([1]SYNC_PROSPECTION_MKT!$I$48,"") -> 0 | J49: =IFERROR([1]SYNC_PROSPECTION_MKT!$K$48,"") -> 0 | K49: =IFERROR(SYNC_FINANCE!$I$48,"") -> 0 | L49: =IFERROR([2]SYNC_COMMERCIAL_VENTE!$S$48,"") -> 0 | M49: 0 | N49: 0 | O49: 0 | P49: 0 | Q49: 0 | R49: 0 | S49: 0 | T49: 0 | U49: 0 | V49: 0 | W49: 0 | X49: 0 | Y49: 0 | Z49: =IFERROR(SUM(N49:Y49),0) -> 0 | AA49: =IFERROR((N49+Q49+T49+W49)-M49,0) -> 0 | AB49: =IFERROR(Z49,0) -> 0 | AC49: =IFERROR(L49-AB49,0) -> 0
A50: 45 | B50: =IFERROR([1]SYNC_PROSPECTION_MKT!$B$49,"") -> 0 | C50: =IFERROR([1]SYNC_PROSPECTION_MKT!$C$49,"") -> 0 | D50: =IFERROR([1]SYNC_PROSPECTION_MKT!$D$49,"") -> 0 | E50: =IFERROR([1]SYNC_PROSPECTION_MKT!$E$49,"") -> 0 | F50: =IFERROR([1]SYNC_PROSPECTION_MKT!$G$49,"") -> 0 | G50: =IFERROR([1]SYNC_PROSPECTION_MKT!$H$49,"") -> 0 | H50: =IFERROR([1]SYNC_PROSPECTION_MKT!$J$49,"") -> 0 | I50: =IFERROR([1]SYNC_PROSPECTION_MKT!$I$49,"") -> 0 | J50: =IFERROR([1]SYNC_PROSPECTION_MKT!$K$49,"") -> 0 | K50: =IFERROR(SYNC_FINANCE!$I$49,"") -> 0 | L50: =IFERROR([2]SYNC_COMMERCIAL_VENTE!$S$49,"") -> 0 | M50: 0 | N50: 0 | O50: 0 | P50: 0 | Q50: 0 | R50: 0 | S50: 0 | T50: 0 | U50: 0 | V50: 0 | W50: 0 | X50: 0 | Y50: 0 | Z50: =IFERROR(SUM(N50:Y50),0) -> 0 | AA50: =IFERROR((N50+Q50+T50+W50)-M50,0) -> 0 | AB50: =IFERROR(Z50,0) -> 0 | AC50: =IFERROR(L50-AB50,0) -> 0
A51: 46 | B51: =IFERROR([1]SYNC_PROSPECTION_MKT!$B$50,"") -> 0 | C51: =IFERROR([1]SYNC_PROSPECTION_MKT!$C$50,"") -> 0 | D51: =IFERROR([1]SYNC_PROSPECTION_MKT!$D$50,"") -> 0 | E51: =IFERROR([1]SYNC_PROSPECTION_MKT!$E$50,"") -> 0 | F51: =IFERROR([1]SYNC_PROSPECTION_MKT!$G$50,"") -> 0 | G51: =IFERROR([1]SYNC_PROSPECTION_MKT!$H$50,"") -> 0 | H51: =IFERROR([1]SYNC_PROSPECTION_MKT!$J$50,"") -> 0 | I51: =IFERROR([1]SYNC_PROSPECTION_MKT!$I$50,"") -> 0 | J51: =IFERROR([1]SYNC_PROSPECTION_MKT!$K$50,"") -> 0 | K51: =IFERROR(SYNC_FINANCE!$I$50,"") -> 0 | L51: =IFERROR([2]SYNC_COMMERCIAL_VENTE!$S$50,"") -> 0 | M51: 0 | N51: 0 | O51: 0 | P51: 0 | Q51: 0 | R51: 0 | S51: 0 | T51: 0 | U51: 0 | V51: 0 | W51: 0 | X51: 0 | Y51: 0 | Z51: =IFERROR(SUM(N51:Y51),0) -> 0 | AA51: =IFERROR((N51+Q51+T51+W51)-M51,0) -> 0 | AB51: =IFERROR(Z51,0) -> 0 | AC51: =IFERROR(L51-AB51,0) -> 0
A52: 47 | B52: =IFERROR([1]SYNC_PROSPECTION_MKT!$B$51,"") -> 0 | C52: =IFERROR([1]SYNC_PROSPECTION_MKT!$C$51,"") -> 0 | D52: =IFERROR([1]SYNC_PROSPECTION_MKT!$D$51,"") -> 0 | E52: =IFERROR([1]SYNC_PROSPECTION_MKT!$E$51,"") -> 0 | F52: =IFERROR([1]SYNC_PROSPECTION_MKT!$G$51,"") -> 0 | G52: =IFERROR([1]SYNC_PROSPECTION_MKT!$H$51,"") -> 0 | H52: =IFERROR([1]SYNC_PROSPECTION_MKT!$J$51,"") -> 0 | I52: =IFERROR([1]SYNC_PROSPECTION_MKT!$I$51,"") -> 0 | J52: =IFERROR([1]SYNC_PROSPECTION_MKT!$K$51,"") -> 0 | K52: =IFERROR(SYNC_FINANCE!$I$51,"") -> 0 | L52: =IFERROR([2]SYNC_COMMERCIAL_VENTE!$S$51,"") -> 0 | M52: 0 | N52: 0 | O52: 0 | P52: 0 | Q52: 0 | R52: 0 | S52: 0 | T52: 0 | U52: 0 | V52: 0 | W52: 0 | X52: 0 | Y52: 0 | Z52: =IFERROR(SUM(N52:Y52),0) -> 0 | AA52: =IFERROR((N52+Q52+T52+W52)-M52,0) -> 0 | AB52: =IFERROR(Z52,0) -> 0 | AC52: =IFERROR(L52-AB52,0) -> 0
A53: 48 | B53: =IFERROR([1]SYNC_PROSPECTION_MKT!$B$52,"") -> 0 | C53: =IFERROR([1]SYNC_PROSPECTION_MKT!$C$52,"") -> 0 | D53: =IFERROR([1]SYNC_PROSPECTION_MKT!$D$52,"") -> 0 | E53: =IFERROR([1]SYNC_PROSPECTION_MKT!$E$52,"") -> 0 | F53: =IFERROR([1]SYNC_PROSPECTION_MKT!$G$52,"") -> 0 | G53: =IFERROR([1]SYNC_PROSPECTION_MKT!$H$52,"") -> 0 | H53: =IFERROR([1]SYNC_PROSPECTION_MKT!$J$52,"") -> 0 | I53: =IFERROR([1]SYNC_PROSPECTION_MKT!$I$52,"") -> 0 | J53: =IFERROR([1]SYNC_PROSPECTION_MKT!$K$52,"") -> 0 | K53: =IFERROR(SYNC_FINANCE!$I$52,"") -> 0 | L53: =IFERROR([2]SYNC_COMMERCIAL_VENTE!$S$52,"") -> 0 | M53: 0 | N53: 0 | O53: 0 | P53: 0 | Q53: 0 | R53: 0 | S53: 0 | T53: 0 | U53: 0 | V53: 0 | W53: 0 | X53: 0 | Y53: 0 | Z53: =IFERROR(SUM(N53:Y53),0) -> 0 | AA53: =IFERROR((N53+Q53+T53+W53)-M53,0) -> 0 | AB53: =IFERROR(Z53,0) -> 0 | AC53: =IFERROR(L53-AB53,0) -> 0
A54: 49 | B54: =IFERROR([1]SYNC_PROSPECTION_MKT!$B$53,"") -> 0 | C54: =IFERROR([1]SYNC_PROSPECTION_MKT!$C$53,"") -> 0 | D54: =IFERROR([1]SYNC_PROSPECTION_MKT!$D$53,"") -> 0 | E54: =IFERROR([1]SYNC_PROSPECTION_MKT!$E$53,"") -> 0 | F54: =IFERROR([1]SYNC_PROSPECTION_MKT!$G$53,"") -> 0 | G54: =IFERROR([1]SYNC_PROSPECTION_MKT!$H$53,"") -> 0 | H54: =IFERROR([1]SYNC_PROSPECTION_MKT!$J$53,"") -> 0 | I54: =IFERROR([1]SYNC_PROSPECTION_MKT!$I$53,"") -> 0 | J54: =IFERROR([1]SYNC_PROSPECTION_MKT!$K$53,"") -> 0 | K54: =IFERROR(SYNC_FINANCE!$I$53,"") -> 0 | L54: =IFERROR([2]SYNC_COMMERCIAL_VENTE!$S$53,"") -> 0 | M54: 0 | N54: 0 | O54: 0 | P54: 0 | Q54: 0 | R54: 0 | S54: 0 | T54: 0 | U54: 0 | V54: 0 | W54: 0 | X54: 0 | Y54: 0 | Z54: =IFERROR(SUM(N54:Y54),0) -> 0 | AA54: =IFERROR((N54+Q54+T54+W54)-M54,0) -> 0 | AB54: =IFERROR(Z54,0) -> 0 | AC54: =IFERROR(L54-AB54,0) -> 0
A55: 50 | B55: =IFERROR([1]SYNC_PROSPECTION_MKT!$B$54,"") -> 0 | C55: =IFERROR([1]SYNC_PROSPECTION_MKT!$C$54,"") -> 0 | D55: =IFERROR([1]SYNC_PROSPECTION_MKT!$D$54,"") -> 0 | E55: =IFERROR([1]SYNC_PROSPECTION_MKT!$E$54,"") -> 0 | F55: =IFERROR([1]SYNC_PROSPECTION_MKT!$G$54,"") -> 0 | G55: =IFERROR([1]SYNC_PROSPECTION_MKT!$H$54,"") -> 0 | H55: =IFERROR([1]SYNC_PROSPECTION_MKT!$J$54,"") -> 0 | I55: =IFERROR([1]SYNC_PROSPECTION_MKT!$I$54,"") -> 0 | J55: =IFERROR([1]SYNC_PROSPECTION_MKT!$K$54,"") -> 0 | K55: =IFERROR(SYNC_FINANCE!$I$54,"") -> 0 | L55: =IFERROR([2]SYNC_COMMERCIAL_VENTE!$S$54,"") -> 0 | M55: 0 | N55: 0 | O55: 0 | P55: 0 | Q55: 0 | R55: 0 | S55: 0 | T55: 0 | U55: 0 | V55: 0 | W55: 0 | X55: 0 | Y55: 0 | Z55: =IFERROR(SUM(N55:Y55),0) -> 0 | AA55: =IFERROR((N55+Q55+T55+W55)-M55,0) -> 0 | AB55: =IFERROR(Z55,0) -> 0 | AC55: =IFERROR(L55-AB55,0) -> 0
A56: 51 | B56: =IFERROR([1]SYNC_PROSPECTION_MKT!$B$55,"") -> 0 | C56: =IFERROR([1]SYNC_PROSPECTION_MKT!$C$55,"") -> 0 | D56: =IFERROR([1]SYNC_PROSPECTION_MKT!$D$55,"") -> 0 | E56: =IFERROR([1]SYNC_PROSPECTION_MKT!$E$55,"") -> 0 | F56: =IFERROR([1]SYNC_PROSPECTION_MKT!$G$55,"") -> 0 | G56: =IFERROR([1]SYNC_PROSPECTION_MKT!$H$55,"") -> 0 | H56: =IFERROR([1]SYNC_PROSPECTION_MKT!$J$55,"") -> 0 | I56: =IFERROR([1]SYNC_PROSPECTION_MKT!$I$55,"") -> 0 | J56: =IFERROR([1]SYNC_PROSPECTION_MKT!$K$55,"") -> 0 | K56: =IFERROR(SYNC_FINANCE!$I$55,"") -> 0 | L56: =IFERROR([2]SYNC_COMMERCIAL_VENTE!$S$55,"") -> 0 | M56: 0 | N56: 0 | O56: 0 | P56: 0 | Q56: 0 | R56: 0 | S56: 0 | T56: 0 | U56: 0 | V56: 0 | W56: 0 | X56: 0 | Y56: 0 | Z56: =IFERROR(SUM(N56:Y56),0) -> 0 | AA56: =IFERROR((N56+Q56+T56+W56)-M56,0) -> 0 | AB56: =IFERROR(Z56,0) -> 0 | AC56: =IFERROR(L56-AB56,0) -> 0
A57: 52 | B57: =IFERROR([1]SYNC_PROSPECTION_MKT!$B$56,"") -> 0 | C57: =IFERROR([1]SYNC_PROSPECTION_MKT!$C$56,"") -> 0 | D57: =IFERROR([1]SYNC_PROSPECTION_MKT!$D$56,"") -> 0 | E57: =IFERROR([1]SYNC_PROSPECTION_MKT!$E$56,"") -> 0 | F57: =IFERROR([1]SYNC_PROSPECTION_MKT!$G$56,"") -> 0 | G57: =IFERROR([1]SYNC_PROSPECTION_MKT!$H$56,"") -> 0 | H57: =IFERROR([1]SYNC_PROSPECTION_MKT!$J$56,"") -> 0 | I57: =IFERROR([1]SYNC_PROSPECTION_MKT!$I$56,"") -> 0 | J57: =IFERROR([1]SYNC_PROSPECTION_MKT!$K$56,"") -> 0 | K57: =IFERROR(SYNC_FINANCE!$I$56,"") -> 0 | L57: =IFERROR([2]SYNC_COMMERCIAL_VENTE!$S$56,"") -> 0 | M57: 0 | N57: 0 | O57: 0 | P57: 0 | Q57: 0 | R57: 0 | S57: 0 | T57: 0 | U57: 0 | V57: 0 | W57: 0 | X57: 0 | Y57: 0 | Z57: =IFERROR(SUM(N57:Y57),0) -> 0 | AA57: =IFERROR((N57+Q57+T57+W57)-M57,0) -> 0 | AB57: =IFERROR(Z57,0) -> 0 | AC57: =IFERROR(L57-AB57,0) -> 0
A58: 53 | B58: =IFERROR([1]SYNC_PROSPECTION_MKT!$B$57,"") -> 0 | C58: =IFERROR([1]SYNC_PROSPECTION_MKT!$C$57,"") -> 0 | D58: =IFERROR([1]SYNC_PROSPECTION_MKT!$D$57,"") -> 0 | E58: =IFERROR([1]SYNC_PROSPECTION_MKT!$E$57,"") -> 0 | F58: =IFERROR([1]SYNC_PROSPECTION_MKT!$G$57,"") -> 0 | G58: =IFERROR([1]SYNC_PROSPECTION_MKT!$H$57,"") -> 0 | H58: =IFERROR([1]SYNC_PROSPECTION_MKT!$J$57,"") -> 0 | I58: =IFERROR([1]SYNC_PROSPECTION_MKT!$I$57,"") -> 0 | J58: =IFERROR([1]SYNC_PROSPECTION_MKT!$K$57,"") -> 0 | K58: =IFERROR(SYNC_FINANCE!$I$57,"") -> 0 | L58: =IFERROR([2]SYNC_COMMERCIAL_VENTE!$S$57,"") -> 0 | M58: 0 | N58: 0 | O58: 0 | P58: 0 | Q58: 0 | R58: 0 | S58: 0 | T58: 0 | U58: 0 | V58: 0 | W58: 0 | X58: 0 | Y58: 0 | Z58: =IFERROR(SUM(N58:Y58),0) -> 0 | AA58: =IFERROR((N58+Q58+T58+W58)-M58,0) -> 0 | AB58: =IFERROR(Z58,0) -> 0 | AC58: =IFERROR(L58-AB58,0) -> 0
A59: 54 | B59: =IFERROR([1]SYNC_PROSPECTION_MKT!$B$58,"") -> 0 | C59: =IFERROR([1]SYNC_PROSPECTION_MKT!$C$58,"") -> 0 | D59: =IFERROR([1]SYNC_PROSPECTION_MKT!$D$58,"") -> 0 | E59: =IFERROR([1]SYNC_PROSPECTION_MKT!$E$58,"") -> 0 | F59: =IFERROR([1]SYNC_PROSPECTION_MKT!$G$58,"") -> 0 | G59: =IFERROR([1]SYNC_PROSPECTION_MKT!$H$58,"") -> 0 | H59: =IFERROR([1]SYNC_PROSPECTION_MKT!$J$58,"") -> 0 | I59: =IFERROR([1]SYNC_PROSPECTION_MKT!$I$58,"") -> 0 | J59: =IFERROR([1]SYNC_PROSPECTION_MKT!$K$58,"") -> 0 | K59: =IFERROR(SYNC_FINANCE!$I$58,"") -> 0 | L59: =IFERROR([2]SYNC_COMMERCIAL_VENTE!$S$58,"") -> 0 | M59: 0 | N59: 0 | O59: 0 | P59: 0 | Q59: 0 | R59: 0 | S59: 0 | T59: 0 | U59: 0 | V59: 0 | W59: 0 | X59: 0 | Y59: 0 | Z59: =IFERROR(SUM(N59:Y59),0) -> 0 | AA59: =IFERROR((N59+Q59+T59+W59)-M59,0) -> 0 | AB59: =IFERROR(Z59,0) -> 0 | AC59: =IFERROR(L59-AB59,0) -> 0
A60: 55 | B60: =IFERROR([1]SYNC_PROSPECTION_MKT!$B$59,"") -> 0 | C60: =IFERROR([1]SYNC_PROSPECTION_MKT!$C$59,"") -> 0 | D60: =IFERROR([1]SYNC_PROSPECTION_MKT!$D$59,"") -> 0 | E60: =IFERROR([1]SYNC_PROSPECTION_MKT!$E$59,"") -> 0 | F60: =IFERROR([1]SYNC_PROSPECTION_MKT!$G$59,"") -> 0 | G60: =IFERROR([1]SYNC_PROSPECTION_MKT!$H$59,"") -> 0 | H60: =IFERROR([1]SYNC_PROSPECTION_MKT!$J$59,"") -> 0 | I60: =IFERROR([1]SYNC_PROSPECTION_MKT!$I$59,"") -> 0 | J60: =IFERROR([1]SYNC_PROSPECTION_MKT!$K$59,"") -> 0 | K60: =IFERROR(SYNC_FINANCE!$I$59,"") -> 0 | L60: =IFERROR([2]SYNC_COMMERCIAL_VENTE!$S$59,"") -> 0 | M60: 0 | N60: 0 | O60: 0 | P60: 0 | Q60: 0 | R60: 0 | S60: 0 | T60: 0 | U60: 0 | V60: 0 | W60: 0 | X60: 0 | Y60: 0 | Z60: =IFERROR(SUM(N60:Y60),0) -> 0 | AA60: =IFERROR((N60+Q60+T60+W60)-M60,0) -> 0 | AB60: =IFERROR(Z60,0) -> 0 | AC60: =IFERROR(L60-AB60,0) -> 0
A61: 56 | B61: =IFERROR([1]SYNC_PROSPECTION_MKT!$B$60,"") -> 0 | C61: =IFERROR([1]SYNC_PROSPECTION_MKT!$C$60,"") -> 0 | D61: =IFERROR([1]SYNC_PROSPECTION_MKT!$D$60,"") -> 0 | E61: =IFERROR([1]SYNC_PROSPECTION_MKT!$E$60,"") -> 0 | F61: =IFERROR([1]SYNC_PROSPECTION_MKT!$G$60,"") -> 0 | G61: =IFERROR([1]SYNC_PROSPECTION_MKT!$H$60,"") -> 0 | H61: =IFERROR([1]SYNC_PROSPECTION_MKT!$J$60,"") -> 0 | I61: =IFERROR([1]SYNC_PROSPECTION_MKT!$I$60,"") -> 0 | J61: =IFERROR([1]SYNC_PROSPECTION_MKT!$K$60,"") -> 0 | K61: =IFERROR(SYNC_FINANCE!$I$60,"") -> 0 | L61: =IFERROR([2]SYNC_COMMERCIAL_VENTE!$S$60,"") -> 0 | M61: 0 | N61: 0 | O61: 0 | P61: 0 | Q61: 0 | R61: 0 | S61: 0 | T61: 0 | U61: 0 | V61: 0 | W61: 0 | X61: 0 | Y61: 0 | Z61: =IFERROR(SUM(N61:Y61),0) -> 0 | AA61: =IFERROR((N61+Q61+T61+W61)-M61,0) -> 0 | AB61: =IFERROR(Z61,0) -> 0 | AC61: =IFERROR(L61-AB61,0) -> 0
A62: 57 | B62: =IFERROR([1]SYNC_PROSPECTION_MKT!$B$61,"") -> 0 | C62: =IFERROR([1]SYNC_PROSPECTION_MKT!$C$61,"") -> 0 | D62: =IFERROR([1]SYNC_PROSPECTION_MKT!$D$61,"") -> 0 | E62: =IFERROR([1]SYNC_PROSPECTION_MKT!$E$61,"") -> 0 | F62: =IFERROR([1]SYNC_PROSPECTION_MKT!$G$61,"") -> 0 | G62: =IFERROR([1]SYNC_PROSPECTION_MKT!$H$61,"") -> 0 | H62: =IFERROR([1]SYNC_PROSPECTION_MKT!$J$61,"") -> 0 | I62: =IFERROR([1]SYNC_PROSPECTION_MKT!$I$61,"") -> 0 | J62: =IFERROR([1]SYNC_PROSPECTION_MKT!$K$61,"") -> 0 | K62: =IFERROR(SYNC_FINANCE!$I$61,"") -> 0 | L62: =IFERROR([2]SYNC_COMMERCIAL_VENTE!$S$61,"") -> 0 | M62: 0 | N62: 0 | O62: 0 | P62: 0 | Q62: 0 | R62: 0 | S62: 0 | T62: 0 | U62: 0 | V62: 0 | W62: 0 | X62: 0 | Y62: 0 | Z62: =IFERROR(SUM(N62:Y62),0) -> 0 | AA62: =IFERROR((N62+Q62+T62+W62)-M62,0) -> 0 | AB62: =IFERROR(Z62,0) -> 0 | AC62: =IFERROR(L62-AB62,0) -> 0
A63: 58 | B63: =IFERROR([1]SYNC_PROSPECTION_MKT!$B$62,"") -> 0 | C63: =IFERROR([1]SYNC_PROSPECTION_MKT!$C$62,"") -> 0 | D63: =IFERROR([1]SYNC_PROSPECTION_MKT!$D$62,"") -> 0 | E63: =IFERROR([1]SYNC_PROSPECTION_MKT!$E$62,"") -> 0 | F63: =IFERROR([1]SYNC_PROSPECTION_MKT!$G$62,"") -> 0 | G63: =IFERROR([1]SYNC_PROSPECTION_MKT!$H$62,"") -> 0 | H63: =IFERROR([1]SYNC_PROSPECTION_MKT!$J$62,"") -> 0 | I63: =IFERROR([1]SYNC_PROSPECTION_MKT!$I$62,"") -> 0 | J63: =IFERROR([1]SYNC_PROSPECTION_MKT!$K$62,"") -> 0 | K63: =IFERROR(SYNC_FINANCE!$I$62,"") -> 0 | L63: =IFERROR([2]SYNC_COMMERCIAL_VENTE!$S$62,"") -> 0 | M63: 0 | N63: 0 | O63: 0 | P63: 0 | Q63: 0 | R63: 0 | S63: 0 | T63: 0 | U63: 0 | V63: 0 | W63: 0 | X63: 0 | Y63: 0 | Z63: =IFERROR(SUM(N63:Y63),0) -> 0 | AA63: =IFERROR((N63+Q63+T63+W63)-M63,0) -> 0 | AB63: =IFERROR(Z63,0) -> 0 | AC63: =IFERROR(L63-AB63,0) -> 0
A64: 59 | B64: =IFERROR([1]SYNC_PROSPECTION_MKT!$B$63,"") -> 0 | C64: =IFERROR([1]SYNC_PROSPECTION_MKT!$C$63,"") -> 0 | D64: =IFERROR([1]SYNC_PROSPECTION_MKT!$D$63,"") -> 0 | E64: =IFERROR([1]SYNC_PROSPECTION_MKT!$E$63,"") -> 0 | F64: =IFERROR([1]SYNC_PROSPECTION_MKT!$G$63,"") -> 0 | G64: =IFERROR([1]SYNC_PROSPECTION_MKT!$H$63,"") -> 0 | H64: =IFERROR([1]SYNC_PROSPECTION_MKT!$J$63,"") -> 0 | I64: =IFERROR([1]SYNC_PROSPECTION_MKT!$I$63,"") -> 0 | J64: =IFERROR([1]SYNC_PROSPECTION_MKT!$K$63,"") -> 0 | K64: =IFERROR(SYNC_FINANCE!$I$63,"") -> 0 | L64: =IFERROR([2]SYNC_COMMERCIAL_VENTE!$S$63,"") -> 0 | M64: 0 | N64: 0 | O64: 0 | P64: 0 | Q64: 0 | R64: 0 | S64: 0 | T64: 0 | U64: 0 | V64: 0 | W64: 0 | X64: 0 | Y64: 0 | Z64: =IFERROR(SUM(N64:Y64),0) -> 0 | AA64: =IFERROR((N64+Q64+T64+W64)-M64,0) -> 0 | AB64: =IFERROR(Z64,0) -> 0 | AC64: =IFERROR(L64-AB64,0) -> 0
A65: 60 | B65: =IFERROR([1]SYNC_PROSPECTION_MKT!$B$64,"") -> 0 | C65: =IFERROR([1]SYNC_PROSPECTION_MKT!$C$64,"") -> 0 | D65: =IFERROR([1]SYNC_PROSPECTION_MKT!$D$64,"") -> 0 | E65: =IFERROR([1]SYNC_PROSPECTION_MKT!$E$64,"") -> 0 | F65: =IFERROR([1]SYNC_PROSPECTION_MKT!$G$64,"") -> 0 | G65: =IFERROR([1]SYNC_PROSPECTION_MKT!$H$64,"") -> 0 | H65: =IFERROR([1]SYNC_PROSPECTION_MKT!$J$64,"") -> 0 | I65: =IFERROR([1]SYNC_PROSPECTION_MKT!$I$64,"") -> 0 | J65: =IFERROR([1]SYNC_PROSPECTION_MKT!$K$64,"") -> 0 | K65: =IFERROR(SYNC_FINANCE!$I$64,"") -> 0 | L65: =IFERROR([2]SYNC_COMMERCIAL_VENTE!$S$64,"") -> 0 | M65: 0 | N65: 0 | O65: 0 | P65: 0 | Q65: 0 | R65: 0 | S65: 0 | T65: 0 | U65: 0 | V65: 0 | W65: 0 | X65: 0 | Y65: 0 | Z65: =IFERROR(SUM(N65:Y65),0) -> 0 | AA65: =IFERROR((N65+Q65+T65+W65)-M65,0) -> 0 | AB65: =IFERROR(Z65,0) -> 0 | AC65: =IFERROR(L65-AB65,0) -> 0
A66: 61 | B66: =IFERROR([1]SYNC_PROSPECTION_MKT!$B$65,"") -> 0 | C66: =IFERROR([1]SYNC_PROSPECTION_MKT!$C$65,"") -> 0 | D66: =IFERROR([1]SYNC_PROSPECTION_MKT!$D$65,"") -> 0 | E66: =IFERROR([1]SYNC_PROSPECTION_MKT!$E$65,"") -> 0 | F66: =IFERROR([1]SYNC_PROSPECTION_MKT!$G$65,"") -> 0 | G66: =IFERROR([1]SYNC_PROSPECTION_MKT!$H$65,"") -> 0 | H66: =IFERROR([1]SYNC_PROSPECTION_MKT!$J$65,"") -> 0 | I66: =IFERROR([1]SYNC_PROSPECTION_MKT!$I$65,"") -> 0 | J66: =IFERROR([1]SYNC_PROSPECTION_MKT!$K$65,"") -> 0 | K66: =IFERROR(SYNC_FINANCE!$I$65,"") -> 0 | L66: =IFERROR([2]SYNC_COMMERCIAL_VENTE!$S$65,"") -> 0 | M66: 0 | N66: 0 | O66: 0 | P66: 0 | Q66: 0 | R66: 0 | S66: 0 | T66: 0 | U66: 0 | V66: 0 | W66: 0 | X66: 0 | Y66: 0 | Z66: =IFERROR(SUM(N66:Y66),0) -> 0 | AA66: =IFERROR((N66+Q66+T66+W66)-M66,0) -> 0 | AB66: =IFERROR(Z66,0) -> 0 | AC66: =IFERROR(L66-AB66,0) -> 0
A67: 62 | B67: =IFERROR([1]SYNC_PROSPECTION_MKT!$B$66,"") -> 0 | C67: =IFERROR([1]SYNC_PROSPECTION_MKT!$C$66,"") -> 0 | D67: =IFERROR([1]SYNC_PROSPECTION_MKT!$D$66,"") -> 0 | E67: =IFERROR([1]SYNC_PROSPECTION_MKT!$E$66,"") -> 0 | F67: =IFERROR([1]SYNC_PROSPECTION_MKT!$G$66,"") -> 0 | G67: =IFERROR([1]SYNC_PROSPECTION_MKT!$H$66,"") -> 0 | H67: =IFERROR([1]SYNC_PROSPECTION_MKT!$J$66,"") -> 0 | I67: =IFERROR([1]SYNC_PROSPECTION_MKT!$I$66,"") -> 0 | J67: =IFERROR([1]SYNC_PROSPECTION_MKT!$K$66,"") -> 0 | K67: =IFERROR(SYNC_FINANCE!$I$66,"") -> 0 | L67: =IFERROR([2]SYNC_COMMERCIAL_VENTE!$S$66,"") -> 0 | M67: 0 | N67: 0 | O67: 0 | P67: 0 | Q67: 0 | R67: 0 | S67: 0 | T67: 0 | U67: 0 | V67: 0 | W67: 0 | X67: 0 | Y67: 0 | Z67: =IFERROR(SUM(N67:Y67),0) -> 0 | AA67: =IFERROR((N67+Q67+T67+W67)-M67,0) -> 0 | AB67: =IFERROR(Z67,0) -> 0 | AC67: =IFERROR(L67-AB67,0) -> 0
A68: 63 | B68: =IFERROR([1]SYNC_PROSPECTION_MKT!$B$67,"") -> 0 | C68: =IFERROR([1]SYNC_PROSPECTION_MKT!$C$67,"") -> 0 | D68: =IFERROR([1]SYNC_PROSPECTION_MKT!$D$67,"") -> 0 | E68: =IFERROR([1]SYNC_PROSPECTION_MKT!$E$67,"") -> 0 | F68: =IFERROR([1]SYNC_PROSPECTION_MKT!$G$67,"") -> 0 | G68: =IFERROR([1]SYNC_PROSPECTION_MKT!$H$67,"") -> 0 | H68: =IFERROR([1]SYNC_PROSPECTION_MKT!$J$67,"") -> 0 | I68: =IFERROR([1]SYNC_PROSPECTION_MKT!$I$67,"") -> 0 | J68: =IFERROR([1]SYNC_PROSPECTION_MKT!$K$67,"") -> 0 | K68: =IFERROR(SYNC_FINANCE!$I$67,"") -> 0 | L68: =IFERROR([2]SYNC_COMMERCIAL_VENTE!$S$67,"") -> 0 | M68: 0 | N68: 0 | O68: 0 | P68: 0 | Q68: 0 | R68: 0 | S68: 0 | T68: 0 | U68: 0 | V68: 0 | W68: 0 | X68: 0 | Y68: 0 | Z68: =IFERROR(SUM(N68:Y68),0) -> 0 | AA68: =IFERROR((N68+Q68+T68+W68)-M68,0) -> 0 | AB68: =IFERROR(Z68,0) -> 0 | AC68: =IFERROR(L68-AB68,0) -> 0
A69: 64 | B69: =IFERROR([1]SYNC_PROSPECTION_MKT!$B$68,"") -> 0 | C69: =IFERROR([1]SYNC_PROSPECTION_MKT!$C$68,"") -> 0 | D69: =IFERROR([1]SYNC_PROSPECTION_MKT!$D$68,"") -> 0 | E69: =IFERROR([1]SYNC_PROSPECTION_MKT!$E$68,"") -> 0 | F69: =IFERROR([1]SYNC_PROSPECTION_MKT!$G$68,"") -> 0 | G69: =IFERROR([1]SYNC_PROSPECTION_MKT!$H$68,"") -> 0 | H69: =IFERROR([1]SYNC_PROSPECTION_MKT!$J$68,"") -> 0 | I69: =IFERROR([1]SYNC_PROSPECTION_MKT!$I$68,"") -> 0 | J69: =IFERROR([1]SYNC_PROSPECTION_MKT!$K$68,"") -> 0 | K69: =IFERROR(SYNC_FINANCE!$I$68,"") -> 0 | L69: =IFERROR([2]SYNC_COMMERCIAL_VENTE!$S$68,"") -> 0 | M69: 0 | N69: 0 | O69: 0 | P69: 0 | Q69: 0 | R69: 0 | S69: 0 | T69: 0 | U69: 0 | V69: 0 | W69: 0 | X69: 0 | Y69: 0 | Z69: =IFERROR(SUM(N69:Y69),0) -> 0 | AA69: =IFERROR((N69+Q69+T69+W69)-M69,0) -> 0 | AB69: =IFERROR(Z69,0) -> 0 | AC69: =IFERROR(L69-AB69,0) -> 0
A70: 65 | B70: =IFERROR([1]SYNC_PROSPECTION_MKT!$B$69,"") -> 0 | C70: =IFERROR([1]SYNC_PROSPECTION_MKT!$C$69,"") -> 0 | D70: =IFERROR([1]SYNC_PROSPECTION_MKT!$D$69,"") -> 0 | E70: =IFERROR([1]SYNC_PROSPECTION_MKT!$E$69,"") -> 0 | F70: =IFERROR([1]SYNC_PROSPECTION_MKT!$G$69,"") -> 0 | G70: =IFERROR([1]SYNC_PROSPECTION_MKT!$H$69,"") -> 0 | H70: =IFERROR([1]SYNC_PROSPECTION_MKT!$J$69,"") -> 0 | I70: =IFERROR([1]SYNC_PROSPECTION_MKT!$I$69,"") -> 0 | J70: =IFERROR([1]SYNC_PROSPECTION_MKT!$K$69,"") -> 0 | K70: =IFERROR(SYNC_FINANCE!$I$69,"") -> 0 | L70: =IFERROR([2]SYNC_COMMERCIAL_VENTE!$S$69,"") -> 0 | M70: 0 | N70: 0 | O70: 0 | P70: 0 | Q70: 0 | R70: 0 | S70: 0 | T70: 0 | U70: 0 | V70: 0 | W70: 0 | X70: 0 | Y70: 0 | Z70: =IFERROR(SUM(N70:Y70),0) -> 0 | AA70: =IFERROR((N70+Q70+T70+W70)-M70,0) -> 0 | AB70: =IFERROR(Z70,0) -> 0 | AC70: =IFERROR(L70-AB70,0) -> 0
A71: 66 | B71: =IFERROR([1]SYNC_PROSPECTION_MKT!$B$70,"") -> 0 | C71: =IFERROR([1]SYNC_PROSPECTION_MKT!$C$70,"") -> 0 | D71: =IFERROR([1]SYNC_PROSPECTION_MKT!$D$70,"") -> 0 | E71: =IFERROR([1]SYNC_PROSPECTION_MKT!$E$70,"") -> 0 | F71: =IFERROR([1]SYNC_PROSPECTION_MKT!$G$70,"") -> 0 | G71: =IFERROR([1]SYNC_PROSPECTION_MKT!$H$70,"") -> 0 | H71: =IFERROR([1]SYNC_PROSPECTION_MKT!$J$70,"") -> 0 | I71: =IFERROR([1]SYNC_PROSPECTION_MKT!$I$70,"") -> 0 | J71: =IFERROR([1]SYNC_PROSPECTION_MKT!$K$70,"") -> 0 | K71: =IFERROR(SYNC_FINANCE!$I$70,"") -> 0 | L71: =IFERROR([2]SYNC_COMMERCIAL_VENTE!$S$70,"") -> 0 | M71: 0 | N71: 0 | O71: 0 | P71: 0 | Q71: 0 | R71: 0 | S71: 0 | T71: 0 | U71: 0 | V71: 0 | W71: 0 | X71: 0 | Y71: 0 | Z71: =IFERROR(SUM(N71:Y71),0) -> 0 | AA71: =IFERROR((N71+Q71+T71+W71)-M71,0) -> 0 | AB71: =IFERROR(Z71,0) -> 0 | AC71: =IFERROR(L71-AB71,0) -> 0
A72: 67 | B72: =IFERROR([1]SYNC_PROSPECTION_MKT!$B$71,"") -> 0 | C72: =IFERROR([1]SYNC_PROSPECTION_MKT!$C$71,"") -> 0 | D72: =IFERROR([1]SYNC_PROSPECTION_MKT!$D$71,"") -> 0 | E72: =IFERROR([1]SYNC_PROSPECTION_MKT!$E$71,"") -> 0 | F72: =IFERROR([1]SYNC_PROSPECTION_MKT!$G$71,"") -> 0 | G72: =IFERROR([1]SYNC_PROSPECTION_MKT!$H$71,"") -> 0 | H72: =IFERROR([1]SYNC_PROSPECTION_MKT!$J$71,"") -> 0 | I72: =IFERROR([1]SYNC_PROSPECTION_MKT!$I$71,"") -> 0 | J72: =IFERROR([1]SYNC_PROSPECTION_MKT!$K$71,"") -> 0 | K72: =IFERROR(SYNC_FINANCE!$I$71,"") -> 0 | L72: =IFERROR([2]SYNC_COMMERCIAL_VENTE!$S$71,"") -> 0 | M72: 0 | N72: 0 | O72: 0 | P72: 0 | Q72: 0 | R72: 0 | S72: 0 | T72: 0 | U72: 0 | V72: 0 | W72: 0 | X72: 0 | Y72: 0 | Z72: =IFERROR(SUM(N72:Y72),0) -> 0 | AA72: =IFERROR((N72+Q72+T72+W72)-M72,0) -> 0 | AB72: =IFERROR(Z72,0) -> 0 | AC72: =IFERROR(L72-AB72,0) -> 0
A73: 68 | B73: =IFERROR([1]SYNC_PROSPECTION_MKT!$B$72,"") -> 0 | C73: =IFERROR([1]SYNC_PROSPECTION_MKT!$C$72,"") -> 0 | D73: =IFERROR([1]SYNC_PROSPECTION_MKT!$D$72,"") -> 0 | E73: =IFERROR([1]SYNC_PROSPECTION_MKT!$E$72,"") -> 0 | F73: =IFERROR([1]SYNC_PROSPECTION_MKT!$G$72,"") -> 0 | G73: =IFERROR([1]SYNC_PROSPECTION_MKT!$H$72,"") -> 0 | H73: =IFERROR([1]SYNC_PROSPECTION_MKT!$J$72,"") -> 0 | I73: =IFERROR([1]SYNC_PROSPECTION_MKT!$I$72,"") -> 0 | J73: =IFERROR([1]SYNC_PROSPECTION_MKT!$K$72,"") -> 0 | K73: =IFERROR(SYNC_FINANCE!$I$72,"") -> 0 | L73: =IFERROR([2]SYNC_COMMERCIAL_VENTE!$S$72,"") -> 0 | M73: 0 | N73: 0 | O73: 0 | P73: 0 | Q73: 0 | R73: 0 | S73: 0 | T73: 0 | U73: 0 | V73: 0 | W73: 0 | X73: 0 | Y73: 0 | Z73: =IFERROR(SUM(N73:Y73),0) -> 0 | AA73: =IFERROR((N73+Q73+T73+W73)-M73,0) -> 0 | AB73: =IFERROR(Z73,0) -> 0 | AC73: =IFERROR(L73-AB73,0) -> 0
A74: 69 | B74: =IFERROR([1]SYNC_PROSPECTION_MKT!$B$73,"") -> 0 | C74: =IFERROR([1]SYNC_PROSPECTION_MKT!$C$73,"") -> 0 | D74: =IFERROR([1]SYNC_PROSPECTION_MKT!$D$73,"") -> 0 | E74: =IFERROR([1]SYNC_PROSPECTION_MKT!$E$73,"") -> 0 | F74: =IFERROR([1]SYNC_PROSPECTION_MKT!$G$73,"") -> 0 | G74: =IFERROR([1]SYNC_PROSPECTION_MKT!$H$73,"") -> 0 | H74: =IFERROR([1]SYNC_PROSPECTION_MKT!$J$73,"") -> 0 | I74: =IFERROR([1]SYNC_PROSPECTION_MKT!$I$73,"") -> 0 | J74: =IFERROR([1]SYNC_PROSPECTION_MKT!$K$73,"") -> 0 | K74: =IFERROR(SYNC_FINANCE!$I$73,"") -> 0 | L74: =IFERROR([2]SYNC_COMMERCIAL_VENTE!$S$73,"") -> 0 | M74: 0 | N74: 0 | O74: 0 | P74: 0 | Q74: 0 | R74: 0 | S74: 0 | T74: 0 | U74: 0 | V74: 0 | W74: 0 | X74: 0 | Y74: 0 | Z74: =IFERROR(SUM(N74:Y74),0) -> 0 | AA74: =IFERROR((N74+Q74+T74+W74)-M74,0) -> 0 | AB74: =IFERROR(Z74,0) -> 0 | AC74: =IFERROR(L74-AB74,0) -> 0
A75: 70 | B75: =IFERROR([1]SYNC_PROSPECTION_MKT!$B$74,"") -> 0 | C75: =IFERROR([1]SYNC_PROSPECTION_MKT!$C$74,"") -> 0 | D75: =IFERROR([1]SYNC_PROSPECTION_MKT!$D$74,"") -> 0 | E75: =IFERROR([1]SYNC_PROSPECTION_MKT!$E$74,"") -> 0 | F75: =IFERROR([1]SYNC_PROSPECTION_MKT!$G$74,"") -> 0 | G75: =IFERROR([1]SYNC_PROSPECTION_MKT!$H$74,"") -> 0 | H75: =IFERROR([1]SYNC_PROSPECTION_MKT!$J$74,"") -> 0 | I75: =IFERROR([1]SYNC_PROSPECTION_MKT!$I$74,"") -> 0 | J75: =IFERROR([1]SYNC_PROSPECTION_MKT!$K$74,"") -> 0 | K75: =IFERROR(SYNC_FINANCE!$I$74,"") -> 0 | L75: =IFERROR([2]SYNC_COMMERCIAL_VENTE!$S$74,"") -> 0 | M75: 0 | N75: 0 | O75: 0 | P75: 0 | Q75: 0 | R75: 0 | S75: 0 | T75: 0 | U75: 0 | V75: 0 | W75: 0 | X75: 0 | Y75: 0 | Z75: =IFERROR(SUM(N75:Y75),0) -> 0 | AA75: =IFERROR((N75+Q75+T75+W75)-M75,0) -> 0 | AB75: =IFERROR(Z75,0) -> 0 | AC75: =IFERROR(L75-AB75,0) -> 0
A76: 71 | B76: =IFERROR([1]SYNC_PROSPECTION_MKT!$B$75,"") -> 0 | C76: =IFERROR([1]SYNC_PROSPECTION_MKT!$C$75,"") -> 0 | D76: =IFERROR([1]SYNC_PROSPECTION_MKT!$D$75,"") -> 0 | E76: =IFERROR([1]SYNC_PROSPECTION_MKT!$E$75,"") -> 0 | F76: =IFERROR([1]SYNC_PROSPECTION_MKT!$G$75,"") -> 0 | G76: =IFERROR([1]SYNC_PROSPECTION_MKT!$H$75,"") -> 0 | H76: =IFERROR([1]SYNC_PROSPECTION_MKT!$J$75,"") -> 0 | I76: =IFERROR([1]SYNC_PROSPECTION_MKT!$I$75,"") -> 0 | J76: =IFERROR([1]SYNC_PROSPECTION_MKT!$K$75,"") -> 0 | K76: =IFERROR(SYNC_FINANCE!$I$75,"") -> 0 | L76: =IFERROR([2]SYNC_COMMERCIAL_VENTE!$S$75,"") -> 0 | M76: 0 | N76: 0 | O76: 0 | P76: 0 | Q76: 0 | R76: 0 | S76: 0 | T76: 0 | U76: 0 | V76: 0 | W76: 0 | X76: 0 | Y76: 0 | Z76: =IFERROR(SUM(N76:Y76),0) -> 0 | AA76: =IFERROR((N76+Q76+T76+W76)-M76,0) -> 0 | AB76: =IFERROR(Z76,0) -> 0 | AC76: =IFERROR(L76-AB76,0) -> 0
A77: 72 | B77: =IFERROR([1]SYNC_PROSPECTION_MKT!$B$76,"") -> 0 | C77: =IFERROR([1]SYNC_PROSPECTION_MKT!$C$76,"") -> 0 | D77: =IFERROR([1]SYNC_PROSPECTION_MKT!$D$76,"") -> 0 | E77: =IFERROR([1]SYNC_PROSPECTION_MKT!$E$76,"") -> 0 | F77: =IFERROR([1]SYNC_PROSPECTION_MKT!$G$76,"") -> 0 | G77: =IFERROR([1]SYNC_PROSPECTION_MKT!$H$76,"") -> 0 | H77: =IFERROR([1]SYNC_PROSPECTION_MKT!$J$76,"") -> 0 | I77: =IFERROR([1]SYNC_PROSPECTION_MKT!$I$76,"") -> 0 | J77: =IFERROR([1]SYNC_PROSPECTION_MKT!$K$76,"") -> 0 | K77: =IFERROR(SYNC_FINANCE!$I$76,"") -> 0 | L77: =IFERROR([2]SYNC_COMMERCIAL_VENTE!$S$76,"") -> 0 | M77: 0 | N77: 0 | O77: 0 | P77: 0 | Q77: 0 | R77: 0 | S77: 0 | T77: 0 | U77: 0 | V77: 0 | W77: 0 | X77: 0 | Y77: 0 | Z77: =IFERROR(SUM(N77:Y77),0) -> 0 | AA77: =IFERROR((N77+Q77+T77+W77)-M77,0) -> 0 | AB77: =IFERROR(Z77,0) -> 0 | AC77: =IFERROR(L77-AB77,0) -> 0
A78: 73 | B78: =IFERROR([1]SYNC_PROSPECTION_MKT!$B$77,"") -> 0 | C78: =IFERROR([1]SYNC_PROSPECTION_MKT!$C$77,"") -> 0 | D78: =IFERROR([1]SYNC_PROSPECTION_MKT!$D$77,"") -> 0 | E78: =IFERROR([1]SYNC_PROSPECTION_MKT!$E$77,"") -> 0 | F78: =IFERROR([1]SYNC_PROSPECTION_MKT!$G$77,"") -> 0 | G78: =IFERROR([1]SYNC_PROSPECTION_MKT!$H$77,"") -> 0 | H78: =IFERROR([1]SYNC_PROSPECTION_MKT!$J$77,"") -> 0 | I78: =IFERROR([1]SYNC_PROSPECTION_MKT!$I$77,"") -> 0 | J78: =IFERROR([1]SYNC_PROSPECTION_MKT!$K$77,"") -> 0 | K78: =IFERROR(SYNC_FINANCE!$I$77,"") -> 0 | L78: =IFERROR([2]SYNC_COMMERCIAL_VENTE!$S$77,"") -> 0 | M78: 0 | N78: 0 | O78: 0 | P78: 0 | Q78: 0 | R78: 0 | S78: 0 | T78: 0 | U78: 0 | V78: 0 | W78: 0 | X78: 0 | Y78: 0 | Z78: =IFERROR(SUM(N78:Y78),0) -> 0 | AA78: =IFERROR((N78+Q78+T78+W78)-M78,0) -> 0 | AB78: =IFERROR(Z78,0) -> 0 | AC78: =IFERROR(L78-AB78,0) -> 0
A79: 74 | B79: =IFERROR([1]SYNC_PROSPECTION_MKT!$B$78,"") -> 0 | C79: =IFERROR([1]SYNC_PROSPECTION_MKT!$C$78,"") -> 0 | D79: =IFERROR([1]SYNC_PROSPECTION_MKT!$D$78,"") -> 0 | E79: =IFERROR([1]SYNC_PROSPECTION_MKT!$E$78,"") -> 0 | F79: =IFERROR([1]SYNC_PROSPECTION_MKT!$G$78,"") -> 0 | G79: =IFERROR([1]SYNC_PROSPECTION_MKT!$H$78,"") -> 0 | H79: =IFERROR([1]SYNC_PROSPECTION_MKT!$J$78,"") -> 0 | I79: =IFERROR([1]SYNC_PROSPECTION_MKT!$I$78,"") -> 0 | J79: =IFERROR([1]SYNC_PROSPECTION_MKT!$K$78,"") -> 0 | K79: =IFERROR(SYNC_FINANCE!$I$78,"") -> 0 | L79: =IFERROR([2]SYNC_COMMERCIAL_VENTE!$S$78,"") -> 0 | M79: 0 | N79: 0 | O79: 0 | P79: 0 | Q79: 0 | R79: 0 | S79: 0 | T79: 0 | U79: 0 | V79: 0 | W79: 0 | X79: 0 | Y79: 0 | Z79: =IFERROR(SUM(N79:Y79),0) -> 0 | AA79: =IFERROR((N79+Q79+T79+W79)-M79,0) -> 0 | AB79: =IFERROR(Z79,0) -> 0 | AC79: =IFERROR(L79-AB79,0) -> 0
A80: 75 | B80: =IFERROR([1]SYNC_PROSPECTION_MKT!$B$79,"") -> 0 | C80: =IFERROR([1]SYNC_PROSPECTION_MKT!$C$79,"") -> 0 | D80: =IFERROR([1]SYNC_PROSPECTION_MKT!$D$79,"") -> 0 | E80: =IFERROR([1]SYNC_PROSPECTION_MKT!$E$79,"") -> 0 | F80: =IFERROR([1]SYNC_PROSPECTION_MKT!$G$79,"") -> 0 | G80: =IFERROR([1]SYNC_PROSPECTION_MKT!$H$79,"") -> 0 | H80: =IFERROR([1]SYNC_PROSPECTION_MKT!$J$79,"") -> 0 | I80: =IFERROR([1]SYNC_PROSPECTION_MKT!$I$79,"") -> 0 | J80: =IFERROR([1]SYNC_PROSPECTION_MKT!$K$79,"") -> 0 | K80: =IFERROR(SYNC_FINANCE!$I$79,"") -> 0 | L80: =IFERROR([2]SYNC_COMMERCIAL_VENTE!$S$79,"") -> 0 | M80: 0 | N80: 0 | O80: 0 | P80: 0 | Q80: 0 | R80: 0 | S80: 0 | T80: 0 | U80: 0 | V80: 0 | W80: 0 | X80: 0 | Y80: 0 | Z80: =IFERROR(SUM(N80:Y80),0) -> 0 | AA80: =IFERROR((N80+Q80+T80+W80)-M80,0) -> 0 | AB80: =IFERROR(Z80,0) -> 0 | AC80: =IFERROR(L80-AB80,0) -> 0
A81: 76 | B81: =IFERROR([1]SYNC_PROSPECTION_MKT!$B$80,"") -> 0 | C81: =IFERROR([1]SYNC_PROSPECTION_MKT!$C$80,"") -> 0 | D81: =IFERROR([1]SYNC_PROSPECTION_MKT!$D$80,"") -> 0 | E81: =IFERROR([1]SYNC_PROSPECTION_MKT!$E$80,"") -> 0 | F81: =IFERROR([1]SYNC_PROSPECTION_MKT!$G$80,"") -> 0 | G81: =IFERROR([1]SYNC_PROSPECTION_MKT!$H$80,"") -> 0 | H81: =IFERROR([1]SYNC_PROSPECTION_MKT!$J$80,"") -> 0 | I81: =IFERROR([1]SYNC_PROSPECTION_MKT!$I$80,"") -> 0 | J81: =IFERROR([1]SYNC_PROSPECTION_MKT!$K$80,"") -> 0 | K81: =IFERROR(SYNC_FINANCE!$I$80,"") -> 0 | L81: =IFERROR([2]SYNC_COMMERCIAL_VENTE!$S$80,"") -> 0 | M81: 0 | N81: 0 | O81: 0 | P81: 0 | Q81: 0 | R81: 0 | S81: 0 | T81: 0 | U81: 0 | V81: 0 | W81: 0 | X81: 0 | Y81: 0 | Z81: =IFERROR(SUM(N81:Y81),0) -> 0 | AA81: =IFERROR((N81+Q81+T81+W81)-M81,0) -> 0 | AB81: =IFERROR(Z81,0) -> 0 | AC81: =IFERROR(L81-AB81,0) -> 0
A82: 77 | B82: =IFERROR([1]SYNC_PROSPECTION_MKT!$B$81,"") -> 0 | C82: =IFERROR([1]SYNC_PROSPECTION_MKT!$C$81,"") -> 0 | D82: =IFERROR([1]SYNC_PROSPECTION_MKT!$D$81,"") -> 0 | E82: =IFERROR([1]SYNC_PROSPECTION_MKT!$E$81,"") -> 0 | F82: =IFERROR([1]SYNC_PROSPECTION_MKT!$G$81,"") -> 0 | G82: =IFERROR([1]SYNC_PROSPECTION_MKT!$H$81,"") -> 0 | H82: =IFERROR([1]SYNC_PROSPECTION_MKT!$J$81,"") -> 0 | I82: =IFERROR([1]SYNC_PROSPECTION_MKT!$I$81,"") -> 0 | J82: =IFERROR([1]SYNC_PROSPECTION_MKT!$K$81,"") -> 0 | K82: =IFERROR(SYNC_FINANCE!$I$81,"") -> 0 | L82: =IFERROR([2]SYNC_COMMERCIAL_VENTE!$S$81,"") -> 0 | M82: 0 | N82: 0 | O82: 0 | P82: 0 | Q82: 0 | R82: 0 | S82: 0 | T82: 0 | U82: 0 | V82: 0 | W82: 0 | X82: 0 | Y82: 0 | Z82: =IFERROR(SUM(N82:Y82),0) -> 0 | AA82: =IFERROR((N82+Q82+T82+W82)-M82,0) -> 0 | AB82: =IFERROR(Z82,0) -> 0 | AC82: =IFERROR(L82-AB82,0) -> 0
A83: 78 | B83: =IFERROR([1]SYNC_PROSPECTION_MKT!$B$82,"") -> 0 | C83: =IFERROR([1]SYNC_PROSPECTION_MKT!$C$82,"") -> 0 | D83: =IFERROR([1]SYNC_PROSPECTION_MKT!$D$82,"") -> 0 | E83: =IFERROR([1]SYNC_PROSPECTION_MKT!$E$82,"") -> 0 | F83: =IFERROR([1]SYNC_PROSPECTION_MKT!$G$82,"") -> 0 | G83: =IFERROR([1]SYNC_PROSPECTION_MKT!$H$82,"") -> 0 | H83: =IFERROR([1]SYNC_PROSPECTION_MKT!$J$82,"") -> 0 | I83: =IFERROR([1]SYNC_PROSPECTION_MKT!$I$82,"") -> 0 | J83: =IFERROR([1]SYNC_PROSPECTION_MKT!$K$82,"") -> 0 | K83: =IFERROR(SYNC_FINANCE!$I$82,"") -> 0 | L83: =IFERROR([2]SYNC_COMMERCIAL_VENTE!$S$82,"") -> 0 | M83: 0 | N83: 0 | O83: 0 | P83: 0 | Q83: 0 | R83: 0 | S83: 0 | T83: 0 | U83: 0 | V83: 0 | W83: 0 | X83: 0 | Y83: 0 | Z83: =IFERROR(SUM(N83:Y83),0) -> 0 | AA83: =IFERROR((N83+Q83+T83+W83)-M83,0) -> 0 | AB83: =IFERROR(Z83,0) -> 0 | AC83: =IFERROR(L83-AB83,0) -> 0
A84: 79 | B84: =IFERROR([1]SYNC_PROSPECTION_MKT!$B$83,"") -> 0 | C84: =IFERROR([1]SYNC_PROSPECTION_MKT!$C$83,"") -> 0 | D84: =IFERROR([1]SYNC_PROSPECTION_MKT!$D$83,"") -> 0 | E84: =IFERROR([1]SYNC_PROSPECTION_MKT!$E$83,"") -> 0 | F84: =IFERROR([1]SYNC_PROSPECTION_MKT!$G$83,"") -> 0 | G84: =IFERROR([1]SYNC_PROSPECTION_MKT!$H$83,"") -> 0 | H84: =IFERROR([1]SYNC_PROSPECTION_MKT!$J$83,"") -> 0 | I84: =IFERROR([1]SYNC_PROSPECTION_MKT!$I$83,"") -> 0 | J84: =IFERROR([1]SYNC_PROSPECTION_MKT!$K$83,"") -> 0 | K84: =IFERROR(SYNC_FINANCE!$I$83,"") -> 0 | L84: =IFERROR([2]SYNC_COMMERCIAL_VENTE!$S$83,"") -> 0 | M84: 0 | N84: 0 | O84: 0 | P84: 0 | Q84: 0 | R84: 0 | S84: 0 | T84: 0 | U84: 0 | V84: 0 | W84: 0 | X84: 0 | Y84: 0 | Z84: =IFERROR(SUM(N84:Y84),0) -> 0 | AA84: =IFERROR((N84+Q84+T84+W84)-M84,0) -> 0 | AB84: =IFERROR(Z84,0) -> 0 | AC84: =IFERROR(L84-AB84,0) -> 0
A85: 80 | B85: =IFERROR([1]SYNC_PROSPECTION_MKT!$B$84,"") -> 0 | C85: =IFERROR([1]SYNC_PROSPECTION_MKT!$C$84,"") -> 0 | D85: =IFERROR([1]SYNC_PROSPECTION_MKT!$D$84,"") -> 0 | E85: =IFERROR([1]SYNC_PROSPECTION_MKT!$E$84,"") -> 0 | F85: =IFERROR([1]SYNC_PROSPECTION_MKT!$G$84,"") -> 0 | G85: =IFERROR([1]SYNC_PROSPECTION_MKT!$H$84,"") -> 0 | H85: =IFERROR([1]SYNC_PROSPECTION_MKT!$J$84,"") -> 0 | I85: =IFERROR([1]SYNC_PROSPECTION_MKT!$I$84,"") -> 0 | J85: =IFERROR([1]SYNC_PROSPECTION_MKT!$K$84,"") -> 0 | K85: =IFERROR(SYNC_FINANCE!$I$84,"") -> 0 | L85: =IFERROR([2]SYNC_COMMERCIAL_VENTE!$S$84,"") -> 0 | M85: 0 | N85: 0 | O85: 0 | P85: 0 | Q85: 0 | R85: 0 | S85: 0 | T85: 0 | U85: 0 | V85: 0 | W85: 0 | X85: 0 | Y85: 0 | Z85: =IFERROR(SUM(N85:Y85),0) -> 0 | AA85: =IFERROR((N85+Q85+T85+W85)-M85,0) -> 0 | AB85: =IFERROR(Z85,0) -> 0 | AC85: =IFERROR(L85-AB85,0) -> 0
A86: 81 | B86: =IFERROR([1]SYNC_PROSPECTION_MKT!$B$85,"") -> 0 | C86: =IFERROR([1]SYNC_PROSPECTION_MKT!$C$85,"") -> 0 | D86: =IFERROR([1]SYNC_PROSPECTION_MKT!$D$85,"") -> 0 | E86: =IFERROR([1]SYNC_PROSPECTION_MKT!$E$85,"") -> 0 | F86: =IFERROR([1]SYNC_PROSPECTION_MKT!$G$85,"") -> 0 | G86: =IFERROR([1]SYNC_PROSPECTION_MKT!$H$85,"") -> 0 | H86: =IFERROR([1]SYNC_PROSPECTION_MKT!$J$85,"") -> 0 | I86: =IFERROR([1]SYNC_PROSPECTION_MKT!$I$85,"") -> 0 | J86: =IFERROR([1]SYNC_PROSPECTION_MKT!$K$85,"") -> 0 | K86: =IFERROR(SYNC_FINANCE!$I$85,"") -> 0 | L86: =IFERROR([2]SYNC_COMMERCIAL_VENTE!$S$85,"") -> 0 | M86: 0 | N86: 0 | O86: 0 | P86: 0 | Q86: 0 | R86: 0 | S86: 0 | T86: 0 | U86: 0 | V86: 0 | W86: 0 | X86: 0 | Y86: 0 | Z86: =IFERROR(SUM(N86:Y86),0) -> 0 | AA86: =IFERROR((N86+Q86+T86+W86)-M86,0) -> 0 | AB86: =IFERROR(Z86,0) -> 0 | AC86: =IFERROR(L86-AB86,0) -> 0
A87: 82 | B87: =IFERROR([1]SYNC_PROSPECTION_MKT!$B$86,"") -> 0 | C87: =IFERROR([1]SYNC_PROSPECTION_MKT!$C$86,"") -> 0 | D87: =IFERROR([1]SYNC_PROSPECTION_MKT!$D$86,"") -> 0 | E87: =IFERROR([1]SYNC_PROSPECTION_MKT!$E$86,"") -> 0 | F87: =IFERROR([1]SYNC_PROSPECTION_MKT!$G$86,"") -> 0 | G87: =IFERROR([1]SYNC_PROSPECTION_MKT!$H$86,"") -> 0 | H87: =IFERROR([1]SYNC_PROSPECTION_MKT!$J$86,"") -> 0 | I87: =IFERROR([1]SYNC_PROSPECTION_MKT!$I$86,"") -> 0 | J87: =IFERROR([1]SYNC_PROSPECTION_MKT!$K$86,"") -> 0 | K87: =IFERROR(SYNC_FINANCE!$I$86,"") -> 0 | L87: =IFERROR([2]SYNC_COMMERCIAL_VENTE!$S$86,"") -> 0 | M87: 0 | N87: 0 | O87: 0 | P87: 0 | Q87: 0 | R87: 0 | S87: 0 | T87: 0 | U87: 0 | V87: 0 | W87: 0 | X87: 0 | Y87: 0 | Z87: =IFERROR(SUM(N87:Y87),0) -> 0 | AA87: =IFERROR((N87+Q87+T87+W87)-M87,0) -> 0 | AB87: =IFERROR(Z87,0) -> 0 | AC87: =IFERROR(L87-AB87,0) -> 0
A88: 83 | B88: =IFERROR([1]SYNC_PROSPECTION_MKT!$B$87,"") -> 0 | C88: =IFERROR([1]SYNC_PROSPECTION_MKT!$C$87,"") -> 0 | D88: =IFERROR([1]SYNC_PROSPECTION_MKT!$D$87,"") -> 0 | E88: =IFERROR([1]SYNC_PROSPECTION_MKT!$E$87,"") -> 0 | F88: =IFERROR([1]SYNC_PROSPECTION_MKT!$G$87,"") -> 0 | G88: =IFERROR([1]SYNC_PROSPECTION_MKT!$H$87,"") -> 0 | H88: =IFERROR([1]SYNC_PROSPECTION_MKT!$J$87,"") -> 0 | I88: =IFERROR([1]SYNC_PROSPECTION_MKT!$I$87,"") -> 0 | J88: =IFERROR([1]SYNC_PROSPECTION_MKT!$K$87,"") -> 0 | K88: =IFERROR(SYNC_FINANCE!$I$87,"") -> 0 | L88: =IFERROR([2]SYNC_COMMERCIAL_VENTE!$S$87,"") -> 0 | M88: 0 | N88: 0 | O88: 0 | P88: 0 | Q88: 0 | R88: 0 | S88: 0 | T88: 0 | U88: 0 | V88: 0 | W88: 0 | X88: 0 | Y88: 0 | Z88: =IFERROR(SUM(N88:Y88),0) -> 0 | AA88: =IFERROR((N88+Q88+T88+W88)-M88,0) -> 0 | AB88: =IFERROR(Z88,0) -> 0 | AC88: =IFERROR(L88-AB88,0) -> 0
A89: 84 | B89: =IFERROR([1]SYNC_PROSPECTION_MKT!$B$88,"") -> 0 | C89: =IFERROR([1]SYNC_PROSPECTION_MKT!$C$88,"") -> 0 | D89: =IFERROR([1]SYNC_PROSPECTION_MKT!$D$88,"") -> 0 | E89: =IFERROR([1]SYNC_PROSPECTION_MKT!$E$88,"") -> 0 | F89: =IFERROR([1]SYNC_PROSPECTION_MKT!$G$88,"") -> 0 | G89: =IFERROR([1]SYNC_PROSPECTION_MKT!$H$88,"") -> 0 | H89: =IFERROR([1]SYNC_PROSPECTION_MKT!$J$88,"") -> 0 | I89: =IFERROR([1]SYNC_PROSPECTION_MKT!$I$88,"") -> 0 | J89: =IFERROR([1]SYNC_PROSPECTION_MKT!$K$88,"") -> 0 | K89: =IFERROR(SYNC_FINANCE!$I$88,"") -> 0 | L89: =IFERROR([2]SYNC_COMMERCIAL_VENTE!$S$88,"") -> 0 | M89: 0 | N89: 0 | O89: 0 | P89: 0 | Q89: 0 | R89: 0 | S89: 0 | T89: 0 | U89: 0 | V89: 0 | W89: 0 | X89: 0 | Y89: 0 | Z89: =IFERROR(SUM(N89:Y89),0) -> 0 | AA89: =IFERROR((N89+Q89+T89+W89)-M89,0) -> 0 | AB89: =IFERROR(Z89,0) -> 0 | AC89: =IFERROR(L89-AB89,0) -> 0
A90: 85 | B90: =IFERROR([1]SYNC_PROSPECTION_MKT!$B$89,"") -> 0 | C90: =IFERROR([1]SYNC_PROSPECTION_MKT!$C$89,"") -> 0 | D90: =IFERROR([1]SYNC_PROSPECTION_MKT!$D$89,"") -> 0 | E90: =IFERROR([1]SYNC_PROSPECTION_MKT!$E$89,"") -> 0 | F90: =IFERROR([1]SYNC_PROSPECTION_MKT!$G$89,"") -> 0 | G90: =IFERROR([1]SYNC_PROSPECTION_MKT!$H$89,"") -> 0 | H90: =IFERROR([1]SYNC_PROSPECTION_MKT!$J$89,"") -> 0 | I90: =IFERROR([1]SYNC_PROSPECTION_MKT!$I$89,"") -> 0 | J90: =IFERROR([1]SYNC_PROSPECTION_MKT!$K$89,"") -> 0 | K90: =IFERROR(SYNC_FINANCE!$I$89,"") -> 0 | L90: =IFERROR([2]SYNC_COMMERCIAL_VENTE!$S$89,"") -> 0 | M90: 0 | N90: 0 | O90: 0 | P90: 0 | Q90: 0 | R90: 0 | S90: 0 | T90: 0 | U90: 0 | V90: 0 | W90: 0 | X90: 0 | Y90: 0 | Z90: =IFERROR(SUM(N90:Y90),0) -> 0 | AA90: =IFERROR((N90+Q90+T90+W90)-M90,0) -> 0 | AB90: =IFERROR(Z90,0) -> 0 | AC90: =IFERROR(L90-AB90,0) -> 0
A91: 86 | B91: =IFERROR([1]SYNC_PROSPECTION_MKT!$B$90,"") -> 0 | C91: =IFERROR([1]SYNC_PROSPECTION_MKT!$C$90,"") -> 0 | D91: =IFERROR([1]SYNC_PROSPECTION_MKT!$D$90,"") -> 0 | E91: =IFERROR([1]SYNC_PROSPECTION_MKT!$E$90,"") -> 0 | F91: =IFERROR([1]SYNC_PROSPECTION_MKT!$G$90,"") -> 0 | G91: =IFERROR([1]SYNC_PROSPECTION_MKT!$H$90,"") -> 0 | H91: =IFERROR([1]SYNC_PROSPECTION_MKT!$J$90,"") -> 0 | I91: =IFERROR([1]SYNC_PROSPECTION_MKT!$I$90,"") -> 0 | J91: =IFERROR([1]SYNC_PROSPECTION_MKT!$K$90,"") -> 0 | K91: =IFERROR(SYNC_FINANCE!$I$90,"") -> 0 | L91: =IFERROR([2]SYNC_COMMERCIAL_VENTE!$S$90,"") -> 0 | M91: 0 | N91: 0 | O91: 0 | P91: 0 | Q91: 0 | R91: 0 | S91: 0 | T91: 0 | U91: 0 | V91: 0 | W91: 0 | X91: 0 | Y91: 0 | Z91: =IFERROR(SUM(N91:Y91),0) -> 0 | AA91: =IFERROR((N91+Q91+T91+W91)-M91,0) -> 0 | AB91: =IFERROR(Z91,0) -> 0 | AC91: =IFERROR(L91-AB91,0) -> 0
A92: 87 | B92: =IFERROR([1]SYNC_PROSPECTION_MKT!$B$91,"") -> 0 | C92: =IFERROR([1]SYNC_PROSPECTION_MKT!$C$91,"") -> 0 | D92: =IFERROR([1]SYNC_PROSPECTION_MKT!$D$91,"") -> 0 | E92: =IFERROR([1]SYNC_PROSPECTION_MKT!$E$91,"") -> 0 | F92: =IFERROR([1]SYNC_PROSPECTION_MKT!$G$91,"") -> 0 | G92: =IFERROR([1]SYNC_PROSPECTION_MKT!$H$91,"") -> 0 | H92: =IFERROR([1]SYNC_PROSPECTION_MKT!$J$91,"") -> 0 | I92: =IFERROR([1]SYNC_PROSPECTION_MKT!$I$91,"") -> 0 | J92: =IFERROR([1]SYNC_PROSPECTION_MKT!$K$91,"") -> 0 | K92: =IFERROR(SYNC_FINANCE!$I$91,"") -> 0 | L92: =IFERROR([2]SYNC_COMMERCIAL_VENTE!$S$91,"") -> 0 | M92: 0 | N92: 0 | O92: 0 | P92: 0 | Q92: 0 | R92: 0 | S92: 0 | T92: 0 | U92: 0 | V92: 0 | W92: 0 | X92: 0 | Y92: 0 | Z92: =IFERROR(SUM(N92:Y92),0) -> 0 | AA92: =IFERROR((N92+Q92+T92+W92)-M92,0) -> 0 | AB92: =IFERROR(Z92,0) -> 0 | AC92: =IFERROR(L92-AB92,0) -> 0
A93: 88 | B93: =IFERROR([1]SYNC_PROSPECTION_MKT!$B$92,"") -> 0 | C93: =IFERROR([1]SYNC_PROSPECTION_MKT!$C$92,"") -> 0 | D93: =IFERROR([1]SYNC_PROSPECTION_MKT!$D$92,"") -> 0 | E93: =IFERROR([1]SYNC_PROSPECTION_MKT!$E$92,"") -> 0 | F93: =IFERROR([1]SYNC_PROSPECTION_MKT!$G$92,"") -> 0 | G93: =IFERROR([1]SYNC_PROSPECTION_MKT!$H$92,"") -> 0 | H93: =IFERROR([1]SYNC_PROSPECTION_MKT!$J$92,"") -> 0 | I93: =IFERROR([1]SYNC_PROSPECTION_MKT!$I$92,"") -> 0 | J93: =IFERROR([1]SYNC_PROSPECTION_MKT!$K$92,"") -> 0 | K93: =IFERROR(SYNC_FINANCE!$I$92,"") -> 0 | L93: =IFERROR([2]SYNC_COMMERCIAL_VENTE!$S$92,"") -> 0 | M93: 0 | N93: 0 | O93: 0 | P93: 0 | Q93: 0 | R93: 0 | S93: 0 | T93: 0 | U93: 0 | V93: 0 | W93: 0 | X93: 0 | Y93: 0 | Z93: =IFERROR(SUM(N93:Y93),0) -> 0 | AA93: =IFERROR((N93+Q93+T93+W93)-M93,0) -> 0 | AB93: =IFERROR(Z93,0) -> 0 | AC93: =IFERROR(L93-AB93,0) -> 0
A94: 89 | B94: =IFERROR([1]SYNC_PROSPECTION_MKT!$B$93,"") -> 0 | C94: =IFERROR([1]SYNC_PROSPECTION_MKT!$C$93,"") -> 0 | D94: =IFERROR([1]SYNC_PROSPECTION_MKT!$D$93,"") -> 0 | E94: =IFERROR([1]SYNC_PROSPECTION_MKT!$E$93,"") -> 0 | F94: =IFERROR([1]SYNC_PROSPECTION_MKT!$G$93,"") -> 0 | G94: =IFERROR([1]SYNC_PROSPECTION_MKT!$H$93,"") -> 0 | H94: =IFERROR([1]SYNC_PROSPECTION_MKT!$J$93,"") -> 0 | I94: =IFERROR([1]SYNC_PROSPECTION_MKT!$I$93,"") -> 0 | J94: =IFERROR([1]SYNC_PROSPECTION_MKT!$K$93,"") -> 0 | K94: =IFERROR(SYNC_FINANCE!$I$93,"") -> 0 | L94: =IFERROR([2]SYNC_COMMERCIAL_VENTE!$S$93,"") -> 0 | M94: 0 | N94: 0 | O94: 0 | P94: 0 | Q94: 0 | R94: 0 | S94: 0 | T94: 0 | U94: 0 | V94: 0 | W94: 0 | X94: 0 | Y94: 0 | Z94: =IFERROR(SUM(N94:Y94),0) -> 0 | AA94: =IFERROR((N94+Q94+T94+W94)-M94,0) -> 0 | AB94: =IFERROR(Z94,0) -> 0 | AC94: =IFERROR(L94-AB94,0) -> 0
A95: 90 | B95: =IFERROR([1]SYNC_PROSPECTION_MKT!$B$94,"") -> 0 | C95: =IFERROR([1]SYNC_PROSPECTION_MKT!$C$94,"") -> 0 | D95: =IFERROR([1]SYNC_PROSPECTION_MKT!$D$94,"") -> 0 | E95: =IFERROR([1]SYNC_PROSPECTION_MKT!$E$94,"") -> 0 | F95: =IFERROR([1]SYNC_PROSPECTION_MKT!$G$94,"") -> 0 | G95: =IFERROR([1]SYNC_PROSPECTION_MKT!$H$94,"") -> 0 | H95: =IFERROR([1]SYNC_PROSPECTION_MKT!$J$94,"") -> 0 | I95: =IFERROR([1]SYNC_PROSPECTION_MKT!$I$94,"") -> 0 | J95: =IFERROR([1]SYNC_PROSPECTION_MKT!$K$94,"") -> 0 | K95: =IFERROR(SYNC_FINANCE!$I$94,"") -> 0 | L95: =IFERROR([2]SYNC_COMMERCIAL_VENTE!$S$94,"") -> 0 | M95: 0 | N95: 0 | O95: 0 | P95: 0 | Q95: 0 | R95: 0 | S95: 0 | T95: 0 | U95: 0 | V95: 0 | W95: 0 | X95: 0 | Y95: 0 | Z95: =IFERROR(SUM(N95:Y95),0) -> 0 | AA95: =IFERROR((N95+Q95+T95+W95)-M95,0) -> 0 | AB95: =IFERROR(Z95,0) -> 0 | AC95: =IFERROR(L95-AB95,0) -> 0
A96: 91 | B96: =IFERROR([1]SYNC_PROSPECTION_MKT!$B$95,"") -> 0 | C96: =IFERROR([1]SYNC_PROSPECTION_MKT!$C$95,"") -> 0 | D96: =IFERROR([1]SYNC_PROSPECTION_MKT!$D$95,"") -> 0 | E96: =IFERROR([1]SYNC_PROSPECTION_MKT!$E$95,"") -> 0 | F96: =IFERROR([1]SYNC_PROSPECTION_MKT!$G$95,"") -> 0 | G96: =IFERROR([1]SYNC_PROSPECTION_MKT!$H$95,"") -> 0 | H96: =IFERROR([1]SYNC_PROSPECTION_MKT!$J$95,"") -> 0 | I96: =IFERROR([1]SYNC_PROSPECTION_MKT!$I$95,"") -> 0 | J96: =IFERROR([1]SYNC_PROSPECTION_MKT!$K$95,"") -> 0 | K96: =IFERROR(SYNC_FINANCE!$I$95,"") -> 0 | L96: =IFERROR([2]SYNC_COMMERCIAL_VENTE!$S$95,"") -> 0 | M96: 0 | N96: 0 | O96: 0 | P96: 0 | Q96: 0 | R96: 0 | S96: 0 | T96: 0 | U96: 0 | V96: 0 | W96: 0 | X96: 0 | Y96: 0 | Z96: =IFERROR(SUM(N96:Y96),0) -> 0 | AA96: =IFERROR((N96+Q96+T96+W96)-M96,0) -> 0 | AB96: =IFERROR(Z96,0) -> 0 | AC96: =IFERROR(L96-AB96,0) -> 0
A97: 92 | B97: =IFERROR([1]SYNC_PROSPECTION_MKT!$B$96,"") -> 0 | C97: =IFERROR([1]SYNC_PROSPECTION_MKT!$C$96,"") -> 0 | D97: =IFERROR([1]SYNC_PROSPECTION_MKT!$D$96,"") -> 0 | E97: =IFERROR([1]SYNC_PROSPECTION_MKT!$E$96,"") -> 0 | F97: =IFERROR([1]SYNC_PROSPECTION_MKT!$G$96,"") -> 0 | G97: =IFERROR([1]SYNC_PROSPECTION_MKT!$H$96,"") -> 0 | H97: =IFERROR([1]SYNC_PROSPECTION_MKT!$J$96,"") -> 0 | I97: =IFERROR([1]SYNC_PROSPECTION_MKT!$I$96,"") -> 0 | J97: =IFERROR([1]SYNC_PROSPECTION_MKT!$K$96,"") -> 0 | K97: =IFERROR(SYNC_FINANCE!$I$96,"") -> 0 | L97: =IFERROR([2]SYNC_COMMERCIAL_VENTE!$S$96,"") -> 0 | M97: 0 | N97: 0 | O97: 0 | P97: 0 | Q97: 0 | R97: 0 | S97: 0 | T97: 0 | U97: 0 | V97: 0 | W97: 0 | X97: 0 | Y97: 0 | Z97: =IFERROR(SUM(N97:Y97),0) -> 0 | AA97: =IFERROR((N97+Q97+T97+W97)-M97,0) -> 0 | AB97: =IFERROR(Z97,0) -> 0 | AC97: =IFERROR(L97-AB97,0) -> 0
A98: 93 | B98: =IFERROR([1]SYNC_PROSPECTION_MKT!$B$97,"") -> 0 | C98: =IFERROR([1]SYNC_PROSPECTION_MKT!$C$97,"") -> 0 | D98: =IFERROR([1]SYNC_PROSPECTION_MKT!$D$97,"") -> 0 | E98: =IFERROR([1]SYNC_PROSPECTION_MKT!$E$97,"") -> 0 | F98: =IFERROR([1]SYNC_PROSPECTION_MKT!$G$97,"") -> 0 | G98: =IFERROR([1]SYNC_PROSPECTION_MKT!$H$97,"") -> 0 | H98: =IFERROR([1]SYNC_PROSPECTION_MKT!$J$97,"") -> 0 | I98: =IFERROR([1]SYNC_PROSPECTION_MKT!$I$97,"") -> 0 | J98: =IFERROR([1]SYNC_PROSPECTION_MKT!$K$97,"") -> 0 | K98: =IFERROR(SYNC_FINANCE!$I$97,"") -> 0 | L98: =IFERROR([2]SYNC_COMMERCIAL_VENTE!$S$97,"") -> 0 | M98: 0 | N98: 0 | O98: 0 | P98: 0 | Q98: 0 | R98: 0 | S98: 0 | T98: 0 | U98: 0 | V98: 0 | W98: 0 | X98: 0 | Y98: 0 | Z98: =IFERROR(SUM(N98:Y98),0) -> 0 | AA98: =IFERROR((N98+Q98+T98+W98)-M98,0) -> 0 | AB98: =IFERROR(Z98,0) -> 0 | AC98: =IFERROR(L98-AB98,0) -> 0
A99: 94 | B99: =IFERROR([1]SYNC_PROSPECTION_MKT!$B$98,"") -> 0 | C99: =IFERROR([1]SYNC_PROSPECTION_MKT!$C$98,"") -> 0 | D99: =IFERROR([1]SYNC_PROSPECTION_MKT!$D$98,"") -> 0 | E99: =IFERROR([1]SYNC_PROSPECTION_MKT!$E$98,"") -> 0 | F99: =IFERROR([1]SYNC_PROSPECTION_MKT!$G$98,"") -> 0 | G99: =IFERROR([1]SYNC_PROSPECTION_MKT!$H$98,"") -> 0 | H99: =IFERROR([1]SYNC_PROSPECTION_MKT!$J$98,"") -> 0 | I99: =IFERROR([1]SYNC_PROSPECTION_MKT!$I$98,"") -> 0 | J99: =IFERROR([1]SYNC_PROSPECTION_MKT!$K$98,"") -> 0 | K99: =IFERROR(SYNC_FINANCE!$I$98,"") -> 0 | L99: =IFERROR([2]SYNC_COMMERCIAL_VENTE!$S$98,"") -> 0 | M99: 0 | N99: 0 | O99: 0 | P99: 0 | Q99: 0 | R99: 0 | S99: 0 | T99: 0 | U99: 0 | V99: 0 | W99: 0 | X99: 0 | Y99: 0 | Z99: =IFERROR(SUM(N99:Y99),0) -> 0 | AA99: =IFERROR((N99+Q99+T99+W99)-M99,0) -> 0 | AB99: =IFERROR(Z99,0) -> 0 | AC99: =IFERROR(L99-AB99,0) -> 0
A100: 95 | B100: =IFERROR([1]SYNC_PROSPECTION_MKT!$B$99,"") -> 0 | C100: =IFERROR([1]SYNC_PROSPECTION_MKT!$C$99,"") -> 0 | D100: =IFERROR([1]SYNC_PROSPECTION_MKT!$D$99,"") -> 0 | E100: =IFERROR([1]SYNC_PROSPECTION_MKT!$E$99,"") -> 0 | F100: =IFERROR([1]SYNC_PROSPECTION_MKT!$G$99,"") -> 0 | G100: =IFERROR([1]SYNC_PROSPECTION_MKT!$H$99,"") -> 0 | H100: =IFERROR([1]SYNC_PROSPECTION_MKT!$J$99,"") -> 0 | I100: =IFERROR([1]SYNC_PROSPECTION_MKT!$I$99,"") -> 0 | J100: =IFERROR([1]SYNC_PROSPECTION_MKT!$K$99,"") -> 0 | K100: =IFERROR(SYNC_FINANCE!$I$99,"") -> 0 | L100: =IFERROR([2]SYNC_COMMERCIAL_VENTE!$S$99,"") -> 0 | M100: 0 | N100: 0 | O100: 0 | P100: 0 | Q100: 0 | R100: 0 | S100: 0 | T100: 0 | U100: 0 | V100: 0 | W100: 0 | X100: 0 | Y100: 0 | Z100: =IFERROR(SUM(N100:Y100),0) -> 0 | AA100: =IFERROR((N100+Q100+T100+W100)-M100,0) -> 0 | AB100: =IFERROR(Z100,0) -> 0 | AC100: =IFERROR(L100-AB100,0) -> 0
...

Sheet PAIEMENTS JUILLET 2026
A1: 💰 PAIEMENTS JUILLET 2026 — LEMI SARL | BRASUS v3.2
A2: ⚠️ Saisie des paiements reçus par semaine. Alimente automatiquement le SUIVI 13 MOIS.
A3: 🔒 Identité client (auto) | K3: 📋 Contrat | N3: ✏️ PAIEMENTS JUILLET — 4 semaines × (Paiement + Droit + Apport) | Z3: ⚙️ CALCULS AUTO
N4: 01/07-07/07 | Q4: 08/07-15/07 | T4: 16/07-24/07 | W4: 25/07-31/07
A5: N° | B5: N° IDENTIFIANT | C5: NOM & PRÉNOMS DU CLIENT | D5: SOURCE DU PROSPECT | E5: DATE PREMIER CONTACT | F5: TÉLÉPHONE / WHATSAPP | G5: PROFESSION | H5: RÉGION D'HABITATION | I5: RÉGION DU PROJET | J5: LIEU DU PROJET | K5: N° CONTRAT | L5: MONTANT TTC (FCFA) | M5: MENSUALITÉ (FCFA) | N5: PAIEMENT | O5: DROIT ADHÉSION | P5: APPORT INITIAL | Q5: PAIEMENT | R5: DROIT ADHÉSION | S5: APPORT INITIAL | T5: PAIEMENT | U5: DROIT ADHÉSION | V5: APPORT INITIAL | W5: PAIEMENT | X5: DROIT ADHÉSION | Y5: APPORT INITIAL | Z5: TOTAL MOIS | AA5: MENSUALITÉ DUE | AB5: CUMUL PAIEMENTS | AC5: RESTANT DÛ
A6: 1 | B6: =IFERROR([1]SYNC_PROSPECTION_MKT!$B$5,"") -> 0 | C6: =IFERROR([1]SYNC_PROSPECTION_MKT!$C$5,"") -> TANOH KONAN GERVAIS ARMAND | D6: =IFERROR([1]SYNC_PROSPECTION_MKT!$D$5,"") -> 0 | E6: =IFERROR([1]SYNC_PROSPECTION_MKT!$E$5,"") -> 0 | F6: =IFERROR([1]SYNC_PROSPECTION_MKT!$G$5,"") -> 0 | G6: =IFERROR([1]SYNC_PROSPECTION_MKT!$H$5,"") -> 0 | H6: =IFERROR([1]SYNC_PROSPECTION_MKT!$J$5,"") -> 0 | I6: =IFERROR([1]SYNC_PROSPECTION_MKT!$I$5,"") -> 0 | J6: =IFERROR([1]SYNC_PROSPECTION_MKT!$K$5,"") -> 0 | K6: =IFERROR(SYNC_FINANCE!$I$5,"") -> 0 | L6: =IFERROR([2]SYNC_COMMERCIAL_VENTE!$S$5,"") -> 0 | M6: 138889 | N6: 138889 | O6: 250000 | P6: 3000000 | Q6: 0 | R6: 0 | S6: 0 | T6: 0 | U6: 0 | V6: 0 | W6: 0 | X6: 0 | Y6: 0 | Z6: =IFERROR(SUM(N6:Y6),0) -> 3388889 | AA6: =IFERROR((N6+Q6+T6+W6)-M6,0) -> 0 | AB6: =IFERROR(Z6,0) -> 3388889 | AC6: =IFERROR(L6-AB6,0) -> -3388889
A7: 2 | B7: =IFERROR([1]SYNC_PROSPECTION_MKT!$B$6,"") -> 0 | C7: =IFERROR([1]SYNC_PROSPECTION_MKT!$C$6,"") -> N'DRI ép. NGBESSO AKISSI ELIANE | D7: =IFERROR([1]SYNC_PROSPECTION_MKT!$D$6,"") -> 0 | E7: =IFERROR([1]SYNC_PROSPECTION_MKT!$E$6,"") -> 0 | F7: =IFERROR([1]SYNC_PROSPECTION_MKT!$G$6,"") -> 0 | G7: =IFERROR([1]SYNC_PROSPECTION_MKT!$H$6,"") -> 0 | H7: =IFERROR([1]SYNC_PROSPECTION_MKT!$J$6,"") -> 0 | I7: =IFERROR([1]SYNC_PROSPECTION_MKT!$I$6,"") -> 0 | J7: =IFERROR([1]SYNC_PROSPECTION_MKT!$K$6,"") -> 0 | K7: =IFERROR(SYNC_FINANCE!$I$6,"") -> 0 | L7: =IFERROR([2]SYNC_COMMERCIAL_VENTE!$S$6,"") -> 0 | M7: 0 | N7: 0 | O7: 0 | P7: 0 | Q7: 0 | R7: 0 | S7: 0 | T7: 0 | U7: 0 | V7: 0 | W7: 0 | X7: 0 | Y7: 0 | Z7: =IFERROR(SUM(N7:Y7),0) -> 0 | AA7: =IFERROR((N7+Q7+T7+W7)-M7,0) -> 0 | AB7: =IFERROR(Z7,0) -> 0 | AC7: =IFERROR(L7-AB7,0) -> 0
A8: 3 | B8: =IFERROR([1]SYNC_PROSPECTION_MKT!$B$7,"") -> 0 | C8: =IFERROR([1]SYNC_PROSPECTION_MKT!$C$7,"") -> N'GORAN KOFFI | D8: =IFERROR([1]SYNC_PROSPECTION_MKT!$D$7,"") -> 0 | E8: =IFERROR([1]SYNC_PROSPECTION_MKT!$E$7,"") -> 0 | F8: =IFERROR([1]SYNC_PROSPECTION_MKT!$G$7,"") -> 0 | G8: =IFERROR([1]SYNC_PROSPECTION_MKT!$H$7,"") -> 0 | H8: =IFERROR([1]SYNC_PROSPECTION_MKT!$J$7,"") -> 0 | I8: =IFERROR([1]SYNC_PROSPECTION_MKT!$I$7,"") -> 0 | J8: =IFERROR([1]SYNC_PROSPECTION_MKT!$K$7,"") -> 0 | K8: =IFERROR(SYNC_FINANCE!$I$7,"") -> 0 | L8: =IFERROR([2]SYNC_COMMERCIAL_VENTE!$S$7,"") -> 0 | M8: 0 | N8: 0 | O8: 0 | P8: 0 | Q8: 0 | R8: 0 | S8: 0 | T8: 0 | U8: 0 | V8: 0 | W8: 0 | X8: 0 | Y8: 0 | Z8: =IFERROR(SUM(N8:Y8),0) -> 0 | AA8: =IFERROR((N8+Q8+T8+W8)-M8,0) -> 0 | AB8: =IFERROR(Z8,0) -> 0 | AC8: =IFERROR(L8-AB8,0) -> 0
A9: 4 | B9: =IFERROR([1]SYNC_PROSPECTION_MKT!$B$8,"") -> 0 | C9: =IFERROR([1]SYNC_PROSPECTION_MKT!$C$8,"") -> KOUASSI VINCENT DE PAUL ASSOUMOU | D9: =IFERROR([1]SYNC_PROSPECTION_MKT!$D$8,"") -> 0 | E9: =IFERROR([1]SYNC_PROSPECTION_MKT!$E$8,"") -> 0 | F9: =IFERROR([1]SYNC_PROSPECTION_MKT!$G$8,"") -> 0 | G9: =IFERROR([1]SYNC_PROSPECTION_MKT!$H$8,"") -> 0 | H9: =IFERROR([1]SYNC_PROSPECTION_MKT!$J$8,"") -> 0 | I9: =IFERROR([1]SYNC_PROSPECTION_MKT!$I$8,"") -> 0 | J9: =IFERROR([1]SYNC_PROSPECTION_MKT!$K$8,"") -> 0 | K9: =IFERROR(SYNC_FINANCE!$I$8,"") -> 0 | L9: =IFERROR([2]SYNC_COMMERCIAL_VENTE!$S$8,"") -> 0 | M9: 0 | N9: 0 | O9: 0 | P9: 0 | Q9: 0 | R9: 0 | S9: 0 | T9: 0 | U9: 0 | V9: 0 | W9: 0 | X9: 0 | Y9: 0 | Z9: =IFERROR(SUM(N9:Y9),0) -> 0 | AA9: =IFERROR((N9+Q9+T9+W9)-M9,0) -> 0 | AB9: =IFERROR(Z9,0) -> 0 | AC9: =IFERROR(L9-AB9,0) -> 0
A10: 5 | B10: =IFERROR([1]SYNC_PROSPECTION_MKT!$B$9,"") -> 0 | C10: =IFERROR([1]SYNC_PROSPECTION_MKT!$C$9,"") -> KOUASSI HONORE | D10: =IFERROR([1]SYNC_PROSPECTION_MKT!$D$9,"") -> 0 | E10: =IFERROR([1]SYNC_PROSPECTION_MKT!$E$9,"") -> 0 | F10: =IFERROR([1]SYNC_PROSPECTION_MKT!$G$9,"") -> 0 | G10: =IFERROR([1]SYNC_PROSPECTION_MKT!$H$9,"") -> 0 | H10: =IFERROR([1]SYNC_PROSPECTION_MKT!$J$9,"") -> 0 | I10: =IFERROR([1]SYNC_PROSPECTION_MKT!$I$9,"") -> 0 | J10: =IFERROR([1]SYNC_PROSPECTION_MKT!$K$9,"") -> 0 | K10: =IFERROR(SYNC_FINANCE!$I$9,"") -> 0 | L10: =IFERROR([2]SYNC_COMMERCIAL_VENTE!$S$9,"") -> 0 | M10: 0 | N10: 0 | O10: 0 | P10: 0 | Q10: 0 | R10: 0 | S10: 0 | T10: 0 | U10: 0 | V10: 0 | W10: 0 | X10: 0 | Y10: 0 | Z10: =IFERROR(SUM(N10:Y10),0) -> 0 | AA10: =IFERROR((N10+Q10+T10+W10)-M10,0) -> 0 | AB10: =IFERROR(Z10,0) -> 0 | AC10: =IFERROR(L10-AB10,0) -> 0
A11: 6 | B11: =IFERROR([1]SYNC_PROSPECTION_MKT!$B$10,"") -> 0 | C11: =IFERROR([1]SYNC_PROSPECTION_MKT!$C$10,"") -> AKISSI ELIANE KONAN | D11: =IFERROR([1]SYNC_PROSPECTION_MKT!$D$10,"") -> 0 | E11: =IFERROR([1]SYNC_PROSPECTION_MKT!$E$10,"") -> 0 | F11: =IFERROR([1]SYNC_PROSPECTION_MKT!$G$10,"") -> 0 | G11: =IFERROR([1]SYNC_PROSPECTION_MKT!$H$10,"") -> 0 | H11: =IFERROR([1]SYNC_PROSPECTION_MKT!$J$10,"") -> 0 | I11: =IFERROR([1]SYNC_PROSPECTION_MKT!$I$10,"") -> 0 | J11: =IFERROR([1]SYNC_PROSPECTION_MKT!$K$10,"") -> 0 | K11: =IFERROR(SYNC_FINANCE!$I$10,"") -> 0 | L11: =IFERROR([2]SYNC_COMMERCIAL_VENTE!$S$10,"") -> 0 | M11: 0 | N11: 0 | O11: 0 | P11: 0 | Q11: 0 | R11: 0 | S11: 0 | T11: 0 | U11: 0 | V11: 0 | W11: 0 | X11: 0 | Y11: 0 | Z11: =IFERROR(SUM(N11:Y11),0) -> 0 | AA11: =IFERROR((N11+Q11+T11+W11)-M11,0) -> 0 | AB11: =IFERROR(Z11,0) -> 0 | AC11: =IFERROR(L11-AB11,0) -> 0
A12: 7 | B12: =IFERROR([1]SYNC_PROSPECTION_MKT!$B$11,"") -> 0 | C12: =IFERROR([1]SYNC_PROSPECTION_MKT!$C$11,"") -> BROU LAMBERT KOUASSI | D12: =IFERROR([1]SYNC_PROSPECTION_MKT!$D$11,"") -> 0 | E12: =IFERROR([1]SYNC_PROSPECTION_MKT!$E$11,"") -> 0 | F12: =IFERROR([1]SYNC_PROSPECTION_MKT!$G$11,"") -> 0 | G12: =IFERROR([1]SYNC_PROSPECTION_MKT!$H$11,"") -> 0 | H12: =IFERROR([1]SYNC_PROSPECTION_MKT!$J$11,"") -> 0 | I12: =IFERROR([1]SYNC_PROSPECTION_MKT!$I$11,"") -> 0 | J12: =IFERROR([1]SYNC_PROSPECTION_MKT!$K$11,"") -> 0 | K12: =IFERROR(SYNC_FINANCE!$I$11,"") -> 0 | L12: =IFERROR([2]SYNC_COMMERCIAL_VENTE!$S$11,"") -> 0 | M12: 0 | N12: 0 | O12: 0 | P12: 0 | Q12: 0 | R12: 0 | S12: 0 | T12: 0 | U12: 0 | V12: 0 | W12: 0 | X12: 0 | Y12: 0 | Z12: =IFERROR(SUM(N12:Y12),0) -> 0 | AA12: =IFERROR((N12+Q12+T12+W12)-M12,0) -> 0 | AB12: =IFERROR(Z12,0) -> 0 | AC12: =IFERROR(L12-AB12,0) -> 0
A13: 8 | B13: =IFERROR([1]SYNC_PROSPECTION_MKT!$B$12,"") -> 0 | C13: =IFERROR([1]SYNC_PROSPECTION_MKT!$C$12,"") -> DJEDRI KOUAKOU JEAN PIERRE | D13: =IFERROR([1]SYNC_PROSPECTION_MKT!$D$12,"") -> 0 | E13: =IFERROR([1]SYNC_PROSPECTION_MKT!$E$12,"") -> 0 | F13: =IFERROR([1]SYNC_PROSPECTION_MKT!$G$12,"") -> 0 | G13: =IFERROR([1]SYNC_PROSPECTION_MKT!$H$12,"") -> 0 | H13: =IFERROR([1]SYNC_PROSPECTION_MKT!$J$12,"") -> 0 | I13: =IFERROR([1]SYNC_PROSPECTION_MKT!$I$12,"") -> 0 | J13: =IFERROR([1]SYNC_PROSPECTION_MKT!$K$12,"") -> 0 | K13: =IFERROR(SYNC_FINANCE!$I$12,"") -> 0 | L13: =IFERROR([2]SYNC_COMMERCIAL_VENTE!$S$12,"") -> 0 | M13: 0 | N13: 0 | O13: 0 | P13: 0 | Q13: 0 | R13: 0 | S13: 0 | T13: 0 | U13: 0 | V13: 0 | W13: 0 | X13: 0 | Y13: 0 | Z13: =IFERROR(SUM(N13:Y13),0) -> 0 | AA13: =IFERROR((N13+Q13+T13+W13)-M13,0) -> 0 | AB13: =IFERROR(Z13,0) -> 0 | AC13: =IFERROR(L13-AB13,0) -> 0
A14: 9 | B14: =IFERROR([1]SYNC_PROSPECTION_MKT!$B$13,"") -> 0 | C14: =IFERROR([1]SYNC_PROSPECTION_MKT!$C$13,"") -> DJAMAN KOUAKOU MATHIEU | D14: =IFERROR([1]SYNC_PROSPECTION_MKT!$D$13,"") -> 0 | E14: =IFERROR([1]SYNC_PROSPECTION_MKT!$E$13,"") -> 0 | F14: =IFERROR([1]SYNC_PROSPECTION_MKT!$G$13,"") -> 0 | G14: =IFERROR([1]SYNC_PROSPECTION_MKT!$H$13,"") -> 0 | H14: =IFERROR([1]SYNC_PROSPECTION_MKT!$J$13,"") -> 0 | I14: =IFERROR([1]SYNC_PROSPECTION_MKT!$I$13,"") -> 0 | J14: =IFERROR([1]SYNC_PROSPECTION_MKT!$K$13,"") -> 0 | K14: =IFERROR(SYNC_FINANCE!$I$13,"") -> 0 | L14: =IFERROR([2]SYNC_COMMERCIAL_VENTE!$S$13,"") -> 0 | M14: 0 | N14: 0 | O14: 0 | P14: 0 | Q14: 0 | R14: 0 | S14: 0 | T14: 0 | U14: 0 | V14: 0 | W14: 0 | X14: 0 | Y14: 0 | Z14: =IFERROR(SUM(N14:Y14),0) -> 0 | AA14: =IFERROR((N14+Q14+T14+W14)-M14,0) -> 0 | AB14: =IFERROR(Z14,0) -> 0 | AC14: =IFERROR(L14-AB14,0) -> 0
A15: 10 | B15: =IFERROR([1]SYNC_PROSPECTION_MKT!$B$14,"") -> 0 | C15: =IFERROR([1]SYNC_PROSPECTION_MKT!$C$14,"") -> N'GUESSAN KOUASSI | D15: =IFERROR([1]SYNC_PROSPECTION_MKT!$D$14,"") -> 0 | E15: =IFERROR([1]SYNC_PROSPECTION_MKT!$E$14,"") -> 0 | F15: =IFERROR([1]SYNC_PROSPECTION_MKT!$G$14,"") -> 0 | G15: =IFERROR([1]SYNC_PROSPECTION_MKT!$H$14,"") -> 0 | H15: =IFERROR([1]SYNC_PROSPECTION_MKT!$J$14,"") -> 0 | I15: =IFERROR([1]SYNC_PROSPECTION_MKT!$I$14,"") -> 0 | J15: =IFERROR([1]SYNC_PROSPECTION_MKT!$K$14,"") -> 0 | K15: =IFERROR(SYNC_FINANCE!$I$14,"") -> 0 | L15: =IFERROR([2]SYNC_COMMERCIAL_VENTE!$S$14,"") -> 0 | M15: 0 | N15: 0 | O15: 0 | P15: 0 | Q15: 0 | R15: 0 | S15: 0 | T15: 0 | U15: 0 | V15: 0 | W15: 0 | X15: 0 | Y15: 0 | Z15: =IFERROR(SUM(N15:Y15),0) -> 0 | AA15: =IFERROR((N15+Q15+T15+W15)-M15,0) -> 0 | AB15: =IFERROR(Z15,0) -> 0 | AC15: =IFERROR(L15-AB15,0) -> 0
A16: 11 | B16: =IFERROR([1]SYNC_PROSPECTION_MKT!$B$15,"") -> 0 | C16: =IFERROR([1]SYNC_PROSPECTION_MKT!$C$15,"") -> N'ZUE N'GUESSAN | D16: =IFERROR([1]SYNC_PROSPECTION_MKT!$D$15,"") -> 0 | E16: =IFERROR([1]SYNC_PROSPECTION_MKT!$E$15,"") -> 0 | F16: =IFERROR([1]SYNC_PROSPECTION_MKT!$G$15,"") -> 0 | G16: =IFERROR([1]SYNC_PROSPECTION_MKT!$H$15,"") -> 0 | H16: =IFERROR([1]SYNC_PROSPECTION_MKT!$J$15,"") -> 0 | I16: =IFERROR([1]SYNC_PROSPECTION_MKT!$I$15,"") -> 0 | J16: =IFERROR([1]SYNC_PROSPECTION_MKT!$K$15,"") -> 0 | K16: =IFERROR(SYNC_FINANCE!$I$15,"") -> 0 | L16: =IFERROR([2]SYNC_COMMERCIAL_VENTE!$S$15,"") -> 0 | M16: 0 | N16: 0 | O16: 0 | P16: 0 | Q16: 0 | R16: 0 | S16: 0 | T16: 0 | U16: 0 | V16: 0 | W16: 0 | X16: 0 | Y16: 0 | Z16: =IFERROR(SUM(N16:Y16),0) -> 0 | AA16: =IFERROR((N16+Q16+T16+W16)-M16,0) -> 0 | AB16: =IFERROR(Z16,0) -> 0 | AC16: =IFERROR(L16-AB16,0) -> 0
A17: 12 | B17: =IFERROR([1]SYNC_PROSPECTION_MKT!$B$16,"") -> 0 | C17: =IFERROR([1]SYNC_PROSPECTION_MKT!$C$16,"") -> CASIMIR | D17: =IFERROR([1]SYNC_PROSPECTION_MKT!$D$16,"") -> 0 | E17: =IFERROR([1]SYNC_PROSPECTION_MKT!$E$16,"") -> 0 | F17: =IFERROR([1]SYNC_PROSPECTION_MKT!$G$16,"") -> 0 | G17: =IFERROR([1]SYNC_PROSPECTION_MKT!$H$16,"") -> 0 | H17: =IFERROR([1]SYNC_PROSPECTION_MKT!$J$16,"") -> 0 | I17: =IFERROR([1]SYNC_PROSPECTION_MKT!$I$16,"") -> 0 | J17: =IFERROR([1]SYNC_PROSPECTION_MKT!$K$16,"") -> 0 | K17: =IFERROR(SYNC_FINANCE!$I$16,"") -> 0 | L17: =IFERROR([2]SYNC_COMMERCIAL_VENTE!$S$16,"") -> 0 | M17: 0 | N17: 0 | O17: 0 | P17: 0 | Q17: 0 | R17: 0 | S17: 0 | T17: 0 | U17: 0 | V17: 0 | W17: 0 | X17: 0 | Y17: 0 | Z17: =IFERROR(SUM(N17:Y17),0) -> 0 | AA17: =IFERROR((N17+Q17+T17+W17)-M17,0) -> 0 | AB17: =IFERROR(Z17,0) -> 0 | AC17: =IFERROR(L17-AB17,0) -> 0
A18: 13 | B18: =IFERROR([1]SYNC_PROSPECTION_MKT!$B$17,"") -> 0 | C18: =IFERROR([1]SYNC_PROSPECTION_MKT!$C$17,"") -> 0 | D18: =IFERROR([1]SYNC_PROSPECTION_MKT!$D$17,"") -> 0 | E18: =IFERROR([1]SYNC_PROSPECTION_MKT!$E$17,"") -> 0 | F18: =IFERROR([1]SYNC_PROSPECTION_MKT!$G$17,"") -> 0 | G18: =IFERROR([1]SYNC_PROSPECTION_MKT!$H$17,"") -> 0 | H18: =IFERROR([1]SYNC_PROSPECTION_MKT!$J$17,"") -> 0 | I18: =IFERROR([1]SYNC_PROSPECTION_MKT!$I$17,"") -> 0 | J18: =IFERROR([1]SYNC_PROSPECTION_MKT!$K$17,"") -> 0 | K18: =IFERROR(SYNC_FINANCE!$I$17,"") -> 0 | L18: =IFERROR([2]SYNC_COMMERCIAL_VENTE!$S$17,"") -> 0 | M18: 0 | N18: 0 | O18: 0 | P18: 0 | Q18: 0 | R18: 0 | S18: 0 | T18: 0 | U18: 0 | V18: 0 | W18: 0 | X18: 0 | Y18: 0 | Z18: =IFERROR(SUM(N18:Y18),0) -> 0 | AA18: =IFERROR((N18+Q18+T18+W18)-M18,0) -> 0 | AB18: =IFERROR(Z18,0) -> 0 | AC18: =IFERROR(L18-AB18,0) -> 0
A19: 14 | B19: =IFERROR([1]SYNC_PROSPECTION_MKT!$B$18,"") -> 0 | C19: =IFERROR([1]SYNC_PROSPECTION_MKT!$C$18,"") -> 0 | D19: =IFERROR([1]SYNC_PROSPECTION_MKT!$D$18,"") -> 0 | E19: =IFERROR([1]SYNC_PROSPECTION_MKT!$E$18,"") -> 0 | F19: =IFERROR([1]SYNC_PROSPECTION_MKT!$G$18,"") -> 0 | G19: =IFERROR([1]SYNC_PROSPECTION_MKT!$H$18,"") -> 0 | H19: =IFERROR([1]SYNC_PROSPECTION_MKT!$J$18,"") -> 0 | I19: =IFERROR([1]SYNC_PROSPECTION_MKT!$I$18,"") -> 0 | J19: =IFERROR([1]SYNC_PROSPECTION_MKT!$K$18,"") -> 0 | K19: =IFERROR(SYNC_FINANCE!$I$18,"") -> 0 | L19: =IFERROR([2]SYNC_COMMERCIAL_VENTE!$S$18,"") -> 0 | M19: 0 | N19: 0 | O19: 0 | P19: 0 | Q19: 0 | R19: 0 | S19: 0 | T19: 0 | U19: 0 | V19: 0 | W19: 0 | X19: 0 | Y19: 0 | Z19: =IFERROR(SUM(N19:Y19),0) -> 0 | AA19: =IFERROR((N19+Q19+T19+W19)-M19,0) -> 0 | AB19: =IFERROR(Z19,0) -> 0 | AC19: =IFERROR(L19-AB19,0) -> 0
A20: 15 | B20: =IFERROR([1]SYNC_PROSPECTION_MKT!$B$19,"") -> 0 | C20: =IFERROR([1]SYNC_PROSPECTION_MKT!$C$19,"") -> 0 | D20: =IFERROR([1]SYNC_PROSPECTION_MKT!$D$19,"") -> 0 | E20: =IFERROR([1]SYNC_PROSPECTION_MKT!$E$19,"") -> 0 | F20: =IFERROR([1]SYNC_PROSPECTION_MKT!$G$19,"") -> 0 | G20: =IFERROR([1]SYNC_PROSPECTION_MKT!$H$19,"") -> 0 | H20: =IFERROR([1]SYNC_PROSPECTION_MKT!$J$19,"") -> 0 | I20: =IFERROR([1]SYNC_PROSPECTION_MKT!$I$19,"") -> 0 | J20: =IFERROR([1]SYNC_PROSPECTION_MKT!$K$19,"") -> 0 | K20: =IFERROR(SYNC_FINANCE!$I$19,"") -> 0 | L20: =IFERROR([2]SYNC_COMMERCIAL_VENTE!$S$19,"") -> 0 | M20: 0 | N20: 0 | O20: 0 | P20: 0 | Q20: 0 | R20: 0 | S20: 0 | T20: 0 | U20: 0 | V20: 0 | W20: 0 | X20: 0 | Y20: 0 | Z20: =IFERROR(SUM(N20:Y20),0) -> 0 | AA20: =IFERROR((N20+Q20+T20+W20)-M20,0) -> 0 | AB20: =IFERROR(Z20,0) -> 0 | AC20: =IFERROR(L20-AB20,0) -> 0
A21: 16 | B21: =IFERROR([1]SYNC_PROSPECTION_MKT!$B$20,"") -> 0 | C21: =IFERROR([1]SYNC_PROSPECTION_MKT!$C$20,"") -> 0 | D21: =IFERROR([1]SYNC_PROSPECTION_MKT!$D$20,"") -> 0 | E21: =IFERROR([1]SYNC_PROSPECTION_MKT!$E$20,"") -> 0 | F21: =IFERROR([1]SYNC_PROSPECTION_MKT!$G$20,"") -> 0 | G21: =IFERROR([1]SYNC_PROSPECTION_MKT!$H$20,"") -> 0 | H21: =IFERROR([1]SYNC_PROSPECTION_MKT!$J$20,"") -> 0 | I21: =IFERROR([1]SYNC_PROSPECTION_MKT!$I$20,"") -> 0 | J21: =IFERROR([1]SYNC_PROSPECTION_MKT!$K$20,"") -> 0 | K21: =IFERROR(SYNC_FINANCE!$I$20,"") -> 0 | L21: =IFERROR([2]SYNC_COMMERCIAL_VENTE!$S$20,"") -> 0 | M21: 0 | N21: 0 | O21: 0 | P21: 0 | Q21: 0 | R21: 0 | S21: 0 | T21: 0 | U21: 0 | V21: 0 | W21: 0 | X21: 0 | Y21: 0 | Z21: =IFERROR(SUM(N21:Y21),0) -> 0 | AA21: =IFERROR((N21+Q21+T21+W21)-M21,0) -> 0 | AB21: =IFERROR(Z21,0) -> 0 | AC21: =IFERROR(L21-AB21,0) -> 0
A22: 17 | B22: =IFERROR([1]SYNC_PROSPECTION_MKT!$B$21,"") -> 0 | C22: =IFERROR([1]SYNC_PROSPECTION_MKT!$C$21,"") -> 0 | D22: =IFERROR([1]SYNC_PROSPECTION_MKT!$D$21,"") -> 0 | E22: =IFERROR([1]SYNC_PROSPECTION_MKT!$E$21,"") -> 0 | F22: =IFERROR([1]SYNC_PROSPECTION_MKT!$G$21,"") -> 0 | G22: =IFERROR([1]SYNC_PROSPECTION_MKT!$H$21,"") -> 0 | H22: =IFERROR([1]SYNC_PROSPECTION_MKT!$J$21,"") -> 0 | I22: =IFERROR([1]SYNC_PROSPECTION_MKT!$I$21,"") -> 0 | J22: =IFERROR([1]SYNC_PROSPECTION_MKT!$K$21,"") -> 0 | K22: =IFERROR(SYNC_FINANCE!$I$21,"") -> 0 | L22: =IFERROR([2]SYNC_COMMERCIAL_VENTE!$S$21,"") -> 0 | M22: 0 | N22: 0 | O22: 0 | P22: 0 | Q22: 0 | R22: 0 | S22: 0 | T22: 0 | U22: 0 | V22: 0 | W22: 0 | X22: 0 | Y22: 0 | Z22: =IFERROR(SUM(N22:Y22),0) -> 0 | AA22: =IFERROR((N22+Q22+T22+W22)-M22,0) -> 0 | AB22: =IFERROR(Z22,0) -> 0 | AC22: =IFERROR(L22-AB22,0) -> 0
A23: 18 | B23: =IFERROR([1]SYNC_PROSPECTION_MKT!$B$22,"") -> 0 | C23: =IFERROR([1]SYNC_PROSPECTION_MKT!$C$22,"") -> 0 | D23: =IFERROR([1]SYNC_PROSPECTION_MKT!$D$22,"") -> 0 | E23: =IFERROR([1]SYNC_PROSPECTION_MKT!$E$22,"") -> 0 | F23: =IFERROR([1]SYNC_PROSPECTION_MKT!$G$22,"") -> 0 | G23: =IFERROR([1]SYNC_PROSPECTION_MKT!$H$22,"") -> 0 | H23: =IFERROR([1]SYNC_PROSPECTION_MKT!$J$22,"") -> 0 | I23: =IFERROR([1]SYNC_PROSPECTION_MKT!$I$22,"") -> 0 | J23: =IFERROR([1]SYNC_PROSPECTION_MKT!$K$22,"") -> 0 | K23: =IFERROR(SYNC_FINANCE!$I$22,"") -> 0 | L23: =IFERROR([2]SYNC_COMMERCIAL_VENTE!$S$22,"") -> 0 | M23: 0 | N23: 0 | O23: 0 | P23: 0 | Q23: 0 | R23: 0 | S23: 0 | T23: 0 | U23: 0 | V23: 0 | W23: 0 | X23: 0 | Y23: 0 | Z23: =IFERROR(SUM(N23:Y23),0) -> 0 | AA23: =IFERROR((N23+Q23+T23+W23)-M23,0) -> 0 | AB23: =IFERROR(Z23,0) -> 0 | AC23: =IFERROR(L23-AB23,0) -> 0
A24: 19 | B24: =IFERROR([1]SYNC_PROSPECTION_MKT!$B$23,"") -> 0 | C24: =IFERROR([1]SYNC_PROSPECTION_MKT!$C$23,"") -> 0 | D24: =IFERROR([1]SYNC_PROSPECTION_MKT!$D$23,"") -> 0 | E24: =IFERROR([1]SYNC_PROSPECTION_MKT!$E$23,"") -> 0 | F24: =IFERROR([1]SYNC_PROSPECTION_MKT!$G$23,"") -> 0 | G24: =IFERROR([1]SYNC_PROSPECTION_MKT!$H$23,"") -> 0 | H24: =IFERROR([1]SYNC_PROSPECTION_MKT!$J$23,"") -> 0 | I24: =IFERROR([1]SYNC_PROSPECTION_MKT!$I$23,"") -> 0 | J24: =IFERROR([1]SYNC_PROSPECTION_MKT!$K$23,"") -> 0 | K24: =IFERROR(SYNC_FINANCE!$I$23,"") -> 0 | L24: =IFERROR([2]SYNC_COMMERCIAL_VENTE!$S$23,"") -> 0 | M24: 0 | N24: 0 | O24: 0 | P24: 0 | Q24: 0 | R24: 0 | S24: 0 | T24: 0 | U24: 0 | V24: 0 | W24: 0 | X24: 0 | Y24: 0 | Z24: =IFERROR(SUM(N24:Y24),0) -> 0 | AA24: =IFERROR((N24+Q24+T24+W24)-M24,0) -> 0 | AB24: =IFERROR(Z24,0) -> 0 | AC24: =IFERROR(L24-AB24,0) -> 0
A25: 20 | B25: =IFERROR([1]SYNC_PROSPECTION_MKT!$B$24,"") -> 0 | C25: =IFERROR([1]SYNC_PROSPECTION_MKT!$C$24,"") -> 0 | D25: =IFERROR([1]SYNC_PROSPECTION_MKT!$D$24,"") -> 0 | E25: =IFERROR([1]SYNC_PROSPECTION_MKT!$E$24,"") -> 0 | F25: =IFERROR([1]SYNC_PROSPECTION_MKT!$G$24,"") -> 0 | G25: =IFERROR([1]SYNC_PROSPECTION_MKT!$H$24,"") -> 0 | H25: =IFERROR([1]SYNC_PROSPECTION_MKT!$J$24,"") -> 0 | I25: =IFERROR([1]SYNC_PROSPECTION_MKT!$I$24,"") -> 0 | J25: =IFERROR([1]SYNC_PROSPECTION_MKT!$K$24,"") -> 0 | K25: =IFERROR(SYNC_FINANCE!$I$24,"") -> 0 | L25: =IFERROR([2]SYNC_COMMERCIAL_VENTE!$S$24,"") -> 0 | M25: 0 | N25: 0 | O25: 0 | P25: 0 | Q25: 0 | R25: 0 | S25: 0 | T25: 0 | U25: 0 | V25: 0 | W25: 0 | X25: 0 | Y25: 0 | Z25: =IFERROR(SUM(N25:Y25),0) -> 0 | AA25: =IFERROR((N25+Q25+T25+W25)-M25,0) -> 0 | AB25: =IFERROR(Z25,0) -> 0 | AC25: =IFERROR(L25-AB25,0) -> 0
A26: 21 | B26: =IFERROR([1]SYNC_PROSPECTION_MKT!$B$25,"") -> 0 | C26: =IFERROR([1]SYNC_PROSPECTION_MKT!$C$25,"") -> 0 | D26: =IFERROR([1]SYNC_PROSPECTION_MKT!$D$25,"") -> 0 | E26: =IFERROR([1]SYNC_PROSPECTION_MKT!$E$25,"") -> 0 | F26: =IFERROR([1]SYNC_PROSPECTION_MKT!$G$25,"") -> 0 | G26: =IFERROR([1]SYNC_PROSPECTION_MKT!$H$25,"") -> 0 | H26: =IFERROR([1]SYNC_PROSPECTION_MKT!$J$25,"") -> 0 | I26: =IFERROR([1]SYNC_PROSPECTION_MKT!$I$25,"") -> 0 | J26: =IFERROR([1]SYNC_PROSPECTION_MKT!$K$25,"") -> 0 | K26: =IFERROR(SYNC_FINANCE!$I$25,"") -> 0 | L26: =IFERROR([2]SYNC_COMMERCIAL_VENTE!$S$25,"") -> 0 | M26: 0 | N26: 0 | O26: 0 | P26: 0 | Q26: 0 | R26: 0 | S26: 0 | T26: 0 | U26: 0 | V26: 0 | W26: 0 | X26: 0 | Y26: 0 | Z26: =IFERROR(SUM(N26:Y26),0) -> 0 | AA26: =IFERROR((N26+Q26+T26+W26)-M26,0) -> 0 | AB26: =IFERROR(Z26,0) -> 0 | AC26: =IFERROR(L26-AB26,0) -> 0
A27: 22 | B27: =IFERROR([1]SYNC_PROSPECTION_MKT!$B$26,"") -> 0 | C27: =IFERROR([1]SYNC_PROSPECTION_MKT!$C$26,"") -> 0 | D27: =IFERROR([1]SYNC_PROSPECTION_MKT!$D$26,"") -> 0 | E27: =IFERROR([1]SYNC_PROSPECTION_MKT!$E$26,"") -> 0 | F27: =IFERROR([1]SYNC_PROSPECTION_MKT!$G$26,"") -> 0 | G27: =IFERROR([1]SYNC_PROSPECTION_MKT!$H$26,"") -> 0 | H27: =IFERROR([1]SYNC_PROSPECTION_MKT!$J$26,"") -> 0 | I27: =IFERROR([1]SYNC_PROSPECTION_MKT!$I$26,"") -> 0 | J27: =IFERROR([1]SYNC_PROSPECTION_MKT!$K$26,"") -> 0 | K27: =IFERROR(SYNC_FINANCE!$I$26,"") -> 0 | L27: =IFERROR([2]SYNC_COMMERCIAL_VENTE!$S$26,"") -> 0 | M27: 0 | N27: 0 | O27: 0 | P27: 0 | Q27: 0 | R27: 0 | S27: 0 | T27: 0 | U27: 0 | V27: 0 | W27: 0 | X27: 0 | Y27: 0 | Z27: =IFERROR(SUM(N27:Y27),0) -> 0 | AA27: =IFERROR((N27+Q27+T27+W27)-M27,0) -> 0 | AB27: =IFERROR(Z27,0) -> 0 | AC27: =IFERROR(L27-AB27,0) -> 0
A28: 23 | B28: =IFERROR([1]SYNC_PROSPECTION_MKT!$B$27,"") -> 0 | C28: =IFERROR([1]SYNC_PROSPECTION_MKT!$C$27,"") -> 0 | D28: =IFERROR([1]SYNC_PROSPECTION_MKT!$D$27,"") -> 0 | E28: =IFERROR([1]SYNC_PROSPECTION_MKT!$E$27,"") -> 0 | F28: =IFERROR([1]SYNC_PROSPECTION_MKT!$G$27,"") -> 0 | G28: =IFERROR([1]SYNC_PROSPECTION_MKT!$H$27,"") -> 0 | H28: =IFERROR([1]SYNC_PROSPECTION_MKT!$J$27,"") -> 0 | I28: =IFERROR([1]SYNC_PROSPECTION_MKT!$I$27,"") -> 0 | J28: =IFERROR([1]SYNC_PROSPECTION_MKT!$K$27,"") -> 0 | K28: =IFERROR(SYNC_FINANCE!$I$27,"") -> 0 | L28: =IFERROR([2]SYNC_COMMERCIAL_VENTE!$S$27,"") -> 0 | M28: 0 | N28: 0 | O28: 0 | P28: 0 | Q28: 0 | R28: 0 | S28: 0 | T28: 0 | U28: 0 | V28: 0 | W28: 0 | X28: 0 | Y28: 0 | Z28: =IFERROR(SUM(N28:Y28),0) -> 0 | AA28: =IFERROR((N28+Q28+T28+W28)-M28,0) -> 0 | AB28: =IFERROR(Z28,0) -> 0 | AC28: =IFERROR(L28-AB28,0) -> 0
A29: 24 | B29: =IFERROR([1]SYNC_PROSPECTION_MKT!$B$28,"") -> 0 | C29: =IFERROR([1]SYNC_PROSPECTION_MKT!$C$28,"") -> 0 | D29: =IFERROR([1]SYNC_PROSPECTION_MKT!$D$28,"") -> 0 | E29: =IFERROR([1]SYNC_PROSPECTION_MKT!$E$28,"") -> 0 | F29: =IFERROR([1]SYNC_PROSPECTION_MKT!$G$28,"") -> 0 | G29: =IFERROR([1]SYNC_PROSPECTION_MKT!$H$28,"") -> 0 | H29: =IFERROR([1]SYNC_PROSPECTION_MKT!$J$28,"") -> 0 | I29: =IFERROR([1]SYNC_PROSPECTION_MKT!$I$28,"") -> 0 | J29: =IFERROR([1]SYNC_PROSPECTION_MKT!$K$28,"") -> 0 | K29: =IFERROR(SYNC_FINANCE!$I$28,"") -> 0 | L29: =IFERROR([2]SYNC_COMMERCIAL_VENTE!$S$28,"") -> 0 | M29: 0 | N29: 0 | O29: 0 | P29: 0 | Q29: 0 | R29: 0 | S29: 0 | T29: 0 | U29: 0 | V29: 0 | W29: 0 | X29: 0 | Y29: 0 | Z29: =IFERROR(SUM(N29:Y29),0) -> 0 | AA29: =IFERROR((N29+Q29+T29+W29)-M29,0) -> 0 | AB29: =IFERROR(Z29,0) -> 0 | AC29: =IFERROR(L29-AB29,0) -> 0
A30: 25 | B30: =IFERROR([1]SYNC_PROSPECTION_MKT!$B$29,"") -> 0 | C30: =IFERROR([1]SYNC_PROSPECTION_MKT!$C$29,"") -> 0 | D30: =IFERROR([1]SYNC_PROSPECTION_MKT!$D$29,"") -> 0 | E30: =IFERROR([1]SYNC_PROSPECTION_MKT!$E$29,"") -> 0 | F30: =IFERROR([1]SYNC_PROSPECTION_MKT!$G$29,"") -> 0 | G30: =IFERROR([1]SYNC_PROSPECTION_MKT!$H$29,"") -> 0 | H30: =IFERROR([1]SYNC_PROSPECTION_MKT!$J$29,"") -> 0 | I30: =IFERROR([1]SYNC_PROSPECTION_MKT!$I$29,"") -> 0 | J30: =IFERROR([1]SYNC_PROSPECTION_MKT!$K$29,"") -> 0 | K30: =IFERROR(SYNC_FINANCE!$I$29,"") -> 0 | L30: =IFERROR([2]SYNC_COMMERCIAL_VENTE!$S$29,"") -> 0 | M30: 0 | N30: 0 | O30: 0 | P30: 0 | Q30: 0 | R30: 0 | S30: 0 | T30: 0 | U30: 0 | V30: 0 | W30: 0 | X30: 0 | Y30: 0 | Z30: =IFERROR(SUM(N30:Y30),0) -> 0 | AA30: =IFERROR((N30+Q30+T30+W30)-M30,0) -> 0 | AB30: =IFERROR(Z30,0) -> 0 | AC30: =IFERROR(L30-AB30,0) -> 0
A31: 26 | B31: =IFERROR([1]SYNC_PROSPECTION_MKT!$B$30,"") -> 0 | C31: =IFERROR([1]SYNC_PROSPECTION_MKT!$C$30,"") -> 0 | D31: =IFERROR([1]SYNC_PROSPECTION_MKT!$D$30,"") -> 0 | E31: =IFERROR([1]SYNC_PROSPECTION_MKT!$E$30,"") -> 0 | F31: =IFERROR([1]SYNC_PROSPECTION_MKT!$G$30,"") -> 0 | G31: =IFERROR([1]SYNC_PROSPECTION_MKT!$H$30,"") -> 0 | H31: =IFERROR([1]SYNC_PROSPECTION_MKT!$J$30,"") -> 0 | I31: =IFERROR([1]SYNC_PROSPECTION_MKT!$I$30,"") -> 0 | J31: =IFERROR([1]SYNC_PROSPECTION_MKT!$K$30,"") -> 0 | K31: =IFERROR(SYNC_FINANCE!$I$30,"") -> 0 | L31: =IFERROR([2]SYNC_COMMERCIAL_VENTE!$S$30,"") -> 0 | M31: 0 | N31: 0 | O31: 0 | P31: 0 | Q31: 0 | R31: 0 | S31: 0 | T31: 0 | U31: 0 | V31: 0 | W31: 0 | X31: 0 | Y31: 0 | Z31: =IFERROR(SUM(N31:Y31),0) -> 0 | AA31: =IFERROR((N31+Q31+T31+W31)-M31,0) -> 0 | AB31: =IFERROR(Z31,0) -> 0 | AC31: =IFERROR(L31-AB31,0) -> 0
A32: 27 | B32: =IFERROR([1]SYNC_PROSPECTION_MKT!$B$31,"") -> 0 | C32: =IFERROR([1]SYNC_PROSPECTION_MKT!$C$31,"") -> 0 | D32: =IFERROR([1]SYNC_PROSPECTION_MKT!$D$31,"") -> 0 | E32: =IFERROR([1]SYNC_PROSPECTION_MKT!$E$31,"") -> 0 | F32: =IFERROR([1]SYNC_PROSPECTION_MKT!$G$31,"") -> 0 | G32: =IFERROR([1]SYNC_PROSPECTION_MKT!$H$31,"") -> 0 | H32: =IFERROR([1]SYNC_PROSPECTION_MKT!$J$31,"") -> 0 | I32: =IFERROR([1]SYNC_PROSPECTION_MKT!$I$31,"") -> 0 | J32: =IFERROR([1]SYNC_PROSPECTION_MKT!$K$31,"") -> 0 | K32: =IFERROR(SYNC_FINANCE!$I$31,"") -> 0 | L32: =IFERROR([2]SYNC_COMMERCIAL_VENTE!$S$31,"") -> 0 | M32: 0 | N32: 0 | O32: 0 | P32: 0 | Q32: 0 | R32: 0 | S32: 0 | T32: 0 | U32: 0 | V32: 0 | W32: 0 | X32: 0 | Y32: 0 | Z32: =IFERROR(SUM(N32:Y32),0) -> 0 | AA32: =IFERROR((N32+Q32+T32+W32)-M32,0) -> 0 | AB32: =IFERROR(Z32,0) -> 0 | AC32: =IFERROR(L32-AB32,0) -> 0
A33: 28 | B33: =IFERROR([1]SYNC_PROSPECTION_MKT!$B$32,"") -> 0 | C33: =IFERROR([1]SYNC_PROSPECTION_MKT!$C$32,"") -> 0 | D33: =IFERROR([1]SYNC_PROSPECTION_MKT!$D$32,"") -> 0 | E33: =IFERROR([1]SYNC_PROSPECTION_MKT!$E$32,"") -> 0 | F33: =IFERROR([1]SYNC_PROSPECTION_MKT!$G$32,"") -> 0 | G33: =IFERROR([1]SYNC_PROSPECTION_MKT!$H$32,"") -> 0 | H33: =IFERROR([1]SYNC_PROSPECTION_MKT!$J$32,"") -> 0 | I33: =IFERROR([1]SYNC_PROSPECTION_MKT!$I$32,"") -> 0 | J33: =IFERROR([1]SYNC_PROSPECTION_MKT!$K$32,"") -> 0 | K33: =IFERROR(SYNC_FINANCE!$I$32,"") -> 0 | L33: =IFERROR([2]SYNC_COMMERCIAL_VENTE!$S$32,"") -> 0 | M33: 0 | N33: 0 | O33: 0 | P33: 0 | Q33: 0 | R33: 0 | S33: 0 | T33: 0 | U33: 0 | V33: 0 | W33: 0 | X33: 0 | Y33: 0 | Z33: =IFERROR(SUM(N33:Y33),0) -> 0 | AA33: =IFERROR((N33+Q33+T33+W33)-M33,0) -> 0 | AB33: =IFERROR(Z33,0) -> 0 | AC33: =IFERROR(L33-AB33,0) -> 0
A34: 29 | B34: =IFERROR([1]SYNC_PROSPECTION_MKT!$B$33,"") -> 0 | C34: =IFERROR([1]SYNC_PROSPECTION_MKT!$C$33,"") -> 0 | D34: =IFERROR([1]SYNC_PROSPECTION_MKT!$D$33,"") -> 0 | E34: =IFERROR([1]SYNC_PROSPECTION_MKT!$E$33,"") -> 0 | F34: =IFERROR([1]SYNC_PROSPECTION_MKT!$G$33,"") -> 0 | G34: =IFERROR([1]SYNC_PROSPECTION_MKT!$H$33,"") -> 0 | H34: =IFERROR([1]SYNC_PROSPECTION_MKT!$J$33,"") -> 0 | I34: =IFERROR([1]SYNC_PROSPECTION_MKT!$I$33,"") -> 0 | J34: =IFERROR([1]SYNC_PROSPECTION_MKT!$K$33,"") -> 0 | K34: =IFERROR(SYNC_FINANCE!$I$33,"") -> 0 | L34: =IFERROR([2]SYNC_COMMERCIAL_VENTE!$S$33,"") -> 0 | M34: 0 | N34: 0 | O34: 0 | P34: 0 | Q34: 0 | R34: 0 | S34: 0 | T34: 0 | U34: 0 | V34: 0 | W34: 0 | X34: 0 | Y34: 0 | Z34: =IFERROR(SUM(N34:Y34),0) -> 0 | AA34: =IFERROR((N34+Q34+T34+W34)-M34,0) -> 0 | AB34: =IFERROR(Z34,0) -> 0 | AC34: =IFERROR(L34-AB34,0) -> 0
A35: 30 | B35: =IFERROR([1]SYNC_PROSPECTION_MKT!$B$34,"") -> 0 | C35: =IFERROR([1]SYNC_PROSPECTION_MKT!$C$34,"") -> 0 | D35: =IFERROR([1]SYNC_PROSPECTION_MKT!$D$34,"") -> 0 | E35: =IFERROR([1]SYNC_PROSPECTION_MKT!$E$34,"") -> 0 | F35: =IFERROR([1]SYNC_PROSPECTION_MKT!$G$34,"") -> 0 | G35: =IFERROR([1]SYNC_PROSPECTION_MKT!$H$34,"") -> 0 | H35: =IFERROR([1]SYNC_PROSPECTION_MKT!$J$34,"") -> 0 | I35: =IFERROR([1]SYNC_PROSPECTION_MKT!$I$34,"") -> 0 | J35: =IFERROR([1]SYNC_PROSPECTION_MKT!$K$34,"") -> 0 | K35: =IFERROR(SYNC_FINANCE!$I$34,"") -> 0 | L35: =IFERROR([2]SYNC_COMMERCIAL_VENTE!$S$34,"") -> 0 | M35: 0 | N35: 0 | O35: 0 | P35: 0 | Q35: 0 | R35: 0 | S35: 0 | T35: 0 | U35: 0 | V35: 0 | W35: 0 | X35: 0 | Y35: 0 | Z35: =IFERROR(SUM(N35:Y35),0) -> 0 | AA35: =IFERROR((N35+Q35+T35+W35)-M35,0) -> 0 | AB35: =IFERROR(Z35,0) -> 0 | AC35: =IFERROR(L35-AB35,0) -> 0
A36: 31 | B36: =IFERROR([1]SYNC_PROSPECTION_MKT!$B$35,"") -> 0 | C36: =IFERROR([1]SYNC_PROSPECTION_MKT!$C$35,"") -> 0 | D36: =IFERROR([1]SYNC_PROSPECTION_MKT!$D$35,"") -> 0 | E36: =IFERROR([1]SYNC_PROSPECTION_MKT!$E$35,"") -> 0 | F36: =IFERROR([1]SYNC_PROSPECTION_MKT!$G$35,"") -> 0 | G36: =IFERROR([1]SYNC_PROSPECTION_MKT!$H$35,"") -> 0 | H36: =IFERROR([1]SYNC_PROSPECTION_MKT!$J$35,"") -> 0 | I36: =IFERROR([1]SYNC_PROSPECTION_MKT!$I$35,"") -> 0 | J36: =IFERROR([1]SYNC_PROSPECTION_MKT!$K$35,"") -> 0 | K36: =IFERROR(SYNC_FINANCE!$I$35,"") -> 0 | L36: =IFERROR([2]SYNC_COMMERCIAL_VENTE!$S$35,"") -> 0 | M36: 0 | N36: 0 | O36: 0 | P36: 0 | Q36: 0 | R36: 0 | S36: 0 | T36: 0 | U36: 0 | V36: 0 | W36: 0 | X36: 0 | Y36: 0 | Z36: =IFERROR(SUM(N36:Y36),0) -> 0 | AA36: =IFERROR((N36+Q36+T36+W36)-M36,0) -> 0 | AB36: =IFERROR(Z36,0) -> 0 | AC36: =IFERROR(L36-AB36,0) -> 0
A37: 32 | B37: =IFERROR([1]SYNC_PROSPECTION_MKT!$B$36,"") -> 0 | C37: =IFERROR([1]SYNC_PROSPECTION_MKT!$C$36,"") -> 0 | D37: =IFERROR([1]SYNC_PROSPECTION_MKT!$D$36,"") -> 0 | E37: =IFERROR([1]SYNC_PROSPECTION_MKT!$E$36,"") -> 0 | F37: =IFERROR([1]SYNC_PROSPECTION_MKT!$G$36,"") -> 0 | G37: =IFERROR([1]SYNC_PROSPECTION_MKT!$H$36,"") -> 0 | H37: =IFERROR([1]SYNC_PROSPECTION_MKT!$J$36,"") -> 0 | I37: =IFERROR([1]SYNC_PROSPECTION_MKT!$I$36,"") -> 0 | J37: =IFERROR([1]SYNC_PROSPECTION_MKT!$K$36,"") -> 0 | K37: =IFERROR(SYNC_FINANCE!$I$36,"") -> 0 | L37: =IFERROR([2]SYNC_COMMERCIAL_VENTE!$S$36,"") -> 0 | M37: 0 | N37: 0 | O37: 0 | P37: 0 | Q37: 0 | R37: 0 | S37: 0 | T37: 0 | U37: 0 | V37: 0 | W37: 0 | X37: 0 | Y37: 0 | Z37: =IFERROR(SUM(N37:Y37),0) -> 0 | AA37: =IFERROR((N37+Q37+T37+W37)-M37,0) -> 0 | AB37: =IFERROR(Z37,0) -> 0 | AC37: =IFERROR(L37-AB37,0) -> 0
A38: 33 | B38: =IFERROR([1]SYNC_PROSPECTION_MKT!$B$37,"") -> 0 | C38: =IFERROR([1]SYNC_PROSPECTION_MKT!$C$37,"") -> 0 | D38: =IFERROR([1]SYNC_PROSPECTION_MKT!$D$37,"") -> 0 | E38: =IFERROR([1]SYNC_PROSPECTION_MKT!$E$37,"") -> 0 | F38: =IFERROR([1]SYNC_PROSPECTION_MKT!$G$37,"") -> 0 | G38: =IFERROR([1]SYNC_PROSPECTION_MKT!$H$37,"") -> 0 | H38: =IFERROR([1]SYNC_PROSPECTION_MKT!$J$37,"") -> 0 | I38: =IFERROR([1]SYNC_PROSPECTION_MKT!$I$37,"") -> 0 | J38: =IFERROR([1]SYNC_PROSPECTION_MKT!$K$37,"") -> 0 | K38: =IFERROR(SYNC_FINANCE!$I$37,"") -> 0 | L38: =IFERROR([2]SYNC_COMMERCIAL_VENTE!$S$37,"") -> 0 | M38: 0 | N38: 0 | O38: 0 | P38: 0 | Q38: 0 | R38: 0 | S38: 0 | T38: 0 | U38: 0 | V38: 0 | W38: 0 | X38: 0 | Y38: 0 | Z38: =IFERROR(SUM(N38:Y38),0) -> 0 | AA38: =IFERROR((N38+Q38+T38+W38)-M38,0) -> 0 | AB38: =IFERROR(Z38,0) -> 0 | AC38: =IFERROR(L38-AB38,0) -> 0
A39: 34 | B39: =IFERROR([1]SYNC_PROSPECTION_MKT!$B$38,"") -> 0 | C39: =IFERROR([1]SYNC_PROSPECTION_MKT!$C$38,"") -> 0 | D39: =IFERROR([1]SYNC_PROSPECTION_MKT!$D$38,"") -> 0 | E39: =IFERROR([1]SYNC_PROSPECTION_MKT!$E$38,"") -> 0 | F39: =IFERROR([1]SYNC_PROSPECTION_MKT!$G$38,"") -> 0 | G39: =IFERROR([1]SYNC_PROSPECTION_MKT!$H$38,"") -> 0 | H39: =IFERROR([1]SYNC_PROSPECTION_MKT!$J$38,"") -> 0 | I39: =IFERROR([1]SYNC_PROSPECTION_MKT!$I$38,"") -> 0 | J39: =IFERROR([1]SYNC_PROSPECTION_MKT!$K$38,"") -> 0 | K39: =IFERROR(SYNC_FINANCE!$I$38,"") -> 0 | L39: =IFERROR([2]SYNC_COMMERCIAL_VENTE!$S$38,"") -> 0 | M39: 0 | N39: 0 | O39: 0 | P39: 0 | Q39: 0 | R39: 0 | S39: 0 | T39: 0 | U39: 0 | V39: 0 | W39: 0 | X39: 0 | Y39: 0 | Z39: =IFERROR(SUM(N39:Y39),0) -> 0 | AA39: =IFERROR((N39+Q39+T39+W39)-M39,0) -> 0 | AB39: =IFERROR(Z39,0) -> 0 | AC39: =IFERROR(L39-AB39,0) -> 0
A40: 35 | B40: =IFERROR([1]SYNC_PROSPECTION_MKT!$B$39,"") -> 0 | C40: =IFERROR([1]SYNC_PROSPECTION_MKT!$C$39,"") -> 0 | D40: =IFERROR([1]SYNC_PROSPECTION_MKT!$D$39,"") -> 0 | E40: =IFERROR([1]SYNC_PROSPECTION_MKT!$E$39,"") -> 0 | F40: =IFERROR([1]SYNC_PROSPECTION_MKT!$G$39,"") -> 0 | G40: =IFERROR([1]SYNC_PROSPECTION_MKT!$H$39,"") -> 0 | H40: =IFERROR([1]SYNC_PROSPECTION_MKT!$J$39,"") -> 0 | I40: =IFERROR([1]SYNC_PROSPECTION_MKT!$I$39,"") -> 0 | J40: =IFERROR([1]SYNC_PROSPECTION_MKT!$K$39,"") -> 0 | K40: =IFERROR(SYNC_FINANCE!$I$39,"") -> 0 | L40: =IFERROR([2]SYNC_COMMERCIAL_VENTE!$S$39,"") -> 0 | M40: 0 | N40: 0 | O40: 0 | P40: 0 | Q40: 0 | R40: 0 | S40: 0 | T40: 0 | U40: 0 | V40: 0 | W40: 0 | X40: 0 | Y40: 0 | Z40: =IFERROR(SUM(N40:Y40),0) -> 0 | AA40: =IFERROR((N40+Q40+T40+W40)-M40,0) -> 0 | AB40: =IFERROR(Z40,0) -> 0 | AC40: =IFERROR(L40-AB40,0) -> 0
A41: 36 | B41: =IFERROR([1]SYNC_PROSPECTION_MKT!$B$40,"") -> 0 | C41: =IFERROR([1]SYNC_PROSPECTION_MKT!$C$40,"") -> 0 | D41: =IFERROR([1]SYNC_PROSPECTION_MKT!$D$40,"") -> 0 | E41: =IFERROR([1]SYNC_PROSPECTION_MKT!$E$40,"") -> 0 | F41: =IFERROR([1]SYNC_PROSPECTION_MKT!$G$40,"") -> 0 | G41: =IFERROR([1]SYNC_PROSPECTION_MKT!$H$40,"") -> 0 | H41: =IFERROR([1]SYNC_PROSPECTION_MKT!$J$40,"") -> 0 | I41: =IFERROR([1]SYNC_PROSPECTION_MKT!$I$40,"") -> 0 | J41: =IFERROR([1]SYNC_PROSPECTION_MKT!$K$40,"") -> 0 | K41: =IFERROR(SYNC_FINANCE!$I$40,"") -> 0 | L41: =IFERROR([2]SYNC_COMMERCIAL_VENTE!$S$40,"") -> 0 | M41: 0 | N41: 0 | O41: 0 | P41: 0 | Q41: 0 | R41: 0 | S41: 0 | T41: 0 | U41: 0 | V41: 0 | W41: 0 | X41: 0 | Y41: 0 | Z41: =IFERROR(SUM(N41:Y41),0) -> 0 | AA41: =IFERROR((N41+Q41+T41+W41)-M41,0) -> 0 | AB41: =IFERROR(Z41,0) -> 0 | AC41: =IFERROR(L41-AB41,0) -> 0
A42: 37 | B42: =IFERROR([1]SYNC_PROSPECTION_MKT!$B$41,"") -> 0 | C42: =IFERROR([1]SYNC_PROSPECTION_MKT!$C$41,"") -> 0 | D42: =IFERROR([1]SYNC_PROSPECTION_MKT!$D$41,"") -> 0 | E42: =IFERROR([1]SYNC_PROSPECTION_MKT!$E$41,"") -> 0 | F42: =IFERROR([1]SYNC_PROSPECTION_MKT!$G$41,"") -> 0 | G42: =IFERROR([1]SYNC_PROSPECTION_MKT!$H$41,"") -> 0 | H42: =IFERROR([1]SYNC_PROSPECTION_MKT!$J$41,"") -> 0 | I42: =IFERROR([1]SYNC_PROSPECTION_MKT!$I$41,"") -> 0 | J42: =IFERROR([1]SYNC_PROSPECTION_MKT!$K$41,"") -> 0 | K42: =IFERROR(SYNC_FINANCE!$I$41,"") -> 0 | L42: =IFERROR([2]SYNC_COMMERCIAL_VENTE!$S$41,"") -> 0 | M42: 0 | N42: 0 | O42: 0 | P42: 0 | Q42: 0 | R42: 0 | S42: 0 | T42: 0 | U42: 0 | V42: 0 | W42: 0 | X42: 0 | Y42: 0 | Z42: =IFERROR(SUM(N42:Y42),0) -> 0 | AA42: =IFERROR((N42+Q42+T42+W42)-M42,0) -> 0 | AB42: =IFERROR(Z42,0) -> 0 | AC42: =IFERROR(L42-AB42,0) -> 0
A43: 38 | B43: =IFERROR([1]SYNC_PROSPECTION_MKT!$B$42,"") -> 0 | C43: =IFERROR([1]SYNC_PROSPECTION_MKT!$C$42,"") -> 0 | D43: =IFERROR([1]SYNC_PROSPECTION_MKT!$D$42,"") -> 0 | E43: =IFERROR([1]SYNC_PROSPECTION_MKT!$E$42,"") -> 0 | F43: =IFERROR([1]SYNC_PROSPECTION_MKT!$G$42,"") -> 0 | G43: =IFERROR([1]SYNC_PROSPECTION_MKT!$H$42,"") -> 0 | H43: =IFERROR([1]SYNC_PROSPECTION_MKT!$J$42,"") -> 0 | I43: =IFERROR([1]SYNC_PROSPECTION_MKT!$I$42,"") -> 0 | J43: =IFERROR([1]SYNC_PROSPECTION_MKT!$K$42,"") -> 0 | K43: =IFERROR(SYNC_FINANCE!$I$42,"") -> 0 | L43: =IFERROR([2]SYNC_COMMERCIAL_VENTE!$S$42,"") -> 0 | M43: 0 | N43: 0 | O43: 0 | P43: 0 | Q43: 0 | R43: 0 | S43: 0 | T43: 0 | U43: 0 | V43: 0 | W43: 0 | X43: 0 | Y43: 0 | Z43: =IFERROR(SUM(N43:Y43),0) -> 0 | AA43: =IFERROR((N43+Q43+T43+W43)-M43,0) -> 0 | AB43: =IFERROR(Z43,0) -> 0 | AC43: =IFERROR(L43-AB43,0) -> 0
A44: 39 | B44: =IFERROR([1]SYNC_PROSPECTION_MKT!$B$43,"") -> 0 | C44: =IFERROR([1]SYNC_PROSPECTION_MKT!$C$43,"") -> 0 | D44: =IFERROR([1]SYNC_PROSPECTION_MKT!$D$43,"") -> 0 | E44: =IFERROR([1]SYNC_PROSPECTION_MKT!$E$43,"") -> 0 | F44: =IFERROR([1]SYNC_PROSPECTION_MKT!$G$43,"") -> 0 | G44: =IFERROR([1]SYNC_PROSPECTION_MKT!$H$43,"") -> 0 | H44: =IFERROR([1]SYNC_PROSPECTION_MKT!$J$43,"") -> 0 | I44: =IFERROR([1]SYNC_PROSPECTION_MKT!$I$43,"") -> 0 | J44: =IFERROR([1]SYNC_PROSPECTION_MKT!$K$43,"") -> 0 | K44: =IFERROR(SYNC_FINANCE!$I$43,"") -> 0 | L44: =IFERROR([2]SYNC_COMMERCIAL_VENTE!$S$43,"") -> 0 | M44: 0 | N44: 0 | O44: 0 | P44: 0 | Q44: 0 | R44: 0 | S44: 0 | T44: 0 | U44: 0 | V44: 0 | W44: 0 | X44: 0 | Y44: 0 | Z44: =IFERROR(SUM(N44:Y44),0) -> 0 | AA44: =IFERROR((N44+Q44+T44+W44)-M44,0) -> 0 | AB44: =IFERROR(Z44,0) -> 0 | AC44: =IFERROR(L44-AB44,0) -> 0
A45: 40 | B45: =IFERROR([1]SYNC_PROSPECTION_MKT!$B$44,"") -> 0 | C45: =IFERROR([1]SYNC_PROSPECTION_MKT!$C$44,"") -> 0 | D45: =IFERROR([1]SYNC_PROSPECTION_MKT!$D$44,"") -> 0 | E45: =IFERROR([1]SYNC_PROSPECTION_MKT!$E$44,"") -> 0 | F45: =IFERROR([1]SYNC_PROSPECTION_MKT!$G$44,"") -> 0 | G45: =IFERROR([1]SYNC_PROSPECTION_MKT!$H$44,"") -> 0 | H45: =IFERROR([1]SYNC_PROSPECTION_MKT!$J$44,"") -> 0 | I45: =IFERROR([1]SYNC_PROSPECTION_MKT!$I$44,"") -> 0 | J45: =IFERROR([1]SYNC_PROSPECTION_MKT!$K$44,"") -> 0 | K45: =IFERROR(SYNC_FINANCE!$I$44,"") -> 0 | L45: =IFERROR([2]SYNC_COMMERCIAL_VENTE!$S$44,"") -> 0 | M45: 0 | N45: 0 | O45: 0 | P45: 0 | Q45: 0 | R45: 0 | S45: 0 | T45: 0 | U45: 0 | V45: 0 | W45: 0 | X45: 0 | Y45: 0 | Z45: =IFERROR(SUM(N45:Y45),0) -> 0 | AA45: =IFERROR((N45+Q45+T45+W45)-M45,0) -> 0 | AB45: =IFERROR(Z45,0) -> 0 | AC45: =IFERROR(L45-AB45,0) -> 0
A46: 41 | B46: =IFERROR([1]SYNC_PROSPECTION_MKT!$B$45,"") -> 0 | C46: =IFERROR([1]SYNC_PROSPECTION_MKT!$C$45,"") -> 0 | D46: =IFERROR([1]SYNC_PROSPECTION_MKT!$D$45,"") -> 0 | E46: =IFERROR([1]SYNC_PROSPECTION_MKT!$E$45,"") -> 0 | F46: =IFERROR([1]SYNC_PROSPECTION_MKT!$G$45,"") -> 0 | G46: =IFERROR([1]SYNC_PROSPECTION_MKT!$H$45,"") -> 0 | H46: =IFERROR([1]SYNC_PROSPECTION_MKT!$J$45,"") -> 0 | I46: =IFERROR([1]SYNC_PROSPECTION_MKT!$I$45,"") -> 0 | J46: =IFERROR([1]SYNC_PROSPECTION_MKT!$K$45,"") -> 0 | K46: =IFERROR(SYNC_FINANCE!$I$45,"") -> 0 | L46: =IFERROR([2]SYNC_COMMERCIAL_VENTE!$S$45,"") -> 0 | M46: 0 | N46: 0 | O46: 0 | P46: 0 | Q46: 0 | R46: 0 | S46: 0 | T46: 0 | U46: 0 | V46: 0 | W46: 0 | X46: 0 | Y46: 0 | Z46: =IFERROR(SUM(N46:Y46),0) -> 0 | AA46: =IFERROR((N46+Q46+T46+W46)-M46,0) -> 0 | AB46: =IFERROR(Z46,0) -> 0 | AC46: =IFERROR(L46-AB46,0) -> 0
A47: 42 | B47: =IFERROR([1]SYNC_PROSPECTION_MKT!$B$46,"") -> 0 | C47: =IFERROR([1]SYNC_PROSPECTION_MKT!$C$46,"") -> 0 | D47: =IFERROR([1]SYNC_PROSPECTION_MKT!$D$46,"") -> 0 | E47: =IFERROR([1]SYNC_PROSPECTION_MKT!$E$46,"") -> 0 | F47: =IFERROR([1]SYNC_PROSPECTION_MKT!$G$46,"") -> 0 | G47: =IFERROR([1]SYNC_PROSPECTION_MKT!$H$46,"") -> 0 | H47: =IFERROR([1]SYNC_PROSPECTION_MKT!$J$46,"") -> 0 | I47: =IFERROR([1]SYNC_PROSPECTION_MKT!$I$46,"") -> 0 | J47: =IFERROR([1]SYNC_PROSPECTION_MKT!$K$46,"") -> 0 | K47: =IFERROR(SYNC_FINANCE!$I$46,"") -> 0 | L47: =IFERROR([2]SYNC_COMMERCIAL_VENTE!$S$46,"") -> 0 | M47: 0 | N47: 0 | O47: 0 | P47: 0 | Q47: 0 | R47: 0 | S47: 0 | T47: 0 | U47: 0 | V47: 0 | W47: 0 | X47: 0 | Y47: 0 | Z47: =IFERROR(SUM(N47:Y47),0) -> 0 | AA47: =IFERROR((N47+Q47+T47+W47)-M47,0) -> 0 | AB47: =IFERROR(Z47,0) -> 0 | AC47: =IFERROR(L47-AB47,0) -> 0
A48: 43 | B48: =IFERROR([1]SYNC_PROSPECTION_MKT!$B$47,"") -> 0 | C48: =IFERROR([1]SYNC_PROSPECTION_MKT!$C$47,"") -> 0 | D48: =IFERROR([1]SYNC_PROSPECTION_MKT!$D$47,"") -> 0 | E48: =IFERROR([1]SYNC_PROSPECTION_MKT!$E$47,"") -> 0 | F48: =IFERROR([1]SYNC_PROSPECTION_MKT!$G$47,"") -> 0 | G48: =IFERROR([1]SYNC_PROSPECTION_MKT!$H$47,"") -> 0 | H48: =IFERROR([1]SYNC_PROSPECTION_MKT!$J$47,"") -> 0 | I48: =IFERROR([1]SYNC_PROSPECTION_MKT!$I$47,"") -> 0 | J48: =IFERROR([1]SYNC_PROSPECTION_MKT!$K$47,"") -> 0 | K48: =IFERROR(SYNC_FINANCE!$I$47,"") -> 0 | L48: =IFERROR([2]SYNC_COMMERCIAL_VENTE!$S$47,"") -> 0 | M48: 0 | N48: 0 | O48: 0 | P48: 0 | Q48: 0 | R48: 0 | S48: 0 | T48: 0 | U48: 0 | V48: 0 | W48: 0 | X48: 0 | Y48: 0 | Z48: =IFERROR(SUM(N48:Y48),0) -> 0 | AA48: =IFERROR((N48+Q48+T48+W48)-M48,0) -> 0 | AB48: =IFERROR(Z48,0) -> 0 | AC48: =IFERROR(L48-AB48,0) -> 0
A49: 44 | B49: =IFERROR([1]SYNC_PROSPECTION_MKT!$B$48,"") -> 0 | C49: =IFERROR([1]SYNC_PROSPECTION_MKT!$C$48,"") -> 0 | D49: =IFERROR([1]SYNC_PROSPECTION_MKT!$D$48,"") -> 0 | E49: =IFERROR([1]SYNC_PROSPECTION_MKT!$E$48,"") -> 0 | F49: =IFERROR([1]SYNC_PROSPECTION_MKT!$G$48,"") -> 0 | G49: =IFERROR([1]SYNC_PROSPECTION_MKT!$H$48,"") -> 0 | H49: =IFERROR([1]SYNC_PROSPECTION_MKT!$J$48,"") -> 0 | I49: =IFERROR([1]SYNC_PROSPECTION_MKT!$I$48,"") -> 0 | J49: =IFERROR([1]SYNC_PROSPECTION_MKT!$K$48,"") -> 0 | K49: =IFERROR(SYNC_FINANCE!$I$48,"") -> 0 | L49: =IFERROR([2]SYNC_COMMERCIAL_VENTE!$S$48,"") -> 0 | M49: 0 | N49: 0 | O49: 0 | P49: 0 | Q49: 0 | R49: 0 | S49: 0 | T49: 0 | U49: 0 | V49: 0 | W49: 0 | X49: 0 | Y49: 0 | Z49: =IFERROR(SUM(N49:Y49),0) -> 0 | AA49: =IFERROR((N49+Q49+T49+W49)-M49,0) -> 0 | AB49: =IFERROR(Z49,0) -> 0 | AC49: =IFERROR(L49-AB49,0) -> 0
A50: 45 | B50: =IFERROR([1]SYNC_PROSPECTION_MKT!$B$49,"") -> 0 | C50: =IFERROR([1]SYNC_PROSPECTION_MKT!$C$49,"") -> 0 | D50: =IFERROR([1]SYNC_PROSPECTION_MKT!$D$49,"") -> 0 | E50: =IFERROR([1]SYNC_PROSPECTION_MKT!$E$49,"") -> 0 | F50: =IFERROR([1]SYNC_PROSPECTION_MKT!$G$49,"") -> 0 | G50: =IFERROR([1]SYNC_PROSPECTION_MKT!$H$49,"") -> 0 | H50: =IFERROR([1]SYNC_PROSPECTION_MKT!$J$49,"") -> 0 | I50: =IFERROR([1]SYNC_PROSPECTION_MKT!$I$49,"") -> 0 | J50: =IFERROR([1]SYNC_PROSPECTION_MKT!$K$49,"") -> 0 | K50: =IFERROR(SYNC_FINANCE!$I$49,"") -> 0 | L50: =IFERROR([2]SYNC_COMMERCIAL_VENTE!$S$49,"") -> 0 | M50: 0 | N50: 0 | O50: 0 | P50: 0 | Q50: 0 | R50: 0 | S50: 0 | T50: 0 | U50: 0 | V50: 0 | W50: 0 | X50: 0 | Y50: 0 | Z50: =IFERROR(SUM(N50:Y50),0) -> 0 | AA50: =IFERROR((N50+Q50+T50+W50)-M50,0) -> 0 | AB50: =IFERROR(Z50,0) -> 0 | AC50: =IFERROR(L50-AB50,0) -> 0
A51: 46 | B51: =IFERROR([1]SYNC_PROSPECTION_MKT!$B$50,"") -> 0 | C51: =IFERROR([1]SYNC_PROSPECTION_MKT!$C$50,"") -> 0 | D51: =IFERROR([1]SYNC_PROSPECTION_MKT!$D$50,"") -> 0 | E51: =IFERROR([1]SYNC_PROSPECTION_MKT!$E$50,"") -> 0 | F51: =IFERROR([1]SYNC_PROSPECTION_MKT!$G$50,"") -> 0 | G51: =IFERROR([1]SYNC_PROSPECTION_MKT!$H$50,"") -> 0 | H51: =IFERROR([1]SYNC_PROSPECTION_MKT!$J$50,"") -> 0 | I51: =IFERROR([1]SYNC_PROSPECTION_MKT!$I$50,"") -> 0 | J51: =IFERROR([1]SYNC_PROSPECTION_MKT!$K$50,"") -> 0 | K51: =IFERROR(SYNC_FINANCE!$I$50,"") -> 0 | L51: =IFERROR([2]SYNC_COMMERCIAL_VENTE!$S$50,"") -> 0 | M51: 0 | N51: 0 | O51: 0 | P51: 0 | Q51: 0 | R51: 0 | S51: 0 | T51: 0 | U51: 0 | V51: 0 | W51: 0 | X51: 0 | Y51: 0 | Z51: =IFERROR(SUM(N51:Y51),0) -> 0 | AA51: =IFERROR((N51+Q51+T51+W51)-M51,0) -> 0 | AB51: =IFERROR(Z51,0) -> 0 | AC51: =IFERROR(L51-AB51,0) -> 0
A52: 47 | B52: =IFERROR([1]SYNC_PROSPECTION_MKT!$B$51,"") -> 0 | C52: =IFERROR([1]SYNC_PROSPECTION_MKT!$C$51,"") -> 0 | D52: =IFERROR([1]SYNC_PROSPECTION_MKT!$D$51,"") -> 0 | E52: =IFERROR([1]SYNC_PROSPECTION_MKT!$E$51,"") -> 0 | F52: =IFERROR([1]SYNC_PROSPECTION_MKT!$G$51,"") -> 0 | G52: =IFERROR([1]SYNC_PROSPECTION_MKT!$H$51,"") -> 0 | H52: =IFERROR([1]SYNC_PROSPECTION_MKT!$J$51,"") -> 0 | I52: =IFERROR([1]SYNC_PROSPECTION_MKT!$I$51,"") -> 0 | J52: =IFERROR([1]SYNC_PROSPECTION_MKT!$K$51,"") -> 0 | K52: =IFERROR(SYNC_FINANCE!$I$51,"") -> 0 | L52: =IFERROR([2]SYNC_COMMERCIAL_VENTE!$S$51,"") -> 0 | M52: 0 | N52: 0 | O52: 0 | P52: 0 | Q52: 0 | R52: 0 | S52: 0 | T52: 0 | U52: 0 | V52: 0 | W52: 0 | X52: 0 | Y52: 0 | Z52: =IFERROR(SUM(N52:Y52),0) -> 0 | AA52: =IFERROR((N52+Q52+T52+W52)-M52,0) -> 0 | AB52: =IFERROR(Z52,0) -> 0 | AC52: =IFERROR(L52-AB52,0) -> 0
A53: 48 | B53: =IFERROR([1]SYNC_PROSPECTION_MKT!$B$52,"") -> 0 | C53: =IFERROR([1]SYNC_PROSPECTION_MKT!$C$52,"") -> 0 | D53: =IFERROR([1]SYNC_PROSPECTION_MKT!$D$52,"") -> 0 | E53: =IFERROR([1]SYNC_PROSPECTION_MKT!$E$52,"") -> 0 | F53: =IFERROR([1]SYNC_PROSPECTION_MKT!$G$52,"") -> 0 | G53: =IFERROR([1]SYNC_PROSPECTION_MKT!$H$52,"") -> 0 | H53: =IFERROR([1]SYNC_PROSPECTION_MKT!$J$52,"") -> 0 | I53: =IFERROR([1]SYNC_PROSPECTION_MKT!$I$52,"") -> 0 | J53: =IFERROR([1]SYNC_PROSPECTION_MKT!$K$52,"") -> 0 | K53: =IFERROR(SYNC_FINANCE!$I$52,"") -> 0 | L53: =IFERROR([2]SYNC_COMMERCIAL_VENTE!$S$52,"") -> 0 | M53: 0 | N53: 0 | O53: 0 | P53: 0 | Q53: 0 | R53: 0 | S53: 0 | T53: 0 | U53: 0 | V53: 0 | W53: 0 | X53: 0 | Y53: 0 | Z53: =IFERROR(SUM(N53:Y53),0) -> 0 | AA53: =IFERROR((N53+Q53+T53+W53)-M53,0) -> 0 | AB53: =IFERROR(Z53,0) -> 0 | AC53: =IFERROR(L53-AB53,0) -> 0
A54: 49 | B54: =IFERROR([1]SYNC_PROSPECTION_MKT!$B$53,"") -> 0 | C54: =IFERROR([1]SYNC_PROSPECTION_MKT!$C$53,"") -> 0 | D54: =IFERROR([1]SYNC_PROSPECTION_MKT!$D$53,"") -> 0 | E54: =IFERROR([1]SYNC_PROSPECTION_MKT!$E$53,"") -> 0 | F54: =IFERROR([1]SYNC_PROSPECTION_MKT!$G$53,"") -> 0 | G54: =IFERROR([1]SYNC_PROSPECTION_MKT!$H$53,"") -> 0 | H54: =IFERROR([1]SYNC_PROSPECTION_MKT!$J$53,"") -> 0 | I54: =IFERROR([1]SYNC_PROSPECTION_MKT!$I$53,"") -> 0 | J54: =IFERROR([1]SYNC_PROSPECTION_MKT!$K$53,"") -> 0 | K54: =IFERROR(SYNC_FINANCE!$I$53,"") -> 0 | L54: =IFERROR([2]SYNC_COMMERCIAL_VENTE!$S$53,"") -> 0 | M54: 0 | N54: 0 | O54: 0 | P54: 0 | Q54: 0 | R54: 0 | S54: 0 | T54: 0 | U54: 0 | V54: 0 | W54: 0 | X54: 0 | Y54: 0 | Z54: =IFERROR(SUM(N54:Y54),0) -> 0 | AA54: =IFERROR((N54+Q54+T54+W54)-M54,0) -> 0 | AB54: =IFERROR(Z54,0) -> 0 | AC54: =IFERROR(L54-AB54,0) -> 0
A55: 50 | B55: =IFERROR([1]SYNC_PROSPECTION_MKT!$B$54,"") -> 0 | C55: =IFERROR([1]SYNC_PROSPECTION_MKT!$C$54,"") -> 0 | D55: =IFERROR([1]SYNC_PROSPECTION_MKT!$D$54,"") -> 0 | E55: =IFERROR([1]SYNC_PROSPECTION_MKT!$E$54,"") -> 0 | F55: =IFERROR([1]SYNC_PROSPECTION_MKT!$G$54,"") -> 0 | G55: =IFERROR([1]SYNC_PROSPECTION_MKT!$H$54,"") -> 0 | H55: =IFERROR([1]SYNC_PROSPECTION_MKT!$J$54,"") -> 0 | I55: =IFERROR([1]SYNC_PROSPECTION_MKT!$I$54,"") -> 0 | J55: =IFERROR([1]SYNC_PROSPECTION_MKT!$K$54,"") -> 0 | K55: =IFERROR(SYNC_FINANCE!$I$54,"") -> 0 | L55: =IFERROR([2]SYNC_COMMERCIAL_VENTE!$S$54,"") -> 0 | M55: 0 | N55: 0 | O55: 0 | P55: 0 | Q55: 0 | R55: 0 | S55: 0 | T55: 0 | U55: 0 | V55: 0 | W55: 0 | X55: 0 | Y55: 0 | Z55: =IFERROR(SUM(N55:Y55),0) -> 0 | AA55: =IFERROR((N55+Q55+T55+W55)-M55,0) -> 0 | AB55: =IFERROR(Z55,0) -> 0 | AC55: =IFERROR(L55-AB55,0) -> 0
A56: 51 | B56: =IFERROR([1]SYNC_PROSPECTION_MKT!$B$55,"") -> 0 | C56: =IFERROR([1]SYNC_PROSPECTION_MKT!$C$55,"") -> 0 | D56: =IFERROR([1]SYNC_PROSPECTION_MKT!$D$55,"") -> 0 | E56: =IFERROR([1]SYNC_PROSPECTION_MKT!$E$55,"") -> 0 | F56: =IFERROR([1]SYNC_PROSPECTION_MKT!$G$55,"") -> 0 | G56: =IFERROR([1]SYNC_PROSPECTION_MKT!$H$55,"") -> 0 | H56: =IFERROR([1]SYNC_PROSPECTION_MKT!$J$55,"") -> 0 | I56: =IFERROR([1]SYNC_PROSPECTION_MKT!$I$55,"") -> 0 | J56: =IFERROR([1]SYNC_PROSPECTION_MKT!$K$55,"") -> 0 | K56: =IFERROR(SYNC_FINANCE!$I$55,"") -> 0 | L56: =IFERROR([2]SYNC_COMMERCIAL_VENTE!$S$55,"") -> 0 | M56: 0 | N56: 0 | O56: 0 | P56: 0 | Q56: 0 | R56: 0 | S56: 0 | T56: 0 | U56: 0 | V56: 0 | W56: 0 | X56: 0 | Y56: 0 | Z56: =IFERROR(SUM(N56:Y56),0) -> 0 | AA56: =IFERROR((N56+Q56+T56+W56)-M56,0) -> 0 | AB56: =IFERROR(Z56,0) -> 0 | AC56: =IFERROR(L56-AB56,0) -> 0
A57: 52 | B57: =IFERROR([1]SYNC_PROSPECTION_MKT!$B$56,"") -> 0 | C57: =IFERROR([1]SYNC_PROSPECTION_MKT!$C$56,"") -> 0 | D57: =IFERROR([1]SYNC_PROSPECTION_MKT!$D$56,"") -> 0 | E57: =IFERROR([1]SYNC_PROSPECTION_MKT!$E$56,"") -> 0 | F57: =IFERROR([1]SYNC_PROSPECTION_MKT!$G$56,"") -> 0 | G57: =IFERROR([1]SYNC_PROSPECTION_MKT!$H$56,"") -> 0 | H57: =IFERROR([1]SYNC_PROSPECTION_MKT!$J$56,"") -> 0 | I57: =IFERROR([1]SYNC_PROSPECTION_MKT!$I$56,"") -> 0 | J57: =IFERROR([1]SYNC_PROSPECTION_MKT!$K$56,"") -> 0 | K57: =IFERROR(SYNC_FINANCE!$I$56,"") -> 0 | L57: =IFERROR([2]SYNC_COMMERCIAL_VENTE!$S$56,"") -> 0 | M57: 0 | N57: 0 | O57: 0 | P57: 0 | Q57: 0 | R57: 0 | S57: 0 | T57: 0 | U57: 0 | V57: 0 | W57: 0 | X57: 0 | Y57: 0 | Z57: =IFERROR(SUM(N57:Y57),0) -> 0 | AA57: =IFERROR((N57+Q57+T57+W57)-M57,0) -> 0 | AB57: =IFERROR(Z57,0) -> 0 | AC57: =IFERROR(L57-AB57,0) -> 0
A58: 53 | B58: =IFERROR([1]SYNC_PROSPECTION_MKT!$B$57,"") -> 0 | C58: =IFERROR([1]SYNC_PROSPECTION_MKT!$C$57,"") -> 0 | D58: =IFERROR([1]SYNC_PROSPECTION_MKT!$D$57,"") -> 0 | E58: =IFERROR([1]SYNC_PROSPECTION_MKT!$E$57,"") -> 0 | F58: =IFERROR([1]SYNC_PROSPECTION_MKT!$G$57,"") -> 0 | G58: =IFERROR([1]SYNC_PROSPECTION_MKT!$H$57,"") -> 0 | H58: =IFERROR([1]SYNC_PROSPECTION_MKT!$J$57,"") -> 0 | I58: =IFERROR([1]SYNC_PROSPECTION_MKT!$I$57,"") -> 0 | J58: =IFERROR([1]SYNC_PROSPECTION_MKT!$K$57,"") -> 0 | K58: =IFERROR(SYNC_FINANCE!$I$57,"") -> 0 | L58: =IFERROR([2]SYNC_COMMERCIAL_VENTE!$S$57,"") -> 0 | M58: 0 | N58: 0 | O58: 0 | P58: 0 | Q58: 0 | R58: 0 | S58: 0 | T58: 0 | U58: 0 | V58: 0 | W58: 0 | X58: 0 | Y58: 0 | Z58: =IFERROR(SUM(N58:Y58),0) -> 0 | AA58: =IFERROR((N58+Q58+T58+W58)-M58,0) -> 0 | AB58: =IFERROR(Z58,0) -> 0 | AC58: =IFERROR(L58-AB58,0) -> 0
A59: 54 | B59: =IFERROR([1]SYNC_PROSPECTION_MKT!$B$58,"") -> 0 | C59: =IFERROR([1]SYNC_PROSPECTION_MKT!$C$58,"") -> 0 | D59: =IFERROR([1]SYNC_PROSPECTION_MKT!$D$58,"") -> 0 | E59: =IFERROR([1]SYNC_PROSPECTION_MKT!$E$58,"") -> 0 | F59: =IFERROR([1]SYNC_PROSPECTION_MKT!$G$58,"") -> 0 | G59: =IFERROR([1]SYNC_PROSPECTION_MKT!$H$58,"") -> 0 | H59: =IFERROR([1]SYNC_PROSPECTION_MKT!$J$58,"") -> 0 | I59: =IFERROR([1]SYNC_PROSPECTION_MKT!$I$58,"") -> 0 | J59: =IFERROR([1]SYNC_PROSPECTION_MKT!$K$58,"") -> 0 | K59: =IFERROR(SYNC_FINANCE!$I$58,"") -> 0 | L59: =IFERROR([2]SYNC_COMMERCIAL_VENTE!$S$58,"") -> 0 | M59: 0 | N59: 0 | O59: 0 | P59: 0 | Q59: 0 | R59: 0 | S59: 0 | T59: 0 | U59: 0 | V59: 0 | W59: 0 | X59: 0 | Y59: 0 | Z59: =IFERROR(SUM(N59:Y59),0) -> 0 | AA59: =IFERROR((N59+Q59+T59+W59)-M59,0) -> 0 | AB59: =IFERROR(Z59,0) -> 0 | AC59: =IFERROR(L59-AB59,0) -> 0
A60: 55 | B60: =IFERROR([1]SYNC_PROSPECTION_MKT!$B$59,"") -> 0 | C60: =IFERROR([1]SYNC_PROSPECTION_MKT!$C$59,"") -> 0 | D60: =IFERROR([1]SYNC_PROSPECTION_MKT!$D$59,"") -> 0 | E60: =IFERROR([1]SYNC_PROSPECTION_MKT!$E$59,"") -> 0 | F60: =IFERROR([1]SYNC_PROSPECTION_MKT!$G$59,"") -> 0 | G60: =IFERROR([1]SYNC_PROSPECTION_MKT!$H$59,"") -> 0 | H60: =IFERROR([1]SYNC_PROSPECTION_MKT!$J$59,"") -> 0 | I60: =IFERROR([1]SYNC_PROSPECTION_MKT!$I$59,"") -> 0 | J60: =IFERROR([1]SYNC_PROSPECTION_MKT!$K$59,"") -> 0 | K60: =IFERROR(SYNC_FINANCE!$I$59,"") -> 0 | L60: =IFERROR([2]SYNC_COMMERCIAL_VENTE!$S$59,"") -> 0 | M60: 0 | N60: 0 | O60: 0 | P60: 0 | Q60: 0 | R60: 0 | S60: 0 | T60: 0 | U60: 0 | V60: 0 | W60: 0 | X60: 0 | Y60: 0 | Z60: =IFERROR(SUM(N60:Y60),0) -> 0 | AA60: =IFERROR((N60+Q60+T60+W60)-M60,0) -> 0 | AB60: =IFERROR(Z60,0) -> 0 | AC60: =IFERROR(L60-AB60,0) -> 0
A61: 56 | B61: =IFERROR([1]SYNC_PROSPECTION_MKT!$B$60,"") -> 0 | C61: =IFERROR([1]SYNC_PROSPECTION_MKT!$C$60,"") -> 0 | D61: =IFERROR([1]SYNC_PROSPECTION_MKT!$D$60,"") -> 0 | E61: =IFERROR([1]SYNC_PROSPECTION_MKT!$E$60,"") -> 0 | F61: =IFERROR([1]SYNC_PROSPECTION_MKT!$G$60,"") -> 0 | G61: =IFERROR([1]SYNC_PROSPECTION_MKT!$H$60,"") -> 0 | H61: =IFERROR([1]SYNC_PROSPECTION_MKT!$J$60,"") -> 0 | I61: =IFERROR([1]SYNC_PROSPECTION_MKT!$I$60,"") -> 0 | J61: =IFERROR([1]SYNC_PROSPECTION_MKT!$K$60,"") -> 0 | K61: =IFERROR(SYNC_FINANCE!$I$60,"") -> 0 | L61: =IFERROR([2]SYNC_COMMERCIAL_VENTE!$S$60,"") -> 0 | M61: 0 | N61: 0 | O61: 0 | P61: 0 | Q61: 0 | R61: 0 | S61: 0 | T61: 0 | U61: 0 | V61: 0 | W61: 0 | X61: 0 | Y61: 0 | Z61: =IFERROR(SUM(N61:Y61),0) -> 0 | AA61: =IFERROR((N61+Q61+T61+W61)-M61,0) -> 0 | AB61: =IFERROR(Z61,0) -> 0 | AC61: =IFERROR(L61-AB61,0) -> 0
A62: 57 | B62: =IFERROR([1]SYNC_PROSPECTION_MKT!$B$61,"") -> 0 | C62: =IFERROR([1]SYNC_PROSPECTION_MKT!$C$61,"") -> 0 | D62: =IFERROR([1]SYNC_PROSPECTION_MKT!$D$61,"") -> 0 | E62: =IFERROR([1]SYNC_PROSPECTION_MKT!$E$61,"") -> 0 | F62: =IFERROR([1]SYNC_PROSPECTION_MKT!$G$61,"") -> 0 | G62: =IFERROR([1]SYNC_PROSPECTION_MKT!$H$61,"") -> 0 | H62: =IFERROR([1]SYNC_PROSPECTION_MKT!$J$61,"") -> 0 | I62: =IFERROR([1]SYNC_PROSPECTION_MKT!$I$61,"") -> 0 | J62: =IFERROR([1]SYNC_PROSPECTION_MKT!$K$61,"") -> 0 | K62: =IFERROR(SYNC_FINANCE!$I$61,"") -> 0 | L62: =IFERROR([2]SYNC_COMMERCIAL_VENTE!$S$61,"") -> 0 | M62: 0 | N62: 0 | O62: 0 | P62: 0 | Q62: 0 | R62: 0 | S62: 0 | T62: 0 | U62: 0 | V62: 0 | W62: 0 | X62: 0 | Y62: 0 | Z62: =IFERROR(SUM(N62:Y62),0) -> 0 | AA62: =IFERROR((N62+Q62+T62+W62)-M62,0) -> 0 | AB62: =IFERROR(Z62,0) -> 0 | AC62: =IFERROR(L62-AB62,0) -> 0
A63: 58 | B63: =IFERROR([1]SYNC_PROSPECTION_MKT!$B$62,"") -> 0 | C63: =IFERROR([1]SYNC_PROSPECTION_MKT!$C$62,"") -> 0 | D63: =IFERROR([1]SYNC_PROSPECTION_MKT!$D$62,"") -> 0 | E63: =IFERROR([1]SYNC_PROSPECTION_MKT!$E$62,"") -> 0 | F63: =IFERROR([1]SYNC_PROSPECTION_MKT!$G$62,"") -> 0 | G63: =IFERROR([1]SYNC_PROSPECTION_MKT!$H$62,"") -> 0 | H63: =IFERROR([1]SYNC_PROSPECTION_MKT!$J$62,"") -> 0 | I63: =IFERROR([1]SYNC_PROSPECTION_MKT!$I$62,"") -> 0 | J63: =IFERROR([1]SYNC_PROSPECTION_MKT!$K$62,"") -> 0 | K63: =IFERROR(SYNC_FINANCE!$I$62,"") -> 0 | L63: =IFERROR([2]SYNC_COMMERCIAL_VENTE!$S$62,"") -> 0 | M63: 0 | N63: 0 | O63: 0 | P63: 0 | Q63: 0 | R63: 0 | S63: 0 | T63: 0 | U63: 0 | V63: 0 | W63: 0 | X63: 0 | Y63: 0 | Z63: =IFERROR(SUM(N63:Y63),0) -> 0 | AA63: =IFERROR((N63+Q63+T63+W63)-M63,0) -> 0 | AB63: =IFERROR(Z63,0) -> 0 | AC63: =IFERROR(L63-AB63,0) -> 0
A64: 59 | B64: =IFERROR([1]SYNC_PROSPECTION_MKT!$B$63,"") -> 0 | C64: =IFERROR([1]SYNC_PROSPECTION_MKT!$C$63,"") -> 0 | D64: =IFERROR([1]SYNC_PROSPECTION_MKT!$D$63,"") -> 0 | E64: =IFERROR([1]SYNC_PROSPECTION_MKT!$E$63,"") -> 0 | F64: =IFERROR([1]SYNC_PROSPECTION_MKT!$G$63,"") -> 0 | G64: =IFERROR([1]SYNC_PROSPECTION_MKT!$H$63,"") -> 0 | H64: =IFERROR([1]SYNC_PROSPECTION_MKT!$J$63,"") -> 0 | I64: =IFERROR([1]SYNC_PROSPECTION_MKT!$I$63,"") -> 0 | J64: =IFERROR([1]SYNC_PROSPECTION_MKT!$K$63,"") -> 0 | K64: =IFERROR(SYNC_FINANCE!$I$63,"") -> 0 | L64: =IFERROR([2]SYNC_COMMERCIAL_VENTE!$S$63,"") -> 0 | M64: 0 | N64: 0 | O64: 0 | P64: 0 | Q64: 0 | R64: 0 | S64: 0 | T64: 0 | U64: 0 | V64: 0 | W64: 0 | X64: 0 | Y64: 0 | Z64: =IFERROR(SUM(N64:Y64),0) -> 0 | AA64: =IFERROR((N64+Q64+T64+W64)-M64,0) -> 0 | AB64: =IFERROR(Z64,0) -> 0 | AC64: =IFERROR(L64-AB64,0) -> 0
A65: 60 | B65: =IFERROR([1]SYNC_PROSPECTION_MKT!$B$64,"") -> 0 | C65: =IFERROR([1]SYNC_PROSPECTION_MKT!$C$64,"") -> 0 | D65: =IFERROR([1]SYNC_PROSPECTION_MKT!$D$64,"") -> 0 | E65: =IFERROR([1]SYNC_PROSPECTION_MKT!$E$64,"") -> 0 | F65: =IFERROR([1]SYNC_PROSPECTION_MKT!$G$64,"") -> 0 | G65: =IFERROR([1]SYNC_PROSPECTION_MKT!$H$64,"") -> 0 | H65: =IFERROR([1]SYNC_PROSPECTION_MKT!$J$64,"") -> 0 | I65: =IFERROR([1]SYNC_PROSPECTION_MKT!$I$64,"") -> 0 | J65: =IFERROR([1]SYNC_PROSPECTION_MKT!$K$64,"") -> 0 | K65: =IFERROR(SYNC_FINANCE!$I$64,"") -> 0 | L65: =IFERROR([2]SYNC_COMMERCIAL_VENTE!$S$64,"") -> 0 | M65: 0 | N65: 0 | O65: 0 | P65: 0 | Q65: 0 | R65: 0 | S65: 0 | T65: 0 | U65: 0 | V65: 0 | W65: 0 | X65: 0 | Y65: 0 | Z65: =IFERROR(SUM(N65:Y65),0) -> 0 | AA65: =IFERROR((N65+Q65+T65+W65)-M65,0) -> 0 | AB65: =IFERROR(Z65,0) -> 0 | AC65: =IFERROR(L65-AB65,0) -> 0
A66: 61 | B66: =IFERROR([1]SYNC_PROSPECTION_MKT!$B$65,"") -> 0 | C66: =IFERROR([1]SYNC_PROSPECTION_MKT!$C$65,"") -> 0 | D66: =IFERROR([1]SYNC_PROSPECTION_MKT!$D$65,"") -> 0 | E66: =IFERROR([1]SYNC_PROSPECTION_MKT!$E$65,"") -> 0 | F66: =IFERROR([1]SYNC_PROSPECTION_MKT!$G$65,"") -> 0 | G66: =IFERROR([1]SYNC_PROSPECTION_MKT!$H$65,"") -> 0 | H66: =IFERROR([1]SYNC_PROSPECTION_MKT!$J$65,"") -> 0 | I66: =IFERROR([1]SYNC_PROSPECTION_MKT!$I$65,"") -> 0 | J66: =IFERROR([1]SYNC_PROSPECTION_MKT!$K$65,"") -> 0 | K66: =IFERROR(SYNC_FINANCE!$I$65,"") -> 0 | L66: =IFERROR([2]SYNC_COMMERCIAL_VENTE!$S$65,"") -> 0 | M66: 0 | N66: 0 | O66: 0 | P66: 0 | Q66: 0 | R66: 0 | S66: 0 | T66: 0 | U66: 0 | V66: 0 | W66: 0 | X66: 0 | Y66: 0 | Z66: =IFERROR(SUM(N66:Y66),0) -> 0 | AA66: =IFERROR((N66+Q66+T66+W66)-M66,0) -> 0 | AB66: =IFERROR(Z66,0) -> 0 | AC66: =IFERROR(L66-AB66,0) -> 0
A67: 62 | B67: =IFERROR([1]SYNC_PROSPECTION_MKT!$B$66,"") -> 0 | C67: =IFERROR([1]SYNC_PROSPECTION_MKT!$C$66,"") -> 0 | D67: =IFERROR([1]SYNC_PROSPECTION_MKT!$D$66,"") -> 0 | E67: =IFERROR([1]SYNC_PROSPECTION_MKT!$E$66,"") -> 0 | F67: =IFERROR([1]SYNC_PROSPECTION_MKT!$G$66,"") -> 0 | G67: =IFERROR([1]SYNC_PROSPECTION_MKT!$H$66,"") -> 0 | H67: =IFERROR([1]SYNC_PROSPECTION_MKT!$J$66,"") -> 0 | I67: =IFERROR([1]SYNC_PROSPECTION_MKT!$I$66,"") -> 0 | J67: =IFERROR([1]SYNC_PROSPECTION_MKT!$K$66,"") -> 0 | K67: =IFERROR(SYNC_FINANCE!$I$66,"") -> 0 | L67: =IFERROR([2]SYNC_COMMERCIAL_VENTE!$S$66,"") -> 0 | M67: 0 | N67: 0 | O67: 0 | P67: 0 | Q67: 0 | R67: 0 | S67: 0 | T67: 0 | U67: 0 | V67: 0 | W67: 0 | X67: 0 | Y67: 0 | Z67: =IFERROR(SUM(N67:Y67),0) -> 0 | AA67: =IFERROR((N67+Q67+T67+W67)-M67,0) -> 0 | AB67: =IFERROR(Z67,0) -> 0 | AC67: =IFERROR(L67-AB67,0) -> 0
A68: 63 | B68: =IFERROR([1]SYNC_PROSPECTION_MKT!$B$67,"") -> 0 | C68: =IFERROR([1]SYNC_PROSPECTION_MKT!$C$67,"") -> 0 | D68: =IFERROR([1]SYNC_PROSPECTION_MKT!$D$67,"") -> 0 | E68: =IFERROR([1]SYNC_PROSPECTION_MKT!$E$67,"") -> 0 | F68: =IFERROR([1]SYNC_PROSPECTION_MKT!$G$67,"") -> 0 | G68: =IFERROR([1]SYNC_PROSPECTION_MKT!$H$67,"") -> 0 | H68: =IFERROR([1]SYNC_PROSPECTION_MKT!$J$67,"") -> 0 | I68: =IFERROR([1]SYNC_PROSPECTION_MKT!$I$67,"") -> 0 | J68: =IFERROR([1]SYNC_PROSPECTION_MKT!$K$67,"") -> 0 | K68: =IFERROR(SYNC_FINANCE!$I$67,"") -> 0 | L68: =IFERROR([2]SYNC_COMMERCIAL_VENTE!$S$67,"") -> 0 | M68: 0 | N68: 0 | O68: 0 | P68: 0 | Q68: 0 | R68: 0 | S68: 0 | T68: 0 | U68: 0 | V68: 0 | W68: 0 | X68: 0 | Y68: 0 | Z68: =IFERROR(SUM(N68:Y68),0) -> 0 | AA68: =IFERROR((N68+Q68+T68+W68)-M68,0) -> 0 | AB68: =IFERROR(Z68,0) -> 0 | AC68: =IFERROR(L68-AB68,0) -> 0
A69: 64 | B69: =IFERROR([1]SYNC_PROSPECTION_MKT!$B$68,"") -> 0 | C69: =IFERROR([1]SYNC_PROSPECTION_MKT!$C$68,"") -> 0 | D69: =IFERROR([1]SYNC_PROSPECTION_MKT!$D$68,"") -> 0 | E69: =IFERROR([1]SYNC_PROSPECTION_MKT!$E$68,"") -> 0 | F69: =IFERROR([1]SYNC_PROSPECTION_MKT!$G$68,"") -> 0 | G69: =IFERROR([1]SYNC_PROSPECTION_MKT!$H$68,"") -> 0 | H69: =IFERROR([1]SYNC_PROSPECTION_MKT!$J$68,"") -> 0 | I69: =IFERROR([1]SYNC_PROSPECTION_MKT!$I$68,"") -> 0 | J69: =IFERROR([1]SYNC_PROSPECTION_MKT!$K$68,"") -> 0 | K69: =IFERROR(SYNC_FINANCE!$I$68,"") -> 0 | L69: =IFERROR([2]SYNC_COMMERCIAL_VENTE!$S$68,"") -> 0 | M69: 0 | N69: 0 | O69: 0 | P69: 0 | Q69: 0 | R69: 0 | S69: 0 | T69: 0 | U69: 0 | V69: 0 | W69: 0 | X69: 0 | Y69: 0 | Z69: =IFERROR(SUM(N69:Y69),0) -> 0 | AA69: =IFERROR((N69+Q69+T69+W69)-M69,0) -> 0 | AB69: =IFERROR(Z69,0) -> 0 | AC69: =IFERROR(L69-AB69,0) -> 0
A70: 65 | B70: =IFERROR([1]SYNC_PROSPECTION_MKT!$B$69,"") -> 0 | C70: =IFERROR([1]SYNC_PROSPECTION_MKT!$C$69,"") -> 0 | D70: =IFERROR([1]SYNC_PROSPECTION_MKT!$D$69,"") -> 0 | E70: =IFERROR([1]SYNC_PROSPECTION_MKT!$E$69,"") -> 0 | F70: =IFERROR([1]SYNC_PROSPECTION_MKT!$G$69,"") -> 0 | G70: =IFERROR([1]SYNC_PROSPECTION_MKT!$H$69,"") -> 0 | H70: =IFERROR([1]SYNC_PROSPECTION_MKT!$J$69,"") -> 0 | I70: =IFERROR([1]SYNC_PROSPECTION_MKT!$I$69,"") -> 0 | J70: =IFERROR([1]SYNC_PROSPECTION_MKT!$K$69,"") -> 0 | K70: =IFERROR(SYNC_FINANCE!$I$69,"") -> 0 | L70: =IFERROR([2]SYNC_COMMERCIAL_VENTE!$S$69,"") -> 0 | M70: 0 | N70: 0 | O70: 0 | P70: 0 | Q70: 0 | R70: 0 | S70: 0 | T70: 0 | U70: 0 | V70: 0 | W70: 0 | X70: 0 | Y70: 0 | Z70: =IFERROR(SUM(N70:Y70),0) -> 0 | AA70: =IFERROR((N70+Q70+T70+W70)-M70,0) -> 0 | AB70: =IFERROR(Z70,0) -> 0 | AC70: =IFERROR(L70-AB70,0) -> 0
A71: 66 | B71: =IFERROR([1]SYNC_PROSPECTION_MKT!$B$70,"") -> 0 | C71: =IFERROR([1]SYNC_PROSPECTION_MKT!$C$70,"") -> 0 | D71: =IFERROR([1]SYNC_PROSPECTION_MKT!$D$70,"") -> 0 | E71: =IFERROR([1]SYNC_PROSPECTION_MKT!$E$70,"") -> 0 | F71: =IFERROR([1]SYNC_PROSPECTION_MKT!$G$70,"") -> 0 | G71: =IFERROR([1]SYNC_PROSPECTION_MKT!$H$70,"") -> 0 | H71: =IFERROR([1]SYNC_PROSPECTION_MKT!$J$70,"") -> 0 | I71: =IFERROR([1]SYNC_PROSPECTION_MKT!$I$70,"") -> 0 | J71: =IFERROR([1]SYNC_PROSPECTION_MKT!$K$70,"") -> 0 | K71: =IFERROR(SYNC_FINANCE!$I$70,"") -> 0 | L71: =IFERROR([2]SYNC_COMMERCIAL_VENTE!$S$70,"") -> 0 | M71: 0 | N71: 0 | O71: 0 | P71: 0 | Q71: 0 | R71: 0 | S71: 0 | T71: 0 | U71: 0 | V71: 0 | W71: 0 | X71: 0 | Y71: 0 | Z71: =IFERROR(SUM(N71:Y71),0) -> 0 | AA71: =IFERROR((N71+Q71+T71+W71)-M71,0) -> 0 | AB71: =IFERROR(Z71,0) -> 0 | AC71: =IFERROR(L71-AB71,0) -> 0
A72: 67 | B72: =IFERROR([1]SYNC_PROSPECTION_MKT!$B$71,"") -> 0 | C72: =IFERROR([1]SYNC_PROSPECTION_MKT!$C$71,"") -> 0 | D72: =IFERROR([1]SYNC_PROSPECTION_MKT!$D$71,"") -> 0 | E72: =IFERROR([1]SYNC_PROSPECTION_MKT!$E$71,"") -> 0 | F72: =IFERROR([1]SYNC_PROSPECTION_MKT!$G$71,"") -> 0 | G72: =IFERROR([1]SYNC_PROSPECTION_MKT!$H$71,"") -> 0 | H72: =IFERROR([1]SYNC_PROSPECTION_MKT!$J$71,"") -> 0 | I72: =IFERROR([1]SYNC_PROSPECTION_MKT!$I$71,"") -> 0 | J72: =IFERROR([1]SYNC_PROSPECTION_MKT!$K$71,"") -> 0 | K72: =IFERROR(SYNC_FINANCE!$I$71,"") -> 0 | L72: =IFERROR([2]SYNC_COMMERCIAL_VENTE!$S$71,"") -> 0 | M72: 0 | N72: 0 | O72: 0 | P72: 0 | Q72: 0 | R72: 0 | S72: 0 | T72: 0 | U72: 0 | V72: 0 | W72: 0 | X72: 0 | Y72: 0 | Z72: =IFERROR(SUM(N72:Y72),0) -> 0 | AA72: =IFERROR((N72+Q72+T72+W72)-M72,0) -> 0 | AB72: =IFERROR(Z72,0) -> 0 | AC72: =IFERROR(L72-AB72,0) -> 0
A73: 68 | B73: =IFERROR([1]SYNC_PROSPECTION_MKT!$B$72,"") -> 0 | C73: =IFERROR([1]SYNC_PROSPECTION_MKT!$C$72,"") -> 0 | D73: =IFERROR([1]SYNC_PROSPECTION_MKT!$D$72,"") -> 0 | E73: =IFERROR([1]SYNC_PROSPECTION_MKT!$E$72,"") -> 0 | F73: =IFERROR([1]SYNC_PROSPECTION_MKT!$G$72,"") -> 0 | G73: =IFERROR([1]SYNC_PROSPECTION_MKT!$H$72,"") -> 0 | H73: =IFERROR([1]SYNC_PROSPECTION_MKT!$J$72,"") -> 0 | I73: =IFERROR([1]SYNC_PROSPECTION_MKT!$I$72,"") -> 0 | J73: =IFERROR([1]SYNC_PROSPECTION_MKT!$K$72,"") -> 0 | K73: =IFERROR(SYNC_FINANCE!$I$72,"") -> 0 | L73: =IFERROR([2]SYNC_COMMERCIAL_VENTE!$S$72,"") -> 0 | M73: 0 | N73: 0 | O73: 0 | P73: 0 | Q73: 0 | R73: 0 | S73: 0 | T73: 0 | U73: 0 | V73: 0 | W73: 0 | X73: 0 | Y73: 0 | Z73: =IFERROR(SUM(N73:Y73),0) -> 0 | AA73: =IFERROR((N73+Q73+T73+W73)-M73,0) -> 0 | AB73: =IFERROR(Z73,0) -> 0 | AC73: =IFERROR(L73-AB73,0) -> 0
A74: 69 | B74: =IFERROR([1]SYNC_PROSPECTION_MKT!$B$73,"") -> 0 | C74: =IFERROR([1]SYNC_PROSPECTION_MKT!$C$73,"") -> 0 | D74: =IFERROR([1]SYNC_PROSPECTION_MKT!$D$73,"") -> 0 | E74: =IFERROR([1]SYNC_PROSPECTION_MKT!$E$73,"") -> 0 | F74: =IFERROR([1]SYNC_PROSPECTION_MKT!$G$73,"") -> 0 | G74: =IFERROR([1]SYNC_PROSPECTION_MKT!$H$73,"") -> 0 | H74: =IFERROR([1]SYNC_PROSPECTION_MKT!$J$73,"") -> 0 | I74: =IFERROR([1]SYNC_PROSPECTION_MKT!$I$73,"") -> 0 | J74: =IFERROR([1]SYNC_PROSPECTION_MKT!$K$73,"") -> 0 | K74: =IFERROR(SYNC_FINANCE!$I$73,"") -> 0 | L74: =IFERROR([2]SYNC_COMMERCIAL_VENTE!$S$73,"") -> 0 | M74: 0 | N74: 0 | O74: 0 | P74: 0 | Q74: 0 | R74: 0 | S74: 0 | T74: 0 | U74: 0 | V74: 0 | W74: 0 | X74: 0 | Y74: 0 | Z74: =IFERROR(SUM(N74:Y74),0) -> 0 | AA74: =IFERROR((N74+Q74+T74+W74)-M74,0) -> 0 | AB74: =IFERROR(Z74,0) -> 0 | AC74: =IFERROR(L74-AB74,0) -> 0
A75: 70 | B75: =IFERROR([1]SYNC_PROSPECTION_MKT!$B$74,"") -> 0 | C75: =IFERROR([1]SYNC_PROSPECTION_MKT!$C$74,"") -> 0 | D75: =IFERROR([1]SYNC_PROSPECTION_MKT!$D$74,"") -> 0 | E75: =IFERROR([1]SYNC_PROSPECTION_MKT!$E$74,"") -> 0 | F75: =IFERROR([1]SYNC_PROSPECTION_MKT!$G$74,"") -> 0 | G75: =IFERROR([1]SYNC_PROSPECTION_MKT!$H$74,"") -> 0 | H75: =IFERROR([1]SYNC_PROSPECTION_MKT!$J$74,"") -> 0 | I75: =IFERROR([1]SYNC_PROSPECTION_MKT!$I$74,"") -> 0 | J75: =IFERROR([1]SYNC_PROSPECTION_MKT!$K$74,"") -> 0 | K75: =IFERROR(SYNC_FINANCE!$I$74,"") -> 0 | L75: =IFERROR([2]SYNC_COMMERCIAL_VENTE!$S$74,"") -> 0 | M75: 0 | N75: 0 | O75: 0 | P75: 0 | Q75: 0 | R75: 0 | S75: 0 | T75: 0 | U75: 0 | V75: 0 | W75: 0 | X75: 0 | Y75: 0 | Z75: =IFERROR(SUM(N75:Y75),0) -> 0 | AA75: =IFERROR((N75+Q75+T75+W75)-M75,0) -> 0 | AB75: =IFERROR(Z75,0) -> 0 | AC75: =IFERROR(L75-AB75,0) -> 0
A76: 71 | B76: =IFERROR([1]SYNC_PROSPECTION_MKT!$B$75,"") -> 0 | C76: =IFERROR([1]SYNC_PROSPECTION_MKT!$C$75,"") -> 0 | D76: =IFERROR([1]SYNC_PROSPECTION_MKT!$D$75,"") -> 0 | E76: =IFERROR([1]SYNC_PROSPECTION_MKT!$E$75,"") -> 0 | F76: =IFERROR([1]SYNC_PROSPECTION_MKT!$G$75,"") -> 0 | G76: =IFERROR([1]SYNC_PROSPECTION_MKT!$H$75,"") -> 0 | H76: =IFERROR([1]SYNC_PROSPECTION_MKT!$J$75,"") -> 0 | I76: =IFERROR([1]SYNC_PROSPECTION_MKT!$I$75,"") -> 0 | J76: =IFERROR([1]SYNC_PROSPECTION_MKT!$K$75,"") -> 0 | K76: =IFERROR(SYNC_FINANCE!$I$75,"") -> 0 | L76: =IFERROR([2]SYNC_COMMERCIAL_VENTE!$S$75,"") -> 0 | M76: 0 | N76: 0 | O76: 0 | P76: 0 | Q76: 0 | R76: 0 | S76: 0 | T76: 0 | U76: 0 | V76: 0 | W76: 0 | X76: 0 | Y76: 0 | Z76: =IFERROR(SUM(N76:Y76),0) -> 0 | AA76: =IFERROR((N76+Q76+T76+W76)-M76,0) -> 0 | AB76: =IFERROR(Z76,0) -> 0 | AC76: =IFERROR(L76-AB76,0) -> 0
A77: 72 | B77: =IFERROR([1]SYNC_PROSPECTION_MKT!$B$76,"") -> 0 | C77: =IFERROR([1]SYNC_PROSPECTION_MKT!$C$76,"") -> 0 | D77: =IFERROR([1]SYNC_PROSPECTION_MKT!$D$76,"") -> 0 | E77: =IFERROR([1]SYNC_PROSPECTION_MKT!$E$76,"") -> 0 | F77: =IFERROR([1]SYNC_PROSPECTION_MKT!$G$76,"") -> 0 | G77: =IFERROR([1]SYNC_PROSPECTION_MKT!$H$76,"") -> 0 | H77: =IFERROR([1]SYNC_PROSPECTION_MKT!$J$76,"") -> 0 | I77: =IFERROR([1]SYNC_PROSPECTION_MKT!$I$76,"") -> 0 | J77: =IFERROR([1]SYNC_PROSPECTION_MKT!$K$76,"") -> 0 | K77: =IFERROR(SYNC_FINANCE!$I$76,"") -> 0 | L77: =IFERROR([2]SYNC_COMMERCIAL_VENTE!$S$76,"") -> 0 | M77: 0 | N77: 0 | O77: 0 | P77: 0 | Q77: 0 | R77: 0 | S77: 0 | T77: 0 | U77: 0 | V77: 0 | W77: 0 | X77: 0 | Y77: 0 | Z77: =IFERROR(SUM(N77:Y77),0) -> 0 | AA77: =IFERROR((N77+Q77+T77+W77)-M77,0) -> 0 | AB77: =IFERROR(Z77,0) -> 0 | AC77: =IFERROR(L77-AB77,0) -> 0
A78: 73 | B78: =IFERROR([1]SYNC_PROSPECTION_MKT!$B$77,"") -> 0 | C78: =IFERROR([1]SYNC_PROSPECTION_MKT!$C$77,"") -> 0 | D78: =IFERROR([1]SYNC_PROSPECTION_MKT!$D$77,"") -> 0 | E78: =IFERROR([1]SYNC_PROSPECTION_MKT!$E$77,"") -> 0 | F78: =IFERROR([1]SYNC_PROSPECTION_MKT!$G$77,"") -> 0 | G78: =IFERROR([1]SYNC_PROSPECTION_MKT!$H$77,"") -> 0 | H78: =IFERROR([1]SYNC_PROSPECTION_MKT!$J$77,"") -> 0 | I78: =IFERROR([1]SYNC_PROSPECTION_MKT!$I$77,"") -> 0 | J78: =IFERROR([1]SYNC_PROSPECTION_MKT!$K$77,"") -> 0 | K78: =IFERROR(SYNC_FINANCE!$I$77,"") -> 0 | L78: =IFERROR([2]SYNC_COMMERCIAL_VENTE!$S$77,"") -> 0 | M78: 0 | N78: 0 | O78: 0 | P78: 0 | Q78: 0 | R78: 0 | S78: 0 | T78: 0 | U78: 0 | V78: 0 | W78: 0 | X78: 0 | Y78: 0 | Z78: =IFERROR(SUM(N78:Y78),0) -> 0 | AA78: =IFERROR((N78+Q78+T78+W78)-M78,0) -> 0 | AB78: =IFERROR(Z78,0) -> 0 | AC78: =IFERROR(L78-AB78,0) -> 0
A79: 74 | B79: =IFERROR([1]SYNC_PROSPECTION_MKT!$B$78,"") -> 0 | C79: =IFERROR([1]SYNC_PROSPECTION_MKT!$C$78,"") -> 0 | D79: =IFERROR([1]SYNC_PROSPECTION_MKT!$D$78,"") -> 0 | E79: =IFERROR([1]SYNC_PROSPECTION_MKT!$E$78,"") -> 0 | F79: =IFERROR([1]SYNC_PROSPECTION_MKT!$G$78,"") -> 0 | G79: =IFERROR([1]SYNC_PROSPECTION_MKT!$H$78,"") -> 0 | H79: =IFERROR([1]SYNC_PROSPECTION_MKT!$J$78,"") -> 0 | I79: =IFERROR([1]SYNC_PROSPECTION_MKT!$I$78,"") -> 0 | J79: =IFERROR([1]SYNC_PROSPECTION_MKT!$K$78,"") -> 0 | K79: =IFERROR(SYNC_FINANCE!$I$78,"") -> 0 | L79: =IFERROR([2]SYNC_COMMERCIAL_VENTE!$S$78,"") -> 0 | M79: 0 | N79: 0 | O79: 0 | P79: 0 | Q79: 0 | R79: 0 | S79: 0 | T79: 0 | U79: 0 | V79: 0 | W79: 0 | X79: 0 | Y79: 0 | Z79: =IFERROR(SUM(N79:Y79),0) -> 0 | AA79: =IFERROR((N79+Q79+T79+W79)-M79,0) -> 0 | AB79: =IFERROR(Z79,0) -> 0 | AC79: =IFERROR(L79-AB79,0) -> 0
A80: 75 | B80: =IFERROR([1]SYNC_PROSPECTION_MKT!$B$79,"") -> 0 | C80: =IFERROR([1]SYNC_PROSPECTION_MKT!$C$79,"") -> 0 | D80: =IFERROR([1]SYNC_PROSPECTION_MKT!$D$79,"") -> 0 | E80: =IFERROR([1]SYNC_PROSPECTION_MKT!$E$79,"") -> 0 | F80: =IFERROR([1]SYNC_PROSPECTION_MKT!$G$79,"") -> 0 | G80: =IFERROR([1]SYNC_PROSPECTION_MKT!$H$79,"") -> 0 | H80: =IFERROR([1]SYNC_PROSPECTION_MKT!$J$79,"") -> 0 | I80: =IFERROR([1]SYNC_PROSPECTION_MKT!$I$79,"") -> 0 | J80: =IFERROR([1]SYNC_PROSPECTION_MKT!$K$79,"") -> 0 | K80: =IFERROR(SYNC_FINANCE!$I$79,"") -> 0 | L80: =IFERROR([2]SYNC_COMMERCIAL_VENTE!$S$79,"") -> 0 | M80: 0 | N80: 0 | O80: 0 | P80: 0 | Q80: 0 | R80: 0 | S80: 0 | T80: 0 | U80: 0 | V80: 0 | W80: 0 | X80: 0 | Y80: 0 | Z80: =IFERROR(SUM(N80:Y80),0) -> 0 | AA80: =IFERROR((N80+Q80+T80+W80)-M80,0) -> 0 | AB80: =IFERROR(Z80,0) -> 0 | AC80: =IFERROR(L80-AB80,0) -> 0
A81: 76 | B81: =IFERROR([1]SYNC_PROSPECTION_MKT!$B$80,"") -> 0 | C81: =IFERROR([1]SYNC_PROSPECTION_MKT!$C$80,"") -> 0 | D81: =IFERROR([1]SYNC_PROSPECTION_MKT!$D$80,"") -> 0 | E81: =IFERROR([1]SYNC_PROSPECTION_MKT!$E$80,"") -> 0 | F81: =IFERROR([1]SYNC_PROSPECTION_MKT!$G$80,"") -> 0 | G81: =IFERROR([1]SYNC_PROSPECTION_MKT!$H$80,"") -> 0 | H81: =IFERROR([1]SYNC_PROSPECTION_MKT!$J$80,"") -> 0 | I81: =IFERROR([1]SYNC_PROSPECTION_MKT!$I$80,"") -> 0 | J81: =IFERROR([1]SYNC_PROSPECTION_MKT!$K$80,"") -> 0 | K81: =IFERROR(SYNC_FINANCE!$I$80,"") -> 0 | L81: =IFERROR([2]SYNC_COMMERCIAL_VENTE!$S$80,"") -> 0 | M81: 0 | N81: 0 | O81: 0 | P81: 0 | Q81: 0 | R81: 0 | S81: 0 | T81: 0 | U81: 0 | V81: 0 | W81: 0 | X81: 0 | Y81: 0 | Z81: =IFERROR(SUM(N81:Y81),0) -> 0 | AA81: =IFERROR((N81+Q81+T81+W81)-M81,0) -> 0 | AB81: =IFERROR(Z81,0) -> 0 | AC81: =IFERROR(L81-AB81,0) -> 0
A82: 77 | B82: =IFERROR([1]SYNC_PROSPECTION_MKT!$B$81,"") -> 0 | C82: =IFERROR([1]SYNC_PROSPECTION_MKT!$C$81,"") -> 0 | D82: =IFERROR([1]SYNC_PROSPECTION_MKT!$D$81,"") -> 0 | E82: =IFERROR([1]SYNC_PROSPECTION_MKT!$E$81,"") -> 0 | F82: =IFERROR([1]SYNC_PROSPECTION_MKT!$G$81,"") -> 0 | G82: =IFERROR([1]SYNC_PROSPECTION_MKT!$H$81,"") -> 0 | H82: =IFERROR([1]SYNC_PROSPECTION_MKT!$J$81,"") -> 0 | I82: =IFERROR([1]SYNC_PROSPECTION_MKT!$I$81,"") -> 0 | J82: =IFERROR([1]SYNC_PROSPECTION_MKT!$K$81,"") -> 0 | K82: =IFERROR(SYNC_FINANCE!$I$81,"") -> 0 | L82: =IFERROR([2]SYNC_COMMERCIAL_VENTE!$S$81,"") -> 0 | M82: 0 | N82: 0 | O82: 0 | P82: 0 | Q82: 0 | R82: 0 | S82: 0 | T82: 0 | U82: 0 | V82: 0 | W82: 0 | X82: 0 | Y82: 0 | Z82: =IFERROR(SUM(N82:Y82),0) -> 0 | AA82: =IFERROR((N82+Q82+T82+W82)-M82,0) -> 0 | AB82: =IFERROR(Z82,0) -> 0 | AC82: =IFERROR(L82-AB82,0) -> 0
A83: 78 | B83: =IFERROR([1]SYNC_PROSPECTION_MKT!$B$82,"") -> 0 | C83: =IFERROR([1]SYNC_PROSPECTION_MKT!$C$82,"") -> 0 | D83: =IFERROR([1]SYNC_PROSPECTION_MKT!$D$82,"") -> 0 | E83: =IFERROR([1]SYNC_PROSPECTION_MKT!$E$82,"") -> 0 | F83: =IFERROR([1]SYNC_PROSPECTION_MKT!$G$82,"") -> 0 | G83: =IFERROR([1]SYNC_PROSPECTION_MKT!$H$82,"") -> 0 | H83: =IFERROR([1]SYNC_PROSPECTION_MKT!$J$82,"") -> 0 | I83: =IFERROR([1]SYNC_PROSPECTION_MKT!$I$82,"") -> 0 | J83: =IFERROR([1]SYNC_PROSPECTION_MKT!$K$82,"") -> 0 | K83: =IFERROR(SYNC_FINANCE!$I$82,"") -> 0 | L83: =IFERROR([2]SYNC_COMMERCIAL_VENTE!$S$82,"") -> 0 | M83: 0 | N83: 0 | O83: 0 | P83: 0 | Q83: 0 | R83: 0 | S83: 0 | T83: 0 | U83: 0 | V83: 0 | W83: 0 | X83: 0 | Y83: 0 | Z83: =IFERROR(SUM(N83:Y83),0) -> 0 | AA83: =IFERROR((N83+Q83+T83+W83)-M83,0) -> 0 | AB83: =IFERROR(Z83,0) -> 0 | AC83: =IFERROR(L83-AB83,0) -> 0
A84: 79 | B84: =IFERROR([1]SYNC_PROSPECTION_MKT!$B$83,"") -> 0 | C84: =IFERROR([1]SYNC_PROSPECTION_MKT!$C$83,"") -> 0 | D84: =IFERROR([1]SYNC_PROSPECTION_MKT!$D$83,"") -> 0 | E84: =IFERROR([1]SYNC_PROSPECTION_MKT!$E$83,"") -> 0 | F84: =IFERROR([1]SYNC_PROSPECTION_MKT!$G$83,"") -> 0 | G84: =IFERROR([1]SYNC_PROSPECTION_MKT!$H$83,"") -> 0 | H84: =IFERROR([1]SYNC_PROSPECTION_MKT!$J$83,"") -> 0 | I84: =IFERROR([1]SYNC_PROSPECTION_MKT!$I$83,"") -> 0 | J84: =IFERROR([1]SYNC_PROSPECTION_MKT!$K$83,"") -> 0 | K84: =IFERROR(SYNC_FINANCE!$I$83,"") -> 0 | L84: =IFERROR([2]SYNC_COMMERCIAL_VENTE!$S$83,"") -> 0 | M84: 0 | N84: 0 | O84: 0 | P84: 0 | Q84: 0 | R84: 0 | S84: 0 | T84: 0 | U84: 0 | V84: 0 | W84: 0 | X84: 0 | Y84: 0 | Z84: =IFERROR(SUM(N84:Y84),0) -> 0 | AA84: =IFERROR((N84+Q84+T84+W84)-M84,0) -> 0 | AB84: =IFERROR(Z84,0) -> 0 | AC84: =IFERROR(L84-AB84,0) -> 0
A85: 80 | B85: =IFERROR([1]SYNC_PROSPECTION_MKT!$B$84,"") -> 0 | C85: =IFERROR([1]SYNC_PROSPECTION_MKT!$C$84,"") -> 0 | D85: =IFERROR([1]SYNC_PROSPECTION_MKT!$D$84,"") -> 0 | E85: =IFERROR([1]SYNC_PROSPECTION_MKT!$E$84,"") -> 0 | F85: =IFERROR([1]SYNC_PROSPECTION_MKT!$G$84,"") -> 0 | G85: =IFERROR([1]SYNC_PROSPECTION_MKT!$H$84,"") -> 0 | H85: =IFERROR([1]SYNC_PROSPECTION_MKT!$J$84,"") -> 0 | I85: =IFERROR([1]SYNC_PROSPECTION_MKT!$I$84,"") -> 0 | J85: =IFERROR([1]SYNC_PROSPECTION_MKT!$K$84,"") -> 0 | K85: =IFERROR(SYNC_FINANCE!$I$84,"") -> 0 | L85: =IFERROR([2]SYNC_COMMERCIAL_VENTE!$S$84,"") -> 0 | M85: 0 | N85: 0 | O85: 0 | P85: 0 | Q85: 0 | R85: 0 | S85: 0 | T85: 0 | U85: 0 | V85: 0 | W85: 0 | X85: 0 | Y85: 0 | Z85: =IFERROR(SUM(N85:Y85),0) -> 0 | AA85: =IFERROR((N85+Q85+T85+W85)-M85,0) -> 0 | AB85: =IFERROR(Z85,0) -> 0 | AC85: =IFERROR(L85-AB85,0) -> 0
A86: 81 | B86: =IFERROR([1]SYNC_PROSPECTION_MKT!$B$85,"") -> 0 | C86: =IFERROR([1]SYNC_PROSPECTION_MKT!$C$85,"") -> 0 | D86: =IFERROR([1]SYNC_PROSPECTION_MKT!$D$85,"") -> 0 | E86: =IFERROR([1]SYNC_PROSPECTION_MKT!$E$85,"") -> 0 | F86: =IFERROR([1]SYNC_PROSPECTION_MKT!$G$85,"") -> 0 | G86: =IFERROR([1]SYNC_PROSPECTION_MKT!$H$85,"") -> 0 | H86: =IFERROR([1]SYNC_PROSPECTION_MKT!$J$85,"") -> 0 | I86: =IFERROR([1]SYNC_PROSPECTION_MKT!$I$85,"") -> 0 | J86: =IFERROR([1]SYNC_PROSPECTION_MKT!$K$85,"") -> 0 | K86: =IFERROR(SYNC_FINANCE!$I$85,"") -> 0 | L86: =IFERROR([2]SYNC_COMMERCIAL_VENTE!$S$85,"") -> 0 | M86: 0 | N86: 0 | O86: 0 | P86: 0 | Q86: 0 | R86: 0 | S86: 0 | T86: 0 | U86: 0 | V86: 0 | W86: 0 | X86: 0 | Y86: 0 | Z86: =IFERROR(SUM(N86:Y86),0) -> 0 | AA86: =IFERROR((N86+Q86+T86+W86)-M86,0) -> 0 | AB86: =IFERROR(Z86,0) -> 0 | AC86: =IFERROR(L86-AB86,0) -> 0
A87: 82 | B87: =IFERROR([1]SYNC_PROSPECTION_MKT!$B$86,"") -> 0 | C87: =IFERROR([1]SYNC_PROSPECTION_MKT!$C$86,"") -> 0 | D87: =IFERROR([1]SYNC_PROSPECTION_MKT!$D$86,"") -> 0 | E87: =IFERROR([1]SYNC_PROSPECTION_MKT!$E$86,"") -> 0 | F87: =IFERROR([1]SYNC_PROSPECTION_MKT!$G$86,"") -> 0 | G87: =IFERROR([1]SYNC_PROSPECTION_MKT!$H$86,"") -> 0 | H87: =IFERROR([1]SYNC_PROSPECTION_MKT!$J$86,"") -> 0 | I87: =IFERROR([1]SYNC_PROSPECTION_MKT!$I$86,"") -> 0 | J87: =IFERROR([1]SYNC_PROSPECTION_MKT!$K$86,"") -> 0 | K87: =IFERROR(SYNC_FINANCE!$I$86,"") -> 0 | L87: =IFERROR([2]SYNC_COMMERCIAL_VENTE!$S$86,"") -> 0 | M87: 0 | N87: 0 | O87: 0 | P87: 0 | Q87: 0 | R87: 0 | S87: 0 | T87: 0 | U87: 0 | V87: 0 | W87: 0 | X87: 0 | Y87: 0 | Z87: =IFERROR(SUM(N87:Y87),0) -> 0 | AA87: =IFERROR((N87+Q87+T87+W87)-M87,0) -> 0 | AB87: =IFERROR(Z87,0) -> 0 | AC87: =IFERROR(L87-AB87,0) -> 0
A88: 83 | B88: =IFERROR([1]SYNC_PROSPECTION_MKT!$B$87,"") -> 0 | C88: =IFERROR([1]SYNC_PROSPECTION_MKT!$C$87,"") -> 0 | D88: =IFERROR([1]SYNC_PROSPECTION_MKT!$D$87,"") -> 0 | E88: =IFERROR([1]SYNC_PROSPECTION_MKT!$E$87,"") -> 0 | F88: =IFERROR([1]SYNC_PROSPECTION_MKT!$G$87,"") -> 0 | G88: =IFERROR([1]SYNC_PROSPECTION_MKT!$H$87,"") -> 0 | H88: =IFERROR([1]SYNC_PROSPECTION_MKT!$J$87,"") -> 0 | I88: =IFERROR([1]SYNC_PROSPECTION_MKT!$I$87,"") -> 0 | J88: =IFERROR([1]SYNC_PROSPECTION_MKT!$K$87,"") -> 0 | K88: =IFERROR(SYNC_FINANCE!$I$87,"") -> 0 | L88: =IFERROR([2]SYNC_COMMERCIAL_VENTE!$S$87,"") -> 0 | M88: 0 | N88: 0 | O88: 0 | P88: 0 | Q88: 0 | R88: 0 | S88: 0 | T88: 0 | U88: 0 | V88: 0 | W88: 0 | X88: 0 | Y88: 0 | Z88: =IFERROR(SUM(N88:Y88),0) -> 0 | AA88: =IFERROR((N88+Q88+T88+W88)-M88,0) -> 0 | AB88: =IFERROR(Z88,0) -> 0 | AC88: =IFERROR(L88-AB88,0) -> 0
A89: 84 | B89: =IFERROR([1]SYNC_PROSPECTION_MKT!$B$88,"") -> 0 | C89: =IFERROR([1]SYNC_PROSPECTION_MKT!$C$88,"") -> 0 | D89: =IFERROR([1]SYNC_PROSPECTION_MKT!$D$88,"") -> 0 | E89: =IFERROR([1]SYNC_PROSPECTION_MKT!$E$88,"") -> 0 | F89: =IFERROR([1]SYNC_PROSPECTION_MKT!$G$88,"") -> 0 | G89: =IFERROR([1]SYNC_PROSPECTION_MKT!$H$88,"") -> 0 | H89: =IFERROR([1]SYNC_PROSPECTION_MKT!$J$88,"") -> 0 | I89: =IFERROR([1]SYNC_PROSPECTION_MKT!$I$88,"") -> 0 | J89: =IFERROR([1]SYNC_PROSPECTION_MKT!$K$88,"") -> 0 | K89: =IFERROR(SYNC_FINANCE!$I$88,"") -> 0 | L89: =IFERROR([2]SYNC_COMMERCIAL_VENTE!$S$88,"") -> 0 | M89: 0 | N89: 0 | O89: 0 | P89: 0 | Q89: 0 | R89: 0 | S89: 0 | T89: 0 | U89: 0 | V89: 0 | W89: 0 | X89: 0 | Y89: 0 | Z89: =IFERROR(SUM(N89:Y89),0) -> 0 | AA89: =IFERROR((N89+Q89+T89+W89)-M89,0) -> 0 | AB89: =IFERROR(Z89,0) -> 0 | AC89: =IFERROR(L89-AB89,0) -> 0
A90: 85 | B90: =IFERROR([1]SYNC_PROSPECTION_MKT!$B$89,"") -> 0 | C90: =IFERROR([1]SYNC_PROSPECTION_MKT!$C$89,"") -> 0 | D90: =IFERROR([1]SYNC_PROSPECTION_MKT!$D$89,"") -> 0 | E90: =IFERROR([1]SYNC_PROSPECTION_MKT!$E$89,"") -> 0 | F90: =IFERROR([1]SYNC_PROSPECTION_MKT!$G$89,"") -> 0 | G90: =IFERROR([1]SYNC_PROSPECTION_MKT!$H$89,"") -> 0 | H90: =IFERROR([1]SYNC_PROSPECTION_MKT!$J$89,"") -> 0 | I90: =IFERROR([1]SYNC_PROSPECTION_MKT!$I$89,"") -> 0 | J90: =IFERROR([1]SYNC_PROSPECTION_MKT!$K$89,"") -> 0 | K90: =IFERROR(SYNC_FINANCE!$I$89,"") -> 0 | L90: =IFERROR([2]SYNC_COMMERCIAL_VENTE!$S$89,"") -> 0 | M90: 0 | N90: 0 | O90: 0 | P90: 0 | Q90: 0 | R90: 0 | S90: 0 | T90: 0 | U90: 0 | V90: 0 | W90: 0 | X90: 0 | Y90: 0 | Z90: =IFERROR(SUM(N90:Y90),0) -> 0 | AA90: =IFERROR((N90+Q90+T90+W90)-M90,0) -> 0 | AB90: =IFERROR(Z90,0) -> 0 | AC90: =IFERROR(L90-AB90,0) -> 0
A91: 86 | B91: =IFERROR([1]SYNC_PROSPECTION_MKT!$B$90,"") -> 0 | C91: =IFERROR([1]SYNC_PROSPECTION_MKT!$C$90,"") -> 0 | D91: =IFERROR([1]SYNC_PROSPECTION_MKT!$D$90,"") -> 0 | E91: =IFERROR([1]SYNC_PROSPECTION_MKT!$E$90,"") -> 0 | F91: =IFERROR([1]SYNC_PROSPECTION_MKT!$G$90,"") -> 0 | G91: =IFERROR([1]SYNC_PROSPECTION_MKT!$H$90,"") -> 0 | H91: =IFERROR([1]SYNC_PROSPECTION_MKT!$J$90,"") -> 0 | I91: =IFERROR([1]SYNC_PROSPECTION_MKT!$I$90,"") -> 0 | J91: =IFERROR([1]SYNC_PROSPECTION_MKT!$K$90,"") -> 0 | K91: =IFERROR(SYNC_FINANCE!$I$90,"") -> 0 | L91: =IFERROR([2]SYNC_COMMERCIAL_VENTE!$S$90,"") -> 0 | M91: 0 | N91: 0 | O91: 0 | P91: 0 | Q91: 0 | R91: 0 | S91: 0 | T91: 0 | U91: 0 | V91: 0 | W91: 0 | X91: 0 | Y91: 0 | Z91: =IFERROR(SUM(N91:Y91),0) -> 0 | AA91: =IFERROR((N91+Q91+T91+W91)-M91,0) -> 0 | AB91: =IFERROR(Z91,0) -> 0 | AC91: =IFERROR(L91-AB91,0) -> 0
A92: 87 | B92: =IFERROR([1]SYNC_PROSPECTION_MKT!$B$91,"") -> 0 | C92: =IFERROR([1]SYNC_PROSPECTION_MKT!$C$91,"") -> 0 | D92: =IFERROR([1]SYNC_PROSPECTION_MKT!$D$91,"") -> 0 | E92: =IFERROR([1]SYNC_PROSPECTION_MKT!$E$91,"") -> 0 | F92: =IFERROR([1]SYNC_PROSPECTION_MKT!$G$91,"") -> 0 | G92: =IFERROR([1]SYNC_PROSPECTION_MKT!$H$91,"") -> 0 | H92: =IFERROR([1]SYNC_PROSPECTION_MKT!$J$91,"") -> 0 | I92: =IFERROR([1]SYNC_PROSPECTION_MKT!$I$91,"") -> 0 | J92: =IFERROR([1]SYNC_PROSPECTION_MKT!$K$91,"") -> 0 | K92: =IFERROR(SYNC_FINANCE!$I$91,"") -> 0 | L92: =IFERROR([2]SYNC_COMMERCIAL_VENTE!$S$91,"") -> 0 | M92: 0 | N92: 0 | O92: 0 | P92: 0 | Q92: 0 | R92: 0 | S92: 0 | T92: 0 | U92: 0 | V92: 0 | W92: 0 | X92: 0 | Y92: 0 | Z92: =IFERROR(SUM(N92:Y92),0) -> 0 | AA92: =IFERROR((N92+Q92+T92+W92)-M92,0) -> 0 | AB92: =IFERROR(Z92,0) -> 0 | AC92: =IFERROR(L92-AB92,0) -> 0
A93: 88 | B93: =IFERROR([1]SYNC_PROSPECTION_MKT!$B$92,"") -> 0 | C93: =IFERROR([1]SYNC_PROSPECTION_MKT!$C$92,"") -> 0 | D93: =IFERROR([1]SYNC_PROSPECTION_MKT!$D$92,"") -> 0 | E93: =IFERROR([1]SYNC_PROSPECTION_MKT!$E$92,"") -> 0 | F93: =IFERROR([1]SYNC_PROSPECTION_MKT!$G$92,"") -> 0 | G93: =IFERROR([1]SYNC_PROSPECTION_MKT!$H$92,"") -> 0 | H93: =IFERROR([1]SYNC_PROSPECTION_MKT!$J$92,"") -> 0 | I93: =IFERROR([1]SYNC_PROSPECTION_MKT!$I$92,"") -> 0 | J93: =IFERROR([1]SYNC_PROSPECTION_MKT!$K$92,"") -> 0 | K93: =IFERROR(SYNC_FINANCE!$I$92,"") -> 0 | L93: =IFERROR([2]SYNC_COMMERCIAL_VENTE!$S$92,"") -> 0 | M93: 0 | N93: 0 | O93: 0 | P93: 0 | Q93: 0 | R93: 0 | S93: 0 | T93: 0 | U93: 0 | V93: 0 | W93: 0 | X93: 0 | Y93: 0 | Z93: =IFERROR(SUM(N93:Y93),0) -> 0 | AA93: =IFERROR((N93+Q93+T93+W93)-M93,0) -> 0 | AB93: =IFERROR(Z93,0) -> 0 | AC93: =IFERROR(L93-AB93,0) -> 0
A94: 89 | B94: =IFERROR([1]SYNC_PROSPECTION_MKT!$B$93,"") -> 0 | C94: =IFERROR([1]SYNC_PROSPECTION_MKT!$C$93,"") -> 0 | D94: =IFERROR([1]SYNC_PROSPECTION_MKT!$D$93,"") -> 0 | E94: =IFERROR([1]SYNC_PROSPECTION_MKT!$E$93,"") -> 0 | F94: =IFERROR([1]SYNC_PROSPECTION_MKT!$G$93,"") -> 0 | G94: =IFERROR([1]SYNC_PROSPECTION_MKT!$H$93,"") -> 0 | H94: =IFERROR([1]SYNC_PROSPECTION_MKT!$J$93,"") -> 0 | I94: =IFERROR([1]SYNC_PROSPECTION_MKT!$I$93,"") -> 0 | J94: =IFERROR([1]SYNC_PROSPECTION_MKT!$K$93,"") -> 0 | K94: =IFERROR(SYNC_FINANCE!$I$93,"") -> 0 | L94: =IFERROR([2]SYNC_COMMERCIAL_VENTE!$S$93,"") -> 0 | M94: 0 | N94: 0 | O94: 0 | P94: 0 | Q94: 0 | R94: 0 | S94: 0 | T94: 0 | U94: 0 | V94: 0 | W94: 0 | X94: 0 | Y94: 0 | Z94: =IFERROR(SUM(N94:Y94),0) -> 0 | AA94: =IFERROR((N94+Q94+T94+W94)-M94,0) -> 0 | AB94: =IFERROR(Z94,0) -> 0 | AC94: =IFERROR(L94-AB94,0) -> 0
A95: 90 | B95: =IFERROR([1]SYNC_PROSPECTION_MKT!$B$94,"") -> 0 | C95: =IFERROR([1]SYNC_PROSPECTION_MKT!$C$94,"") -> 0 | D95: =IFERROR([1]SYNC_PROSPECTION_MKT!$D$94,"") -> 0 | E95: =IFERROR([1]SYNC_PROSPECTION_MKT!$E$94,"") -> 0 | F95: =IFERROR([1]SYNC_PROSPECTION_MKT!$G$94,"") -> 0 | G95: =IFERROR([1]SYNC_PROSPECTION_MKT!$H$94,"") -> 0 | H95: =IFERROR([1]SYNC_PROSPECTION_MKT!$J$94,"") -> 0 | I95: =IFERROR([1]SYNC_PROSPECTION_MKT!$I$94,"") -> 0 | J95: =IFERROR([1]SYNC_PROSPECTION_MKT!$K$94,"") -> 0 | K95: =IFERROR(SYNC_FINANCE!$I$94,"") -> 0 | L95: =IFERROR([2]SYNC_COMMERCIAL_VENTE!$S$94,"") -> 0 | M95: 0 | N95: 0 | O95: 0 | P95: 0 | Q95: 0 | R95: 0 | S95: 0 | T95: 0 | U95: 0 | V95: 0 | W95: 0 | X95: 0 | Y95: 0 | Z95: =IFERROR(SUM(N95:Y95),0) -> 0 | AA95: =IFERROR((N95+Q95+T95+W95)-M95,0) -> 0 | AB95: =IFERROR(Z95,0) -> 0 | AC95: =IFERROR(L95-AB95,0) -> 0
A96: 91 | B96: =IFERROR([1]SYNC_PROSPECTION_MKT!$B$95,"") -> 0 | C96: =IFERROR([1]SYNC_PROSPECTION_MKT!$C$95,"") -> 0 | D96: =IFERROR([1]SYNC_PROSPECTION_MKT!$D$95,"") -> 0 | E96: =IFERROR([1]SYNC_PROSPECTION_MKT!$E$95,"") -> 0 | F96: =IFERROR([1]SYNC_PROSPECTION_MKT!$G$95,"") -> 0 | G96: =IFERROR([1]SYNC_PROSPECTION_MKT!$H$95,"") -> 0 | H96: =IFERROR([1]SYNC_PROSPECTION_MKT!$J$95,"") -> 0 | I96: =IFERROR([1]SYNC_PROSPECTION_MKT!$I$95,"") -> 0 | J96: =IFERROR([1]SYNC_PROSPECTION_MKT!$K$95,"") -> 0 | K96: =IFERROR(SYNC_FINANCE!$I$95,"") -> 0 | L96: =IFERROR([2]SYNC_COMMERCIAL_VENTE!$S$95,"") -> 0 | M96: 0 | N96: 0 | O96: 0 | P96: 0 | Q96: 0 | R96: 0 | S96: 0 | T96: 0 | U96: 0 | V96: 0 | W96: 0 | X96: 0 | Y96: 0 | Z96: =IFERROR(SUM(N96:Y96),0) -> 0 | AA96: =IFERROR((N96+Q96+T96+W96)-M96,0) -> 0 | AB96: =IFERROR(Z96,0) -> 0 | AC96: =IFERROR(L96-AB96,0) -> 0
A97: 92 | B97: =IFERROR([1]SYNC_PROSPECTION_MKT!$B$96,"") -> 0 | C97: =IFERROR([1]SYNC_PROSPECTION_MKT!$C$96,"") -> 0 | D97: =IFERROR([1]SYNC_PROSPECTION_MKT!$D$96,"") -> 0 | E97: =IFERROR([1]SYNC_PROSPECTION_MKT!$E$96,"") -> 0 | F97: =IFERROR([1]SYNC_PROSPECTION_MKT!$G$96,"") -> 0 | G97: =IFERROR([1]SYNC_PROSPECTION_MKT!$H$96,"") -> 0 | H97: =IFERROR([1]SYNC_PROSPECTION_MKT!$J$96,"") -> 0 | I97: =IFERROR([1]SYNC_PROSPECTION_MKT!$I$96,"") -> 0 | J97: =IFERROR([1]SYNC_PROSPECTION_MKT!$K$96,"") -> 0 | K97: =IFERROR(SYNC_FINANCE!$I$96,"") -> 0 | L97: =IFERROR([2]SYNC_COMMERCIAL_VENTE!$S$96,"") -> 0 | M97: 0 | N97: 0 | O97: 0 | P97: 0 | Q97: 0 | R97: 0 | S97: 0 | T97: 0 | U97: 0 | V97: 0 | W97: 0 | X97: 0 | Y97: 0 | Z97: =IFERROR(SUM(N97:Y97),0) -> 0 | AA97: =IFERROR((N97+Q97+T97+W97)-M97,0) -> 0 | AB97: =IFERROR(Z97,0) -> 0 | AC97: =IFERROR(L97-AB97,0) -> 0
A98: 93 | B98: =IFERROR([1]SYNC_PROSPECTION_MKT!$B$97,"") -> 0 | C98: =IFERROR([1]SYNC_PROSPECTION_MKT!$C$97,"") -> 0 | D98: =IFERROR([1]SYNC_PROSPECTION_MKT!$D$97,"") -> 0 | E98: =IFERROR([1]SYNC_PROSPECTION_MKT!$E$97,"") -> 0 | F98: =IFERROR([1]SYNC_PROSPECTION_MKT!$G$97,"") -> 0 | G98: =IFERROR([1]SYNC_PROSPECTION_MKT!$H$97,"") -> 0 | H98: =IFERROR([1]SYNC_PROSPECTION_MKT!$J$97,"") -> 0 | I98: =IFERROR([1]SYNC_PROSPECTION_MKT!$I$97,"") -> 0 | J98: =IFERROR([1]SYNC_PROSPECTION_MKT!$K$97,"") -> 0 | K98: =IFERROR(SYNC_FINANCE!$I$97,"") -> 0 | L98: =IFERROR([2]SYNC_COMMERCIAL_VENTE!$S$97,"") -> 0 | M98: 0 | N98: 0 | O98: 0 | P98: 0 | Q98: 0 | R98: 0 | S98: 0 | T98: 0 | U98: 0 | V98: 0 | W98: 0 | X98: 0 | Y98: 0 | Z98: =IFERROR(SUM(N98:Y98),0) -> 0 | AA98: =IFERROR((N98+Q98+T98+W98)-M98,0) -> 0 | AB98: =IFERROR(Z98,0) -> 0 | AC98: =IFERROR(L98-AB98,0) -> 0
A99: 94 | B99: =IFERROR([1]SYNC_PROSPECTION_MKT!$B$98,"") -> 0 | C99: =IFERROR([1]SYNC_PROSPECTION_MKT!$C$98,"") -> 0 | D99: =IFERROR([1]SYNC_PROSPECTION_MKT!$D$98,"") -> 0 | E99: =IFERROR([1]SYNC_PROSPECTION_MKT!$E$98,"") -> 0 | F99: =IFERROR([1]SYNC_PROSPECTION_MKT!$G$98,"") -> 0 | G99: =IFERROR([1]SYNC_PROSPECTION_MKT!$H$98,"") -> 0 | H99: =IFERROR([1]SYNC_PROSPECTION_MKT!$J$98,"") -> 0 | I99: =IFERROR([1]SYNC_PROSPECTION_MKT!$I$98,"") -> 0 | J99: =IFERROR([1]SYNC_PROSPECTION_MKT!$K$98,"") -> 0 | K99: =IFERROR(SYNC_FINANCE!$I$98,"") -> 0 | L99: =IFERROR([2]SYNC_COMMERCIAL_VENTE!$S$98,"") -> 0 | M99: 0 | N99: 0 | O99: 0 | P99: 0 | Q99: 0 | R99: 0 | S99: 0 | T99: 0 | U99: 0 | V99: 0 | W99: 0 | X99: 0 | Y99: 0 | Z99: =IFERROR(SUM(N99:Y99),0) -> 0 | AA99: =IFERROR((N99+Q99+T99+W99)-M99,0) -> 0 | AB99: =IFERROR(Z99,0) -> 0 | AC99: =IFERROR(L99-AB99,0) -> 0
A100: 95 | B100: =IFERROR([1]SYNC_PROSPECTION_MKT!$B$99,"") -> 0 | C100: =IFERROR([1]SYNC_PROSPECTION_MKT!$C$99,"") -> 0 | D100: =IFERROR([1]SYNC_PROSPECTION_MKT!$D$99,"") -> 0 | E100: =IFERROR([1]SYNC_PROSPECTION_MKT!$E$99,"") -> 0 | F100: =IFERROR([1]SYNC_PROSPECTION_MKT!$G$99,"") -> 0 | G100: =IFERROR([1]SYNC_PROSPECTION_MKT!$H$99,"") -> 0 | H100: =IFERROR([1]SYNC_PROSPECTION_MKT!$J$99,"") -> 0 | I100: =IFERROR([1]SYNC_PROSPECTION_MKT!$I$99,"") -> 0 | J100: =IFERROR([1]SYNC_PROSPECTION_MKT!$K$99,"") -> 0 | K100: =IFERROR(SYNC_FINANCE!$I$99,"") -> 0 | L100: =IFERROR([2]SYNC_COMMERCIAL_VENTE!$S$99,"") -> 0 | M100: 0 | N100: 0 | O100: 0 | P100: 0 | Q100: 0 | R100: 0 | S100: 0 | T100: 0 | U100: 0 | V100: 0 | W100: 0 | X100: 0 | Y100: 0 | Z100: =IFERROR(SUM(N100:Y100),0) -> 0 | AA100: =IFERROR((N100+Q100+T100+W100)-M100,0) -> 0 | AB100: =IFERROR(Z100,0) -> 0 | AC100: =IFERROR(L100-AB100,0) -> 0
...

Sheet PAIEMENTS AOUT 2026
A1: 💰 PAIEMENTS AOUT 2026 — LEMI SARL | BRASUS v3.2
A2: ⚠️ Saisie des paiements reçus par semaine. Alimente automatiquement le SUIVI 13 MOIS.
A3: 🔒 Identité client (auto) | K3: 📋 Contrat | N3: ✏️ PAIEMENTS AOÛT — 4 semaines × (Paiement + Droit + Apport) | Z3: ⚙️ CALCULS AUTO
N4: 01/08-07/08 | Q4: 08/08-15/08 | T4: 16/08-24/08 | W4: 25/08-31/08
A5: N° | B5: N° IDENTIFIANT | C5: NOM & PRÉNOMS DU CLIENT | D5: SOURCE DU PROSPECT | E5: DATE PREMIER CONTACT | F5: TÉLÉPHONE / WHATSAPP | G5: PROFESSION | H5: RÉGION D'HABITATION | I5: RÉGION DU PROJET | J5: LIEU DU PROJET | K5: N° CONTRAT | L5: MONTANT TTC (FCFA) | M5: MENSUALITÉ (FCFA) | N5: PAIEMENT | O5: DROIT ADHÉSION | P5: APPORT INITIAL | Q5: PAIEMENT | R5: DROIT ADHÉSION | S5: APPORT INITIAL | T5: PAIEMENT | U5: DROIT ADHÉSION | V5: APPORT INITIAL | W5: PAIEMENT | X5: DROIT ADHÉSION | Y5: APPORT INITIAL | Z5: TOTAL MOIS | AA5: MENSUALITÉ DUE | AB5: CUMUL PAIEMENTS | AC5: RESTANT DÛ
A6: 1 | B6: =IFERROR([1]SYNC_PROSPECTION_MKT!$B$5,"") -> 0 | C6: =IFERROR([1]SYNC_PROSPECTION_MKT!$C$5,"") -> TANOH KONAN GERVAIS ARMAND | D6: =IFERROR([1]SYNC_PROSPECTION_MKT!$D$5,"") -> 0 | E6: =IFERROR([1]SYNC_PROSPECTION_MKT!$E$5,"") -> 0 | F6: =IFERROR([1]SYNC_PROSPECTION_MKT!$G$5,"") -> 0 | G6: =IFERROR([1]SYNC_PROSPECTION_MKT!$H$5,"") -> 0 | H6: =IFERROR([1]SYNC_PROSPECTION_MKT!$J$5,"") -> 0 | I6: =IFERROR([1]SYNC_PROSPECTION_MKT!$I$5,"") -> 0 | J6: =IFERROR([1]SYNC_PROSPECTION_MKT!$K$5,"") -> 0 | K6: =IFERROR(SYNC_FINANCE!$I$5,"") -> 0 | L6: =IFERROR([2]SYNC_COMMERCIAL_VENTE!$S$5,"") -> 0 | M6: 0 | N6: 0 | O6: 0 | P6: 0 | Q6: 0 | R6: 0 | S6: 0 | T6: 0 | U6: 0 | V6: 0 | W6: 0 | X6: 0 | Y6: 0 | Z6: =IFERROR(SUM(N6:Y6),0) -> 0 | AA6: =IFERROR((N6+Q6+T6+W6)-M6,0) -> 0 | AB6: =IFERROR(Z6,0) -> 0 | AC6: =IFERROR(L6-AB6,0) -> 0
A7: 2 | B7: =IFERROR([1]SYNC_PROSPECTION_MKT!$B$6,"") -> 0 | C7: =IFERROR([1]SYNC_PROSPECTION_MKT!$C$6,"") -> N'DRI ép. NGBESSO AKISSI ELIANE | D7: =IFERROR([1]SYNC_PROSPECTION_MKT!$D$6,"") -> 0 | E7: =IFERROR([1]SYNC_PROSPECTION_MKT!$E$6,"") -> 0 | F7: =IFERROR([1]SYNC_PROSPECTION_MKT!$G$6,"") -> 0 | G7: =IFERROR([1]SYNC_PROSPECTION_MKT!$H$6,"") -> 0 | H7: =IFERROR([1]SYNC_PROSPECTION_MKT!$J$6,"") -> 0 | I7: =IFERROR([1]SYNC_PROSPECTION_MKT!$I$6,"") -> 0 | J7: =IFERROR([1]SYNC_PROSPECTION_MKT!$K$6,"") -> 0 | K7: =IFERROR(SYNC_FINANCE!$I$6,"") -> 0 | L7: =IFERROR([2]SYNC_COMMERCIAL_VENTE!$S$6,"") -> 0 | M7: 0 | N7: 0 | O7: 0 | P7: 0 | Q7: 0 | R7: 0 | S7: 0 | T7: 0 | U7: 0 | V7: 0 | W7: 0 | X7: 0 | Y7: 0 | Z7: =IFERROR(SUM(N7:Y7),0) -> 0 | AA7: =IFERROR((N7+Q7+T7+W7)-M7,0) -> 0 | AB7: =IFERROR(Z7,0) -> 0 | AC7: =IFERROR(L7-AB7,0) -> 0
A8: 3 | B8: =IFERROR([1]SYNC_PROSPECTION_MKT!$B$7,"") -> 0 | C8: =IFERROR([1]SYNC_PROSPECTION_MKT!$C$7,"") -> N'GORAN KOFFI | D8: =IFERROR([1]SYNC_PROSPECTION_MKT!$D$7,"") -> 0 | E8: =IFERROR([1]SYNC_PROSPECTION_MKT!$E$7,"") -> 0 | F8: =IFERROR([1]SYNC_PROSPECTION_MKT!$G$7,"") -> 0 | G8: =IFERROR([1]SYNC_PROSPECTION_MKT!$H$7,"") -> 0 | H8: =IFERROR([1]SYNC_PROSPECTION_MKT!$J$7,"") -> 0 | I8: =IFERROR([1]SYNC_PROSPECTION_MKT!$I$7,"") -> 0 | J8: =IFERROR([1]SYNC_PROSPECTION_MKT!$K$7,"") -> 0 | K8: =IFERROR(SYNC_FINANCE!$I$7,"") -> 0 | L8: =IFERROR([2]SYNC_COMMERCIAL_VENTE!$S$7,"") -> 0 | M8: 0 | N8: 0 | O8: 0 | P8: 0 | Q8: 0 | R8: 0 | S8: 0 | T8: 0 | U8: 0 | V8: 0 | W8: 0 | X8: 0 | Y8: 0 | Z8: =IFERROR(SUM(N8:Y8),0) -> 0 | AA8: =IFERROR((N8+Q8+T8+W8)-M8,0) -> 0 | AB8: =IFERROR(Z8,0) -> 0 | AC8: =IFERROR(L8-AB8,0) -> 0
A9: 4 | B9: =IFERROR([1]SYNC_PROSPECTION_MKT!$B$8,"") -> 0 | C9: =IFERROR([1]SYNC_PROSPECTION_MKT!$C$8,"") -> KOUASSI VINCENT DE PAUL ASSOUMOU | D9: =IFERROR([1]SYNC_PROSPECTION_MKT!$D$8,"") -> 0 | E9: =IFERROR([1]SYNC_PROSPECTION_MKT!$E$8,"") -> 0 | F9: =IFERROR([1]SYNC_PROSPECTION_MKT!$G$8,"") -> 0 | G9: =IFERROR([1]SYNC_PROSPECTION_MKT!$H$8,"") -> 0 | H9: =IFERROR([1]SYNC_PROSPECTION_MKT!$J$8,"") -> 0 | I9: =IFERROR([1]SYNC_PROSPECTION_MKT!$I$8,"") -> 0 | J9: =IFERROR([1]SYNC_PROSPECTION_MKT!$K$8,"") -> 0 | K9: =IFERROR(SYNC_FINANCE!$I$8,"") -> 0 | L9: =IFERROR([2]SYNC_COMMERCIAL_VENTE!$S$8,"") -> 0 | M9: 0 | N9: 0 | O9: 0 | P9: 0 | Q9: 0 | R9: 0 | S9: 0 | T9: 0 | U9: 0 | V9: 0 | W9: 0 | X9: 0 | Y9: 0 | Z9: =IFERROR(SUM(N9:Y9),0) -> 0 | AA9: =IFERROR((N9+Q9+T9+W9)-M9,0) -> 0 | AB9: =IFERROR(Z9,0) -> 0 | AC9: =IFERROR(L9-AB9,0) -> 0
A10: 5 | B10: =IFERROR([1]SYNC_PROSPECTION_MKT!$B$9,"") -> 0 | C10: =IFERROR([1]SYNC_PROSPECTION_MKT!$C$9,"") -> KOUASSI HONORE | D10: =IFERROR([1]SYNC_PROSPECTION_MKT!$D$9,"") -> 0 | E10: =IFERROR([1]SYNC_PROSPECTION_MKT!$E$9,"") -> 0 | F10: =IFERROR([1]SYNC_PROSPECTION_MKT!$G$9,"") -> 0 | G10: =IFERROR([1]SYNC_PROSPECTION_MKT!$H$9,"") -> 0 | H10: =IFERROR([1]SYNC_PROSPECTION_MKT!$J$9,"") -> 0 | I10: =IFERROR([1]SYNC_PROSPECTION_MKT!$I$9,"") -> 0 | J10: =IFERROR([1]SYNC_PROSPECTION_MKT!$K$9,"") -> 0 | K10: =IFERROR(SYNC_FINANCE!$I$9,"") -> 0 | L10: =IFERROR([2]SYNC_COMMERCIAL_VENTE!$S$9,"") -> 0 | M10: 0 | N10: 0 | O10: 0 | P10: 0 | Q10: 0 | R10: 0 | S10: 0 | T10: 0 | U10: 0 | V10: 0 | W10: 0 | X10: 0 | Y10: 0 | Z10: =IFERROR(SUM(N10:Y10),0) -> 0 | AA10: =IFERROR((N10+Q10+T10+W10)-M10,0) -> 0 | AB10: =IFERROR(Z10,0) -> 0 | AC10: =IFERROR(L10-AB10,0) -> 0
A11: 6 | B11: =IFERROR([1]SYNC_PROSPECTION_MKT!$B$10,"") -> 0 | C11: =IFERROR([1]SYNC_PROSPECTION_MKT!$C$10,"") -> AKISSI ELIANE KONAN | D11: =IFERROR([1]SYNC_PROSPECTION_MKT!$D$10,"") -> 0 | E11: =IFERROR([1]SYNC_PROSPECTION_MKT!$E$10,"") -> 0 | F11: =IFERROR([1]SYNC_PROSPECTION_MKT!$G$10,"") -> 0 | G11: =IFERROR([1]SYNC_PROSPECTION_MKT!$H$10,"") -> 0 | H11: =IFERROR([1]SYNC_PROSPECTION_MKT!$J$10,"") -> 0 | I11: =IFERROR([1]SYNC_PROSPECTION_MKT!$I$10,"") -> 0 | J11: =IFERROR([1]SYNC_PROSPECTION_MKT!$K$10,"") -> 0 | K11: =IFERROR(SYNC_FINANCE!$I$10,"") -> 0 | L11: =IFERROR([2]SYNC_COMMERCIAL_VENTE!$S$10,"") -> 0 | M11: 0 | N11: 0 | O11: 0 | P11: 0 | Q11: 0 | R11: 0 | S11: 0 | T11: 0 | U11: 0 | V11: 0 | W11: 0 | X11: 0 | Y11: 0 | Z11: =IFERROR(SUM(N11:Y11),0) -> 0 | AA11: =IFERROR((N11+Q11+T11+W11)-M11,0) -> 0 | AB11: =IFERROR(Z11,0) -> 0 | AC11: =IFERROR(L11-AB11,0) -> 0
A12: 7 | B12: =IFERROR([1]SYNC_PROSPECTION_MKT!$B$11,"") -> 0 | C12: =IFERROR([1]SYNC_PROSPECTION_MKT!$C$11,"") -> BROU LAMBERT KOUASSI | D12: =IFERROR([1]SYNC_PROSPECTION_MKT!$D$11,"") -> 0 | E12: =IFERROR([1]SYNC_PROSPECTION_MKT!$E$11,"") -> 0 | F12: =IFERROR([1]SYNC_PROSPECTION_MKT!$G$11,"") -> 0 | G12: =IFERROR([1]SYNC_PROSPECTION_MKT!$H$11,"") -> 0 | H12: =IFERROR([1]SYNC_PROSPECTION_MKT!$J$11,"") -> 0 | I12: =IFERROR([1]SYNC_PROSPECTION_MKT!$I$11,"") -> 0 | J12: =IFERROR([1]SYNC_PROSPECTION_MKT!$K$11,"") -> 0 | K12: =IFERROR(SYNC_FINANCE!$I$11,"") -> 0 | L12: =IFERROR([2]SYNC_COMMERCIAL_VENTE!$S$11,"") -> 0 | M12: 0 | N12: 0 | O12: 0 | P12: 0 | Q12: 0 | R12: 0 | S12: 0 | T12: 0 | U12: 0 | V12: 0 | W12: 0 | X12: 0 | Y12: 0 | Z12: =IFERROR(SUM(N12:Y12),0) -> 0 | AA12: =IFERROR((N12+Q12+T12+W12)-M12,0) -> 0 | AB12: =IFERROR(Z12,0) -> 0 | AC12: =IFERROR(L12-AB12,0) -> 0
A13: 8 | B13: =IFERROR([1]SYNC_PROSPECTION_MKT!$B$12,"") -> 0 | C13: =IFERROR([1]SYNC_PROSPECTION_MKT!$C$12,"") -> DJEDRI KOUAKOU JEAN PIERRE | D13: =IFERROR([1]SYNC_PROSPECTION_MKT!$D$12,"") -> 0 | E13: =IFERROR([1]SYNC_PROSPECTION_MKT!$E$12,"") -> 0 | F13: =IFERROR([1]SYNC_PROSPECTION_MKT!$G$12,"") -> 0 | G13: =IFERROR([1]SYNC_PROSPECTION_MKT!$H$12,"") -> 0 | H13: =IFERROR([1]SYNC_PROSPECTION_MKT!$J$12,"") -> 0 | I13: =IFERROR([1]SYNC_PROSPECTION_MKT!$I$12,"") -> 0 | J13: =IFERROR([1]SYNC_PROSPECTION_MKT!$K$12,"") -> 0 | K13: =IFERROR(SYNC_FINANCE!$I$12,"") -> 0 | L13: =IFERROR([2]SYNC_COMMERCIAL_VENTE!$S$12,"") -> 0 | M13: 0 | N13: 0 | O13: 0 | P13: 0 | Q13: 0 | R13: 0 | S13: 0 | T13: 0 | U13: 0 | V13: 0 | W13: 0 | X13: 0 | Y13: 0 | Z13: =IFERROR(SUM(N13:Y13),0) -> 0 | AA13: =IFERROR((N13+Q13+T13+W13)-M13,0) -> 0 | AB13: =IFERROR(Z13,0) -> 0 | AC13: =IFERROR(L13-AB13,0) -> 0
A14: 9 | B14: =IFERROR([1]SYNC_PROSPECTION_MKT!$B$13,"") -> 0 | C14: =IFERROR([1]SYNC_PROSPECTION_MKT!$C$13,"") -> DJAMAN KOUAKOU MATHIEU | D14: =IFERROR([1]SYNC_PROSPECTION_MKT!$D$13,"") -> 0 | E14: =IFERROR([1]SYNC_PROSPECTION_MKT!$E$13,"") -> 0 | F14: =IFERROR([1]SYNC_PROSPECTION_MKT!$G$13,"") -> 0 | G14: =IFERROR([1]SYNC_PROSPECTION_MKT!$H$13,"") -> 0 | H14: =IFERROR([1]SYNC_PROSPECTION_MKT!$J$13,"") -> 0 | I14: =IFERROR([1]SYNC_PROSPECTION_MKT!$I$13,"") -> 0 | J14: =IFERROR([1]SYNC_PROSPECTION_MKT!$K$13,"") -> 0 | K14: =IFERROR(SYNC_FINANCE!$I$13,"") -> 0 | L14: =IFERROR([2]SYNC_COMMERCIAL_VENTE!$S$13,"") -> 0 | M14: 0 | N14: 0 | O14: 0 | P14: 0 | Q14: 0 | R14: 0 | S14: 0 | T14: 0 | U14: 0 | V14: 0 | W14: 0 | X14: 0 | Y14: 0 | Z14: =IFERROR(SUM(N14:Y14),0) -> 0 | AA14: =IFERROR((N14+Q14+T14+W14)-M14,0) -> 0 | AB14: =IFERROR(Z14,0) -> 0 | AC14: =IFERROR(L14-AB14,0) -> 0
A15: 10 | B15: =IFERROR([1]SYNC_PROSPECTION_MKT!$B$14,"") -> 0 | C15: =IFERROR([1]SYNC_PROSPECTION_MKT!$C$14,"") -> N'GUESSAN KOUASSI | D15: =IFERROR([1]SYNC_PROSPECTION_MKT!$D$14,"") -> 0 | E15: =IFERROR([1]SYNC_PROSPECTION_MKT!$E$14,"") -> 0 | F15: =IFERROR([1]SYNC_PROSPECTION_MKT!$G$14,"") -> 0 | G15: =IFERROR([1]SYNC_PROSPECTION_MKT!$H$14,"") -> 0 | H15: =IFERROR([1]SYNC_PROSPECTION_MKT!$J$14,"") -> 0 | I15: =IFERROR([1]SYNC_PROSPECTION_MKT!$I$14,"") -> 0 | J15: =IFERROR([1]SYNC_PROSPECTION_MKT!$K$14,"") -> 0 | K15: =IFERROR(SYNC_FINANCE!$I$14,"") -> 0 | L15: =IFERROR([2]SYNC_COMMERCIAL_VENTE!$S$14,"") -> 0 | M15: 0 | N15: 200000 | O15: 0 | P15: 5000000 | Q15: 0 | R15: 0 | S15: 0 | T15: 0 | U15: 0 | V15: 0 | W15: 0 | X15: 0 | Y15: 0 | Z15: =IFERROR(SUM(N15:Y15),0) -> 5200000 | AA15: =IFERROR((N15+Q15+T15+W15)-M15,0) -> 200000 | AB15: =IFERROR(Z15,0) -> 5200000 | AC15: =IFERROR(L15-AB15,0) -> -5200000
A16: 11 | B16: =IFERROR([1]SYNC_PROSPECTION_MKT!$B$15,"") -> 0 | C16: =IFERROR([1]SYNC_PROSPECTION_MKT!$C$15,"") -> N'ZUE N'GUESSAN | D16: =IFERROR([1]SYNC_PROSPECTION_MKT!$D$15,"") -> 0 | E16: =IFERROR([1]SYNC_PROSPECTION_MKT!$E$15,"") -> 0 | F16: =IFERROR([1]SYNC_PROSPECTION_MKT!$G$15,"") -> 0 | G16: =IFERROR([1]SYNC_PROSPECTION_MKT!$H$15,"") -> 0 | H16: =IFERROR([1]SYNC_PROSPECTION_MKT!$J$15,"") -> 0 | I16: =IFERROR([1]SYNC_PROSPECTION_MKT!$I$15,"") -> 0 | J16: =IFERROR([1]SYNC_PROSPECTION_MKT!$K$15,"") -> 0 | K16: =IFERROR(SYNC_FINANCE!$I$15,"") -> 0 | L16: =IFERROR([2]SYNC_COMMERCIAL_VENTE!$S$15,"") -> 0 | M16: 0 | N16: 0 | O16: 0 | P16: 0 | Q16: 0 | R16: 0 | S16: 0 | T16: 0 | U16: 0 | V16: 0 | W16: 0 | X16: 0 | Y16: 0 | Z16: =IFERROR(SUM(N16:Y16),0) -> 0 | AA16: =IFERROR((N16+Q16+T16+W16)-M16,0) -> 0 | AB16: =IFERROR(Z16,0) -> 0 | AC16: =IFERROR(L16-AB16,0) -> 0
A17: 12 | B17: =IFERROR([1]SYNC_PROSPECTION_MKT!$B$16,"") -> 0 | C17: =IFERROR([1]SYNC_PROSPECTION_MKT!$C$16,"") -> CASIMIR | D17: =IFERROR([1]SYNC_PROSPECTION_MKT!$D$16,"") -> 0 | E17: =IFERROR([1]SYNC_PROSPECTION_MKT!$E$16,"") -> 0 | F17: =IFERROR([1]SYNC_PROSPECTION_MKT!$G$16,"") -> 0 | G17: =IFERROR([1]SYNC_PROSPECTION_MKT!$H$16,"") -> 0 | H17: =IFERROR([1]SYNC_PROSPECTION_MKT!$J$16,"") -> 0 | I17: =IFERROR([1]SYNC_PROSPECTION_MKT!$I$16,"") -> 0 | J17: =IFERROR([1]SYNC_PROSPECTION_MKT!$K$16,"") -> 0 | K17: =IFERROR(SYNC_FINANCE!$I$16,"") -> 0 | L17: =IFERROR([2]SYNC_COMMERCIAL_VENTE!$S$16,"") -> 0 | M17: 0 | N17: 0 | O17: 0 | P17: 0 | Q17: 0 | R17: 0 | S17: 0 | T17: 0 | U17: 0 | V17: 0 | W17: 0 | X17: 0 | Y17: 0 | Z17: =IFERROR(SUM(N17:Y17),0) -> 0 | AA17: =IFERROR((N17+Q17+T17+W17)-M17,0) -> 0 | AB17: =IFERROR(Z17,0) -> 0 | AC17: =IFERROR(L17-AB17,0) -> 0
A18: 13 | B18: =IFERROR([1]SYNC_PROSPECTION_MKT!$B$17,"") -> 0 | C18: =IFERROR([1]SYNC_PROSPECTION_MKT!$C$17,"") -> 0 | D18: =IFERROR([1]SYNC_PROSPECTION_MKT!$D$17,"") -> 0 | E18: =IFERROR([1]SYNC_PROSPECTION_MKT!$E$17,"") -> 0 | F18: =IFERROR([1]SYNC_PROSPECTION_MKT!$G$17,"") -> 0 | G18: =IFERROR([1]SYNC_PROSPECTION_MKT!$H$17,"") -> 0 | H18: =IFERROR([1]SYNC_PROSPECTION_MKT!$J$17,"") -> 0 | I18: =IFERROR([1]SYNC_PROSPECTION_MKT!$I$17,"") -> 0 | J18: =IFERROR([1]SYNC_PROSPECTION_MKT!$K$17,"") -> 0 | K18: =IFERROR(SYNC_FINANCE!$I$17,"") -> 0 | L18: =IFERROR([2]SYNC_COMMERCIAL_VENTE!$S$17,"") -> 0 | M18: 0 | N18: 0 | O18: 0 | P18: 0 | Q18: 0 | R18: 0 | S18: 0 | T18: 0 | U18: 0 | V18: 0 | W18: 0 | X18: 0 | Y18: 0 | Z18: =IFERROR(SUM(N18:Y18),0) -> 0 | AA18: =IFERROR((N18+Q18+T18+W18)-M18,0) -> 0 | AB18: =IFERROR(Z18,0) -> 0 | AC18: =IFERROR(L18-AB18,0) -> 0
A19: 14 | B19: =IFERROR([1]SYNC_PROSPECTION_MKT!$B$18,"") -> 0 | C19: =IFERROR([1]SYNC_PROSPECTION_MKT!$C$18,"") -> 0 | D19: =IFERROR([1]SYNC_PROSPECTION_MKT!$D$18,"") -> 0 | E19: =IFERROR([1]SYNC_PROSPECTION_MKT!$E$18,"") -> 0 | F19: =IFERROR([1]SYNC_PROSPECTION_MKT!$G$18,"") -> 0 | G19: =IFERROR([1]SYNC_PROSPECTION_MKT!$H$18,"") -> 0 | H19: =IFERROR([1]SYNC_PROSPECTION_MKT!$J$18,"") -> 0 | I19: =IFERROR([1]SYNC_PROSPECTION_MKT!$I$18,"") -> 0 | J19: =IFERROR([1]SYNC_PROSPECTION_MKT!$K$18,"") -> 0 | K19: =IFERROR(SYNC_FINANCE!$I$18,"") -> 0 | L19: =IFERROR([2]SYNC_COMMERCIAL_VENTE!$S$18,"") -> 0 | M19: 0 | N19: 0 | O19: 0 | P19: 0 | Q19: 0 | R19: 0 | S19: 0 | T19: 0 | U19: 0 | V19: 0 | W19: 0 | X19: 0 | Y19: 0 | Z19: =IFERROR(SUM(N19:Y19),0) -> 0 | AA19: =IFERROR((N19+Q19+T19+W19)-M19,0) -> 0 | AB19: =IFERROR(Z19,0) -> 0 | AC19: =IFERROR(L19-AB19,0) -> 0
A20: 15 | B20: =IFERROR([1]SYNC_PROSPECTION_MKT!$B$19,"") -> 0 | C20: =IFERROR([1]SYNC_PROSPECTION_MKT!$C$19,"") -> 0 | D20: =IFERROR([1]SYNC_PROSPECTION_MKT!$D$19,"") -> 0 | E20: =IFERROR([1]SYNC_PROSPECTION_MKT!$E$19,"") -> 0 | F20: =IFERROR([1]SYNC_PROSPECTION_MKT!$G$19,"") -> 0 | G20: =IFERROR([1]SYNC_PROSPECTION_MKT!$H$19,"") -> 0 | H20: =IFERROR([1]SYNC_PROSPECTION_MKT!$J$19,"") -> 0 | I20: =IFERROR([1]SYNC_PROSPECTION_MKT!$I$19,"") -> 0 | J20: =IFERROR([1]SYNC_PROSPECTION_MKT!$K$19,"") -> 0 | K20: =IFERROR(SYNC_FINANCE!$I$19,"") -> 0 | L20: =IFERROR([2]SYNC_COMMERCIAL_VENTE!$S$19,"") -> 0 | M20: 0 | N20: 0 | O20: 0 | P20: 0 | Q20: 0 | R20: 0 | S20: 0 | T20: 0 | U20: 0 | V20: 0 | W20: 0 | X20: 0 | Y20: 0 | Z20: =IFERROR(SUM(N20:Y20),0) -> 0 | AA20: =IFERROR((N20+Q20+T20+W20)-M20,0) -> 0 | AB20: =IFERROR(Z20,0) -> 0 | AC20: =IFERROR(L20-AB20,0) -> 0
A21: 16 | B21: =IFERROR([1]SYNC_PROSPECTION_MKT!$B$20,"") -> 0 | C21: =IFERROR([1]SYNC_PROSPECTION_MKT!$C$20,"") -> 0 | D21: =IFERROR([1]SYNC_PROSPECTION_MKT!$D$20,"") -> 0 | E21: =IFERROR([1]SYNC_PROSPECTION_MKT!$E$20,"") -> 0 | F21: =IFERROR([1]SYNC_PROSPECTION_MKT!$G$20,"") -> 0 | G21: =IFERROR([1]SYNC_PROSPECTION_MKT!$H$20,"") -> 0 | H21: =IFERROR([1]SYNC_PROSPECTION_MKT!$J$20,"") -> 0 | I21: =IFERROR([1]SYNC_PROSPECTION_MKT!$I$20,"") -> 0 | J21: =IFERROR([1]SYNC_PROSPECTION_MKT!$K$20,"") -> 0 | K21: =IFERROR(SYNC_FINANCE!$I$20,"") -> 0 | L21: =IFERROR([2]SYNC_COMMERCIAL_VENTE!$S$20,"") -> 0 | M21: 0 | N21: 0 | O21: 0 | P21: 0 | Q21: 0 | R21: 0 | S21: 0 | T21: 0 | U21: 0 | V21: 0 | W21: 0 | X21: 0 | Y21: 0 | Z21: =IFERROR(SUM(N21:Y21),0) -> 0 | AA21: =IFERROR((N21+Q21+T21+W21)-M21,0) -> 0 | AB21: =IFERROR(Z21,0) -> 0 | AC21: =IFERROR(L21-AB21,0) -> 0
A22: 17 | B22: =IFERROR([1]SYNC_PROSPECTION_MKT!$B$21,"") -> 0 | C22: =IFERROR([1]SYNC_PROSPECTION_MKT!$C$21,"") -> 0 | D22: =IFERROR([1]SYNC_PROSPECTION_MKT!$D$21,"") -> 0 | E22: =IFERROR([1]SYNC_PROSPECTION_MKT!$E$21,"") -> 0 | F22: =IFERROR([1]SYNC_PROSPECTION_MKT!$G$21,"") -> 0 | G22: =IFERROR([1]SYNC_PROSPECTION_MKT!$H$21,"") -> 0 | H22: =IFERROR([1]SYNC_PROSPECTION_MKT!$J$21,"") -> 0 | I22: =IFERROR([1]SYNC_PROSPECTION_MKT!$I$21,"") -> 0 | J22: =IFERROR([1]SYNC_PROSPECTION_MKT!$K$21,"") -> 0 | K22: =IFERROR(SYNC_FINANCE!$I$21,"") -> 0 | L22: =IFERROR([2]SYNC_COMMERCIAL_VENTE!$S$21,"") -> 0 | M22: 0 | N22: 0 | O22: 0 | P22: 0 | Q22: 0 | R22: 0 | S22: 0 | T22: 0 | U22: 0 | V22: 0 | W22: 0 | X22: 0 | Y22: 0 | Z22: =IFERROR(SUM(N22:Y22),0) -> 0 | AA22: =IFERROR((N22+Q22+T22+W22)-M22,0) -> 0 | AB22: =IFERROR(Z22,0) -> 0 | AC22: =IFERROR(L22-AB22,0) -> 0
